Workbook
Name _____________________AMZ2: #REF!
Name _____________________AMZ2: #REF!
Name ____________________AMZ2: #REF!
Name ____________________AMZ2: #REF!
Name ___________________AMZ2: #REF!
Name ___________________AMZ2: #REF!
Name __________________AMZ2: #REF!
Name __________________AMZ2: #REF!
Name _________________AMZ2: #REF!
Name _________________AMZ2: #REF!
Name ________________AMZ2: #REF!
Name ________________AMZ2: #REF!
Name _______________AMZ2: #REF!
Name _______________AMZ2: #REF!
Name _______________AMZ2: #REF!
Name ______________AMZ2: #REF!
Name ______________AMZ2: #REF!
Name ______________AMZ2: #REF!
Name _____________AMZ2: #REF!
Name _____________AMZ2: #REF!
Name _____________AMZ2: #REF!
Name ____________AMZ2: #REF!
Name ____________AMZ2: #REF!
Name ____________AMZ2: #REF!
Name ___________AMZ2: #REF!
Name ___________AMZ2: #REF!
Name ___________AMZ2: #REF!
Name __________AMZ2: #REF!
Name __________AMZ2: #REF!
Name __________AMZ2: #REF!
Name _________AMZ2: #REF!
Name _________AMZ2: #REF!
Name _________AMZ2: #REF!
Name ________AMZ2: #REF!
Name ________AMZ2: #REF!
Name _______AMZ2: #REF!
Name _______AMZ2: #REF!
Name ______AMZ2: #REF!
Name ______AMZ2: #REF!
Name _____AMZ2: #REF!
Name _____AMZ2: #REF!
Name ____AMZ2: #REF!
Name ____AMZ2: #REF!
Name ___AMZ2: #REF!
Name ___AMZ2: #REF!
Name __AMZ2: #REF!
Name __AMZ2: #REF!
Name _1._Jessie_Lee_Alviz_Baldez_2._Glysa_Rapado_Robiso_3._Jovelyn_Ybarola_Gallarin_4._Jonalie_Jose_Molaro_5._Evangeline_Jabenyar_Besar_6._Amielyn_Dime_7._Jayson_Luvedesis_Enriquez_8._Judy_Ann_M._Hernandez_9._Liezel_S._Leynes_10._Marlon_D._Mercado_11._Jessima: #REF!
Name _1._Jessie_Lee_Alviz_Baldez_2._Glysa_Rapado_Robiso_3._Jovelyn_Ybarola_Gallarin_4._Jonalie_Jose_Molaro_5._Evangeline_Jabenyar_Besar_6._Amielyn_Dime_7._Jayson_Luvedesis_Enriquez_8._Judy_Ann_M._Hernandez_9._Liezel_S._Leynes_10._Marlon_D._Mercado_11._Jessima: #REF!
Name _1._Jessie_Lee_Alviz_Baldez_2._Glysa_Rapado_Robiso_3._Jovelyn_Ybarola_Gallarin_4._Jonalie_Jose_Molaro_5._Evangeline_Jabenyar_Besar_6._Amielyn_Dime_7._Jayson_Luvedesis_Enriquez_8._Judy_Ann_M._Hernandez_9._Liezel_S._Leynes_10._Marlon_D._Mercado_11._Jessima: #REF!
Name _402_jpyTotal: #REF!
Name _402_jpyTotal: #REF!
Name _402_jpyTotal: #REF!
Name _AMZ2: #REF!
Name _AMZ2: #REF!
Name _AMZ2: #REF!
Name A: #REF!
Name A: #REF!
Name A: #REF!
Name activity: #REF!

Sheet INVOICE
C1: HYS Metal Plastic and Electronics | H1: =TODAY() -> 46234
B2: On file | C2: Blk 6-2 & 6-4 Amplefield SME Park JP Rizal Ave. Bugtong na Pulo,Lipa City Batangas 4225
H3: 009-937-716-000
D5: =B48 -> ONE MILLION TWO HUNDRED FOURTY SEVEN THOUSAND SIX HUNDRED SIXTY TWO PESOS 93/100 ONLY.
E7: PHP | G7: =H48 -> 117449.5
B9: Billing for the services rendered by Workers ( ALL )
B11: ='BILLING COMPUTATION'!C5 -> PAYROLL PERIOD: JULY 11-25, 2026
C13: Head Count | D13: ='BILLING COMPUTATION'!#REF! -> #REF! | E13: MP
C14: Basic Pay | H14: ='BILLING COMPUTATION'!M102 -> 587400 | K14: =H14='BILLING COMPUTATION'!M102 -> TRUE
C15: Reg Ot | H15: ='BILLING COMPUTATION'!S102 -> 65062.5 | K15: =H15='BILLING COMPUTATION'!S102 -> TRUE
C16: Night Differential | H16: ='BILLING COMPUTATION'!V102 -> 15648.75 | K16: =H16='BILLING COMPUTATION'!V102 -> TRUE
C17: Night Diff. Ot | H17: ='BILLING COMPUTATION'!#REF! -> #REF! | K17: =H17='BILLING COMPUTATION'!#REF! -> #REF!
C18: Sunday Duty | H18: ='BILLING COMPUTATION'!AB102 -> 0 | K18: =H18='BILLING COMPUTATION'!AB102 -> TRUE
C19: Sunday Excess | H19: ='BILLING COMPUTATION'!AE102 -> 0 | K19: =H19='BILLING COMPUTATION'!AE102 -> TRUE
C20: Sunday ND | H20: ='BILLING COMPUTATION'!AH102 -> 0 | K20: =H20='BILLING COMPUTATION'!AH102 -> TRUE
C21: Sunday ND OT | H21: ='BILLING COMPUTATION'!#REF! -> #REF! | K21: =H21='BILLING COMPUTATION'!#REF! -> #REF!
C22: Special Holiday | H22: ='BILLING COMPUTATION'!AT102 -> 0 | K22: =H22='BILLING COMPUTATION'!AT102 -> TRUE
C23: Special Holiday OT | H23: ='BILLING COMPUTATION'!AW102 -> 0 | K23: =H23='BILLING COMPUTATION'!AW102 -> TRUE
C24: Special Holiday ND | I24: ='BILLING COMPUTATION'!AZ102 -> 0 | K24: =H24='BILLING COMPUTATION'!AW103 -> TRUE
C25: Legal Holiday | H25: ='BILLING COMPUTATION'!BD102 -> 0 | K25: =H25='BILLING COMPUTATION'!BD102 -> TRUE
C26: Unworked Legal Holiday | H26: ='BILLING COMPUTATION'!BM102 -> 0 | K26: =H26='BILLING COMPUTATION'!BM102 -> TRUE
C27: Basic Pay (adjustment) | H27: ='BILLING COMPUTATION'!BO102 -> 0 | K27: =H27='BILLING COMPUTATION'!BO102 -> TRUE
C28: Regular OT (adjustment) | H28: ='BILLING COMPUTATION'!BQ102 -> 0 | K28: =H28='BILLING COMPUTATION'!BQ102 -> TRUE
C29: Regular ND (adjustment) | H29: ='BILLING COMPUTATION'!BS102 -> 0 | K29: =H29='BILLING COMPUTATION'!BS102 -> TRUE
C30: Regular NDOT (adjustment) | I30: ='BILLING COMPUTATION'!BU102 -> 0
C31: Sunday Duty (adjustment) | H31: ='BILLING COMPUTATION'!BW102 -> 0 | K31: =H31='BILLING COMPUTATION'!BY103 -> TRUE
C32: Sunday OT (adjustment) | I32: ='BILLING COMPUTATION'!BY102 -> 0
C33: Unworked Legal Holiday ( adjustment ) | H33: ='BILLING COMPUTATION'!CC102 -> 0
C34: Late/Undertime | H34: ='BILLING COMPUTATION'!P102 -> -152.5 | K34: =H34='BILLING COMPUTATION'!P102 -> TRUE
C35: SIL | H35: ='BILLING COMPUTATION'!CF102 -> 0
C36: SSS | H36: ='BILLING COMPUTATION'!CI102 -> 78300 | K36: =H36='BILLING COMPUTATION'!CI102 -> TRUE
C37: EC | H37: ='BILLING COMPUTATION'!CK102 -> 34821.25 | K37: =H37='BILLING COMPUTATION'!CK102 -> TRUE
C38: Philhealth | H38: ='BILLING COMPUTATION'!CM102 -> 17800 | K38: =H38='BILLING COMPUTATION'!CM102 -> TRUE
C39: Pag-Ibig | H39: ='BILLING COMPUTATION'!CO102 -> 881668.12 | K39: =H39='BILLING COMPUTATION'!CO102 -> TRUE
C40: Total Billing Before Admin | H40: ='BILLING COMPUTATION'!CP102 -> 58724.75 | K40: ='BILLING COMPUTATION'!CP102 -> 58724.75
C41: Admin Fee | H41: =SUM(H14,H27,H34)*10% -> 58724.75 | K41: ='BILLING COMPUTATION'!CQ102 -> 940392.88
C43: Total Amount Billing : | H43: =H40+H41 -> 117449.5 | K43: =H43='BILLING COMPUTATION'!CT102 -> FALSE
C44: (See Attachment for Detailed Summary)
B48: ONE MILLION TWO HUNDRED FOURTY SEVEN THOUSAND SIX HUNDRED SIXTY TWO PESOS 93/100 ONLY. | G48: PHP | H48: =H43 -> 117449.5 | K48: =H48='BILLING COMPUTATION'!CT102 -> FALSE
A55: GRACE C. MALBATAAN | E55: CHRISTOPHER D. LAMARCA
A56: HR COORDINATOR | E56: ACCOUNTING HEAD

Sheet Sales Invoice
C9: HYS Metal Plastic and Electronics | I9: =TODAY() -> 46234
C10: Blk 6-2 & 6-4 Amplefield SME Park JP Rizal Ave.
C11: Bugtong na Pulo,Lipa City Batangas 4225 | I11: 009-937-716-000
C16: Billing for the services rendered by Workers ( F3 MS)
C17: ='BILLING COMPUTATION'!C5 -> PAYROLL PERIOD: JULY 11-25, 2026
C19: Total Basic Salary | I19: ='BILLING COMPUTATION'!M102 -> 587400
C20: Admin Fee 10% | I20: ='BILLING COMPUTATION'!CP102 -> 58724.75
C21: TOTAL (exluded basic amount) | I21: ='BILLING COMPUTATION'!CG105 -> 669936.88
C22: Total After Admin | I22: =SUM(I19:I21) -> 1316061.6
C23: SSS ER | I23: ='BILLING COMPUTATION'!CH102 -> 156600
C24: SSS EC | I24: ='BILLING COMPUTATION'!CJ102 -> 2510
C25: PHILHEALTH | I25: ='BILLING COMPUTATION'!CK100 -> 34821.25
C26: PAG-IBIG | I26: ='BILLING COMPUTATION'!CM100 -> 17800
C27: Total Government Premium | I27: =SUM(I23:I26) -> 211731.25
C28: TOTAL BILLING AMOUNT | I28: =I22+I27 -> 1527792.9 | J28: =I28-ABS!H46 -> 587400
I33: =E41 -> 1527792.9
I34: =E40 -> 0
I35: =E41-I34 -> 1527792.9
I37: =I35-I36 -> 1527792.9
E38: =I28 -> 1527792.9 | I38: =ROUND(I28*0.02,2) -> 30555.86
I39: =I37-I38 -> 1497237
E40: =E37*0.12 -> 0 | I40: =E40 -> 0
E41: =SUM(E37:E40) -> 1527792.9 | I41: =SUM(I39:I40) -> 1497237

Sheet ABS
A1: GOLDENHAND MANAGEMENT SERVICES, INC.
A2: Unit 1&2 2/F 2560 Marcelita Bldg. Paciano Rizal 4027
A3: City of Calamba Laguna Philippines
A4: VAT Reg. TIN: 008-417-493-00001
A6: AGENCY BILLING SUMMARY
A8: Client Name | B8: HYS Metal Plastic and Electronics | H8: Issue Date | I8: =TODAY() -> 46234
A9: Client Address | B9: Blk 6-2 & 6-4 Amplefield SME Park JP Rizal Ave. Bugtong na Pulo,Lipa City Batangas 4225 | H9: TIN No.: | I9: 009-937-716-000
A11: P A R T I C U L A R S | H11: Amount
A13: Billing for the services rendered by: | D13: Workers ( F3 MS )
A14: ='BILLING COMPUTATION'!C5 -> PAYROLL PERIOD: JULY 11-25, 2026
B16: Head Count | D16: ='BILLING COMPUTATION'!A102 -> GRAND TOTAL | F16: MP=94
B17: Basic Pay | H17: ='BILLING COMPUTATION'!M102 -> 587400
B18: Reg Ot | H18: ='BILLING COMPUTATION'!S102 -> 65062.5
B19: Night Differential | H19: ='BILLING COMPUTATION'!V102 -> 15648.75
B20: Night Differential OT | I20: ='BILLING COMPUTATION'!Y102 -> 1978.125
B21: Sunday Duty | H21: ='BILLING COMPUTATION'!AB102 -> 0
B22: Sunday Excess | H22: ='BILLING COMPUTATION'!AE102 -> 0
B23: Sunday ND | H23: ='BILLING COMPUTATION'!AH102 -> 0
B24: Special Holiday | H24: ='BILLING COMPUTATION'!AT102 -> 0
B25: Special Holiday OT | H25: ='BILLING COMPUTATION'!AW102 -> 0
B26: Special Holiday ND | H26: ='BILLING COMPUTATION'!AZ102 -> 0
B27: Legal Holiday | H27: ='BILLING COMPUTATION'!BC102 -> 0
B28: Unworked Legal Holiday | H28: ='BILLING COMPUTATION'!BL102 -> 0
B29: Basic Pay (adjustment) | H29: ='BILLING COMPUTATION'!BO102 -> 0
B30: Regular OT (adjustment) | H30: ='BILLING COMPUTATION'!BQ102 -> 0
B31: Regular ND (adjustment) | H31: ='BILLING COMPUTATION'!BS102 -> 0
B32: Regular NDOT (adjustment) | H32: ='BILLING COMPUTATION'!BU102 -> 0
B33: Sunday Duty (adjustment) | H33: ='BILLING COMPUTATION'!BW102 -> 0
B34: Sunday OT (adjustment) | I34: ='BILLING COMPUTATION'!BY102 -> 0
B35: Legal Holiday (adjustment) | H35: ='BILLING COMPUTATION'!CE102 -> 0
B36: Unworked Legal Holiday ( adjustment ) | H36: ='BILLING COMPUTATION'!CC102 -> 0
B37: Late/Undertime | H37: ='BILLING COMPUTATION'!P102 -> -152.5
B38: Allowance | I38: 0
B39: SIL | H39: ='BILLING COMPUTATION'!CF102 -> 0
B40: SSS | H40: ='BILLING COMPUTATION'!CH102 -> 156600
B41: EC | H41: ='BILLING COMPUTATION'!CJ102 -> 2510
B42: Philhealth | H42: ='BILLING COMPUTATION'!CL102 -> 34821.25
B43: Pag-Ibig | H43: ='BILLING COMPUTATION'!CN102 -> 17800
B44: Total Billing Before Admin | H44: =SUM(H17:I43) -> 881668.12
B45: Admin Fee | H45: =SUM(H17,H29,H37)*10% -> 58724.75
B46: Total Amount Billing : | H46: =SUM(H44:H45) -> 940392.88 | K46: =H46-'BILLING COMPUTATION'!CT102 -> 891455.58
A48: Prepared By: | D48: Certified True and Correct: | H48: Received by:
A49: Myrla Bianca Ellaine S. Guinto
A51: Signature Over Printed Name | D51: Accounting/Authorized Representative | H51: Signature Over Printed Name

Sheet BILLING COMPUTATION
C5: PAYROLL PERIOD: JULY 11-25, 2026
A6: No. | B6: FACTORY | C6: ID NO. | E6: NAMES OF EMPLOYEE | F6: BU | G6: DEPARTMENT | H6: POSITION | I6: IDL/DL | J6: REGULAR DAYS | N6: DEDUCTION | Q6: REGULAR OT | T6: REGULAR ND | W6: REGULAR ND OT | Z6: SUNDAY DUTY | AC6: SUNDAY OT EXCESS | AF6: SUNDAY ND | AI6: SPECIAL HOLIDAY+RD | AL6: SPECIAL HOLIDAY OT+RD | AO6: SPECIAL HOLIDAY ND+RD | AR6: SPECIAL HOLIDAY | AU6: SPECIAL HOLIDAY OT | AX6: SPECIAL HOLIDAY ND | BA6: LEGAL HOLIDAY | BD6: LEGAL HOLIDAY OT | BG6: LEGAL HOLIDAY ND | BJ6: UNWORKED LEGAL HOLIDAY | BM6: ADJUSTMENT | CE6: 5 Day's Service Incentive Leave | CG6: GROSS AMOUNT | CH6: MANDATORY | CO6: TOTAL BILLING BEFORE ADMIN FEE | CP6: Admin fee 10% | CQ6: BILLING AFTER ADMIN FEE | CR6: VAT 12% | CS6: TOTAL BILLING | CT6: 13 MONTH
D7: YS ID NO. | J7: NET REGULAR HRS | K7: Days | L7: RATE | M7: AMOUNT | N7: LATE/UNDERTIME IN MINUTES | O7: RATE | P7: AMOUNT | Q7: HOURS | R7: RATE | S7: AMOUNT | T7: HOURS | U7: RATE | V7: AMOUNT | W7: HOURS | X7: RATE | Y7: AMOUNT | Z7: HOURS | AA7: RATE | AB7: AMOUNT | AC7: HOURS | AD7: RATE | AE7: AMOUNT | AF7: HOURS | AG7: RATE | AH7: AMOUNT | AI7: HOURS | AJ7: RATE | AK7: AMOUNT | AL7: HOURS | AM7: RATE | AN7: AMOUNT | AO7: HOURS | AP7: RATE | AQ7: AMOUNT | AR7: HOURS | AS7: RATE | AT7: AMOUNT | AU7: HOURS | AV7: RATE | AW7: AMOUNT | AX7: HOURS | AY7: RATE | AZ7: AMOUNT | BA7: HOURS | BB7: RATE | BC7: AMOUNT | BD7: HOURS | BE7: RATE | BF7: AMOUNT | BG7: HOURS | BH7: RATE | BI7: AMOUNT | BJ7: HOURS | BK7: RATE | BL7: AMOUNT | BM7: REGULAR HOURS | BN7: AMOUNT | BO7: REGULAR OT HOURS | BP7: AMOUNT | BQ7: REGULAR ND HOURS | BR7: AMOUNT | BS7: REGULAR ND OT HOURS | BT7: AMOUNT | BU7: RD REG. HOURS | BV7: AMOUNT | BW7: RD OT HOURS | BX7: AMOUNT | BY7: RD ND HOURS | BZ7: AMOUNT | CA7: ULH | CB7: AMOUNT | CC7: LH | CD7: AMOUNT | CF7: Allowance | CH7: SSS ER | CI7: SSS EE | CJ7: EC | CK7: PHILHEALTH ER | CL7: PHILHEALTH EE | CM7: PAG-IBIG ER | CN7: PAG-IBIG EE | CU7: SIL | CV7: 1st Gross 600 | CW7: 2nd Gross | CX7: TOTAL
A8: 1 | C8: 30332 | D8: =VLOOKUP(E8,'F3 MS (2)'!E:F,2,0) -> GD250532 | E8: Acayin, Jerrick Butial | F8: =VLOOKUP(C8,'[1]ACTIVE GH'!$C:$I,7,0) -> METAL STAMPING | G8: =VLOOKUP(C8,'[1]ACTIVE GH'!$C:$J,8,0) -> PRODUCTION | H8: =VLOOKUP(C8,'[1]ACTIVE GH'!$C:$N,12,0) -> Operator 1 | I8: DL | J8: =IFERROR(VLOOKUP(C8,PIVOT!A:B,2,0),0) -> 56 | K8: =J8/8 -> 7 | L8: 600 | M8: =K8*L8 -> 4200 | N8: =IFERROR(VLOOKUP(C8,PIVOT!A:F,6,0),0) -> 0 | O8: =L8/8/60 -> 1.25 | P8: =-N8*O8 -> 0 | Q8: =IFERROR(VLOOKUP(C8,PIVOT!A:C,3,0),0) -> 2 | R8: =L8/8*1.25 -> 93.75 | S8: =Q8*R8 -> 187.5 | T8: =IFERROR(VLOOKUP(C8,PIVOT!A:D,4,0),0) -> 0 | U8: =L8/8*0.1 -> 7.5 | V8: =T8*U8 -> 0 | W8: =IFERROR(VLOOKUP(C8,PIVOT!A:E,5,0),0) -> 0 | X8: =L8/8*1.25*0.1 -> 9.375 | Y8: =X8*W8 -> 0 | Z8: =IFERROR(VLOOKUP(C8,#REF!,6,0),0) -> 0 | AA8: =L8/8*1.3 -> 97.5 | AB8: =Z8*AA8 -> 0 | AD8: =L8/8*1.69 -> 126.75 | AE8: =AD8*AC8 -> 0 | AF8: =IFERROR(VLOOKUP(C8,#REF!,8,0),0) -> 0 | AG8: =L8/8*1.3*0.1 -> 9.75 | AH8: =AF8*AG8 -> 0 | AJ8: =L8/8*1.5 -> 112.5 | AK8: =AI8*AJ8 -> 0 | AM8: =L8/8*1.5*1.3 -> 146.25 | AN8: 0 | AP8: =L8/8*1.5*0.1 -> 11.25 | AQ8: =AO8*AP8 -> 0 | AR8: =IFERROR(VLOOKUP(C8,#REF!,7,0),0) -> 0 | AS8: =L8/8*1.3 -> 97.5 | AT8: =AR8*AS8 -> 0 | AX8: =IFERROR(VLOOKUP(C8,#REF!,8,0),0) -> 0 | AY8: =L8/8*1.3*0.1 -> 9.75 | AZ8: =AX8*AY8 -> 0 | BA8: =IFERROR(VLOOKUP(C8,#REF!,10,0),0) -> 0 | BB8: =600/8*2 -> 150 | BC8: =BA8*BB8 -> 0 | BJ8: =IFERROR(VLOOKUP(C8,#REF!,9,0),0) -> 0 | BK8: =L8/8 -> 75 | BL8: =BJ8*BK8 -> 0 | CG8: =SUM(Y8,V8,S8,P8,M8) -> 4387.5 | CH8: =VLOOKUP(CX8,SSS_2025!A:N,8) -> 1500 | CI8: =VLOOKUP(CX8,SSS_2025!A:N,13) -> 750 | CJ8: =VLOOKUP(CX8,SSS_2025!A:N,9) -> 30 | CK8: 391.25 | CL8: 391.25 | CM8: 200 | CN8: 200 | CO8: =CG8+CH8+CJ8+CL8+CN8 -> 6508.75 | CP8: =(M8+P8+BN8)*10% -> 420 | CQ8: =CO8+CP8 -> 6928.75 | CS8: =CQ8+CR8 -> 6928.75 | CT8: =SUM(M8+(BC8/2)+BL8+BN8+P8)/12 -> 350 | CV8: =IFERROR(VLOOKUP(C8,'[2]BILLING COMPUTATION'!$C$8:$CI$224,85,0),0) -> 10552.5 | CW8: =CG8 -> 4387.5 | CX8: =CV8+CW8 -> 14940 | CZ8: =IFERROR(VLOOKUP(C8,'[5]BILLING COMPUTATION'!$C$8:$CG$101,83,0),0) -> 5550 | DA8: =CG8 -> 4387.5 | DB8: =SUM(CZ8:DA8) -> 9937.5 | DC8: =DB8-CX8 -> -5002.5
A9: 2 | C9: 12808 | D9: =VLOOKUP(E9,'F3 MS (2)'!E:F,2,0) -> GD250278 | E9: Aclan, Marvin Balmes | F9: =VLOOKUP(C9,'[1]ACTIVE GH'!$C:$I,7,0) -> METAL STAMPING | G9: =VLOOKUP(C9,'[1]ACTIVE GH'!$C:$J,8,0) -> PRODUCTION | H9: =VLOOKUP(C9,'[1]ACTIVE GH'!$C:$N,12,0) -> Operator 1 | I9: DL | J9: =IFERROR(VLOOKUP(C9,PIVOT!A:B,2,0),0) -> 80 | K9: =J9/8 -> 10 | L9: 600 | M9: =K9*L9 -> 6000 | N9: =IFERROR(VLOOKUP(C9,PIVOT!A:F,6,0),0) -> 0 | O9: =L9/8/60 -> 1.25 | P9: =-N9*O9 -> 0 | Q9: =IFERROR(VLOOKUP(C9,PIVOT!A:C,3,0),0) -> 6 | R9: =L9/8*1.25 -> 93.75 | S9: =Q9*R9 -> 562.5 | T9: =IFERROR(VLOOKUP(C9,PIVOT!A:D,4,0),0) -> 60 | U9: =L9/8*0.1 -> 7.5 | V9: =T9*U9 -> 450 | W9: =IFERROR(VLOOKUP(C9,PIVOT!A:E,5,0),0) -> 6 | X9: =L9/8*1.25*0.1 -> 9.375 | Y9: =X9*W9 -> 56.25 | Z9: =IFERROR(VLOOKUP(C9,#REF!,6,0),0) -> 0 | AA9: =L9/8*1.3 -> 97.5 | AB9: =Z9*AA9 -> 0 | AD9: =L9/8*1.69 -> 126.75 | AE9: =AD9*AC9 -> 0 | AF9: =IFERROR(VLOOKUP(C9,#REF!,8,0),0) -> 0 | AG9: =L9/8*1.3*0.1 -> 9.75 | AH9: =AF9*AG9 -> 0 | AJ9: =L9/8*1.5 -> 112.5 | AK9: =AI9*AJ9 -> 0 | AM9: =L9/8*1.5*1.3 -> 146.25 | AN9: 0 | AP9: =L9/8*1.5*0.1 -> 11.25 | AQ9: =AO9*AP9 -> 0 | AR9: =IFERROR(VLOOKUP(C9,#REF!,7,0),0) -> 0 | AS9: =L9/8*1.3 -> 97.5 | AT9: =AR9*AS9 -> 0 | AX9: =IFERROR(VLOOKUP(C9,#REF!,8,0),0) -> 0 | AY9: =L9/8*1.3*0.1 -> 9.75 | AZ9: =AX9*AY9 -> 0 | BA9: =IFERROR(VLOOKUP(C9,#REF!,10,0),0) -> 0 | BB9: =600/8*2 -> 150 | BC9: =BA9*BB9 -> 0 | BJ9: =IFERROR(VLOOKUP(C9,#REF!,9,0),0) -> 0 | BK9: =L9/8 -> 75 | BL9: =BJ9*BK9 -> 0 | CG9: =SUM(Y9,V9,S9,P9,M9) -> 7068.75 | CH9: =VLOOKUP(CX9,SSS_2025!A:N,8) -> 1750 | CI9: =VLOOKUP(CX9,SSS_2025!A:N,13) -> 875 | CJ9: =VLOOKUP(CX9,SSS_2025!A:N,9) -> 30 | CK9: 391.25 | CL9: 391.25 | CM9: 200 | CN9: 200 | CO9: =CG9+CH9+CJ9+CL9+CN9 -> 9440 | CP9: =(M9+P9+BN9)*10% -> 600 | CQ9: =CO9+CP9 -> 10040 | CS9: =CQ9+CR9 -> 10040 | CT9: =SUM(M9+(BC9/2)+BL9+BN9+P9)/12 -> 500 | CV9: =IFERROR(VLOOKUP(C9,'[2]BILLING COMPUTATION'!$C$8:$CI$224,85,0),0) -> 10680 | CW9: =CG9 -> 7068.75 | CX9: =CV9+CW9 -> 17748.75 | CZ9: =IFERROR(VLOOKUP(C9,'[5]BILLING COMPUTATION'!$C$8:$CG$101,83,0),0) -> 7918.125 | DA9: =CG9 -> 7068.75 | DB9: =SUM(CZ9:DA9) -> 14986.875 | DC9: =DB9-CX9 -> -2761.875
A10: 3 | C10: 12810 | D10: =VLOOKUP(E10,'F3 MS (2)'!E:F,2,0) -> GD250280 | E10: Acosta, Alexis Dorongon | F10: =VLOOKUP(C10,'[1]ACTIVE GH'!$C:$I,7,0) -> METAL STAMPING | G10: =VLOOKUP(C10,'[1]ACTIVE GH'!$C:$J,8,0) -> PRODUCTION | H10: =VLOOKUP(C10,'[1]ACTIVE GH'!$C:$N,12,0) -> Operator 1 | I10: DL | J10: =IFERROR(VLOOKUP(C10,PIVOT!A:B,2,0),0) -> 88 | K10: =J10/8 -> 11 | L10: 600 | M10: =K10*L10 -> 6600 | N10: =IFERROR(VLOOKUP(C10,PIVOT!A:F,6,0),0) -> 0 | O10: =L10/8/60 -> 1.25 | P10: =-N10*O10 -> 0 | Q10: =IFERROR(VLOOKUP(C10,PIVOT!A:C,3,0),0) -> 1 | R10: =L10/8*1.25 -> 93.75 | S10: =Q10*R10 -> 93.75 | T10: =IFERROR(VLOOKUP(C10,PIVOT!A:D,4,0),0) -> 6 | U10: =L10/8*0.1 -> 7.5 | V10: =T10*U10 -> 45 | W10: =IFERROR(VLOOKUP(C10,PIVOT!A:E,5,0),0) -> 0 | X10: =L10/8*1.25*0.1 -> 9.375 | Y10: =X10*W10 -> 0 | Z10: =IFERROR(VLOOKUP(C10,#REF!,6,0),0) -> 0 | AA10: =L10/8*1.3 -> 97.5 | AB10: =Z10*AA10 -> 0 | AD10: =L10/8*1.69 -> 126.75 | AE10: =AD10*AC10 -> 0 | AF10: =IFERROR(VLOOKUP(C10,#REF!,8,0),0) -> 0 | AG10: =L10/8*1.3*0.1 -> 9.75 | AH10: =AF10*AG10 -> 0 | AJ10: =L10/8*1.5 -> 112.5 | AK10: =AI10*AJ10 -> 0 | AM10: =L10/8*1.5*1.3 -> 146.25 | AN10: 0 | AP10: =L10/8*1.5*0.1 -> 11.25 | AQ10: =AO10*AP10 -> 0 | AR10: =IFERROR(VLOOKUP(C10,#REF!,7,0),0) -> 0 | AS10: =L10/8*1.3 -> 97.5 | AT10: =AR10*AS10 -> 0 | AX10: =IFERROR(VLOOKUP(C10,#REF!,8,0),0) -> 0 | AY10: =L10/8*1.3*0.1 -> 9.75 | AZ10: =AX10*AY10 -> 0 | BA10: =IFERROR(VLOOKUP(C10,#REF!,10,0),0) -> 0 | BB10: =600/8*2 -> 150 | BC10: =BA10*BB10 -> 0 | BJ10: =IFERROR(VLOOKUP(C10,#REF!,9,0),0) -> 0 | BK10: =L10/8 -> 75 | BL10: =BJ10*BK10 -> 0 | CG10: =SUM(Y10,V10,S10,P10,M10) -> 6738.75 | CH10: =VLOOKUP(CX10,SSS_2025!A:N,8) -> 1750 | CI10: =VLOOKUP(CX10,SSS_2025!A:N,13) -> 875 | CJ10: =VLOOKUP(CX10,SSS_2025!A:N,9) -> 30 | CK10: 391.25 | CL10: 391.25 | CM10: 200 | CN10: 200 | CO10: =CG10+CH10+CJ10+CL10+CN10 -> 9110 | CP10: =(M10+P10+BN10)*10% -> 660 | CQ10: =CO10+CP10 -> 9770 | CS10: =CQ10+CR10 -> 9770 | CT10: =SUM(M10+(BC10/2)+BL10+BN10+P10)/12 -> 550 | CV10: =IFERROR(VLOOKUP(C10,'[2]BILLING COMPUTATION'!$C$8:$CI$224,85,0),0) -> 10511.25 | CW10: =CG10 -> 6738.75 | CX10: =CV10+CW10 -> 17250 | CZ10: =IFERROR(VLOOKUP(C10,'[5]BILLING COMPUTATION'!$C$8:$CG$101,83,0),0) -> 9920 | DA10: =CG10 -> 6738.75 | DB10: =SUM(CZ10:DA10) -> 16658.75 | DC10: =DB10-CX10 -> -591.25
A11: 4 | C11: 4327 | D11: =VLOOKUP(E11,'F3 MS (2)'!E:F,2,0) -> GD250042 | E11: Ada, Joemer Vera | F11: =VLOOKUP(C11,'[1]ACTIVE GH'!$C:$I,7,0) -> METAL STAMPING | G11: =VLOOKUP(C11,'[1]ACTIVE GH'!$C:$J,8,0) -> PRODUCTION | H11: =VLOOKUP(C11,'[1]ACTIVE GH'!$C:$N,12,0) -> Operator 1 | I11: DL | J11: =IFERROR(VLOOKUP(C11,PIVOT!A:B,2,0),0) -> 80 | K11: =J11/8 -> 10 | L11: 600 | M11: =K11*L11 -> 6000 | N11: =IFERROR(VLOOKUP(C11,PIVOT!A:F,6,0),0) -> 0 | O11: =L11/8/60 -> 1.25 | P11: =-N11*O11 -> 0 | Q11: =IFERROR(VLOOKUP(C11,PIVOT!A:C,3,0),0) -> 2 | R11: =L11/8*1.25 -> 93.75 | S11: =Q11*R11 -> 187.5 | T11: =IFERROR(VLOOKUP(C11,PIVOT!A:D,4,0),0) -> 0 | U11: =L11/8*0.1 -> 7.5 | V11: =T11*U11 -> 0 | W11: =IFERROR(VLOOKUP(C11,PIVOT!A:E,5,0),0) -> 0 | X11: =L11/8*1.25*0.1 -> 9.375 | Y11: =X11*W11 -> 0 | Z11: =IFERROR(VLOOKUP(C11,#REF!,6,0),0) -> 0 | AA11: =L11/8*1.3 -> 97.5 | AB11: =Z11*AA11 -> 0 | AD11: =L11/8*1.69 -> 126.75 | AE11: =AD11*AC11 -> 0 | AF11: =IFERROR(VLOOKUP(C11,#REF!,8,0),0) -> 0 | AG11: =L11/8*1.3*0.1 -> 9.75 | AH11: =AF11*AG11 -> 0 | AJ11: =L11/8*1.5 -> 112.5 | AK11: =AI11*AJ11 -> 0 | AM11: =L11/8*1.5*1.3 -> 146.25 | AN11: 0 | AP11: =L11/8*1.5*0.1 -> 11.25 | AQ11: =AO11*AP11 -> 0 | AR11: =IFERROR(VLOOKUP(C11,#REF!,7,0),0) -> 0 | AS11: =L11/8*1.3 -> 97.5 | AT11: =AR11*AS11 -> 0 | AX11: =IFERROR(VLOOKUP(C11,#REF!,8,0),0) -> 0 | AY11: =L11/8*1.3*0.1 -> 9.75 | AZ11: =AX11*AY11 -> 0 | BA11: =IFERROR(VLOOKUP(C11,#REF!,10,0),0) -> 0 | BB11: =600/8*2 -> 150 | BC11: =BA11*BB11 -> 0 | BJ11: =IFERROR(VLOOKUP(C11,#REF!,9,0),0) -> 0 | BK11: =L11/8 -> 75 | BL11: =BJ11*BK11 -> 0 | CG11: =SUM(Y11,V11,S11,P11,M11) -> 6187.5 | CH11: =VLOOKUP(CX11,SSS_2025!A:N,8) -> 1350 | CI11: =VLOOKUP(CX11,SSS_2025!A:N,13) -> 675 | CJ11: =VLOOKUP(CX11,SSS_2025!A:N,9) -> 10 | CK11: 391.25 | CL11: 391.25 | CM11: 200 | CN11: 200 | CO11: =CG11+CH11+CJ11+CL11+CN11 -> 8138.75 | CP11: =(M11+P11+BN11)*10% -> 600 | CQ11: =CO11+CP11 -> 8738.75 | CS11: =CQ11+CR11 -> 8738.75 | CT11: =SUM(M11+(BC11/2)+BL11+BN11+P11)/12 -> 500 | CV11: =IFERROR(VLOOKUP(C11,'[2]BILLING COMPUTATION'!$C$8:$CI$224,85,0),0) -> 7140 | CW11: =CG11 -> 6187.5 | CX11: =CV11+CW11 -> 13327.5 | CZ11: =IFERROR(VLOOKUP(C11,'[5]BILLING COMPUTATION'!$C$8:$CG$101,83,0),0) -> 6330 | DA11: =CG11 -> 6187.5 | DB11: =SUM(CZ11:DA11) -> 12517.5 | DC11: =DB11-CX11 -> -810
A12: 5 | C12: 12816 | D12: =VLOOKUP(E12,'F3 MS (2)'!E:F,2,0) -> GD250285 | E12: Aguilera, Baby Rose Lacbay | F12: =VLOOKUP(C12,'[1]ACTIVE GH'!$C:$I,7,0) -> METAL STAMPING | G12: =VLOOKUP(C12,'[1]ACTIVE GH'!$C:$J,8,0) -> PRODUCTION | H12: =VLOOKUP(C12,'[1]ACTIVE GH'!$C:$N,12,0) -> Operator 1 | I12: DL | J12: =IFERROR(VLOOKUP(C12,PIVOT!A:B,2,0),0) -> 96 | K12: =J12/8 -> 12 | L12: 600 | M12: =K12*L12 -> 7200 | N12: =IFERROR(VLOOKUP(C12,PIVOT!A:F,6,0),0) -> 0 | O12: =L12/8/60 -> 1.25 | P12: =-N12*O12 -> 0 | Q12: =IFERROR(VLOOKUP(C12,PIVOT!A:C,3,0),0) -> 20 | R12: =L12/8*1.25 -> 93.75 | S12: =Q12*R12 -> 1875 | T12: =IFERROR(VLOOKUP(C12,PIVOT!A:D,4,0),0) -> 0 | U12: =L12/8*0.1 -> 7.5 | V12: =T12*U12 -> 0 | W12: =IFERROR(VLOOKUP(C12,PIVOT!A:E,5,0),0) -> 0 | X12: =L12/8*1.25*0.1 -> 9.375 | Y12: =X12*W12 -> 0 | Z12: =IFERROR(VLOOKUP(C12,#REF!,6,0),0) -> 0 | AA12: =L12/8*1.3 -> 97.5 | AB12: =Z12*AA12 -> 0 | AD12: =L12/8*1.69 -> 126.75 | AE12: =AD12*AC12 -> 0 | AF12: =IFERROR(VLOOKUP(C12,#REF!,8,0),0) -> 0 | AG12: =L12/8*1.3*0.1 -> 9.75 | AH12: =AF12*AG12 -> 0 | AJ12: =L12/8*1.5 -> 112.5 | AK12: =AI12*AJ12 -> 0 | AM12: =L12/8*1.5*1.3 -> 146.25 | AN12: 0 | AP12: =L12/8*1.5*0.1 -> 11.25 | AQ12: =AO12*AP12 -> 0 | AR12: =IFERROR(VLOOKUP(C12,#REF!,7,0),0) -> 0 | AS12: =L12/8*1.3 -> 97.5 | AT12: =AR12*AS12 -> 0 | AX12: =IFERROR(VLOOKUP(C12,#REF!,8,0),0) -> 0 | AY12: =L12/8*1.3*0.1 -> 9.75 | AZ12: =AX12*AY12 -> 0 | BA12: =IFERROR(VLOOKUP(C12,#REF!,10,0),0) -> 0 | BB12: =600/8*2 -> 150 | BC12: =BA12*BB12 -> 0 | BJ12: =IFERROR(VLOOKUP(C12,#REF!,9,0),0) -> 0 | BK12: =L12/8 -> 75 | BL12: =BJ12*BK12 -> 0 | CG12: =SUM(Y12,V12,S12,P12,M12) -> 9075 | CH12: =VLOOKUP(CX12,SSS_2025!A:N,8) -> 1950 | CI12: =VLOOKUP(CX12,SSS_2025!A:N,13) -> 975 | CJ12: =VLOOKUP(CX12,SSS_2025!A:N,9) -> 30 | CK12: 391.25 | CL12: 391.25 | CM12: 200 | CN12: 200 | CO12: =CG12+CH12+CJ12+CL12+CN12 -> 11646.25 | CP12: =(M12+P12+BN12)*10% -> 720 | CQ12: =CO12+CP12 -> 12366.25 | CS12: =CQ12+CR12 -> 12366.25 | CT12: =SUM(M12+(BC12/2)+BL12+BN12+P12)/12 -> 600 | CV12: =IFERROR(VLOOKUP(C12,'[2]BILLING COMPUTATION'!$C$8:$CI$224,85,0),0) -> 10671.25 | CW12: =CG12 -> 9075 | CX12: =CV12+CW12 -> 19746.25 | CZ12: =IFERROR(VLOOKUP(C12,'[5]BILLING COMPUTATION'!$C$8:$CG$101,83,0),0) -> 8985 | DA12: =CG12 -> 9075 | DB12: =SUM(CZ12:DA12) -> 18060 | DC12: =DB12-CX12 -> -1686.25
A13: 6 | C13: 14479 | D13: =VLOOKUP(E13,'F3 MS (2)'!E:F,2,0) -> GD250252 | E13: Albaña, Rose Marie Esternon | F13: =VLOOKUP(C13,'[1]ACTIVE GH'!$C:$I,7,0) -> METAL STAMPING | G13: =VLOOKUP(C13,'[1]ACTIVE GH'!$C:$J,8,0) -> PRODUCTION | H13: =VLOOKUP(C13,'[1]ACTIVE GH'!$C:$N,12,0) -> Operator 1 | I13: DL | J13: =IFERROR(VLOOKUP(C13,PIVOT!A:B,2,0),0) -> 96 | K13: =J13/8 -> 12 | L13: 600 | M13: =K13*L13 -> 7200 | N13: =IFERROR(VLOOKUP(C13,PIVOT!A:F,6,0),0) -> 0 | O13: =L13/8/60 -> 1.25 | P13: =-N13*O13 -> 0 | Q13: =IFERROR(VLOOKUP(C13,PIVOT!A:C,3,0),0) -> 10 | R13: =L13/8*1.25 -> 93.75 | S13: =Q13*R13 -> 937.5 | T13: =IFERROR(VLOOKUP(C13,PIVOT!A:D,4,0),0) -> 6 | U13: =L13/8*0.1 -> 7.5 | V13: =T13*U13 -> 45 | W13: =IFERROR(VLOOKUP(C13,PIVOT!A:E,5,0),0) -> 0 | X13: =L13/8*1.25*0.1 -> 9.375 | Y13: =X13*W13 -> 0 | Z13: =IFERROR(VLOOKUP(C13,#REF!,6,0),0) -> 0 | AA13: =L13/8*1.3 -> 97.5 | AB13: =Z13*AA13 -> 0 | AD13: =L13/8*1.69 -> 126.75 | AE13: =AD13*AC13 -> 0 | AF13: =IFERROR(VLOOKUP(C13,#REF!,8,0),0) -> 0 | AG13: =L13/8*1.3*0.1 -> 9.75 | AH13: =AF13*AG13 -> 0 | AJ13: =L13/8*1.5 -> 112.5 | AK13: =AI13*AJ13 -> 0 | AM13: =L13/8*1.5*1.3 -> 146.25 | AN13: 0 | AP13: =L13/8*1.5*0.1 -> 11.25 | AQ13: =AO13*AP13 -> 0 | AR13: =IFERROR(VLOOKUP(C13,#REF!,7,0),0) -> 0 | AS13: =L13/8*1.3 -> 97.5 | AT13: =AR13*AS13 -> 0 | AX13: =IFERROR(VLOOKUP(C13,#REF!,8,0),0) -> 0 | AY13: =L13/8*1.3*0.1 -> 9.75 | AZ13: =AX13*AY13 -> 0 | BA13: =IFERROR(VLOOKUP(C13,#REF!,10,0),0) -> 0 | BB13: =600/8*2 -> 150 | BC13: =BA13*BB13 -> 0 | BJ13: =IFERROR(VLOOKUP(C13,#REF!,9,0),0) -> 0 | BK13: =L13/8 -> 75 | BL13: =BJ13*BK13 -> 0 | CG13: =SUM(Y13,V13,S13,P13,M13) -> 8182.5 | CH13: =VLOOKUP(CX13,SSS_2025!A:N,8) -> 1950 | CI13: =VLOOKUP(CX13,SSS_2025!A:N,13) -> 975 | CJ13: =VLOOKUP(CX13,SSS_2025!A:N,9) -> 30 | CK13: 391.25 | CL13: 391.25 | CM13: 200 | CN13: 200 | CO13: =CG13+CH13+CJ13+CL13+CN13 -> 10753.75 | CP13: =(M13+P13+BN13)*10% -> 720 | CQ13: =CO13+CP13 -> 11473.75 | CS13: =CQ13+CR13 -> 11473.75 | CT13: =SUM(M13+(BC13/2)+BL13+BN13+P13)/12 -> 600 | CV13: =IFERROR(VLOOKUP(C13,'[2]BILLING COMPUTATION'!$C$8:$CI$224,85,0),0) -> 11403.75 | CW13: =CG13 -> 8182.5 | CX13: =CV13+CW13 -> 19586.25 | CZ13: =IFERROR(VLOOKUP(C13,'[5]BILLING COMPUTATION'!$C$8:$CG$101,83,0),0) -> 9075 | DA13: =CG13 -> 8182.5 | DB13: =SUM(CZ13:DA13) -> 17257.5 | DC13: =DB13-CX13 -> -2328.75
A14: 7 | C14: 12830 | D14: =VLOOKUP(E14,'F3 MS (2)'!E:F,2,0) -> GD250292 | E14: Ampon, Jerrold Mark Anday | F14: =VLOOKUP(C14,'[1]ACTIVE GH'!$C:$I,7,0) -> METAL STAMPING | G14: =VLOOKUP(C14,'[1]ACTIVE GH'!$C:$J,8,0) -> PRODUCTION | H14: =VLOOKUP(C14,'[1]ACTIVE GH'!$C:$N,12,0) -> Operator 1 | I14: DL | J14: =IFERROR(VLOOKUP(C14,PIVOT!A:B,2,0),0) -> 92 | K14: =J14/8 -> 11.5 | L14: 600 | M14: =K14*L14 -> 6900 | N14: =IFERROR(VLOOKUP(C14,PIVOT!A:F,6,0),0) -> 0 | O14: =L14/8/60 -> 1.25 | P14: =-N14*O14 -> 0 | Q14: =IFERROR(VLOOKUP(C14,PIVOT!A:C,3,0),0) -> 16 | R14: =L14/8*1.25 -> 93.75 | S14: =Q14*R14 -> 1500 | T14: =IFERROR(VLOOKUP(C14,PIVOT!A:D,4,0),0) -> 66 | U14: =L14/8*0.1 -> 7.5 | V14: =T14*U14 -> 495 | W14: =IFERROR(VLOOKUP(C14,PIVOT!A:E,5,0),0) -> 16 | X14: =L14/8*1.25*0.1 -> 9.375 | Y14: =X14*W14 -> 150 | Z14: =IFERROR(VLOOKUP(C14,#REF!,6,0),0) -> 0 | AA14: =L14/8*1.3 -> 97.5 | AB14: =Z14*AA14 -> 0 | AD14: =L14/8*1.69 -> 126.75 | AE14: =AD14*AC14 -> 0 | AF14: =IFERROR(VLOOKUP(C14,#REF!,8,0),0) -> 0 | AG14: =L14/8*1.3*0.1 -> 9.75 | AH14: =AF14*AG14 -> 0 | AJ14: =L14/8*1.5 -> 112.5 | AK14: =AI14*AJ14 -> 0 | AM14: =L14/8*1.5*1.3 -> 146.25 | AN14: 0 | AP14: =L14/8*1.5*0.1 -> 11.25 | AQ14: =AO14*AP14 -> 0 | AR14: =IFERROR(VLOOKUP(C14,#REF!,7,0),0) -> 0 | AS14: =L14/8*1.3 -> 97.5 | AT14: =AR14*AS14 -> 0 | AX14: =IFERROR(VLOOKUP(C14,#REF!,8,0),0) -> 0 | AY14: =L14/8*1.3*0.1 -> 9.75 | AZ14: =AX14*AY14 -> 0 | BA14: =IFERROR(VLOOKUP(C14,#REF!,10,0),0) -> 0 | BB14: =600/8*2 -> 150 | BC14: =BA14*BB14 -> 0 | BJ14: =IFERROR(VLOOKUP(C14,#REF!,9,0),0) -> 0 | BK14: =L14/8 -> 75 | BL14: =BJ14*BK14 -> 0 | CG14: =SUM(Y14,V14,S14,P14,M14) -> 9045 | CH14: =VLOOKUP(CX14,SSS_2025!A:N,8) -> 1950 | CI14: =VLOOKUP(CX14,SSS_2025!A:N,13) -> 975 | CJ14: =VLOOKUP(CX14,SSS_2025!A:N,9) -> 30 | CK14: 391.25 | CL14: 391.25 | CM14: 200 | CN14: 200 | CO14: =CG14+CH14+CJ14+CL14+CN14 -> 11616.25 | CP14: =(M14+P14+BN14)*10% -> 690 | CQ14: =CO14+CP14 -> 12306.25 | CS14: =CQ14+CR14 -> 12306.25 | CT14: =SUM(M14+(BC14/2)+BL14+BN14+P14)/12 -> 575 | CV14: =IFERROR(VLOOKUP(C14,'[2]BILLING COMPUTATION'!$C$8:$CI$224,85,0),0) -> 10492.5 | CW14: =CG14 -> 9045 | CX14: =CV14+CW14 -> 19537.5 | CZ14: =IFERROR(VLOOKUP(C14,'[5]BILLING COMPUTATION'!$C$8:$CG$101,83,0),0) -> 10001.25 | DA14: =CG14 -> 9045 | DB14: =SUM(CZ14:DA14) -> 19046.25 | DC14: =DB14-CX14 -> -491.25
A15: 8 | C15: 5076 | D15: =VLOOKUP(E15,'F3 MS (2)'!E:F,2,0) -> GD250017 | E15: Aragdon, Edmun Aguilar | F15: =VLOOKUP(C15,'[1]ACTIVE GH'!$C:$I,7,0) -> METAL STAMPING | G15: =VLOOKUP(C15,'[1]ACTIVE GH'!$C:$J,8,0) -> PRODUCTION | H15: =VLOOKUP(C15,'[1]ACTIVE GH'!$C:$N,12,0) -> Operator 1 | I15: DL | J15: =IFERROR(VLOOKUP(C15,PIVOT!A:B,2,0),0) -> 88 | K15: =J15/8 -> 11 | L15: 600 | M15: =K15*L15 -> 6600 | N15: =IFERROR(VLOOKUP(C15,PIVOT!A:F,6,0),0) -> 0 | O15: =L15/8/60 -> 1.25 | P15: =-N15*O15 -> 0 | Q15: =IFERROR(VLOOKUP(C15,PIVOT!A:C,3,0),0) -> 0 | R15: =L15/8*1.25 -> 93.75 | S15: =Q15*R15 -> 0 | T15: =IFERROR(VLOOKUP(C15,PIVOT!A:D,4,0),0) -> 0 | U15: =L15/8*0.1 -> 7.5 | V15: =T15*U15 -> 0 | W15: =IFERROR(VLOOKUP(C15,PIVOT!A:E,5,0),0) -> 0 | X15: =L15/8*1.25*0.1 -> 9.375 | Y15: =X15*W15 -> 0 | Z15: =IFERROR(VLOOKUP(C15,#REF!,6,0),0) -> 0 | AA15: =L15/8*1.3 -> 97.5 | AB15: =Z15*AA15 -> 0 | AD15: =L15/8*1.69 -> 126.75 | AE15: =AD15*AC15 -> 0 | AF15: =IFERROR(VLOOKUP(C15,#REF!,8,0),0) -> 0 | AG15: =L15/8*1.3*0.1 -> 9.75 | AH15: =AF15*AG15 -> 0 | AJ15: =L15/8*1.5 -> 112.5 | AK15: =AI15*AJ15 -> 0 | AM15: =L15/8*1.5*1.3 -> 146.25 | AN15: 0 | AP15: =L15/8*1.5*0.1 -> 11.25 | AQ15: =AO15*AP15 -> 0 | AR15: =IFERROR(VLOOKUP(C15,#REF!,7,0),0) -> 0 | AS15: =L15/8*1.3 -> 97.5 | AT15: =AR15*AS15 -> 0 | AX15: =IFERROR(VLOOKUP(C15,#REF!,8,0),0) -> 0 | AY15: =L15/8*1.3*0.1 -> 9.75 | AZ15: =AX15*AY15 -> 0 | BA15: =IFERROR(VLOOKUP(C15,#REF!,10,0),0) -> 0 | BB15: =600/8*2 -> 150 | BC15: =BA15*BB15 -> 0 | BJ15: =IFERROR(VLOOKUP(C15,#REF!,9,0),0) -> 0 | BK15: =L15/8 -> 75 | BL15: =BJ15*BK15 -> 0 | CG15: =SUM(Y15,V15,S15,P15,M15) -> 6600 | CH15: =VLOOKUP(CX15,SSS_2025!A:N,8) -> 1450 | CI15: =VLOOKUP(CX15,SSS_2025!A:N,13) -> 725 | CJ15: =VLOOKUP(CX15,SSS_2025!A:N,9) -> 10 | CK15: 391.25 | CL15: 391.25 | CM15: 200 | CN15: 200 | CO15: =CG15+CH15+CJ15+CL15+CN15 -> 8651.25 | CP15: =(M15+P15+BN15)*10% -> 660 | CQ15: =CO15+CP15 -> 9311.25 | CS15: =CQ15+CR15 -> 9311.25 | CT15: =SUM(M15+(BC15/2)+BL15+BN15+P15)/12 -> 550 | CV15: =IFERROR(VLOOKUP(C15,'[2]BILLING COMPUTATION'!$C$8:$CI$224,85,0),0) -> 8126.25 | CW15: =CG15 -> 6600 | CX15: =CV15+CW15 -> 14726.25 | CZ15: =IFERROR(VLOOKUP(C15,'[5]BILLING COMPUTATION'!$C$8:$CG$101,83,0),0) -> 8520 | DA15: =CG15 -> 6600 | DB15: =SUM(CZ15:DA15) -> 15120 | DC15: =DB15-CX15 -> 393.75
A16: 10 | C16: 32436 | D16: =VLOOKUP(E16,'F3 MS (2)'!E:F,2,0) -> GD260698 | E16: Bajamonde, Marlon San Andres | F16: =VLOOKUP(C16,'[1]ACTIVE GH'!$C:$I,7,0) -> METAL STAMPING | G16: =VLOOKUP(C16,'[1]ACTIVE GH'!$C:$J,8,0) -> PRODUCTION | H16: =VLOOKUP(C16,'[1]ACTIVE GH'!$C:$N,12,0) -> Operator 1 | I16: DL | J16: =IFERROR(VLOOKUP(C16,PIVOT!A:B,2,0),0) -> 80 | K16: =J16/8 -> 10 | L16: 600 | M16: =K16*L16 -> 6000 | N16: =IFERROR(VLOOKUP(C16,PIVOT!A:F,6,0),0) -> 0 | O16: =L16/8/60 -> 1.25 | P16: =-N16*O16 -> 0 | Q16: =IFERROR(VLOOKUP(C16,PIVOT!A:C,3,0),0) -> 8 | R16: =L16/8*1.25 -> 93.75 | S16: =Q16*R16 -> 750 | T16: =IFERROR(VLOOKUP(C16,PIVOT!A:D,4,0),0) -> 60 | U16: =L16/8*0.1 -> 7.5 | V16: =T16*U16 -> 450 | W16: =IFERROR(VLOOKUP(C16,PIVOT!A:E,5,0),0) -> 8 | X16: =L16/8*1.25*0.1 -> 9.375 | Y16: =X16*W16 -> 75 | Z16: =IFERROR(VLOOKUP(C16,#REF!,6,0),0) -> 0 | AA16: =L16/8*1.3 -> 97.5 | AB16: =Z16*AA16 -> 0 | AD16: =L16/8*1.69 -> 126.75 | AE16: =AD16*AC16 -> 0 | AF16: =IFERROR(VLOOKUP(C16,#REF!,8,0),0) -> 0 | AG16: =L16/8*1.3*0.1 -> 9.75 | AH16: =AF16*AG16 -> 0 | AJ16: =L16/8*1.5 -> 112.5 | AK16: =AI16*AJ16 -> 0 | AM16: =L16/8*1.5*1.3 -> 146.25 | AN16: 0 | AP16: =L16/8*1.5*0.1 -> 11.25 | AQ16: =AO16*AP16 -> 0 | AR16: =IFERROR(VLOOKUP(C16,#REF!,7,0),0) -> 0 | AS16: =L16/8*1.3 -> 97.5 | AT16: =AR16*AS16 -> 0 | AX16: =IFERROR(VLOOKUP(C16,#REF!,8,0),0) -> 0 | AY16: =L16/8*1.3*0.1 -> 9.75 | AZ16: =AX16*AY16 -> 0 | BA16: =IFERROR(VLOOKUP(C16,#REF!,10,0),0) -> 0 | BB16: =600/8*2 -> 150 | BC16: =BA16*BB16 -> 0 | BJ16: =IFERROR(VLOOKUP(C16,#REF!,9,0),0) -> 0 | BK16: =L16/8 -> 75 | BL16: =BJ16*BK16 -> 0 | CG16: =SUM(Y16,V16,S16,P16,M16) -> 7275 | CH16: =VLOOKUP(CX16,SSS_2025!A:N,8) -> 1800 | CI16: =VLOOKUP(CX16,SSS_2025!A:N,13) -> 900 | CJ16: =VLOOKUP(CX16,SSS_2025!A:N,9) -> 30 | CK16: 391.25 | CL16: 391.25 | CM16: 200 | CN16: 200 | CO16: =CG16+CH16+CJ16+CL16+CN16 -> 9696.25 | CP16: =(M16+P16+BN16)*10% -> 600 | CQ16: =CO16+CP16 -> 10296.25 | CS16: =CQ16+CR16 -> 10296.25 | CT16: =SUM(M16+(BC16/2)+BL16+BN16+P16)/12 -> 500 | CV16: =IFERROR(VLOOKUP(C16,'[2]BILLING COMPUTATION'!$C$8:$CI$224,85,0),0) -> 10492.5 | CW16: =CG16 -> 7275 | CX16: =CV16+CW16 -> 17767.5 | CZ16: =IFERROR(VLOOKUP(C16,'[5]BILLING COMPUTATION'!$C$8:$CG$101,83,0),0) -> 7871.25 | DA16: =CG16 -> 7275 | DB16: =SUM(CZ16:DA16) -> 15146.25 | DC16: =DB16-CX16 -> -2621.25
A17: 11 | C17: 14760 | D17: =VLOOKUP(E17,'F3 MS (2)'!E:F,2,0) -> GD250201 | E17: Balba, Christopher Laloma | F17: =VLOOKUP(C17,'[1]ACTIVE GH'!$C:$I,7,0) -> METAL STAMPING | G17: =VLOOKUP(C17,'[1]ACTIVE GH'!$C:$J,8,0) -> PRODUCTION | H17: =VLOOKUP(C17,'[1]ACTIVE GH'!$C:$N,12,0) -> Operator 1 | I17: DL | J17: =IFERROR(VLOOKUP(C17,PIVOT!A:B,2,0),0) -> 88 | K17: =J17/8 -> 11 | L17: 600 | M17: =K17*L17 -> 6600 | N17: =IFERROR(VLOOKUP(C17,PIVOT!A:F,6,0),0) -> 0 | O17: =L17/8/60 -> 1.25 | P17: =-N17*O17 -> 0 | Q17: =IFERROR(VLOOKUP(C17,PIVOT!A:C,3,0),0) -> 14 | R17: =L17/8*1.25 -> 93.75 | S17: =Q17*R17 -> 1312.5 | T17: =IFERROR(VLOOKUP(C17,PIVOT!A:D,4,0),0) -> 66 | U17: =L17/8*0.1 -> 7.5 | V17: =T17*U17 -> 495 | W17: =IFERROR(VLOOKUP(C17,PIVOT!A:E,5,0),0) -> 14 | X17: =L17/8*1.25*0.1 -> 9.375 | Y17: =X17*W17 -> 131.25 | Z17: =IFERROR(VLOOKUP(C17,#REF!,6,0),0) -> 0 | AA17: =L17/8*1.3 -> 97.5 | AB17: =Z17*AA17 -> 0 | AD17: =L17/8*1.69 -> 126.75 | AE17: =AD17*AC17 -> 0 | AF17: =IFERROR(VLOOKUP(C17,#REF!,8,0),0) -> 0 | AG17: =L17/8*1.3*0.1 -> 9.75 | AH17: =AF17*AG17 -> 0 | AJ17: =L17/8*1.5 -> 112.5 | AK17: =AI17*AJ17 -> 0 | AM17: =L17/8*1.5*1.3 -> 146.25 | AN17: 0 | AP17: =L17/8*1.5*0.1 -> 11.25 | AQ17: =AO17*AP17 -> 0 | AR17: =IFERROR(VLOOKUP(C17,#REF!,7,0),0) -> 0 | AS17: =L17/8*1.3 -> 97.5 | AT17: =AR17*AS17 -> 0 | AX17: =IFERROR(VLOOKUP(C17,#REF!,8,0),0) -> 0 | AY17: =L17/8*1.3*0.1 -> 9.75 | AZ17: =AX17*AY17 -> 0 | BA17: =IFERROR(VLOOKUP(C17,#REF!,10,0),0) -> 0 | BB17: =600/8*2 -> 150 | BC17: =BA17*BB17 -> 0 | BJ17: =IFERROR(VLOOKUP(C17,#REF!,9,0),0) -> 0 | BK17: =L17/8 -> 75 | BL17: =BJ17*BK17 -> 0 | CG17: =SUM(Y17,V17,S17,P17,M17) -> 8538.75 | CH17: =VLOOKUP(CX17,SSS_2025!A:N,8) -> 1900 | CI17: =VLOOKUP(CX17,SSS_2025!A:N,13) -> 950 | CJ17: =VLOOKUP(CX17,SSS_2025!A:N,9) -> 30 | CK17: 391.25 | CL17: 391.25 | CM17: 200 | CN17: 200 | CO17: =CG17+CH17+CJ17+CL17+CN17 -> 11060 | CP17: =(M17+P17+BN17)*10% -> 660 | CQ17: =CO17+CP17 -> 11720 | CS17: =CQ17+CR17 -> 11720 | CT17: =SUM(M17+(BC17/2)+BL17+BN17+P17)/12 -> 550 | CV17: =IFERROR(VLOOKUP(C17,'[2]BILLING COMPUTATION'!$C$8:$CI$224,85,0),0) -> 10698.75 | CW17: =CG17 -> 8538.75 | CX17: =CV17+CW17 -> 19237.5 | CZ17: =IFERROR(VLOOKUP(C17,'[5]BILLING COMPUTATION'!$C$8:$CG$101,83,0),0) -> 10141.875 | DA17: =CG17 -> 8538.75 | DB17: =SUM(CZ17:DA17) -> 18680.625 | DC17: =DB17-CX17 -> -556.875
A18: 12 | C18: 30679 | D18: =VLOOKUP(E18,'F3 MS (2)'!E:F,2,0) -> GD250548 | E18: Bardon, Norly Villacruel | F18: =VLOOKUP(C18,'[1]ACTIVE GH'!$C:$I,7,0) -> METAL STAMPING | G18: =VLOOKUP(C18,'[1]ACTIVE GH'!$C:$J,8,0) -> PRODUCTION | H18: =VLOOKUP(C18,'[1]ACTIVE GH'!$C:$N,12,0) -> Operator 1 | I18: DL | J18: =IFERROR(VLOOKUP(C18,PIVOT!A:B,2,0),0) -> 88 | K18: =J18/8 -> 11 | L18: 600 | M18: =K18*L18 -> 6600 | N18: =IFERROR(VLOOKUP(C18,PIVOT!A:F,6,0),0) -> 0 | O18: =L18/8/60 -> 1.25 | P18: =-N18*O18 -> 0 | Q18: =IFERROR(VLOOKUP(C18,PIVOT!A:C,3,0),0) -> 6 | R18: =L18/8*1.25 -> 93.75 | S18: =Q18*R18 -> 562.5 | T18: =IFERROR(VLOOKUP(C18,PIVOT!A:D,4,0),0) -> 60 | U18: =L18/8*0.1 -> 7.5 | V18: =T18*U18 -> 450 | W18: =IFERROR(VLOOKUP(C18,PIVOT!A:E,5,0),0) -> 6 | X18: =L18/8*1.25*0.1 -> 9.375 | Y18: =X18*W18 -> 56.25 | Z18: =IFERROR(VLOOKUP(C18,#REF!,6,0),0) -> 0 | AA18: =L18/8*1.3 -> 97.5 | AB18: =Z18*AA18 -> 0 | AD18: =L18/8*1.69 -> 126.75 | AE18: =AD18*AC18 -> 0 | AF18: =IFERROR(VLOOKUP(C18,#REF!,8,0),0) -> 0 | AG18: =L18/8*1.3*0.1 -> 9.75 | AH18: =AF18*AG18 -> 0 | AJ18: =L18/8*1.5 -> 112.5 | AK18: =AI18*AJ18 -> 0 | AM18: =L18/8*1.5*1.3 -> 146.25 | AN18: 0 | AP18: =L18/8*1.5*0.1 -> 11.25 | AQ18: =AO18*AP18 -> 0 | AR18: =IFERROR(VLOOKUP(C18,#REF!,7,0),0) -> 0 | AS18: =L18/8*1.3 -> 97.5 | AT18: =AR18*AS18 -> 0 | AX18: =IFERROR(VLOOKUP(C18,#REF!,8,0),0) -> 0 | AY18: =L18/8*1.3*0.1 -> 9.75 | AZ18: =AX18*AY18 -> 0 | BA18: =IFERROR(VLOOKUP(C18,#REF!,10,0),0) -> 0 | BB18: =600/8*2 -> 150 | BC18: =BA18*BB18 -> 0 | BJ18: =IFERROR(VLOOKUP(C18,#REF!,9,0),0) -> 0 | BK18: =L18/8 -> 75 | BL18: =BJ18*BK18 -> 0 | CG18: =SUM(Y18,V18,S18,P18,M18) -> 7668.75 | CH18: =VLOOKUP(CX18,SSS_2025!A:N,8) -> 1850 | CI18: =VLOOKUP(CX18,SSS_2025!A:N,13) -> 925 | CJ18: =VLOOKUP(CX18,SSS_2025!A:N,9) -> 30 | CK18: 391.25 | CL18: 391.25 | CM18: 200 | CN18: 200 | CO18: =CG18+CH18+CJ18+CL18+CN18 -> 10140 | CP18: =(M18+P18+BN18)*10% -> 660 | CQ18: =CO18+CP18 -> 10800 | CS18: =CQ18+CR18 -> 10800 | CT18: =SUM(M18+(BC18/2)+BL18+BN18+P18)/12 -> 550 | CV18: =IFERROR(VLOOKUP(C18,'[2]BILLING COMPUTATION'!$C$8:$CI$224,85,0),0) -> 10698.75 | CW18: =CG18 -> 7668.75 | CX18: =CV18+CW18 -> 18367.5 | CZ18: =IFERROR(VLOOKUP(C18,'[5]BILLING COMPUTATION'!$C$8:$CG$101,83,0),0) -> 4852.5 | DA18: =CG18 -> 7668.75 | DB18: =SUM(CZ18:DA18) -> 12521.25 | DC18: =DB18-CX18 -> -5846.25
A19: 13 | C19: 7708 | D19: =VLOOKUP(E19,'F3 MS (2)'!E:F,2,0) -> GD250089 | E19: Belarmino, Jade Espenida | F19: =VLOOKUP(C19,'[1]ACTIVE GH'!$C:$I,7,0) -> METAL STAMPING | G19: =VLOOKUP(C19,'[1]ACTIVE GH'!$C:$J,8,0) -> PRODUCTION | H19: =VLOOKUP(C19,'[1]ACTIVE GH'!$C:$N,12,0) -> Operator 1 | I19: DL | J19: =IFERROR(VLOOKUP(C19,PIVOT!A:B,2,0),0) -> 96 | K19: =J19/8 -> 12 | L19: 600 | M19: =K19*L19 -> 7200 | N19: =IFERROR(VLOOKUP(C19,PIVOT!A:F,6,0),0) -> 0 | O19: =L19/8/60 -> 1.25 | P19: =-N19*O19 -> 0 | Q19: =IFERROR(VLOOKUP(C19,PIVOT!A:C,3,0),0) -> 0 | R19: =L19/8*1.25 -> 93.75 | S19: =Q19*R19 -> 0 | T19: =IFERROR(VLOOKUP(C19,PIVOT!A:D,4,0),0) -> 6 | U19: =L19/8*0.1 -> 7.5 | V19: =T19*U19 -> 45 | W19: =IFERROR(VLOOKUP(C19,PIVOT!A:E,5,0),0) -> 0 | X19: =L19/8*1.25*0.1 -> 9.375 | Y19: =X19*W19 -> 0 | Z19: =IFERROR(VLOOKUP(C19,#REF!,6,0),0) -> 0 | AA19: =L19/8*1.3 -> 97.5 | AB19: =Z19*AA19 -> 0 | AD19: =L19/8*1.69 -> 126.75 | AE19: =AD19*AC19 -> 0 | AF19: =IFERROR(VLOOKUP(C19,#REF!,8,0),0) -> 0 | AG19: =L19/8*1.3*0.1 -> 9.75 | AH19: =AF19*AG19 -> 0 | AJ19: =L19/8*1.5 -> 112.5 | AK19: =AI19*AJ19 -> 0 | AM19: =L19/8*1.5*1.3 -> 146.25 | AN19: 0 | AP19: =L19/8*1.5*0.1 -> 11.25 | AQ19: =AO19*AP19 -> 0 | AR19: =IFERROR(VLOOKUP(C19,#REF!,7,0),0) -> 0 | AS19: =L19/8*1.3 -> 97.5 | AT19: =AR19*AS19 -> 0 | AX19: =IFERROR(VLOOKUP(C19,#REF!,8,0),0) -> 0 | AY19: =L19/8*1.3*0.1 -> 9.75 | AZ19: =AX19*AY19 -> 0 | BA19: =IFERROR(VLOOKUP(C19,#REF!,10,0),0) -> 0 | BB19: =600/8*2 -> 150 | BC19: =BA19*BB19 -> 0 | BJ19: =IFERROR(VLOOKUP(C19,#REF!,9,0),0) -> 0 | BK19: =L19/8 -> 75 | BL19: =BJ19*BK19 -> 0 | CG19: =SUM(Y19,V19,S19,P19,M19) -> 7245 | CH19: =VLOOKUP(CX19,SSS_2025!A:N,8) -> 1750 | CI19: =VLOOKUP(CX19,SSS_2025!A:N,13) -> 875 | CJ19: =VLOOKUP(CX19,SSS_2025!A:N,9) -> 30 | CK19: 391.25 | CL19: 391.25 | CM19: 200 | CN19: 200 | CO19: =CG19+CH19+CJ19+CL19+CN19 -> 9616.25 | CP19: =(M19+P19+BN19)*10% -> 720 | CQ19: =CO19+CP19 -> 10336.25 | CS19: =CQ19+CR19 -> 10336.25 | CT19: =SUM(M19+(BC19/2)+BL19+BN19+P19)/12 -> 600 | CV19: =IFERROR(VLOOKUP(C19,'[2]BILLING COMPUTATION'!$C$8:$CI$224,85,0),0) -> 10192.5 | CW19: =CG19 -> 7245 | CX19: =CV19+CW19 -> 17437.5 | CZ19: =IFERROR(VLOOKUP(C19,'[5]BILLING COMPUTATION'!$C$8:$CG$101,83,0),0) -> 8430 | DA19: =CG19 -> 7245 | DB19: =SUM(CZ19:DA19) -> 15675 | DC19: =DB19-CX19 -> -1762.5
... A21: 15 | C21: 12397 | D21: =VLOOKUP(E21,'F3 MS (2)'!E:F,2,0) -> GD250185 | E21: Capuno, Janarah Nicole Ical | F21: =VLOOKUP(C21,'[1]ACTIVE GH'!$C:$I,7,0) -> METAL STAMPING | G21: =VLOOKUP(C21,'[1]ACTIVE GH'!$C:$J,8,0) -> PRODUCTION | H21: =VLOOKUP(C21,'[1]ACTIVE GH'!$C:$N,12,0) -> Operator 1 | I21: DL | J21: =IFERROR(VLOOKUP(C21,PIVOT!A:B,2,0),0) -> 96 | K21: =J21/8 -> 12 | L21: 600 | M21: =K21*L21 -> 7200 | N21: =IFERROR(VLOOKUP(C21,PIVOT!A:F,6,0),0) -> 0 | O21: =L21/8/60 -> 1.25 | P21: =-N21*O21 -> 0 | Q21: =IFERROR(VLOOKUP(C21,PIVOT!A:C,3,0),0) -> 12 | R21: =L21/8*1.25 -> 93.75 | S21: =Q21*R21 -> 1125 | T21: =IFERROR(VLOOKUP(C21,PIVOT!A:D,4,0),0) -> 0 | U21: =L21/8*0.1 -> 7.5 | V21: =T21*U21 -> 0 | W21: =IFERROR(VLOOKUP(C21,PIVOT!A:E,5,0),0) -> 0 | X21: =L21/8*1.25*0.1 -> 9.375 | Y21: =X21*W21 -> 0 | Z21: =IFERROR(VLOOKUP(C21,#REF!,6,0),0) -> 0 | AA21: =L21/8*1.3 -> 97.5 | AB21: =Z21*AA21 -> 0 | AD21: =L21/8*1.69 -> 126.75 | AE21: =AD21*AC21 -> 0 | AF21: =IFERROR(VLOOKUP(C21,#REF!,8,0),0) -> 0 | AG21: =L21/8*1.3*0.1 -> 9.75 | AH21: =AF21*AG21 -> 0 | AJ21: =L21/8*1.5 -> 112.5 | AK21: =AI21*AJ21 -> 0 | AM21: =L21/8*1.5*1.3 -> 146.25 | AN21: 0 | AP21: =L21/8*1.5*0.1 -> 11.25 | AQ21: =AO21*AP21 -> 0 | AR21: =IFERROR(VLOOKUP(C21,#REF!,7,0),0) -> 0 | AS21: =L21/8*1.3 -> 97.5 | AT21: =AR21*AS21 -> 0 | AX21: =IFERROR(VLOOKUP(C21,#REF!,8,0),0) -> 0 | AY21: =L21/8*1.3*0.1 -> 9.75 | AZ21: =AX21*AY21 -> 0 | BA21: =IFERROR(VLOOKUP(C21,#REF!,10,0),0) -> 0 | BB21: =600/8*2 -> 150 | BC21: =BA21*BB21 -> 0 | BJ21: =IFERROR(VLOOKUP(C21,#REF!,9,0),0) -> 0 | BK21: =L21/8 -> 75 | BL21: =BJ21*BK21 -> 0 | CG21: =SUM(Y21,V21,S21,P21,M21) -> 8325 | CH21: =VLOOKUP(CX21,SSS_2025!A:N,8) -> 1700 | CI21: =VLOOKUP(CX21,SSS_2025!A:N,13) -> 850 | CJ21: =VLOOKUP(CX21,SSS_2025!A:N,9) -> 30 | CK21: 391.25 | CL21: 391.25 | CM21: 200 | CN21: 200 | CO21: =CG21+CH21+CJ21+CL21+CN21 -> 10646.25 | CP21: =(M21+P21+BN21)*10% -> 720 | CQ21: =CO21+CP21 -> 11366.25 | CS21: =CQ21+CR21 -> 11366.25 | CT21: =SUM(M21+(BC21/2)+BL21+BN21+P21)/12 -> 600 | CV21: =IFERROR(VLOOKUP(C21,'[2]BILLING COMPUTATION'!$C$8:$CI$224,85,0),0) -> 8916.25 | CW21: =CG21 -> 8325 | CX21: =CV21+CW21 -> 17241.25 | CZ21: =IFERROR(VLOOKUP(C21,'[5]BILLING COMPUTATION'!$C$8:$CG$101,83,0),0) -> 9480 | DA21: =CG21 -> 8325 | DB21: =SUM(CZ21:DA21) -> 17805 | DC21: =DB21-CX21 -> 563.75
A22: 16 | C22: 32518 | D22: GD260754 | E22: Caringal, Jennylyn | F22: =VLOOKUP(D22,'[1]ACTIVE GH'!$D:$I,6,0) -> METAL STAMPING | G22: PRODUCTION | H22: Operator 1 | I22: DL | J22: =IFERROR(VLOOKUP(C22,PIVOT!A:B,2,0),0) -> 72 | K22: =J22/8 -> 9 | L22: 600 | M22: =K22*L22 -> 5400 | N22: =IFERROR(VLOOKUP(C22,PIVOT!A:F,6,0),0) -> 0 | O22: =L22/8/60 -> 1.25 | P22: =-N22*O22 -> 0 | Q22: =IFERROR(VLOOKUP(C22,PIVOT!A:C,3,0),0) -> 14 | R22: =L22/8*1.25 -> 93.75 | S22: =Q22*R22 -> 1312.5 | T22: =IFERROR(VLOOKUP(C22,PIVOT!A:D,4,0),0) -> 0 | U22: =L22/8*0.1 -> 7.5 | V22: =T22*U22 -> 0 | W22: =IFERROR(VLOOKUP(C22,PIVOT!A:E,5,0),0) -> 0 | X22: =L22/8*1.25*0.1 -> 9.375 | Y22: =X22*W22 -> 0 | Z22: =IFERROR(VLOOKUP(C22,#REF!,6,0),0) -> 0 | AA22: =L22/8*1.3 -> 97.5 | AB22: =Z22*AA22 -> 0 | AD22: =L22/8*1.69 -> 126.75 | AE22: =AD22*AC22 -> 0 | AF22: =IFERROR(VLOOKUP(C22,#REF!,8,0),0) -> 0 | AG22: =L22/8*1.3*0.1 -> 9.75 | AH22: =AF22*AG22 -> 0 | AJ22: =L22/8*1.5 -> 112.5 | AK22: =AI22*AJ22 -> 0 | AM22: =L22/8*1.5*1.3 -> 146.25 | AN22: 0 | AP22: =L22/8*1.5*0.1 -> 11.25 | AQ22: =AO22*AP22 -> 0 | AR22: =IFERROR(VLOOKUP(C22,#REF!,7,0),0) -> 0 | AS22: =L22/8*1.3 -> 97.5 | AT22: =AR22*AS22 -> 0 | AX22: =IFERROR(VLOOKUP(C22,#REF!,8,0),0) -> 0 | AY22: =L22/8*1.3*0.1 -> 9.75 | AZ22: =AX22*AY22 -> 0 | BA22: =IFERROR(VLOOKUP(C22,#REF!,10,0),0) -> 0 | BB22: =600/8*2 -> 150 | BC22: =BA22*BB22 -> 0 | BJ22: =IFERROR(VLOOKUP(C22,#REF!,9,0),0) -> 0 | BK22: =L22/8 -> 75 | BL22: =BJ22*BK22 -> 0 | CG22: =SUM(Y22,V22,S22,P22,M22) -> 6712.5 | CH22: =VLOOKUP(CX22,SSS_2025!A:N,8) -> 1750 | CI22: =VLOOKUP(CX22,SSS_2025!A:N,13) -> 875 | CJ22: =VLOOKUP(CX22,SSS_2025!A:N,9) -> 30 | CK22: 391.25 | CL22: 391.25 | CM22: 200 | CN22: 200 | CO22: =CG22+CH22+CJ22+CL22+CN22 -> 9083.75 | CP22: =(M22+P22+BN22)*10% -> 540 | CQ22: =CO22+CP22 -> 9623.75 | CS22: =CQ22+CR22 -> 9623.75 | CT22: =SUM(M22+(BC22/2)+BL22+BN22+P22)/12 -> 450 | CV22: =IFERROR(VLOOKUP(C22,'[2]BILLING COMPUTATION'!$C$8:$CI$224,85,0),0) -> 10621.25 | CW22: =CG22 -> 6712.5 | CX22: =CV22+CW22 -> 17333.75 | CZ22: =IFERROR(VLOOKUP(C22,'[5]BILLING COMPUTATION'!$C$8:$CG$101,83,0),0) -> 9067.5 | DA22: =CG22 -> 6712.5 | DB22: =SUM(CZ22:DA22) -> 15780 | DC22: =DB22-CX22 -> -1553.75
A23: 17 | C23: 8064 | D23: =VLOOKUP(E23,'F3 MS (2)'!E:F,2,0) -> GD250048 | E23: Caudilla, Arlene | F23: =VLOOKUP(C23,'[1]ACTIVE GH'!$C:$I,7,0) -> METAL STAMPING | G23: =VLOOKUP(C23,'[1]ACTIVE GH'!$C:$J,8,0) -> PRODUCTION | H23: =VLOOKUP(C23,'[1]ACTIVE GH'!$C:$N,12,0) -> Operator 1 | I23: DL | J23: =IFERROR(VLOOKUP(C23,PIVOT!A:B,2,0),0) -> 96 | K23: =J23/8 -> 12 | L23: 600 | M23: =K23*L23 -> 7200 | N23: =IFERROR(VLOOKUP(C23,PIVOT!A:F,6,0),0) -> 6 | O23: =L23/8/60 -> 1.25 | P23: =-N23*O23 -> -7.5 | Q23: =IFERROR(VLOOKUP(C23,PIVOT!A:C,3,0),0) -> 0 | R23: =L23/8*1.25 -> 93.75 | S23: =Q23*R23 -> 0 | T23: =IFERROR(VLOOKUP(C23,PIVOT!A:D,4,0),0) -> 66 | U23: =L23/8*0.1 -> 7.5 | V23: =T23*U23 -> 495 | W23: =IFERROR(VLOOKUP(C23,PIVOT!A:E,5,0),0) -> 0 | X23: =L23/8*1.25*0.1 -> 9.375 | Y23: =X23*W23 -> 0 | Z23: =IFERROR(VLOOKUP(C23,#REF!,6,0),0) -> 0 | AA23: =L23/8*1.3 -> 97.5 | AB23: =Z23*AA23 -> 0 | AD23: =L23/8*1.69 -> 126.75 | AE23: =AD23*AC23 -> 0 | AF23: =IFERROR(VLOOKUP(C23,#REF!,8,0),0) -> 0 | AG23: =L23/8*1.3*0.1 -> 9.75 | AH23: =AF23*AG23 -> 0 | AJ23: =L23/8*1.5 -> 112.5 | AK23: =AI23*AJ23 -> 0 | AM23: =L23/8*1.5*1.3 -> 146.25 | AN23: 0 | AP23: =L23/8*1.5*0.1 -> 11.25 | AQ23: =AO23*AP23 -> 0 | AR23: =IFERROR(VLOOKUP(C23,#REF!,7,0),0) -> 0 | AS23: =L23/8*1.3 -> 97.5 | AT23: =AR23*AS23 -> 0 | AX23: =IFERROR(VLOOKUP(C23,#REF!,8,0),0) -> 0 | AY23: =L23/8*1.3*0.1 -> 9.75 | AZ23: =AX23*AY23 -> 0 | BA23: =IFERROR(VLOOKUP(C23,#REF!,10,0),0) -> 0 | BB23: =600/8*2 -> 150 | BC23: =BA23*BB23 -> 0 | BJ23: =IFERROR(VLOOKUP(C23,#REF!,9,0),0) -> 0 | BK23: =L23/8 -> 75 | BL23: =BJ23*BK23 -> 0 | CG23: =SUM(Y23,V23,S23,P23,M23) -> 7687.5 | CH23: =VLOOKUP(CX23,SSS_2025!A:N,8) -> 1750 | CI23: =VLOOKUP(CX23,SSS_2025!A:N,13) -> 875 | CJ23: =VLOOKUP(CX23,SSS_2025!A:N,9) -> 30 | CK23: 391.25 | CL23: 391.25 | CM23: 200 | CN23: 200 | CO23: =CG23+CH23+CJ23+CL23+CN23 -> 10058.75 | CP23: =(M23+P23+BN23)*10% -> 719.25 | CQ23: =CO23+CP23 -> 10778 | CS23: =CQ23+CR23 -> 10778 | CT23: =SUM(M23+(BC23/2)+BL23+BN23+P23)/12 -> 599.375 | CV23: =IFERROR(VLOOKUP(C23,'[2]BILLING COMPUTATION'!$C$8:$CI$224,85,0),0) -> 9977.5 | CW23: =CG23 -> 7687.5 | CX23: =CV23+CW23 -> 17665 | CZ23: =IFERROR(VLOOKUP(C23,'[5]BILLING COMPUTATION'!$C$8:$CG$101,83,0),0) -> 9398.75 | DA23: =CG23 -> 7687.5 | DB23: =SUM(CZ23:DA23) -> 17086.25 | DC23: =DB23-CX23 -> -578.75
A24: 18 | C24: 12909 | D24: =VLOOKUP(E24,'F3 MS (2)'!E:F,2,0) -> GD250332 | E24: Cerda, Josephine Tirados | F24: =VLOOKUP(C24,'[1]ACTIVE GH'!$C:$I,7,0) -> METAL STAMPING | G24: =VLOOKUP(C24,'[1]ACTIVE GH'!$C:$J,8,0) -> PRODUCTION | H24: =VLOOKUP(C24,'[1]ACTIVE GH'!$C:$N,12,0) -> Operator 1 | I24: DL | J24: =IFERROR(VLOOKUP(C24,PIVOT!A:B,2,0),0) -> 80 | K24: =J24/8 -> 10 | L24: 600 | M24: =K24*L24 -> 6000 | N24: =IFERROR(VLOOKUP(C24,PIVOT!A:F,6,0),0) -> 0 | O24: =L24/8/60 -> 1.25 | P24: =-N24*O24 -> 0 | Q24: =IFERROR(VLOOKUP(C24,PIVOT!A:C,3,0),0) -> 0 | R24: =L24/8*1.25 -> 93.75 | S24: =Q24*R24 -> 0 | T24: =IFERROR(VLOOKUP(C24,PIVOT!A:D,4,0),0) -> 0 | U24: =L24/8*0.1 -> 7.5 | V24: =T24*U24 -> 0 | W24: =IFERROR(VLOOKUP(C24,PIVOT!A:E,5,0),0) -> 0 | X24: =L24/8*1.25*0.1 -> 9.375 | Y24: =X24*W24 -> 0 | Z24: =IFERROR(VLOOKUP(C24,#REF!,6,0),0) -> 0 | AA24: =L24/8*1.3 -> 97.5 | AB24: =Z24*AA24 -> 0 | AD24: =L24/8*1.69 -> 126.75 | AE24: =AD24*AC24 -> 0 | AF24: =IFERROR(VLOOKUP(C24,#REF!,8,0),0) -> 0 | AG24: =L24/8*1.3*0.1 -> 9.75 | AH24: =AF24*AG24 -> 0 | AJ24: =L24/8*1.5 -> 112.5 | AK24: =AI24*AJ24 -> 0 | AM24: =L24/8*1.5*1.3 -> 146.25 | AN24: 0 | AP24: =L24/8*1.5*0.1 -> 11.25 | AQ24: =AO24*AP24 -> 0 | AR24: =IFERROR(VLOOKUP(C24,#REF!,7,0),0) -> 0 | AS24: =L24/8*1.3 -> 97.5 | AT24: =AR24*AS24 -> 0 | AX24: =IFERROR(VLOOKUP(C24,#REF!,8,0),0) -> 0 | AY24: =L24/8*1.3*0.1 -> 9.75 | AZ24: =AX24*AY24 -> 0 | BA24: =IFERROR(VLOOKUP(C24,#REF!,10,0),0) -> 0 | BB24: =600/8*2 -> 150 | BC24: =BA24*BB24 -> 0 | BJ24: =IFERROR(VLOOKUP(C24,#REF!,9,0),0) -> 0 | BK24: =L24/8 -> 75 | BL24: =BJ24*BK24 -> 0 | CG24: =SUM(Y24,V24,S24,P24,M24) -> 6000 | CH24: =VLOOKUP(CX24,SSS_2025!A:N,8) -> 1400 | CI24: =VLOOKUP(CX24,SSS_2025!A:N,13) -> 700 | CJ24: =VLOOKUP(CX24,SSS_2025!A:N,9) -> 10 | CK24: 391.25 | CL24: 391.25 | CM24: 200 | CN24: 200 | CO24: =CG24+CH24+CJ24+CL24+CN24 -> 8001.25 | CP24: =(M24+P24+BN24)*10% -> 600 | CQ24: =CO24+CP24 -> 8601.25 | CS24: =CQ24+CR24 -> 8601.25 | CT24: =SUM(M24+(BC24/2)+BL24+BN24+P24)/12 -> 500 | CV24: =IFERROR(VLOOKUP(C24,'[3]BILLING COMPUTATION'!$C$34:$CF$34,82,0),0) -> 7800 | CW24: =CG24 -> 6000 | CX24: =CV24+CW24 -> 13800 | CZ24: =IFERROR(VLOOKUP(C24,'[5]BILLING COMPUTATION'!$C$8:$CG$101,83,0),0) -> 6600 | DA24: =CG24 -> 6000 | DB24: =SUM(CZ24:DA24) -> 12600 | DC24: =DB24-CX24 -> -1200
A25: 19 | C25: 30293 | D25: =VLOOKUP(E25,'F3 MS (2)'!E:F,2,0) -> GD250531 | E25: Conzaga, Anna Fe Acopio | F25: =VLOOKUP(C25,'[1]ACTIVE GH'!$C:$I,7,0) -> METAL STAMPING | G25: =VLOOKUP(C25,'[1]ACTIVE GH'!$C:$J,8,0) -> PRODUCTION | H25: =VLOOKUP(C25,'[1]ACTIVE GH'!$C:$N,12,0) -> Operator 1 | I25: DL | J25: =IFERROR(VLOOKUP(C25,PIVOT!A:B,2,0),0) -> 96 | K25: =J25/8 -> 12 | L25: 600 | M25: =K25*L25 -> 7200 | N25: =IFERROR(VLOOKUP(C25,PIVOT!A:F,6,0),0) -> 0 | O25: =L25/8/60 -> 1.25 | P25: =-N25*O25 -> 0 | Q25: =IFERROR(VLOOKUP(C25,PIVOT!A:C,3,0),0) -> 20 | R25: =L25/8*1.25 -> 93.75 | S25: =Q25*R25 -> 1875 | T25: =IFERROR(VLOOKUP(C25,PIVOT!A:D,4,0),0) -> 0 | U25: =L25/8*0.1 -> 7.5 | V25: =T25*U25 -> 0 | W25: =IFERROR(VLOOKUP(C25,PIVOT!A:E,5,0),0) -> 0 | X25: =L25/8*1.25*0.1 -> 9.375 | Y25: =X25*W25 -> 0 | Z25: =IFERROR(VLOOKUP(C25,#REF!,6,0),0) -> 0 | AA25: =L25/8*1.3 -> 97.5 | AB25: =Z25*AA25 -> 0 | AD25: =L25/8*1.69 -> 126.75 | AE25: =AD25*AC25 -> 0 | AF25: =IFERROR(VLOOKUP(C25,#REF!,8,0),0) -> 0 | AG25: =L25/8*1.3*0.1 -> 9.75 | AH25: =AF25*AG25 -> 0 | AJ25: =L25/8*1.5 -> 112.5 | AK25: =AI25*AJ25 -> 0 | AM25: =L25/8*1.5*1.3 -> 146.25 | AN25: 0 | AP25: =L25/8*1.5*0.1 -> 11.25 | AQ25: =AO25*AP25 -> 0 | AR25: =IFERROR(VLOOKUP(C25,#REF!,7,0),0) -> 0 | AS25: =L25/8*1.3 -> 97.5 | AT25: =AR25*AS25 -> 0 | AX25: =IFERROR(VLOOKUP(C25,#REF!,8,0),0) -> 0 | AY25: =L25/8*1.3*0.1 -> 9.75 | AZ25: =AX25*AY25 -> 0 | BA25: =IFERROR(VLOOKUP(C25,#REF!,10,0),0) -> 0 | BB25: =600/8*2 -> 150 | BC25: =BA25*BB25 -> 0 | BJ25: =IFERROR(VLOOKUP(C25,#REF!,9,0),0) -> 0 | BK25: =L25/8 -> 75 | BL25: =BJ25*BK25 -> 0 | CG25: =SUM(Y25,V25,S25,P25,M25) -> 9075 | CH25: =VLOOKUP(CX25,SSS_2025!A:N,8) -> 1950 | CI25: =VLOOKUP(CX25,SSS_2025!A:N,13) -> 975 | CJ25: =VLOOKUP(CX25,SSS_2025!A:N,9) -> 30 | CK25: 391.25 | CL25: 391.25 | CM25: 200 | CN25: 200 | CO25: =CG25+CH25+CJ25+CL25+CN25 -> 11646.25 | CP25: =(M25+P25+BN25)*10% -> 720 | CQ25: =CO25+CP25 -> 12366.25 | CS25: =CQ25+CR25 -> 12366.25 | CT25: =SUM(M25+(BC25/2)+BL25+BN25+P25)/12 -> 600 | CV25: =IFERROR(VLOOKUP(C25,'[2]BILLING COMPUTATION'!$C$8:$CI$224,85,0),0) -> 10305 | CW25: =CG25 -> 9075 | CX25: =CV25+CW25 -> 19380 | CZ25: =IFERROR(VLOOKUP(C25,'[5]BILLING COMPUTATION'!$C$8:$CG$101,83,0),0) -> 10747.5 | DA25: =CG25 -> 9075 | DB25: =SUM(CZ25:DA25) -> 19822.5 | DC25: =DB25-CX25 -> 442.5
A26: 20 | C26: 11863 | D26: =VLOOKUP(E26,'F3 MS (2)'!E:F,2,0) -> GD250159 | E26: Cortez, Armin Padis | F26: =VLOOKUP(C26,'[1]ACTIVE GH'!$C:$I,7,0) -> METAL STAMPING | G26: =VLOOKUP(C26,'[1]ACTIVE GH'!$C:$J,8,0) -> PRODUCTION | H26: =VLOOKUP(C26,'[1]ACTIVE GH'!$C:$N,12,0) -> Operator 1 | I26: DL | J26: =IFERROR(VLOOKUP(C26,PIVOT!A:B,2,0),0) -> 96 | K26: =J26/8 -> 12 | L26: 600 | M26: =K26*L26 -> 7200 | N26: =IFERROR(VLOOKUP(C26,PIVOT!A:F,6,0),0) -> 0 | O26: =L26/8/60 -> 1.25 | P26: =-N26*O26 -> 0 | Q26: =IFERROR(VLOOKUP(C26,PIVOT!A:C,3,0),0) -> 0 | R26: =L26/8*1.25 -> 93.75 | S26: =Q26*R26 -> 0 | T26: =IFERROR(VLOOKUP(C26,PIVOT!A:D,4,0),0) -> 6 | U26: =L26/8*0.1 -> 7.5 | V26: =T26*U26 -> 45 | W26: =IFERROR(VLOOKUP(C26,PIVOT!A:E,5,0),0) -> 0 | X26: =L26/8*1.25*0.1 -> 9.375 | Y26: =X26*W26 -> 0 | Z26: =IFERROR(VLOOKUP(C26,#REF!,6,0),0) -> 0 | AA26: =L26/8*1.3 -> 97.5 | AB26: =Z26*AA26 -> 0 | AD26: =L26/8*1.69 -> 126.75 | AE26: =AD26*AC26 -> 0 | AF26: =IFERROR(VLOOKUP(C26,#REF!,8,0),0) -> 0 | AG26: =L26/8*1.3*0.1 -> 9.75 | AH26: =AF26*AG26 -> 0 | AJ26: =L26/8*1.5 -> 112.5 | AK26: =AI26*AJ26 -> 0 | AM26: =L26/8*1.5*1.3 -> 146.25 | AN26: 0 | AP26: =L26/8*1.5*0.1 -> 11.25 | AQ26: =AO26*AP26 -> 0 | AR26: =IFERROR(VLOOKUP(C26,#REF!,7,0),0) -> 0 | AS26: =L26/8*1.3 -> 97.5 | AT26: =AR26*AS26 -> 0 | AX26: =IFERROR(VLOOKUP(C26,#REF!,8,0),0) -> 0 | AY26: =L26/8*1.3*0.1 -> 9.75 | AZ26: =AX26*AY26 -> 0 | BA26: =IFERROR(VLOOKUP(C26,#REF!,10,0),0) -> 0 | BB26: =600/8*2 -> 150 | BC26: =BA26*BB26 -> 0 | BJ26: =IFERROR(VLOOKUP(C26,#REF!,9,0),0) -> 0 | BK26: =L26/8 -> 75 | BL26: =BJ26*BK26 -> 0 | CG26: =SUM(Y26,V26,S26,P26,M26) -> 7245 | CH26: =VLOOKUP(CX26,SSS_2025!A:N,8) -> 1900 | CI26: =VLOOKUP(CX26,SSS_2025!A:N,13) -> 950 | CJ26: =VLOOKUP(CX26,SSS_2025!A:N,9) -> 30 | CK26: 391.25 | CL26: 391.25 | CM26: 200 | CN26: 200 | CO26: =CG26+CH26+CJ26+CL26+CN26 -> 9766.25 | CP26: =(M26+P26+BN26)*10% -> 720 | CQ26: =CO26+CP26 -> 10486.25 | CS26: =CQ26+CR26 -> 10486.25 | CT26: =SUM(M26+(BC26/2)+BL26+BN26+P26)/12 -> 600 | CV26: =IFERROR(VLOOKUP(C26,'[2]BILLING COMPUTATION'!$C$8:$CI$224,85,0),0) -> 11610 | CW26: =CG26 -> 7245 | CX26: =CV26+CW26 -> 18855 | CZ26: =IFERROR(VLOOKUP(C26,'[5]BILLING COMPUTATION'!$C$8:$CG$101,83,0),0) -> 8585 | DA26: =CG26 -> 7245 | DB26: =SUM(CZ26:DA26) -> 15830 | DC26: =DB26-CX26 -> -3025
A27: 21 | C27: 30261 | D27: =VLOOKUP(E27,'F3 MS (2)'!E:F,2,0) -> GD250522 | E27: Dado, Jerome Romero | F27: =VLOOKUP(C27,'[1]ACTIVE GH'!$C:$I,7,0) -> METAL STAMPING | G27: =VLOOKUP(C27,'[1]ACTIVE GH'!$C:$J,8,0) -> PRODUCTION | H27: =VLOOKUP(C27,'[1]ACTIVE GH'!$C:$N,12,0) -> Operator 1 | I27: DL | J27: =IFERROR(VLOOKUP(C27,PIVOT!A:B,2,0),0) -> 80 | K27: =J27/8 -> 10 | L27: 600 | M27: =K27*L27 -> 6000 | N27: =IFERROR(VLOOKUP(C27,PIVOT!A:F,6,0),0) -> 0 | O27: =L27/8/60 -> 1.25 | P27: =-N27*O27 -> 0 | Q27: =IFERROR(VLOOKUP(C27,PIVOT!A:C,3,0),0) -> 6 | R27: =L27/8*1.25 -> 93.75 | S27: =Q27*R27 -> 562.5 | T27: =IFERROR(VLOOKUP(C27,PIVOT!A:D,4,0),0) -> 0 | U27: =L27/8*0.1 -> 7.5 | V27: =T27*U27 -> 0 | W27: =IFERROR(VLOOKUP(C27,PIVOT!A:E,5,0),0) -> 0 | X27: =L27/8*1.25*0.1 -> 9.375 | Y27: =X27*W27 -> 0 | Z27: =IFERROR(VLOOKUP(C27,#REF!,6,0),0) -> 0 | AA27: =L27/8*1.3 -> 97.5 | AB27: =Z27*AA27 -> 0 | AD27: =L27/8*1.69 -> 126.75 | AE27: =AD27*AC27 -> 0 | AF27: =IFERROR(VLOOKUP(C27,#REF!,8,0),0) -> 0 | AG27: =L27/8*1.3*0.1 -> 9.75 | AH27: =AF27*AG27 -> 0 | AJ27: =L27/8*1.5 -> 112.5 | AK27: =AI27*AJ27 -> 0 | AM27: =L27/8*1.5*1.3 -> 146.25 | AN27: 0 | AP27: =L27/8*1.5*0.1 -> 11.25 | AQ27: =AO27*AP27 -> 0 | AR27: =IFERROR(VLOOKUP(C27,#REF!,7,0),0) -> 0 | AS27: =L27/8*1.3 -> 97.5 | AT27: =AR27*AS27 -> 0 | AX27: =IFERROR(VLOOKUP(C27,#REF!,8,0),0) -> 0 | AY27: =L27/8*1.3*0.1 -> 9.75 | AZ27: =AX27*AY27 -> 0 | BA27: =IFERROR(VLOOKUP(C27,#REF!,10,0),0) -> 0 | BB27: =600/8*2 -> 150 | BC27: =BA27*BB27 -> 0 | BJ27: =IFERROR(VLOOKUP(C27,#REF!,9,0),0) -> 0 | BK27: =L27/8 -> 75 | BL27: =BJ27*BK27 -> 0 | CG27: =SUM(Y27,V27,S27,P27,M27) -> 6562.5 | CH27: =VLOOKUP(CX27,SSS_2025!A:N,8) -> 1700 | CI27: =VLOOKUP(CX27,SSS_2025!A:N,13) -> 850 | CJ27: =VLOOKUP(CX27,SSS_2025!A:N,9) -> 30 | CK27: 391.25 | CL27: 391.25 | CM27: 200 | CN27: 200 | CO27: =CG27+CH27+CJ27+CL27+CN27 -> 8883.75 | CP27: =(M27+P27+BN27)*10% -> 600 | CQ27: =CO27+CP27 -> 9483.75 | CS27: =CQ27+CR27 -> 9483.75 | CT27: =SUM(M27+(BC27/2)+BL27+BN27+P27)/12 -> 500 | CV27: =IFERROR(VLOOKUP(C27,'[2]BILLING COMPUTATION'!$C$8:$CI$224,85,0),0) -> 10346.25 | CW27: =CG27 -> 6562.5 | CX27: =CV27+CW27 -> 16908.75 | CZ27: =IFERROR(VLOOKUP(C27,'[5]BILLING COMPUTATION'!$C$8:$CG$101,83,0),0) -> 7388.75 | DA27: =CG27 -> 6562.5 | DB27: =SUM(CZ27:DA27) -> 13951.25 | DC27: =DB27-CX27 -> -2957.5
A28: 22 | C28: 12927 | D28: =VLOOKUP(E28,'F3 MS (2)'!E:F,2,0) -> GD250343 | E28: Dagli, Renz Jemrick Zara | F28: =VLOOKUP(C28,'[1]ACTIVE GH'!$C:$I,7,0) -> METAL STAMPING | G28: =VLOOKUP(C28,'[1]ACTIVE GH'!$C:$J,8,0) -> PRODUCTION | H28: =VLOOKUP(C28,'[1]ACTIVE GH'!$C:$N,12,0) -> Operator 1 | I28: DL | J28: =IFERROR(VLOOKUP(C28,PIVOT!A:B,2,0),0) -> 88 | K28: =J28/8 -> 11 | L28: 600 | M28: =K28*L28 -> 6600 | N28: =IFERROR(VLOOKUP(C28,PIVOT!A:F,6,0),0) -> 0 | O28: =L28/8/60 -> 1.25 | P28: =-N28*O28 -> 0 | Q28: =IFERROR(VLOOKUP(C28,PIVOT!A:C,3,0),0) -> 0 | R28: =L28/8*1.25 -> 93.75 | S28: =Q28*R28 -> 0 | T28: =IFERROR(VLOOKUP(C28,PIVOT!A:D,4,0),0) -> 6 | U28: =L28/8*0.1 -> 7.5 | V28: =T28*U28 -> 45 | W28: =IFERROR(VLOOKUP(C28,PIVOT!A:E,5,0),0) -> 0 | X28: =L28/8*1.25*0.1 -> 9.375 | Y28: =X28*W28 -> 0 | Z28: =IFERROR(VLOOKUP(C28,#REF!,6,0),0) -> 0 | AA28: =L28/8*1.3 -> 97.5 | AB28: =Z28*AA28 -> 0 | AD28: =L28/8*1.69 -> 126.75 | AE28: =AD28*AC28 -> 0 | AF28: =IFERROR(VLOOKUP(C28,#REF!,8,0),0) -> 0 | AG28: =L28/8*1.3*0.1 -> 9.75 | AH28: =AF28*AG28 -> 0 | AJ28: =L28/8*1.5 -> 112.5 | AK28: =AI28*AJ28 -> 0 | AM28: =L28/8*1.5*1.3 -> 146.25 | AN28: 0 | AP28: =L28/8*1.5*0.1 -> 11.25 | AQ28: =AO28*AP28 -> 0 | AR28: =IFERROR(VLOOKUP(C28,#REF!,7,0),0) -> 0 | AS28: =L28/8*1.3 -> 97.5 | AT28: =AR28*AS28 -> 0 | AX28: =IFERROR(VLOOKUP(C28,#REF!,8,0),0) -> 0 | AY28: =L28/8*1.3*0.1 -> 9.75 | AZ28: =AX28*AY28 -> 0 | BA28: =IFERROR(VLOOKUP(C28,#REF!,10,0),0) -> 0 | BB28: =600/8*2 -> 150 | BC28: =BA28*BB28 -> 0 | BJ28: =IFERROR(VLOOKUP(C28,#REF!,9,0),0) -> 0 | BK28: =L28/8 -> 75 | BL28: =BJ28*BK28 -> 0 | CG28: =SUM(Y28,V28,S28,P28,M28) -> 6645 | CH28: =VLOOKUP(CX28,SSS_2025!A:N,8) -> 1800 | CI28: =VLOOKUP(CX28,SSS_2025!A:N,13) -> 900 | CJ28: =VLOOKUP(CX28,SSS_2025!A:N,9) -> 30 | CK28: 391.25 | CL28: 391.25 | CM28: 200 | CN28: 200 | CO28: =CG28+CH28+CJ28+CL28+CN28 -> 9066.25 | CP28: =(M28+P28+BN28)*10% -> 660 | CQ28: =CO28+CP28 -> 9726.25 | CS28: =CQ28+CR28 -> 9726.25 | CT28: =SUM(M28+(BC28/2)+BL28+BN28+P28)/12 -> 550 | CV28: =IFERROR(VLOOKUP(C28,'[2]BILLING COMPUTATION'!$C$8:$CI$224,85,0),0) -> 11422.5 | CW28: =CG28 -> 6645 | CX28: =CV28+CW28 -> 18067.5 | CZ28: =IFERROR(VLOOKUP(C28,'[5]BILLING COMPUTATION'!$C$8:$CG$101,83,0),0) -> 8448.75 | DA28: =CG28 -> 6645 | DB28: =SUM(CZ28:DA28) -> 15093.75 | DC28: =DB28-CX28 -> -2973.75
A29: 23 | C29: 32242 | D29: =VLOOKUP(E29,'F3 MS (2)'!E:F,2,0) -> GD260733 | E29: De Chavez,Joe Antenor | F29: =VLOOKUP(C29,'[1]ACTIVE GH'!$C:$I,7,0) -> METAL STAMPING | G29: =VLOOKUP(C29,'[1]ACTIVE GH'!$C:$J,8,0) -> PRODUCTION | H29: =VLOOKUP(C29,'[1]ACTIVE GH'!$C:$N,12,0) -> Operator 1 | I29: DL | J29: =IFERROR(VLOOKUP(C29,PIVOT!A:B,2,0),0) -> 0 | K29: =J29/8 -> 0 | L29: 600 | M29: =K29*L29 -> 0 | N29: =IFERROR(VLOOKUP(C29,PIVOT!A:F,6,0),0) -> 0 | O29: =L29/8/60 -> 1.25 | P29: =-N29*O29 -> 0 | Q29: =IFERROR(VLOOKUP(C29,PIVOT!A:C,3,0),0) -> 0 | R29: =L29/8*1.25 -> 93.75 | S29: =Q29*R29 -> 0 | T29: =IFERROR(VLOOKUP(C29,PIVOT!A:D,4,0),0) -> 0 | U29: =L29/8*0.1 -> 7.5 | V29: =T29*U29 -> 0 | W29: =IFERROR(VLOOKUP(C29,PIVOT!A:E,5,0),0) -> 0 | X29: =L29/8*1.25*0.1 -> 9.375 | Y29: =X29*W29 -> 0 | Z29: =IFERROR(VLOOKUP(C29,#REF!,6,0),0) -> 0 | AA29: =L29/8*1.3 -> 97.5 | AB29: =Z29*AA29 -> 0 | AD29: =L29/8*1.69 -> 126.75 | AE29: =AD29*AC29 -> 0 | AF29: =IFERROR(VLOOKUP(C29,#REF!,8,0),0) -> 0 | AG29: =L29/8*1.3*0.1 -> 9.75 | AH29: =AF29*AG29 -> 0 | AJ29: =L29/8*1.5 -> 112.5 | AK29: =AI29*AJ29 -> 0 | AM29: =L29/8*1.5*1.3 -> 146.25 | AN29: 0 | AP29: =L29/8*1.5*0.1 -> 11.25 | AQ29: =AO29*AP29 -> 0 | AR29: =IFERROR(VLOOKUP(C29,#REF!,7,0),0) -> 0 | AS29: =L29/8*1.3 -> 97.5 | AT29: =AR29*AS29 -> 0 | AX29: =IFERROR(VLOOKUP(C29,#REF!,8,0),0) -> 0 | AY29: =L29/8*1.3*0.1 -> 9.75 | AZ29: =AX29*AY29 -> 0 | BA29: =IFERROR(VLOOKUP(C29,#REF!,10,0),0) -> 0 | BB29: =600/8*2 -> 150 | BC29: =BA29*BB29 -> 0 | BJ29: =IFERROR(VLOOKUP(C29,#REF!,9,0),0) -> 0 | BK29: =L29/8 -> 75 | BL29: =BJ29*BK29 -> 0 | CG29: =SUM(Y29,V29,S29,P29,M29) -> 0 | CO29: =CG29+CH29+CJ29+CL29+CN29 -> 0 | CP29: =(M29+P29+BN29)*10% -> 0 | CQ29: =CO29+CP29 -> 0 | CS29: =CQ29+CR29 -> 0 | CT29: =SUM(M29+(BC29/2)+BL29+BN29+P29)/12 -> 0 | CV29: =IFERROR(VLOOKUP(C29,'[2]BILLING COMPUTATION'!$C$8:$CI$224,85,0),0) -> 9389.25 | CW29: =CG29 -> 0 | CX29: =CV29+CW29 -> 9389.25 | CZ29: =IFERROR(VLOOKUP(C29,'[5]BILLING COMPUTATION'!$C$8:$CG$101,83,0),0) -> 600 | DA29: =CG29 -> 0 | DB29: =SUM(CZ29:DA29) -> 600 | DC29: =DB29-CX29 -> -8789.25
A30: 24 | C30: 14473 | D30: =VLOOKUP(E30,'F3 MS (2)'!E:F,2,0) -> GD250254 | E30: De Jesus, John Lorren Liwanag | F30: =VLOOKUP(C30,'[1]ACTIVE GH'!$C:$I,7,0) -> METAL STAMPING | G30: =VLOOKUP(C30,'[1]ACTIVE GH'!$C:$J,8,0) -> PRODUCTION | H30: =VLOOKUP(C30,'[1]ACTIVE GH'!$C:$N,12,0) -> Operator 1 | I30: DL | J30: =IFERROR(VLOOKUP(C30,PIVOT!A:B,2,0),0) -> 64 | K30: =J30/8 -> 8 | L30: 600 | M30: =K30*L30 -> 4800 | N30: =IFERROR(VLOOKUP(C30,PIVOT!A:F,6,0),0) -> 0 | O30: =L30/8/60 -> 1.25 | P30: =-N30*O30 -> 0 | Q30: =IFERROR(VLOOKUP(C30,PIVOT!A:C,3,0),0) -> 6 | R30: =L30/8*1.25 -> 93.75 | S30: =Q30*R30 -> 562.5 | T30: =IFERROR(VLOOKUP(C30,PIVOT!A:D,4,0),0) -> 0 | U30: =L30/8*0.1 -> 7.5 | V30: =T30*U30 -> 0 | W30: =IFERROR(VLOOKUP(C30,PIVOT!A:E,5,0),0) -> 0 | X30: =L30/8*1.25*0.1 -> 9.375 | Y30: =X30*W30 -> 0 | Z30: =IFERROR(VLOOKUP(C30,#REF!,6,0),0) -> 0 | AA30: =L30/8*1.3 -> 97.5 | AB30: =Z30*AA30 -> 0 | AD30: =L30/8*1.69 -> 126.75 | AE30: =AD30*AC30 -> 0 | AF30: =IFERROR(VLOOKUP(C30,#REF!,8,0),0) -> 0 | AG30: =L30/8*1.3*0.1 -> 9.75 | AH30: =AF30*AG30 -> 0 | AJ30: =L30/8*1.5 -> 112.5 | AK30: =AI30*AJ30 -> 0 | AM30: =L30/8*1.5*1.3 -> 146.25 | AN30: 0 | AP30: =L30/8*1.5*0.1 -> 11.25 | AQ30: =AO30*AP30 -> 0 | AR30: =IFERROR(VLOOKUP(C30,#REF!,7,0),0) -> 0 | AS30: =L30/8*1.3 -> 97.5 | AT30: =AR30*AS30 -> 0 | AX30: =IFERROR(VLOOKUP(C30,#REF!,8,0),0) -> 0 | AY30: =L30/8*1.3*0.1 -> 9.75 | AZ30: =AX30*AY30 -> 0 | BA30: =IFERROR(VLOOKUP(C30,#REF!,10,0),0) -> 0 | BB30: =600/8*2 -> 150 | BC30: =BA30*BB30 -> 0 | BJ30: =IFERROR(VLOOKUP(C30,#REF!,9,0),0) -> 0 | BK30: =L30/8 -> 75 | BL30: =BJ30*BK30 -> 0 | CG30: =SUM(Y30,V30,S30,P30,M30) -> 5362.5 | CH30: =VLOOKUP(CX30,SSS_2025!A:N,8) -> 1600 | CI30: =VLOOKUP(CX30,SSS_2025!A:N,13) -> 800 | CJ30: =VLOOKUP(CX30,SSS_2025!A:N,9) -> 30 | CK30: 391.25 | CL30: 391.25 | CM30: 200 | CN30: 200 | CO30: =CG30+CH30+CJ30+CL30+CN30 -> 7583.75 | CP30: =(M30+P30+BN30)*10% -> 480 | CQ30: =CO30+CP30 -> 8063.75 | CS30: =CQ30+CR30 -> 8063.75 | CT30: =SUM(M30+(BC30/2)+BL30+BN30+P30)/12 -> 400 | CV30: =IFERROR(VLOOKUP(C30,'[2]BILLING COMPUTATION'!$C$8:$CI$224,85,0),0) -> 10680 | CW30: =CG30 -> 5362.5 | CX30: =CV30+CW30 -> 16042.5 | CZ30: =IFERROR(VLOOKUP(C30,'[5]BILLING COMPUTATION'!$C$8:$CG$101,83,0),0) -> 10860 | DA30: =CG30 -> 5362.5 | DB30: =SUM(CZ30:DA30) -> 16222.5 | DC30: =DB30-CX30 -> 180
A31: 25 | C31: 5585 | D31: =VLOOKUP(E31,'F3 MS (2)'!E:F,2,0) -> GD250031 | E31: De Leon, Jenny Sinodlay | F31: =VLOOKUP(C31,'[1]ACTIVE GH'!$C:$I,7,0) -> METAL STAMPING | G31: =VLOOKUP(C31,'[1]ACTIVE GH'!$C:$J,8,0) -> PRODUCTION | H31: =VLOOKUP(C31,'[1]ACTIVE GH'!$C:$N,12,0) -> Operator 1 | I31: DL | J31: =IFERROR(VLOOKUP(C31,PIVOT!A:B,2,0),0) -> 96 | K31: =J31/8 -> 12 | L31: 600 | M31: =K31*L31 -> 7200 | N31: =IFERROR(VLOOKUP(C31,PIVOT!A:F,6,0),0) -> 0 | O31: =L31/8/60 -> 1.25 | P31: =-N31*O31 -> 0 | Q31: =IFERROR(VLOOKUP(C31,PIVOT!A:C,3,0),0) -> 10 | R31: =L31/8*1.25 -> 93.75 | S31: =Q31*R31 -> 937.5 | T31: =IFERROR(VLOOKUP(C31,PIVOT!A:D,4,0),0) -> 66 | U31: =L31/8*0.1 -> 7.5 | V31: =T31*U31 -> 495 | W31: =IFERROR(VLOOKUP(C31,PIVOT!A:E,5,0),0) -> 10 | X31: =L31/8*1.25*0.1 -> 9.375 | Y31: =X31*W31 -> 93.75 | Z31: =IFERROR(VLOOKUP(C31,#REF!,6,0),0) -> 0 | AA31: =L31/8*1.3 -> 97.5 | AB31: =Z31*AA31 -> 0 | AD31: =L31/8*1.69 -> 126.75 | AE31: =AD31*AC31 -> 0 | AF31: =IFERROR(VLOOKUP(C31,#REF!,8,0),0) -> 0 | AG31: =L31/8*1.3*0.1 -> 9.75 | AH31: =AF31*AG31 -> 0 | AJ31: =L31/8*1.5 -> 112.5 | AK31: =AI31*AJ31 -> 0 | AM31: =L31/8*1.5*1.3 -> 146.25 | AN31: 0 | AP31: =L31/8*1.5*0.1 -> 11.25 | AQ31: =AO31*AP31 -> 0 | AR31: =IFERROR(VLOOKUP(C31,#REF!,7,0),0) -> 0 | AS31: =L31/8*1.3 -> 97.5 | AT31: =AR31*AS31 -> 0 | AX31: =IFERROR(VLOOKUP(C31,#REF!,8,0),0) -> 0 | AY31: =L31/8*1.3*0.1 -> 9.75 | AZ31: =AX31*AY31 -> 0 | BA31: =IFERROR(VLOOKUP(C31,#REF!,10,0),0) -> 0 | BB31: =600/8*2 -> 150 | BC31: =BA31*BB31 -> 0 | BJ31: =IFERROR(VLOOKUP(C31,#REF!,9,0),0) -> 0 | BK31: =L31/8 -> 75 | BL31: =BJ31*BK31 -> 0 | CG31: =SUM(Y31,V31,S31,P31,M31) -> 8726.25 | CH31: =VLOOKUP(CX31,SSS_2025!A:N,8) -> 1950 | CI31: =VLOOKUP(CX31,SSS_2025!A:N,13) -> 975 | CJ31: =VLOOKUP(CX31,SSS_2025!A:N,9) -> 30 | CK31: 391.25 | CL31: 391.25 | CM31: 200 | CN31: 200 | CO31: =CG31+CH31+CJ31+CL31+CN31 -> 11297.5 | CP31: =(M31+P31+BN31)*10% -> 720 | CQ31: =CO31+CP31 -> 12017.5 | CS31: =CQ31+CR31 -> 12017.5 | CT31: =SUM(M31+(BC31/2)+BL31+BN31+P31)/12 -> 600 | CV31: =IFERROR(VLOOKUP(C31,'[2]BILLING COMPUTATION'!$C$8:$CI$224,85,0),0) -> 10698.75 | CW31: =CG31 -> 8726.25 | CX31: =CV31+CW31 -> 19425 | CZ31: =IFERROR(VLOOKUP(C31,'[5]BILLING COMPUTATION'!$C$8:$CG$101,83,0),0) -> 10563.75 | DA31: =CG31 -> 8726.25 | DB31: =SUM(CZ31:DA31) -> 19290 | DC31: =DB31-CX31 -> -135
A32: 26 | C32: 32457 | D32: GD260706 | E32: Deculawan, Marlon | F32: METAL STAMPING | G32: PRODUCTION | H32: Operator 1 | I32: DL | J32: =IFERROR(VLOOKUP(C32,PIVOT!A:B,2,0),0) -> 8 | K32: =J32/8 -> 1 | L32: 600 | M32: =K32*L32 -> 600 | N32: =IFERROR(VLOOKUP(C32,PIVOT!A:F,6,0),0) -> 0 | O32: =L32/8/60 -> 1.25 | P32: =-N32*O32 -> 0 | Q32: =IFERROR(VLOOKUP(C32,PIVOT!A:C,3,0),0) -> 0 | R32: =L32/8*1.25 -> 93.75 | S32: =Q32*R32 -> 0 | T32: =IFERROR(VLOOKUP(C32,PIVOT!A:D,4,0),0) -> 0 | U32: =L32/8*0.1 -> 7.5 | V32: =T32*U32 -> 0 | W32: =IFERROR(VLOOKUP(C32,PIVOT!A:E,5,0),0) -> 0 | X32: =L32/8*1.25*0.1 -> 9.375 | Y32: =X32*W32 -> 0 | Z32: =IFERROR(VLOOKUP(C32,#REF!,6,0),0) -> 0 | AA32: =L32/8*1.3 -> 97.5 | AB32: =Z32*AA32 -> 0 | AD32: =L32/8*1.69 -> 126.75 | AE32: =AD32*AC32 -> 0 | AF32: =IFERROR(VLOOKUP(C32,#REF!,8,0),0) -> 0 | AG32: =L32/8*1.3*0.1 -> 9.75 | AH32: =AF32*AG32 -> 0 | AJ32: =L32/8*1.5 -> 112.5 | AK32: =AI32*AJ32 -> 0 | AM32: =L32/8*1.5*1.3 -> 146.25 | AN32: 0 | AP32: =L32/8*1.5*0.1 -> 11.25 | AQ32: =AO32*AP32 -> 0 | AR32: =IFERROR(VLOOKUP(C32,#REF!,7,0),0) -> 0 | AS32: =L32/8*1.3 -> 97.5 | AT32: =AR32*AS32 -> 0 | AX32: =IFERROR(VLOOKUP(C32,#REF!,8,0),0) -> 0 | AY32: =L32/8*1.3*0.1 -> 9.75 | AZ32: =AX32*AY32 -> 0 | BA32: =IFERROR(VLOOKUP(C32,#REF!,10,0),0) -> 0 | BB32: =600/8*2 -> 150 | BC32: =BA32*BB32 -> 0 | BJ32: =IFERROR(VLOOKUP(C32,#REF!,9,0),0) -> 0 | BK32: =L32/8 -> 75 | BL32: =BJ32*BK32 -> 0 | CG32: =SUM(Y32,V32,S32,P32,M32) -> 600 | CO32: =CG32+CH32+CJ32+CL32+CN32 -> 600 | CP32: =(M32+P32+BN32)*10% -> 60 | CQ32: =CO32+CP32 -> 660 | CS32: =CQ32+CR32 -> 660 | CT32: =SUM(M32+(BC32/2)+BL32+BN32+P32)/12 -> 50 | CV32: =IFERROR(VLOOKUP(C32,'[2]BILLING COMPUTATION'!$C$8:$CI$224,85,0),0) -> 10698.75 | CW32: =CG32 -> 600 | CX32: =CV32+CW32 -> 11298.75 | CZ32: =IFERROR(VLOOKUP(C32,'[5]BILLING COMPUTATION'!$C$8:$CG$101,83,0),0) -> 8415 | DA32: =CG32 -> 600 | DB32: =SUM(CZ32:DA32) -> 9015 | DC32: =DB32-CX32 -> -2283.75
A33: 27 | C33: 7646 | D33: =VLOOKUP(E33,'F3 MS (2)'!E:F,2,0) -> GD250088 | E33: Delos Reyes, Renante Pernecita | F33: =VLOOKUP(C33,'[1]ACTIVE GH'!$C:$I,7,0) -> METAL STAMPING | G33: =VLOOKUP(C33,'[1]ACTIVE GH'!$C:$J,8,0) -> PRODUCTION | H33: =VLOOKUP(C33,'[1]ACTIVE GH'!$C:$N,12,0) -> Operator 1 | I33: DL | J33: =IFERROR(VLOOKUP(C33,PIVOT!A:B,2,0),0) -> 64 | K33: =J33/8 -> 8 | L33: 600 | M33: =K33*L33 -> 4800 | N33: =IFERROR(VLOOKUP(C33,PIVOT!A:F,6,0),0) -> 0 | O33: =L33/8/60 -> 1.25 | P33: =-N33*O33 -> 0 | Q33: =IFERROR(VLOOKUP(C33,PIVOT!A:C,3,0),0) -> 12 | R33: =L33/8*1.25 -> 93.75 | S33: =Q33*R33 -> 1125 | T33: =IFERROR(VLOOKUP(C33,PIVOT!A:D,4,0),0) -> 0 | U33: =L33/8*0.1 -> 7.5 | V33: =T33*U33 -> 0 | W33: =IFERROR(VLOOKUP(C33,PIVOT!A:E,5,0),0) -> 0 | X33: =L33/8*1.25*0.1 -> 9.375 | Y33: =X33*W33 -> 0 | Z33: =IFERROR(VLOOKUP(C33,#REF!,6,0),0) -> 0 | AA33: =L33/8*1.3 -> 97.5 | AB33: =Z33*AA33 -> 0 | AD33: =L33/8*1.69 -> 126.75 | AE33: =AD33*AC33 -> 0 | AF33: =IFERROR(VLOOKUP(C33,#REF!,8,0),0) -> 0 | AG33: =L33/8*1.3*0.1 -> 9.75 | AH33: =AF33*AG33 -> 0 | AJ33: =L33/8*1.5 -> 112.5 | AK33: =AI33*AJ33 -> 0 | AM33: =L33/8*1.5*1.3 -> 146.25 | AN33: 0 | AP33: =L33/8*1.5*0.1 -> 11.25 | AQ33: =AO33*AP33 -> 0 | AR33: =IFERROR(VLOOKUP(C33,#REF!,7,0),0) -> 0 | AS33: =L33/8*1.3 -> 97.5 | AT33: =AR33*AS33 -> 0 | AX33: =IFERROR(VLOOKUP(C33,#REF!,8,0),0) -> 0 | AY33: =L33/8*1.3*0.1 -> 9.75 | AZ33: =AX33*AY33 -> 0 | BA33: =IFERROR(VLOOKUP(C33,#REF!,10,0),0) -> 0 | BB33: =600/8*2 -> 150 | BC33: =BA33*BB33 -> 0 | BJ33: =IFERROR(VLOOKUP(C33,#REF!,9,0),0) -> 0 | BK33: =L33/8 -> 75 | BL33: =BJ33*BK33 -> 0 | CG33: =SUM(Y33,V33,S33,P33,M33) -> 5925 | CH33: =VLOOKUP(CX33,SSS_2025!A:N,8) -> 1400 | CI33: =VLOOKUP(CX33,SSS_2025!A:N,13) -> 700 | CJ33: =VLOOKUP(CX33,SSS_2025!A:N,9) -> 10 | CK33: 391.25 | CL33: 391.25 | CM33: 200 | CN33: 200 | CO33: =CG33+CH33+CJ33+CL33+CN33 -> 7926.25 | CP33: =(M33+P33+BN33)*10% -> 480 | CQ33: =CO33+CP33 -> 8406.25 | CS33: =CQ33+CR33 -> 8406.25 | CT33: =SUM(M33+(BC33/2)+BL33+BN33+P33)/12 -> 400 | CV33: =IFERROR(VLOOKUP(C33,'[2]BILLING COMPUTATION'!$C$8:$CI$224,85,0),0) -> 7863.75 | CW33: =CG33 -> 5925 | CX33: =CV33+CW33 -> 13788.75 | CZ33: =IFERROR(VLOOKUP(C33,'[5]BILLING COMPUTATION'!$C$8:$CG$101,83,0),0) -> 11118.75 | DA33: =CG33 -> 5925 | DB33: =SUM(CZ33:DA33) -> 17043.75 | DC33: =DB33-CX33 -> 3255
A34: 28 | C34: 12956 | D34: =VLOOKUP(E34,'F3 MS (2)'!E:F,2,0) -> GD250359 | E34: Desalisa, Mark Jay Almaida | F34: =VLOOKUP(C34,'[1]ACTIVE GH'!$C:$I,7,0) -> METAL STAMPING | G34: =VLOOKUP(C34,'[1]ACTIVE GH'!$C:$J,8,0) -> PRODUCTION | H34: =VLOOKUP(C34,'[1]ACTIVE GH'!$C:$N,12,0) -> Operator 1 | I34: DL | J34: =IFERROR(VLOOKUP(C34,PIVOT!A:B,2,0),0) -> 80 | K34: =J34/8 -> 10 | L34: 600 | M34: =K34*L34 -> 6000 | N34: =IFERROR(VLOOKUP(C34,PIVOT!A:F,6,0),0) -> 0 | O34: =L34/8/60 -> 1.25 | P34: =-N34*O34 -> 0 | Q34: =IFERROR(VLOOKUP(C34,PIVOT!A:C,3,0),0) -> 12 | R34: =L34/8*1.25 -> 93.75 | S34: =Q34*R34 -> 1125 | T34: =IFERROR(VLOOKUP(C34,PIVOT!A:D,4,0),0) -> 0 | U34: =L34/8*0.1 -> 7.5 | V34: =T34*U34 -> 0 | W34: =IFERROR(VLOOKUP(C34,PIVOT!A:E,5,0),0) -> 0 | X34: =L34/8*1.25*0.1 -> 9.375 | Y34: =X34*W34 -> 0 | Z34: =IFERROR(VLOOKUP(C34,#REF!,6,0),0) -> 0 | AA34: =L34/8*1.3 -> 97.5 | AB34: =Z34*AA34 -> 0 | AD34: =L34/8*1.69 -> 126.75 | AE34: =AD34*AC34 -> 0 | AF34: =IFERROR(VLOOKUP(C34,#REF!,8,0),0) -> 0 | AG34: =L34/8*1.3*0.1 -> 9.75 | AH34: =AF34*AG34 -> 0 | AJ34: =L34/8*1.5 -> 112.5 | AK34: =AI34*AJ34 -> 0 | AM34: =L34/8*1.5*1.3 -> 146.25 | AN34: 0 | AP34: =L34/8*1.5*0.1 -> 11.25 | AQ34: =AO34*AP34 -> 0 | AR34: =IFERROR(VLOOKUP(C34,#REF!,7,0),0) -> 0 | AS34: =L34/8*1.3 -> 97.5 | AT34: =AR34*AS34 -> 0 | AX34: =IFERROR(VLOOKUP(C34,#REF!,8,0),0) -> 0 | AY34: =L34/8*1.3*0.1 -> 9.75 | AZ34: =AX34*AY34 -> 0 | BA34: =IFERROR(VLOOKUP(C34,#REF!,10,0),0) -> 0 | BB34: =600/8*2 -> 150 | BC34: =BA34*BB34 -> 0 | BJ34: =IFERROR(VLOOKUP(C34,#REF!,9,0),0) -> 0 | BK34: =L34/8 -> 75 | BL34: =BJ34*BK34 -> 0 | CG34: =SUM(Y34,V34,S34,P34,M34) -> 7125 | CH34: =VLOOKUP(CX34,SSS_2025!A:N,8) -> 1800 | CI34: =VLOOKUP(CX34,SSS_2025!A:N,13) -> 900 | CJ34: =VLOOKUP(CX34,SSS_2025!A:N,9) -> 30 | CK34: 391.25 | CL34: 391.25 | CM34: 200 | CN34: 200 | CO34: =CG34+CH34+CJ34+CL34+CN34 -> 9546.25 | CP34: =(M34+P34+BN34)*10% -> 600 | CQ34: =CO34+CP34 -> 10146.25 | CS34: =CQ34+CR34 -> 10146.25 | CT34: =SUM(M34+(BC34/2)+BL34+BN34+P34)/12 -> 500 | CV34: =IFERROR(VLOOKUP(C34,'[2]BILLING COMPUTATION'!$C$8:$CI$224,85,0),0) -> 10680 | CW34: =CG34 -> 7125 | CX34: =CV34+CW34 -> 17805 | CZ34: =IFERROR(VLOOKUP(C34,'[5]BILLING COMPUTATION'!$C$8:$CG$101,83,0),0) -> 7863.75 | DA34: =CG34 -> 7125 | DB34: =SUM(CZ34:DA34) -> 14988.75 | DC34: =DB34-CX34 -> -2816.25
A35: 29 | C35: 32498 | D35: =VLOOKUP(E35,'F3 MS (2)'!E:F,2,0) -> GD260701 | E35: Deza, Shae Ann | F35: =VLOOKUP(C35,'[1]ACTIVE GH'!$C:$I,7,0) -> METAL STAMPING | G35: =VLOOKUP(C35,'[1]ACTIVE GH'!$C:$J,8,0) -> PRODUCTION | H35: =VLOOKUP(C35,'[1]ACTIVE GH'!$C:$N,12,0) -> Operator 1 | I35: DL | J35: =IFERROR(VLOOKUP(C35,PIVOT!A:B,2,0),0) -> 96 | K35: =J35/8 -> 12 | L35: 600 | M35: =K35*L35 -> 7200 | N35: =IFERROR(VLOOKUP(C35,PIVOT!A:F,6,0),0) -> 0 | O35: =L35/8/60 -> 1.25 | P35: =-N35*O35 -> 0 | Q35: =IFERROR(VLOOKUP(C35,PIVOT!A:C,3,0),0) -> 14 | R35: =L35/8*1.25 -> 93.75 | S35: =Q35*R35 -> 1312.5 | T35: =IFERROR(VLOOKUP(C35,PIVOT!A:D,4,0),0) -> 0 | U35: =L35/8*0.1 -> 7.5 | V35: =T35*U35 -> 0 | W35: =IFERROR(VLOOKUP(C35,PIVOT!A:E,5,0),0) -> 0 | X35: =L35/8*1.25*0.1 -> 9.375 | Y35: =X35*W35 -> 0 | Z35: =IFERROR(VLOOKUP(C35,#REF!,6,0),0) -> 0 | AA35: =L35/8*1.3 -> 97.5 | AB35: =Z35*AA35 -> 0 | AD35: =L35/8*1.69 -> 126.75 | AE35: =AD35*AC35 -> 0 | AF35: =IFERROR(VLOOKUP(C35,#REF!,8,0),0) -> 0 | AG35: =L35/8*1.3*0.1 -> 9.75 | AH35: =AF35*AG35 -> 0 | AJ35: =L35/8*1.5 -> 112.5 | AK35: =AI35*AJ35 -> 0 | AM35: =L35/8*1.5*1.3 -> 146.25 | AN35: 0 | AP35: =L35/8*1.5*0.1 -> 11.25 | AQ35: =AO35*AP35 -> 0 | AR35: =IFERROR(VLOOKUP(C35,#REF!,7,0),0) -> 0 | AS35: =L35/8*1.3 -> 97.5 | AT35: =AR35*AS35 -> 0 | AX35: =IFERROR(VLOOKUP(C35,#REF!,8,0),0) -> 0 | AY35: =L35/8*1.3*0.1 -> 9.75 | AZ35: =AX35*AY35 -> 0 | BA35: =IFERROR(VLOOKUP(C35,#REF!,10,0),0) -> 0 | BB35: =600/8*2 -> 150 | BC35: =BA35*BB35 -> 0 | BJ35: =IFERROR(VLOOKUP(C35,#REF!,9,0),0) -> 0 | BK35: =L35/8 -> 75 | BL35: =BJ35*BK35 -> 0 | CG35: =SUM(Y35,V35,S35,P35,M35) -> 8512.5 | CH35: =VLOOKUP(CX35,SSS_2025!A:N,8) -> 1900 | CI35: =VLOOKUP(CX35,SSS_2025!A:N,13) -> 950 | CJ35: =VLOOKUP(CX35,SSS_2025!A:N,9) -> 30 | CK35: 391.25 | CL35: 391.25 | CM35: 200 | CN35: 200 | CO35: =CG35+CH35+CJ35+CL35+CN35 -> 11033.75 | CP35: =(M35+P35+BN35)*10% -> 720 | CQ35: =CO35+CP35 -> 11753.75 | CS35: =CQ35+CR35 -> 11753.75 | CT35: =SUM(M35+(BC35/2)+BL35+BN35+P35)/12 -> 600 | CV35: =IFERROR(VLOOKUP(C35,'[2]BILLING COMPUTATION'!$C$8:$CI$224,85,0),0) -> 10305 | CW35: =CG35 -> 8512.5 | CX35: =CV35+CW35 -> 18817.5 | CZ35: =IFERROR(VLOOKUP(C35,'[5]BILLING COMPUTATION'!$C$8:$CG$101,83,0),0) -> 9075 | DA35: =CG35 -> 8512.5 | DB35: =SUM(CZ35:DA35) -> 17587.5 | DC35: =DB35-CX35 -> -1230
A36: 30 | C36: 5983 | D36: =VLOOKUP(E36,'F3 MS (2)'!E:F,2,0) -> GD250036 | E36: Dimalibot, Cristine Barro | F36: =VLOOKUP(C36,'[1]ACTIVE GH'!$C:$I,7,0) -> METAL STAMPING | G36: =VLOOKUP(C36,'[1]ACTIVE GH'!$C:$J,8,0) -> PRODUCTION | H36: =VLOOKUP(C36,'[1]ACTIVE GH'!$C:$N,12,0) -> Operator 1 | I36: DL | J36: =IFERROR(VLOOKUP(C36,PIVOT!A:B,2,0),0) -> 80 | K36: =J36/8 -> 10 | L36: 600 | M36: =K36*L36 -> 6000 | N36: =IFERROR(VLOOKUP(C36,PIVOT!A:F,6,0),0) -> 0 | O36: =L36/8/60 -> 1.25 | P36: =-N36*O36 -> 0 | Q36: =IFERROR(VLOOKUP(C36,PIVOT!A:C,3,0),0) -> 2 | R36: =L36/8*1.25 -> 93.75 | S36: =Q36*R36 -> 187.5 | T36: =IFERROR(VLOOKUP(C36,PIVOT!A:D,4,0),0) -> 6 | U36: =L36/8*0.1 -> 7.5 | V36: =T36*U36 -> 45 | W36: =IFERROR(VLOOKUP(C36,PIVOT!A:E,5,0),0) -> 0 | X36: =L36/8*1.25*0.1 -> 9.375 | Y36: =X36*W36 -> 0 | Z36: =IFERROR(VLOOKUP(C36,#REF!,6,0),0) -> 0 | AA36: =L36/8*1.3 -> 97.5 | AB36: =Z36*AA36 -> 0 | AD36: =L36/8*1.69 -> 126.75 | AE36: =AD36*AC36 -> 0 | AF36: =IFERROR(VLOOKUP(C36,#REF!,8,0),0) -> 0 | AG36: =L36/8*1.3*0.1 -> 9.75 | AH36: =AF36*AG36 -> 0 | AJ36: =L36/8*1.5 -> 112.5 | AK36: =AI36*AJ36 -> 0 | AM36: =L36/8*1.5*1.3 -> 146.25 | AN36: 0 | AP36: =L36/8*1.5*0.1 -> 11.25 | AQ36: =AO36*AP36 -> 0 | AR36: =IFERROR(VLOOKUP(C36,#REF!,7,0),0) -> 0 | AS36: =L36/8*1.3 -> 97.5 | AT36: =AR36*AS36 -> 0 | AX36: =IFERROR(VLOOKUP(C36,#REF!,8,0),0) -> 0 | AY36: =L36/8*1.3*0.1 -> 9.75 | AZ36: =AX36*AY36 -> 0 | BA36: =IFERROR(VLOOKUP(C36,#REF!,10,0),0) -> 0 | BB36: =600/8*2 -> 150 | BC36: =BA36*BB36 -> 0 | BJ36: =IFERROR(VLOOKUP(C36,#REF!,9,0),0) -> 0 | BK36: =L36/8 -> 75 | BL36: =BJ36*BK36 -> 0 | CG36: =SUM(Y36,V36,S36,P36,M36) -> 6232.5 | CH36: =VLOOKUP(CX36,SSS_2025!A:N,8) -> 1750 | CI36: =VLOOKUP(CX36,SSS_2025!A:N,13) -> 875 | CJ36: =VLOOKUP(CX36,SSS_2025!A:N,9) -> 30 | CK36: 391.25 | CL36: 391.25 | CM36: 200 | CN36: 200 | CO36: =CG36+CH36+CJ36+CL36+CN36 -> 8603.75 | CP36: =(M36+P36+BN36)*10% -> 600 | CQ36: =CO36+CP36 -> 9203.75 | CS36: =CQ36+CR36 -> 9203.75 | CT36: =SUM(M36+(BC36/2)+BL36+BN36+P36)/12 -> 500 | CV36: =IFERROR(VLOOKUP(C36,'[2]BILLING COMPUTATION'!$C$8:$CI$224,85,0),0) -> 11422.5 | CW36: =CG36 -> 6232.5 | CX36: =CV36+CW36 -> 17655 | CZ36: =IFERROR(VLOOKUP(C36,'[5]BILLING COMPUTATION'!$C$8:$CG$101,83,0),0) -> 9720 | DA36: =CG36 -> 6232.5 | DB36: =SUM(CZ36:DA36) -> 15952.5 | DC36: =DB36-CX36 -> -1702.5
A37: 31 | C37: 30612 | D37: =VLOOKUP(E37,'F3 MS (2)'!E:F,2,0) -> GD250593 | E37: Dipasupil, Joshua Garcia | F37: =VLOOKUP(C37,'[1]ACTIVE GH'!$C:$I,7,0) -> METAL STAMPING | G37: =VLOOKUP(C37,'[1]ACTIVE GH'!$C:$J,8,0) -> PRODUCTION | H37: =VLOOKUP(C37,'[1]ACTIVE GH'!$C:$N,12,0) -> Operator 1 | I37: DL | J37: =IFERROR(VLOOKUP(C37,PIVOT!A:B,2,0),0) -> 96 | K37: =J37/8 -> 12 | L37: 600 | M37: =K37*L37 -> 7200 | N37: =IFERROR(VLOOKUP(C37,PIVOT!A:F,6,0),0) -> 5 | O37: =L37/8/60 -> 1.25 | P37: =-N37*O37 -> -6.25 | Q37: =IFERROR(VLOOKUP(C37,PIVOT!A:C,3,0),0) -> 0 | R37: =L37/8*1.25 -> 93.75 | S37: =Q37*R37 -> 0 | T37: =IFERROR(VLOOKUP(C37,PIVOT!A:D,4,0),0) -> 6 | U37: =L37/8*0.1 -> 7.5 | V37: =T37*U37 -> 45 | W37: =IFERROR(VLOOKUP(C37,PIVOT!A:E,5,0),0) -> 0 | X37: =L37/8*1.25*0.1 -> 9.375 | Y37: =X37*W37 -> 0 | Z37: =IFERROR(VLOOKUP(C37,#REF!,6,0),0) -> 0 | AA37: =L37/8*1.3 -> 97.5 | AB37: =Z37*AA37 -> 0 | AD37: =L37/8*1.69 -> 126.75 | AE37: =AD37*AC37 -> 0 | AF37: =IFERROR(VLOOKUP(C37,#REF!,8,0),0) -> 0 | AG37: =L37/8*1.3*0.1 -> 9.75 | AH37: =AF37*AG37 -> 0 | AJ37: =L37/8*1.5 -> 112.5 | AK37: =AI37*AJ37 -> 0 | AM37: =L37/8*1.5*1.3 -> 146.25 | AN37: 0 | AP37: =L37/8*1.5*0.1 -> 11.25 | AQ37: =AO37*AP37 -> 0 | AR37: =IFERROR(VLOOKUP(C37,#REF!,7,0),0) -> 0 | AS37: =L37/8*1.3 -> 97.5 | AT37: =AR37*AS37 -> 0 | AX37: =IFERROR(VLOOKUP(C37,#REF!,8,0),0) -> 0 | AY37: =L37/8*1.3*0.1 -> 9.75 | AZ37: =AX37*AY37 -> 0 | BA37: =IFERROR(VLOOKUP(C37,#REF!,10,0),0) -> 0 | BB37: =600/8*2 -> 150 | BC37: =BA37*BB37 -> 0 | BJ37: =IFERROR(VLOOKUP(C37,#REF!,9,0),0) -> 0 | BK37: =L37/8 -> 75 | BL37: =BJ37*BK37 -> 0 | CG37: =SUM(Y37,V37,S37,P37,M37) -> 7238.75 | CH37: =VLOOKUP(CX37,SSS_2025!A:N,8) -> 1600 | CI37: =VLOOKUP(CX37,SSS_2025!A:N,13) -> 800 | CJ37: =VLOOKUP(CX37,SSS_2025!A:N,9) -> 30 | CK37: 391.25 | CL37: 391.25 | CM37: 200 | CN37: 200 | CO37: =CG37+CH37+CJ37+CL37+CN37 -> 9460 | CP37: =(M37+P37+BN37)*10% -> 719.375 | CQ37: =CO37+CP37 -> 10179.375 | CS37: =CQ37+CR37 -> 10179.375 | CT37: =SUM(M37+(BC37/2)+BL37+BN37+P37)/12 -> 599.47917 | CV37: =IFERROR(VLOOKUP(C37,'[2]BILLING COMPUTATION'!$C$8:$CI$224,85,0),0) -> 8887.5 | CW37: =CG37 -> 7238.75 | CX37: =CV37+CW37 -> 16126.25 | CZ37: =IFERROR(VLOOKUP(C37,'[5]BILLING COMPUTATION'!$C$8:$CG$101,83,0),0) -> 9487.5 | DA37: =CG37 -> 7238.75 | DB37: =SUM(CZ37:DA37) -> 16726.25 | DC37: =DB37-CX37 -> 600
A38: 32 | C38: 30296 | D38: =VLOOKUP(E38,'F3 MS (2)'!E:F,2,0) -> GD250529 | E38: Donato, Maria Christina Payumo | F38: =VLOOKUP(C38,'[1]ACTIVE GH'!$C:$I,7,0) -> METAL STAMPING | G38: =VLOOKUP(C38,'[1]ACTIVE GH'!$C:$J,8,0) -> PRODUCTION | H38: =VLOOKUP(C38,'[1]ACTIVE GH'!$C:$N,12,0) -> Operator 1 | I38: DL | J38: =IFERROR(VLOOKUP(C38,PIVOT!A:B,2,0),0) -> 96 | K38: =J38/8 -> 12 | L38: 600 | M38: =K38*L38 -> 7200 | N38: =IFERROR(VLOOKUP(C38,PIVOT!A:F,6,0),0) -> 0 | O38: =L38/8/60 -> 1.25 | P38: =-N38*O38 -> 0 | Q38: =IFERROR(VLOOKUP(C38,PIVOT!A:C,3,0),0) -> 18 | R38: =L38/8*1.25 -> 93.75 | S38: =Q38*R38 -> 1687.5 | T38: =IFERROR(VLOOKUP(C38,PIVOT!A:D,4,0),0) -> 0 | U38: =L38/8*0.1 -> 7.5 | V38: =T38*U38 -> 0 | W38: =IFERROR(VLOOKUP(C38,PIVOT!A:E,5,0),0) -> 0 | X38: =L38/8*1.25*0.1 -> 9.375 | Y38: =X38*W38 -> 0 | Z38: =IFERROR(VLOOKUP(C38,#REF!,6,0),0) -> 0 | AA38: =L38/8*1.3 -> 97.5 | AB38: =Z38*AA38 -> 0 | AD38: =L38/8*1.69 -> 126.75 | AE38: =AD38*AC38 -> 0 | AF38: =IFERROR(VLOOKUP(C38,#REF!,8,0),0) -> 0 | AG38: =L38/8*1.3*0.1 -> 9.75 | AH38: =AF38*AG38 -> 0 | AJ38: =L38/8*1.5 -> 112.5 | AK38: =AI38*AJ38 -> 0 | AM38: =L38/8*1.5*1.3 -> 146.25 | AN38: 0 | AP38: =L38/8*1.5*0.1 -> 11.25 | AQ38: =AO38*AP38 -> 0 | AR38: =IFERROR(VLOOKUP(C38,#REF!,7,0),0) -> 0 | AS38: =L38/8*1.3 -> 97.5 | AT38: =AR38*AS38 -> 0 | AX38: =IFERROR(VLOOKUP(C38,#REF!,8,0),0) -> 0 | AY38: =L38/8*1.3*0.1 -> 9.75 | AZ38: =AX38*AY38 -> 0 | BA38: =IFERROR(VLOOKUP(C38,#REF!,10,0),0) -> 0 | BB38: =600/8*2 -> 150 | BC38: =BA38*BB38 -> 0 | BJ38: =IFERROR(VLOOKUP(C38,#REF!,9,0),0) -> 0 | BK38: =L38/8 -> 75 | BL38: =BJ38*BK38 -> 0 | CG38: =SUM(Y38,V38,S38,P38,M38) -> 8887.5 | CH38: =VLOOKUP(CX38,SSS_2025!A:N,8) -> 1950 | CI38: =VLOOKUP(CX38,SSS_2025!A:N,13) -> 975 | CJ38: =VLOOKUP(CX38,SSS_2025!A:N,9) -> 30 | CK38: 391.25 | CL38: 391.25 | CM38: 200 | CN38: 200 | CO38: =CG38+CH38+CJ38+CL38+CN38 -> 11458.75 | CP38: =(M38+P38+BN38)*10% -> 720 | CQ38: =CO38+CP38 -> 12178.75 | CS38: =CQ38+CR38 -> 12178.75 | CT38: =SUM(M38+(BC38/2)+BL38+BN38+P38)/12 -> 600 | CV38: =IFERROR(VLOOKUP(C38,'[2]BILLING COMPUTATION'!$C$8:$CI$224,85,0),0) -> 10680 | CW38: =CG38 -> 8887.5 | CX38: =CV38+CW38 -> 19567.5 | CZ38: =IFERROR(VLOOKUP(C38,'[5]BILLING COMPUTATION'!$C$8:$CG$101,83,0),0) -> 11047.5 | DA38: =CG38 -> 8887.5 | DB38: =SUM(CZ38:DA38) -> 19935 | DC38: =DB38-CX38 -> 367.5
A39: 33 | C39: 13684 | D39: =VLOOKUP(E39,'F3 MS (2)'!E:F,2,0) -> GD250135 | E39: Doronela, Jimuel Belason | F39: =VLOOKUP(C39,'[1]ACTIVE GH'!$C:$I,7,0) -> METAL STAMPING | G39: =VLOOKUP(C39,'[1]ACTIVE GH'!$C:$J,8,0) -> PRODUCTION | H39: =VLOOKUP(C39,'[1]ACTIVE GH'!$C:$N,12,0) -> Operator 1 | I39: DL | J39: =IFERROR(VLOOKUP(C39,PIVOT!A:B,2,0),0) -> 88 | K39: =J39/8 -> 11 | L39: 600 | M39: =K39*L39 -> 6600 | N39: =IFERROR(VLOOKUP(C39,PIVOT!A:F,6,0),0) -> 0 | O39: =L39/8/60 -> 1.25 | P39: =-N39*O39 -> 0 | Q39: =IFERROR(VLOOKUP(C39,PIVOT!A:C,3,0),0) -> 4 | R39: =L39/8*1.25 -> 93.75 | S39: =Q39*R39 -> 375 | T39: =IFERROR(VLOOKUP(C39,PIVOT!A:D,4,0),0) -> 0 | U39: =L39/8*0.1 -> 7.5 | V39: =T39*U39 -> 0 | W39: =IFERROR(VLOOKUP(C39,PIVOT!A:E,5,0),0) -> 0 | X39: =L39/8*1.25*0.1 -> 9.375 | Y39: =X39*W39 -> 0 | Z39: =IFERROR(VLOOKUP(C39,#REF!,6,0),0) -> 0 | AA39: =L39/8*1.3 -> 97.5 | AB39: =Z39*AA39 -> 0 | AD39: =L39/8*1.69 -> 126.75 | AE39: =AD39*AC39 -> 0 | AF39: =IFERROR(VLOOKUP(C39,#REF!,8,0),0) -> 0 | AG39: =L39/8*1.3*0.1 -> 9.75 | AH39: =AF39*AG39 -> 0 | AJ39: =L39/8*1.5 -> 112.5 | AK39: =AI39*AJ39 -> 0 | AM39: =L39/8*1.5*1.3 -> 146.25 | AN39: 0 | AP39: =L39/8*1.5*0.1 -> 11.25 | AQ39: =AO39*AP39 -> 0 | AR39: =IFERROR(VLOOKUP(C39,#REF!,7,0),0) -> 0 | AS39: =L39/8*1.3 -> 97.5 | AT39: =AR39*AS39 -> 0 | AX39: =IFERROR(VLOOKUP(C39,#REF!,8,0),0) -> 0 | AY39: =L39/8*1.3*0.1 -> 9.75 | AZ39: =AX39*AY39 -> 0 | BA39: =IFERROR(VLOOKUP(C39,#REF!,10,0),0) -> 0 | BB39: =600/8*2 -> 150 | BC39: =BA39*BB39 -> 0 | BJ39: =IFERROR(VLOOKUP(C39,#REF!,9,0),0) -> 0 | BK39: =L39/8 -> 75 | BL39: =BJ39*BK39 -> 0 | CG39: =SUM(Y39,V39,S39,P39,M39) -> 6975 | CH39: =VLOOKUP(CX39,SSS_2025!A:N,8) -> 1800 | CI39: =VLOOKUP(CX39,SSS_2025!A:N,13) -> 900 | CJ39: =VLOOKUP(CX39,SSS_2025!A:N,9) -> 30 | CK39: 391.25 | CL39: 391.25 | CM39: 200 | CN39: 200 | CO39: =CG39+CH39+CJ39+CL39+CN39 -> 9396.25 | CP39: =(M39+P39+BN39)*10% -> 660 | CQ39: =CO39+CP39 -> 10056.25 | CS39: =CQ39+CR39 -> 10056.25 | CT39: =SUM(M39+(BC39/2)+BL39+BN39+P39)/12 -> 550 | CV39: =IFERROR(VLOOKUP(C39,'[2]BILLING COMPUTATION'!$C$8:$CI$224,85,0),0) -> 11197.5 | CW39: =CG39 -> 6975 | CX39: =CV39+CW39 -> 18172.5 | CZ39: =IFERROR(VLOOKUP(C39,'[5]BILLING COMPUTATION'!$C$8:$CG$101,83,0),0) -> 9527.5 | DA39: =CG39 -> 6975 | DB39: =SUM(CZ39:DA39) -> 16502.5 | DC39: =DB39-CX39 -> -1670
A40: 34 | C40: 13337 | D40: =VLOOKUP(E40,'F3 MS (2)'!E:F,2,0) -> GD250225 | E40: Dueñas, Mannex Alvendia | F40: =VLOOKUP(C40,'[1]ACTIVE GH'!$C:$I,7,0) -> METAL STAMPING | G40: =VLOOKUP(C40,'[1]ACTIVE GH'!$C:$J,8,0) -> PRODUCTION | H40: =VLOOKUP(C40,'[1]ACTIVE GH'!$C:$N,12,0) -> Operator 1 | I40: DL | J40: =IFERROR(VLOOKUP(C40,PIVOT!A:B,2,0),0) -> 96 | K40: =J40/8 -> 12 | L40: 600 | M40: =K40*L40 -> 7200 | N40: =IFERROR(VLOOKUP(C40,PIVOT!A:F,6,0),0) -> 0 | O40: =L40/8/60 -> 1.25 | P40: =-N40*O40 -> 0 | Q40: =IFERROR(VLOOKUP(C40,PIVOT!A:C,3,0),0) -> 16 | R40: =L40/8*1.25 -> 93.75 | S40: =Q40*R40 -> 1500 | T40: =IFERROR(VLOOKUP(C40,PIVOT!A:D,4,0),0) -> 66 | U40: =L40/8*0.1 -> 7.5 | V40: =T40*U40 -> 495 | W40: =IFERROR(VLOOKUP(C40,PIVOT!A:E,5,0),0) -> 16 | X40: =L40/8*1.25*0.1 -> 9.375 | Y40: =X40*W40 -> 150 | Z40: =IFERROR(VLOOKUP(C40,#REF!,6,0),0) -> 0 | AA40: =L40/8*1.3 -> 97.5 | AB40: =Z40*AA40 -> 0 | AD40: =L40/8*1.69 -> 126.75 | AE40: =AD40*AC40 -> 0 | AF40: =IFERROR(VLOOKUP(C40,#REF!,8,0),0) -> 0 | AG40: =L40/8*1.3*0.1 -> 9.75 | AH40: =AF40*AG40 -> 0 | AJ40: =L40/8*1.5 -> 112.5 | AK40: =AI40*AJ40 -> 0 | AM40: =L40/8*1.5*1.3 -> 146.25 | AN40: 0 | AP40: =L40/8*1.5*0.1 -> 11.25 | AQ40: =AO40*AP40 -> 0 | AR40: =IFERROR(VLOOKUP(C40,#REF!,7,0),0) -> 0 | AS40: =L40/8*1.3 -> 97.5 | AT40: =AR40*AS40 -> 0 | AX40: =IFERROR(VLOOKUP(C40,#REF!,8,0),0) -> 0 | AY40: =L40/8*1.3*0.1 -> 9.75 | AZ40: =AX40*AY40 -> 0 | BA40: =IFERROR(VLOOKUP(C40,#REF!,10,0),0) -> 0 | BB40: =600/8*2 -> 150 | BC40: =BA40*BB40 -> 0 | BJ40: =IFERROR(VLOOKUP(C40,#REF!,9,0),0) -> 0 | BK40: =L40/8 -> 75 | BL40: =BJ40*BK40 -> 0 | CG40: =SUM(Y40,V40,S40,P40,M40) -> 9345 | CH40: =VLOOKUP(CX40,SSS_2025!A:N,8) -> 1850 | CI40: =VLOOKUP(CX40,SSS_2025!A:N,13) -> 925 | CJ40: =VLOOKUP(CX40,SSS_2025!A:N,9) -> 30 | CK40: 391.25 | CL40: 391.25 | CM40: 200 | CN40: 200 | CO40: =CG40+CH40+CJ40+CL40+CN40 -> 11816.25 | CP40: =(M40+P40+BN40)*10% -> 720 | CQ40: =CO40+CP40 -> 12536.25 | CS40: =CQ40+CR40 -> 12536.25 | CT40: =SUM(M40+(BC40/2)+BL40+BN40+P40)/12 -> 600 | CV40: =IFERROR(VLOOKUP(C40,'[2]BILLING COMPUTATION'!$C$8:$CI$224,85,0),0) -> 9348.75 | CW40: =CG40 -> 9345 | CX40: =CV40+CW40 -> 18693.75 | CZ40: =IFERROR(VLOOKUP(C40,'[5]BILLING COMPUTATION'!$C$8:$CG$101,83,0),0) -> 8842.5 | DA40: =CG40 -> 9345 | DB40: =SUM(CZ40:DA40) -> 18187.5 | DC40: =DB40-CX40 -> -506.25
A41: 35 | C41: 30766 | D41: =VLOOKUP(E41,'F3 MS (2)'!E:F,2,0) -> GD250540 | E41: Eguia, Mary Grace Deomampo | F41: =VLOOKUP(C41,'[1]ACTIVE GH'!$C:$I,7,0) -> METAL STAMPING | G41: =VLOOKUP(C41,'[1]ACTIVE GH'!$C:$J,8,0) -> PRODUCTION | H41: =VLOOKUP(C41,'[1]ACTIVE GH'!$C:$N,12,0) -> Operator 1 | I41: DL | J41: =IFERROR(VLOOKUP(C41,PIVOT!A:B,2,0),0) -> 76 | K41: =J41/8 -> 9.5 | L41: 600 | M41: =K41*L41 -> 5700 | N41: =IFERROR(VLOOKUP(C41,PIVOT!A:F,6,0),0) -> 0 | O41: =L41/8/60 -> 1.25 | P41: =-N41*O41 -> 0 | Q41: =IFERROR(VLOOKUP(C41,PIVOT!A:C,3,0),0) -> 0 | R41: =L41/8*1.25 -> 93.75 | S41: =Q41*R41 -> 0 | T41: =IFERROR(VLOOKUP(C41,PIVOT!A:D,4,0),0) -> 0 | U41: =L41/8*0.1 -> 7.5 | V41: =T41*U41 -> 0 | W41: =IFERROR(VLOOKUP(C41,PIVOT!A:E,5,0),0) -> 0 | X41: =L41/8*1.25*0.1 -> 9.375 | Y41: =X41*W41 -> 0 | Z41: =IFERROR(VLOOKUP(C41,#REF!,6,0),0) -> 0 | AA41: =L41/8*1.3 -> 97.5 | AB41: =Z41*AA41 -> 0 | AD41: =L41/8*1.69 -> 126.75 | AE41: =AD41*AC41 -> 0 | AF41: =IFERROR(VLOOKUP(C41,#REF!,8,0),0) -> 0 | AG41: =L41/8*1.3*0.1 -> 9.75 | AH41: =AF41*AG41 -> 0 | AJ41: =L41/8*1.5 -> 112.5 | AK41: =AI41*AJ41 -> 0 | AM41: =L41/8*1.5*1.3 -> 146.25 | AN41: 0 | AP41: =L41/8*1.5*0.1 -> 11.25 | AQ41: =AO41*AP41 -> 0 | AR41: =IFERROR(VLOOKUP(C41,#REF!,7,0),0) -> 0 | AS41: =L41/8*1.3 -> 97.5 | AT41: =AR41*AS41 -> 0 | AX41: =IFERROR(VLOOKUP(C41,#REF!,8,0),0) -> 0 | AY41: =L41/8*1.3*0.1 -> 9.75 | AZ41: =AX41*AY41 -> 0 | BA41: =IFERROR(VLOOKUP(C41,#REF!,10,0),0) -> 0 | BB41: =600/8*2 -> 150 | BC41: =BA41*BB41 -> 0 | BJ41: =IFERROR(VLOOKUP(C41,#REF!,9,0),0) -> 0 | BK41: =L41/8 -> 75 | BL41: =BJ41*BK41 -> 0 | CG41: =SUM(Y41,V41,S41,P41,M41) -> 5700 | CH41: =VLOOKUP(CX41,SSS_2025!A:N,8) -> 1650 | CI41: =VLOOKUP(CX41,SSS_2025!A:N,13) -> 825 | CJ41: =VLOOKUP(CX41,SSS_2025!A:N,9) -> 30 | CK41: 391.25 | CL41: 391.25 | CM41: 200 | CN41: 200 | CO41: =CG41+CH41+CJ41+CL41+CN41 -> 7971.25 | CP41: =(M41+P41+BN41)*10% -> 570 | CQ41: =CO41+CP41 -> 8541.25 | CS41: =CQ41+CR41 -> 8541.25 | CT41: =SUM(M41+(BC41/2)+BL41+BN41+P41)/12 -> 475 | CV41: =IFERROR(VLOOKUP(C41,'[2]BILLING COMPUTATION'!$C$8:$CI$224,85,0),0) -> 10867.5 | CW41: =CG41 -> 5700 | CX41: =CV41+CW41 -> 16567.5 | CZ41: =IFERROR(VLOOKUP(C41,'[5]BILLING COMPUTATION'!$C$8:$CG$101,83,0),0) -> 9926.25 | DA41: =CG41 -> 5700 | DB41: =SUM(CZ41:DA41) -> 15626.25 | DC41: =DB41-CX41 -> -941.25
A42: 36 | C42: 12985 | D42: =VLOOKUP(E42,'F3 MS (2)'!E:F,2,0) -> GD250372 | E42: Flores, Jayson Cañoneo | F42: =VLOOKUP(C42,'[1]ACTIVE GH'!$C:$I,7,0) -> METAL STAMPING | G42: =VLOOKUP(C42,'[1]ACTIVE GH'!$C:$J,8,0) -> PRODUCTION | H42: =VLOOKUP(C42,'[1]ACTIVE GH'!$C:$N,12,0) -> Operator 1 | I42: DL | J42: =IFERROR(VLOOKUP(C42,PIVOT!A:B,2,0),0) -> 96 | K42: =J42/8 -> 12 | L42: 600 | M42: =K42*L42 -> 7200 | N42: =IFERROR(VLOOKUP(C42,PIVOT!A:F,6,0),0) -> 0 | O42: =L42/8/60 -> 1.25 | P42: =-N42*O42 -> 0 | Q42: =IFERROR(VLOOKUP(C42,PIVOT!A:C,3,0),0) -> 0 | R42: =L42/8*1.25 -> 93.75 | S42: =Q42*R42 -> 0 | T42: =IFERROR(VLOOKUP(C42,PIVOT!A:D,4,0),0) -> 6 | U42: =L42/8*0.1 -> 7.5 | V42: =T42*U42 -> 45 | W42: =IFERROR(VLOOKUP(C42,PIVOT!A:E,5,0),0) -> 0 | X42: =L42/8*1.25*0.1 -> 9.375 | Y42: =X42*W42 -> 0 | Z42: =IFERROR(VLOOKUP(C42,#REF!,6,0),0) -> 0 | AA42: =L42/8*1.3 -> 97.5 | AB42: =Z42*AA42 -> 0 | AD42: =L42/8*1.69 -> 126.75 | AE42: =AD42*AC42 -> 0 | AF42: =IFERROR(VLOOKUP(C42,#REF!,8,0),0) -> 0 | AG42: =L42/8*1.3*0.1 -> 9.75 | AH42: =AF42*AG42 -> 0 | AJ42: =L42/8*1.5 -> 112.5 | AK42: =AI42*AJ42 -> 0 | AM42: =L42/8*1.5*1.3 -> 146.25 | AN42: 0 | AP42: =L42/8*1.5*0.1 -> 11.25 | AQ42: =AO42*AP42 -> 0 | AR42: =IFERROR(VLOOKUP(C42,#REF!,7,0),0) -> 0 | AS42: =L42/8*1.3 -> 97.5 | AT42: =AR42*AS42 -> 0 | AX42: =IFERROR(VLOOKUP(C42,#REF!,8,0),0) -> 0 | AY42: =L42/8*1.3*0.1 -> 9.75 | AZ42: =AX42*AY42 -> 0 | BA42: =IFERROR(VLOOKUP(C42,#REF!,10,0),0) -> 0 | BB42: =600/8*2 -> 150 | BC42: =BA42*BB42 -> 0 | BJ42: =IFERROR(VLOOKUP(C42,#REF!,9,0),0) -> 0 | BK42: =L42/8 -> 75 | BL42: =BJ42*BK42 -> 0 | CG42: =SUM(Y42,V42,S42,P42,M42) -> 7245 | CH42: =VLOOKUP(CX42,SSS_2025!A:N,8) -> 1900 | CI42: =VLOOKUP(CX42,SSS_2025!A:N,13) -> 950 | CJ42: =VLOOKUP(CX42,SSS_2025!A:N,9) -> 30 | CK42: 391.25 | CL42: 391.25 | CM42: 200 | CN42: 200 | CO42: =CG42+CH42+CJ42+CL42+CN42 -> 9766.25 | CP42: =(M42+P42+BN42)*10% -> 720 | CQ42: =CO42+CP42 -> 10486.25 | CS42: =CQ42+CR42 -> 10486.25 | CT42: =SUM(M42+(BC42/2)+BL42+BN42+P42)/12 -> 600 | CV42: =IFERROR(VLOOKUP(C42,'[2]BILLING COMPUTATION'!$C$8:$CI$224,85,0),0) -> 11610 | CW42: =CG42 -> 7245 | CX42: =CV42+CW42 -> 18855 | CZ42: =IFERROR(VLOOKUP(C42,'[5]BILLING COMPUTATION'!$C$8:$CG$101,83,0),0) -> 9798.75 | DA42: =CG42 -> 7245 | DB42: =SUM(CZ42:DA42) -> 17043.75 | DC42: =DB42-CX42 -> -1811.25
A43: 37 | C43: 30254 | D43: =VLOOKUP(E43,'F3 MS (2)'!E:F,2,0) -> GD250519 | E43: Flores, Joey Brasula | F43: =VLOOKUP(C43,'[1]ACTIVE GH'!$C:$I,7,0) -> METAL STAMPING | G43: =VLOOKUP(C43,'[1]ACTIVE GH'!$C:$J,8,0) -> PRODUCTION | H43: =VLOOKUP(C43,'[1]ACTIVE GH'!$C:$N,12,0) -> Operator 1 | I43: DL | J43: =IFERROR(VLOOKUP(C43,PIVOT!A:B,2,0),0) -> 80 | K43: =J43/8 -> 10 | L43: 600 | M43: =K43*L43 -> 6000 | N43: =IFERROR(VLOOKUP(C43,PIVOT!A:F,6,0),0) -> 2 | O43: =L43/8/60 -> 1.25 | P43: =-N43*O43 -> -2.5 | Q43: =IFERROR(VLOOKUP(C43,PIVOT!A:C,3,0),0) -> 3 | R43: =L43/8*1.25 -> 93.75 | S43: =Q43*R43 -> 281.25 | T43: =IFERROR(VLOOKUP(C43,PIVOT!A:D,4,0),0) -> 59 | U43: =L43/8*0.1 -> 7.5 | V43: =T43*U43 -> 442.5 | W43: =IFERROR(VLOOKUP(C43,PIVOT!A:E,5,0),0) -> 3 | X43: =L43/8*1.25*0.1 -> 9.375 | Y43: =X43*W43 -> 28.125 | Z43: =IFERROR(VLOOKUP(C43,#REF!,6,0),0) -> 0 | AA43: =L43/8*1.3 -> 97.5 | AB43: =Z43*AA43 -> 0 | AD43: =L43/8*1.69 -> 126.75 | AE43: =AD43*AC43 -> 0 | AF43: =IFERROR(VLOOKUP(C43,#REF!,8,0),0) -> 0 | AG43: =L43/8*1.3*0.1 -> 9.75 | AH43: =AF43*AG43 -> 0 | AJ43: =L43/8*1.5 -> 112.5 | AK43: =AI43*AJ43 -> 0 | AM43: =L43/8*1.5*1.3 -> 146.25 | AN43: 0 | AP43: =L43/8*1.5*0.1 -> 11.25 | AQ43: =AO43*AP43 -> 0 | AR43: =IFERROR(VLOOKUP(C43,#REF!,7,0),0) -> 0 | AS43: =L43/8*1.3 -> 97.5 | AT43: =AR43*AS43 -> 0 | AX43: =IFERROR(VLOOKUP(C43,#REF!,8,0),0) -> 0 | AY43: =L43/8*1.3*0.1 -> 9.75 | AZ43: =AX43*AY43 -> 0 | BA43: =IFERROR(VLOOKUP(C43,#REF!,10,0),0) -> 0 | BB43: =600/8*2 -> 150 | BC43: =BA43*BB43 -> 0 | BJ43: =IFERROR(VLOOKUP(C43,#REF!,9,0),0) -> 0 | BK43: =L43/8 -> 75 | BL43: =BJ43*BK43 -> 0 | CG43: =SUM(Y43,V43,S43,P43,M43) -> 6749.375 | CH43: =VLOOKUP(CX43,SSS_2025!A:N,8) -> 1750 | CI43: =VLOOKUP(CX43,SSS_2025!A:N,13) -> 875 | CJ43: =VLOOKUP(CX43,SSS_2025!A:N,9) -> 30 | CK43: 391.25 | CL43: 391.25 | CM43: 200 | CN43: 200 | CO43: =CG43+CH43+CJ43+CL43+CN43 -> 9120.625 | CP43: =(M43+P43+BN43)*10% -> 599.75 | CQ43: =CO43+CP43 -> 9720.375 | CS43: =CQ43+CR43 -> 9720.375 | CT43: =SUM(M43+(BC43/2)+BL43+BN43+P43)/12 -> 499.79167 | CV43: =IFERROR(VLOOKUP(C43,'[2]BILLING COMPUTATION'!$C$8:$CI$224,85,0),0) -> 10605 | CW43: =CG43 -> 6749.375 | CX43: =CV43+CW43 -> 17354.375 | CZ43: =IFERROR(VLOOKUP(C43,'[5]BILLING COMPUTATION'!$C$8:$CG$101,83,0),0) -> 7852.5 | DA43: =CG43 -> 6749.375 | DB43: =SUM(CZ43:DA43) -> 14601.875 | DC43: =DB43-CX43 -> -2752.5
A44: 39 | C44: 6354 | D44: =VLOOKUP(E44,'F3 MS (2)'!E:F,2,0) -> GD250069 | E44: Forte, Harlene Mae Frando | F44: =VLOOKUP(C44,'[1]ACTIVE GH'!$C:$I,7,0) -> METAL STAMPING | G44: =VLOOKUP(C44,'[1]ACTIVE GH'!$C:$J,8,0) -> PRODUCTION | H44: =VLOOKUP(C44,'[1]ACTIVE GH'!$C:$N,12,0) -> Operator 1 | I44: DL | J44: =IFERROR(VLOOKUP(C44,PIVOT!A:B,2,0),0) -> 96 | K44: =J44/8 -> 12 | L44: 600 | M44: =K44*L44 -> 7200 | N44: =IFERROR(VLOOKUP(C44,PIVOT!A:F,6,0),0) -> 0 | O44: =L44/8/60 -> 1.25 | P44: =-N44*O44 -> 0 | Q44: =IFERROR(VLOOKUP(C44,PIVOT!A:C,3,0),0) -> 0 | R44: =L44/8*1.25 -> 93.75 | S44: =Q44*R44 -> 0 | T44: =IFERROR(VLOOKUP(C44,PIVOT!A:D,4,0),0) -> 66 | U44: =L44/8*0.1 -> 7.5 | V44: =T44*U44 -> 495 | W44: =IFERROR(VLOOKUP(C44,PIVOT!A:E,5,0),0) -> 0 | X44: =L44/8*1.25*0.1 -> 9.375 | Y44: =X44*W44 -> 0 | Z44: =IFERROR(VLOOKUP(C44,#REF!,6,0),0) -> 0 | AA44: =L44/8*1.3 -> 97.5 | AB44: =Z44*AA44 -> 0 | AD44: =L44/8*1.69 -> 126.75 | AE44: =AD44*AC44 -> 0 | AF44: =IFERROR(VLOOKUP(C44,#REF!,8,0),0) -> 0 | AG44: =L44/8*1.3*0.1 -> 9.75 | AH44: =AF44*AG44 -> 0 | AJ44: =L44/8*1.5 -> 112.5 | AK44: =AI44*AJ44 -> 0 | AM44: =L44/8*1.5*1.3 -> 146.25 | AN44: 0 | AP44: =L44/8*1.5*0.1 -> 11.25 | AQ44: =AO44*AP44 -> 0 | AR44: =IFERROR(VLOOKUP(C44,#REF!,7,0),0) -> 0 | AS44: =L44/8*1.3 -> 97.5 | AT44: =AR44*AS44 -> 0 | AX44: =IFERROR(VLOOKUP(C44,#REF!,8,0),0) -> 0 | AY44: =L44/8*1.3*0.1 -> 9.75 | AZ44: =AX44*AY44 -> 0 | BA44: =IFERROR(VLOOKUP(C44,#REF!,10,0),0) -> 0 | BB44: =600/8*2 -> 150 | BC44: =BA44*BB44 -> 0 | BJ44: =IFERROR(VLOOKUP(C44,#REF!,9,0),0) -> 0 | BK44: =L44/8 -> 75 | BL44: =BJ44*BK44 -> 0 | CG44: =SUM(Y44,V44,S44,P44,M44) -> 7695 | CH44: =VLOOKUP(CX44,SSS_2025!A:N,8) -> 1850 | CI44: =VLOOKUP(CX44,SSS_2025!A:N,13) -> 925 | CJ44: =VLOOKUP(CX44,SSS_2025!A:N,9) -> 30 | CK44: 391.25 | CL44: 391.25 | CM44: 200 | CN44: 200 | CO44: =CG44+CH44+CJ44+CL44+CN44 -> 10166.25 | CP44: =(M44+P44+BN44)*10% -> 720 | CQ44: =CO44+CP44 -> 10886.25 | CS44: =CQ44+CR44 -> 10886.25 | CT44: =SUM(M44+(BC44/2)+BL44+BN44+P44)/12 -> 600 | CV44: =IFERROR(VLOOKUP(C44,'[2]BILLING COMPUTATION'!$C$8:$CI$224,85,0),0) -> 10698.75 | CW44: =CG44 -> 7695 | CX44: =CV44+CW44 -> 18393.75 | CZ44: =IFERROR(VLOOKUP(C44,'[5]BILLING COMPUTATION'!$C$8:$CG$101,83,0),0) -> 9408.75 | DA44: =CG44 -> 7695 | DB44: =SUM(CZ44:DA44) -> 17103.75 | DC44: =DB44-CX44 -> -1290
... A62: 58 | C62: 11829 | D62: =VLOOKUP(E62,'F3 MS (2)'!E:F,2,0) -> GD250168 | E62: Melitante, Maricar Sueno | F62: =VLOOKUP(C62,'[1]ACTIVE GH'!$C:$I,7,0) -> METAL STAMPING | G62: =VLOOKUP(C62,'[1]ACTIVE GH'!$C:$J,8,0) -> PRODUCTION | H62: =VLOOKUP(C62,'[1]ACTIVE GH'!$C:$N,12,0) -> Operator 1 | I62: DL | J62: =IFERROR(VLOOKUP(C62,PIVOT!A:B,2,0),0) -> 96 | K62: =J62/8 -> 12 | L62: 600 | M62: =K62*L62 -> 7200 | N62: =IFERROR(VLOOKUP(C62,PIVOT!A:F,6,0),0) -> 0 | O62: =L62/8/60 -> 1.25 | P62: =-N62*O62 -> 0 | Q62: =IFERROR(VLOOKUP(C62,PIVOT!A:C,3,0),0) -> 20 | R62: =L62/8*1.25 -> 93.75 | S62: =Q62*R62 -> 1875 | T62: =IFERROR(VLOOKUP(C62,PIVOT!A:D,4,0),0) -> 0 | U62: =L62/8*0.1 -> 7.5 | V62: =T62*U62 -> 0 | W62: =IFERROR(VLOOKUP(C62,PIVOT!A:E,5,0),0) -> 0 | X62: =L62/8*1.25*0.1 -> 9.375 | Y62: =X62*W62 -> 0 | Z62: =IFERROR(VLOOKUP(C62,#REF!,6,0),0) -> 0 | AA62: =L62/8*1.3 -> 97.5 | AB62: =Z62*AA62 -> 0 | AD62: =L62/8*1.69 -> 126.75 | AE62: =AD62*AC62 -> 0 | AF62: =IFERROR(VLOOKUP(C62,#REF!,8,0),0) -> 0 | AG62: =L62/8*1.3*0.1 -> 9.75 | AH62: =AF62*AG62 -> 0 | AJ62: =L62/8*1.5 -> 112.5 | AK62: =AI62*AJ62 -> 0 | AM62: =L62/8*1.5*1.3 -> 146.25 | AN62: 0 | AP62: =L62/8*1.5*0.1 -> 11.25 | AQ62: =AO62*AP62 -> 0 | AR62: =IFERROR(VLOOKUP(C62,#REF!,7,0),0) -> 0 | AS62: =L62/8*1.3 -> 97.5 | AT62: =AR62*AS62 -> 0 | AX62: =IFERROR(VLOOKUP(C62,#REF!,8,0),0) -> 0 | AY62: =L62/8*1.3*0.1 -> 9.75 | AZ62: =AX62*AY62 -> 0 | BA62: =IFERROR(VLOOKUP(C62,#REF!,10,0),0) -> 0 | BB62: =600/8*2 -> 150 | BC62: =BA62*BB62 -> 0 | BJ62: =IFERROR(VLOOKUP(C62,#REF!,9,0),0) -> 0 | BK62: =L62/8 -> 75 | BL62: =BJ62*BK62 -> 0 | CG62: =SUM(Y62,V62,S62,P62,M62) -> 9075 | CH62: =VLOOKUP(CX62,SSS_2025!A:N,8) -> 2000 | CI62: =VLOOKUP(CX62,SSS_2025!A:N,13) -> 1000 | CJ62: =VLOOKUP(CX62,SSS_2025!A:N,9) -> 30 | CK62: 391.25 | CL62: 391.25 | CM62: 200 | CN62: 200 | CO62: =CG62+CH62+CJ62+CL62+CN62 -> 11696.25 | CP62: =(M62+P62+BN62)*10% -> 720 | CQ62: =CO62+CP62 -> 12416.25 | CS62: =CQ62+CR62 -> 12416.25 | CT62: =SUM(M62+(BC62/2)+BL62+BN62+P62)/12 -> 600 | CV62: =IFERROR(VLOOKUP(C62,'[2]BILLING COMPUTATION'!$C$8:$CI$224,85,0),0) -> 10867.5 | CW62: =CG62 -> 9075 | CX62: =CV62+CW62 -> 19942.5 | CZ62: =IFERROR(VLOOKUP(C62,'[5]BILLING COMPUTATION'!$C$8:$CG$101,83,0),0) -> 9367.5 | DA62: =CG62 -> 9075 | DB62: =SUM(CZ62:DA62) -> 18442.5 | DC62: =DB62-CX62 -> -1500
A63: 59 | C63: 32515 | D63: GD260699 | E63: Morete, John Dominic | F63: =VLOOKUP(C63,'[1]ACTIVE GH'!$C:$I,7,0) -> METAL STAMPING | G63: =VLOOKUP(C63,'[1]ACTIVE GH'!$C:$J,8,0) -> PRODUCTION | H63: =VLOOKUP(C63,'[1]ACTIVE GH'!$C:$N,12,0) -> Operator 1 | I63: DL | J63: =IFERROR(VLOOKUP(C63,PIVOT!A:B,2,0),0) -> 80 | K63: =J63/8 -> 10 | L63: 600 | M63: =K63*L63 -> 6000 | N63: =IFERROR(VLOOKUP(C63,PIVOT!A:F,6,0),0) -> 0 | O63: =L63/8/60 -> 1.25 | P63: =-N63*O63 -> 0 | Q63: =IFERROR(VLOOKUP(C63,PIVOT!A:C,3,0),0) -> 10 | R63: =L63/8*1.25 -> 93.75 | S63: =Q63*R63 -> 937.5 | T63: =IFERROR(VLOOKUP(C63,PIVOT!A:D,4,0),0) -> 60 | U63: =L63/8*0.1 -> 7.5 | V63: =T63*U63 -> 450 | W63: =IFERROR(VLOOKUP(C63,PIVOT!A:E,5,0),0) -> 10 | X63: =L63/8*1.25*0.1 -> 9.375 | Y63: =X63*W63 -> 93.75 | Z63: =IFERROR(VLOOKUP(C63,#REF!,6,0),0) -> 0 | AA63: =L63/8*1.3 -> 97.5 | AB63: =Z63*AA63 -> 0 | AD63: =L63/8*1.69 -> 126.75 | AE63: =AD63*AC63 -> 0 | AF63: =IFERROR(VLOOKUP(C63,#REF!,8,0),0) -> 0 | AG63: =L63/8*1.3*0.1 -> 9.75 | AH63: =AF63*AG63 -> 0 | AJ63: =L63/8*1.5 -> 112.5 | AK63: =AI63*AJ63 -> 0 | AM63: =L63/8*1.5*1.3 -> 146.25 | AN63: 0 | AP63: =L63/8*1.5*0.1 -> 11.25 | AQ63: =AO63*AP63 -> 0 | AR63: =IFERROR(VLOOKUP(C63,#REF!,7,0),0) -> 0 | AS63: =L63/8*1.3 -> 97.5 | AT63: =AR63*AS63 -> 0 | AX63: =IFERROR(VLOOKUP(C63,#REF!,8,0),0) -> 0 | AY63: =L63/8*1.3*0.1 -> 9.75 | AZ63: =AX63*AY63 -> 0 | BA63: =IFERROR(VLOOKUP(C63,#REF!,10,0),0) -> 0 | BB63: =600/8*2 -> 150 | BC63: =BA63*BB63 -> 0 | BJ63: =IFERROR(VLOOKUP(C63,#REF!,9,0),0) -> 0 | BK63: =L63/8 -> 75 | BL63: =BJ63*BK63 -> 0 | CG63: =SUM(Y63,V63,S63,P63,M63) -> 7481.25 | CH63: =VLOOKUP(CX63,SSS_2025!A:N,8) -> 1700 | CI63: =VLOOKUP(CX63,SSS_2025!A:N,13) -> 850 | CJ63: =VLOOKUP(CX63,SSS_2025!A:N,9) -> 30 | CK63: 391.25 | CL63: 391.25 | CM63: 200 | CN63: 200 | CO63: =CG63+CH63+CJ63+CL63+CN63 -> 9802.5 | CP63: =(M63+P63+BN63)*10% -> 600 | CQ63: =CO63+CP63 -> 10402.5 | CS63: =CQ63+CR63 -> 10402.5 | CT63: =SUM(M63+(BC63/2)+BL63+BN63+P63)/12 -> 500 | CV63: =IFERROR(VLOOKUP(C63,'[2]BILLING COMPUTATION'!$C$8:$CI$224,85,0),0) -> 9508.75 | CW63: =CG63 -> 7481.25 | CX63: =CV63+CW63 -> 16990 | CZ63: =IFERROR(VLOOKUP(C63,'[5]BILLING COMPUTATION'!$C$8:$CG$101,83,0),0) -> 6240 | DA63: =CG63 -> 7481.25 | DB63: =SUM(CZ63:DA63) -> 13721.25 | DC63: =DB63-CX63 -> -3268.75
A64: 60 | C64: 14915 | D64: =VLOOKUP(E64,'F3 MS (2)'!E:F,2,0) -> GD250241 | E64: Natingga, Precious Gotera | F64: =VLOOKUP(C64,'[1]ACTIVE GH'!$C:$I,7,0) -> METAL STAMPING | G64: =VLOOKUP(C64,'[1]ACTIVE GH'!$C:$J,8,0) -> PRODUCTION | H64: =VLOOKUP(C64,'[1]ACTIVE GH'!$C:$N,12,0) -> Operator 1 | I64: DL | J64: =IFERROR(VLOOKUP(C64,PIVOT!A:B,2,0),0) -> 96 | K64: =J64/8 -> 12 | L64: 600 | M64: =K64*L64 -> 7200 | N64: =IFERROR(VLOOKUP(C64,PIVOT!A:F,6,0),0) -> 0 | O64: =L64/8/60 -> 1.25 | P64: =-N64*O64 -> 0 | Q64: =IFERROR(VLOOKUP(C64,PIVOT!A:C,3,0),0) -> 6 | R64: =L64/8*1.25 -> 93.75 | S64: =Q64*R64 -> 562.5 | T64: =IFERROR(VLOOKUP(C64,PIVOT!A:D,4,0),0) -> 6 | U64: =L64/8*0.1 -> 7.5 | V64: =T64*U64 -> 45 | W64: =IFERROR(VLOOKUP(C64,PIVOT!A:E,5,0),0) -> 0 | X64: =L64/8*1.25*0.1 -> 9.375 | Y64: =X64*W64 -> 0 | Z64: =IFERROR(VLOOKUP(C64,#REF!,6,0),0) -> 0 | AA64: =L64/8*1.3 -> 97.5 | AB64: =Z64*AA64 -> 0 | AD64: =L64/8*1.69 -> 126.75 | AE64: =AD64*AC64 -> 0 | AF64: =IFERROR(VLOOKUP(C64,#REF!,8,0),0) -> 0 | AG64: =L64/8*1.3*0.1 -> 9.75 | AH64: =AF64*AG64 -> 0 | AJ64: =L64/8*1.5 -> 112.5 | AK64: =AI64*AJ64 -> 0 | AM64: =L64/8*1.5*1.3 -> 146.25 | AN64: 0 | AP64: =L64/8*1.5*0.1 -> 11.25 | AQ64: =AO64*AP64 -> 0 | AR64: =IFERROR(VLOOKUP(C64,#REF!,7,0),0) -> 0 | AS64: =L64/8*1.3 -> 97.5 | AT64: =AR64*AS64 -> 0 | AX64: =IFERROR(VLOOKUP(C64,#REF!,8,0),0) -> 0 | AY64: =L64/8*1.3*0.1 -> 9.75 | AZ64: =AX64*AY64 -> 0 | BA64: =IFERROR(VLOOKUP(C64,#REF!,10,0),0) -> 0 | BB64: =600/8*2 -> 150 | BC64: =BA64*BB64 -> 0 | BJ64: =IFERROR(VLOOKUP(C64,#REF!,9,0),0) -> 0 | BK64: =L64/8 -> 75 | BL64: =BJ64*BK64 -> 0 | CG64: =SUM(Y64,V64,S64,P64,M64) -> 7807.5 | CH64: =VLOOKUP(CX64,SSS_2025!A:N,8) -> 1500 | CI64: =VLOOKUP(CX64,SSS_2025!A:N,13) -> 750 | CJ64: =VLOOKUP(CX64,SSS_2025!A:N,9) -> 30 | CK64: 391.25 | CL64: 391.25 | CM64: 200 | CN64: 200 | CO64: =CG64+CH64+CJ64+CL64+CN64 -> 9928.75 | CP64: =(M64+P64+BN64)*10% -> 720 | CQ64: =CO64+CP64 -> 10648.75 | CS64: =CQ64+CR64 -> 10648.75 | CT64: =SUM(M64+(BC64/2)+BL64+BN64+P64)/12 -> 600 | CV64: =IFERROR(VLOOKUP(C64,'[2]BILLING COMPUTATION'!$C$8:$CI$224,85,0),0) -> 6978.75 | CW64: =CG64 -> 7807.5 | CX64: =CV64+CW64 -> 14786.25 | CZ64: =IFERROR(VLOOKUP(C64,'[5]BILLING COMPUTATION'!$C$8:$CG$101,83,0),0) -> 8036.25 | DA64: =CG64 -> 7807.5 | DB64: =SUM(CZ64:DA64) -> 15843.75 | DC64: =DB64-CX64 -> 1057.5
A65: 61 | C65: 14326 | D65: =VLOOKUP(E65,'F3 MS (2)'!E:F,2,0) -> GD250439 | E65: Nazarita, Cherry Mae Badinas | F65: =VLOOKUP(C65,'[1]ACTIVE GH'!$C:$I,7,0) -> METAL STAMPING | G65: =VLOOKUP(C65,'[1]ACTIVE GH'!$C:$J,8,0) -> PRODUCTION | H65: =VLOOKUP(C65,'[1]ACTIVE GH'!$C:$N,12,0) -> Operator 1 | I65: DL | J65: =IFERROR(VLOOKUP(C65,PIVOT!A:B,2,0),0) -> 96 | K65: =J65/8 -> 12 | L65: 600 | M65: =K65*L65 -> 7200 | N65: =IFERROR(VLOOKUP(C65,PIVOT!A:F,6,0),0) -> 0 | O65: =L65/8/60 -> 1.25 | P65: =-N65*O65 -> 0 | Q65: =IFERROR(VLOOKUP(C65,PIVOT!A:C,3,0),0) -> 0 | R65: =L65/8*1.25 -> 93.75 | S65: =Q65*R65 -> 0 | T65: =IFERROR(VLOOKUP(C65,PIVOT!A:D,4,0),0) -> 6 | U65: =L65/8*0.1 -> 7.5 | V65: =T65*U65 -> 45 | W65: =IFERROR(VLOOKUP(C65,PIVOT!A:E,5,0),0) -> 0 | X65: =L65/8*1.25*0.1 -> 9.375 | Y65: =X65*W65 -> 0 | Z65: =IFERROR(VLOOKUP(C65,#REF!,6,0),0) -> 0 | AA65: =L65/8*1.3 -> 97.5 | AB65: =Z65*AA65 -> 0 | AD65: =L65/8*1.69 -> 126.75 | AE65: =AD65*AC65 -> 0 | AF65: =IFERROR(VLOOKUP(C65,#REF!,8,0),0) -> 0 | AG65: =L65/8*1.3*0.1 -> 9.75 | AH65: =AF65*AG65 -> 0 | AJ65: =L65/8*1.5 -> 112.5 | AK65: =AI65*AJ65 -> 0 | AM65: =L65/8*1.5*1.3 -> 146.25 | AN65: 0 | AP65: =L65/8*1.5*0.1 -> 11.25 | AQ65: =AO65*AP65 -> 0 | AR65: =IFERROR(VLOOKUP(C65,#REF!,7,0),0) -> 0 | AS65: =L65/8*1.3 -> 97.5 | AT65: =AR65*AS65 -> 0 | AX65: =IFERROR(VLOOKUP(C65,#REF!,8,0),0) -> 0 | AY65: =L65/8*1.3*0.1 -> 9.75 | AZ65: =AX65*AY65 -> 0 | BA65: =IFERROR(VLOOKUP(C65,#REF!,10,0),0) -> 0 | BB65: =600/8*2 -> 150 | BC65: =BA65*BB65 -> 0 | BJ65: =IFERROR(VLOOKUP(C65,#REF!,9,0),0) -> 0 | BK65: =L65/8 -> 75 | BL65: =BJ65*BK65 -> 0 | CG65: =SUM(Y65,V65,S65,P65,M65) -> 7245 | CH65: =VLOOKUP(CX65,SSS_2025!A:N,8) -> 1850 | CI65: =VLOOKUP(CX65,SSS_2025!A:N,13) -> 925 | CJ65: =VLOOKUP(CX65,SSS_2025!A:N,9) -> 30 | CK65: 391.25 | CL65: 391.25 | CM65: 200 | CN65: 200 | CO65: =CG65+CH65+CJ65+CL65+CN65 -> 9716.25 | CP65: =(M65+P65+BN65)*10% -> 720 | CQ65: =CO65+CP65 -> 10436.25 | CS65: =CQ65+CR65 -> 10436.25 | CT65: =SUM(M65+(BC65/2)+BL65+BN65+P65)/12 -> 600 | CV65: =IFERROR(VLOOKUP(C65,'[2]BILLING COMPUTATION'!$C$8:$CI$224,85,0),0) -> 11216.25 | CW65: =CG65 -> 7245 | CX65: =CV65+CW65 -> 18461.25 | CZ65: =IFERROR(VLOOKUP(C65,'[5]BILLING COMPUTATION'!$C$8:$CG$101,83,0),0) -> 10132.5 | DA65: =CG65 -> 7245 | DB65: =SUM(CZ65:DA65) -> 17377.5 | DC65: =DB65-CX65 -> -1083.75
A66: 62 | C66: 14328 | D66: =VLOOKUP(E66,'F3 MS (2)'!E:F,2,0) -> GD250441 | E66: Nialla, Jenny Mae Bravo | F66: =VLOOKUP(C66,'[1]ACTIVE GH'!$C:$I,7,0) -> METAL STAMPING | G66: =VLOOKUP(C66,'[1]ACTIVE GH'!$C:$J,8,0) -> PRODUCTION | H66: =VLOOKUP(C66,'[1]ACTIVE GH'!$C:$N,12,0) -> Operator 1 | I66: DL | J66: =IFERROR(VLOOKUP(C66,PIVOT!A:B,2,0),0) -> 88 | K66: =J66/8 -> 11 | L66: 600 | M66: =K66*L66 -> 6600 | N66: =IFERROR(VLOOKUP(C66,PIVOT!A:F,6,0),0) -> 0 | O66: =L66/8/60 -> 1.25 | P66: =-N66*O66 -> 0 | Q66: =IFERROR(VLOOKUP(C66,PIVOT!A:C,3,0),0) -> 4 | R66: =L66/8*1.25 -> 93.75 | S66: =Q66*R66 -> 375 | T66: =IFERROR(VLOOKUP(C66,PIVOT!A:D,4,0),0) -> 66 | U66: =L66/8*0.1 -> 7.5 | V66: =T66*U66 -> 495 | W66: =IFERROR(VLOOKUP(C66,PIVOT!A:E,5,0),0) -> 4 | X66: =L66/8*1.25*0.1 -> 9.375 | Y66: =X66*W66 -> 37.5 | Z66: =IFERROR(VLOOKUP(C66,#REF!,6,0),0) -> 0 | AA66: =L66/8*1.3 -> 97.5 | AB66: =Z66*AA66 -> 0 | AD66: =L66/8*1.69 -> 126.75 | AE66: =AD66*AC66 -> 0 | AF66: =IFERROR(VLOOKUP(C66,#REF!,8,0),0) -> 0 | AG66: =L66/8*1.3*0.1 -> 9.75 | AH66: =AF66*AG66 -> 0 | AJ66: =L66/8*1.5 -> 112.5 | AK66: =AI66*AJ66 -> 0 | AM66: =L66/8*1.5*1.3 -> 146.25 | AN66: 0 | AP66: =L66/8*1.5*0.1 -> 11.25 | AQ66: =AO66*AP66 -> 0 | AR66: =IFERROR(VLOOKUP(C66,#REF!,7,0),0) -> 0 | AS66: =L66/8*1.3 -> 97.5 | AT66: =AR66*AS66 -> 0 | AX66: =IFERROR(VLOOKUP(C66,#REF!,8,0),0) -> 0 | AY66: =L66/8*1.3*0.1 -> 9.75 | AZ66: =AX66*AY66 -> 0 | BA66: =IFERROR(VLOOKUP(C66,#REF!,10,0),0) -> 0 | BB66: =600/8*2 -> 150 | BC66: =BA66*BB66 -> 0 | BJ66: =IFERROR(VLOOKUP(C66,#REF!,9,0),0) -> 0 | BK66: =L66/8 -> 75 | BL66: =BJ66*BK66 -> 0 | CG66: =SUM(Y66,V66,S66,P66,M66) -> 7507.5 | CH66: =VLOOKUP(CX66,SSS_2025!A:N,8) -> 1800 | CI66: =VLOOKUP(CX66,SSS_2025!A:N,13) -> 900 | CJ66: =VLOOKUP(CX66,SSS_2025!A:N,9) -> 30 | CK66: 391.25 | CL66: 391.25 | CM66: 200 | CN66: 200 | CO66: =CG66+CH66+CJ66+CL66+CN66 -> 9928.75 | CP66: =(M66+P66+BN66)*10% -> 660 | CQ66: =CO66+CP66 -> 10588.75 | CS66: =CQ66+CR66 -> 10588.75 | CT66: =SUM(M66+(BC66/2)+BL66+BN66+P66)/12 -> 550 | CV66: =IFERROR(VLOOKUP(C66,'[2]BILLING COMPUTATION'!$C$8:$CI$224,85,0),0) -> 10698.75 | CW66: =CG66 -> 7507.5 | CX66: =CV66+CW66 -> 18206.25 | CZ66: =IFERROR(VLOOKUP(C66,'[5]BILLING COMPUTATION'!$C$8:$CG$101,83,0),0) -> 8208.75 | DA66: =CG66 -> 7507.5 | DB66: =SUM(CZ66:DA66) -> 15716.25 | DC66: =DB66-CX66 -> -2490
A67: 63 | C67: 10997 | D67: =VLOOKUP(E67,'F3 MS (2)'!E:F,2,0) -> GD250122 | E67: Nicolas, Joey Camigla | F67: =VLOOKUP(C67,'[1]ACTIVE GH'!$C:$I,7,0) -> METAL STAMPING | G67: =VLOOKUP(C67,'[1]ACTIVE GH'!$C:$J,8,0) -> PRODUCTION | H67: =VLOOKUP(C67,'[1]ACTIVE GH'!$C:$N,12,0) -> Operator 1 | I67: DL | J67: =IFERROR(VLOOKUP(C67,PIVOT!A:B,2,0),0) -> 88 | K67: =J67/8 -> 11 | L67: 600 | M67: =K67*L67 -> 6600 | N67: =IFERROR(VLOOKUP(C67,PIVOT!A:F,6,0),0) -> 0 | O67: =L67/8/60 -> 1.25 | P67: =-N67*O67 -> 0 | Q67: =IFERROR(VLOOKUP(C67,PIVOT!A:C,3,0),0) -> 0 | R67: =L67/8*1.25 -> 93.75 | S67: =Q67*R67 -> 0 | T67: =IFERROR(VLOOKUP(C67,PIVOT!A:D,4,0),0) -> 0 | U67: =L67/8*0.1 -> 7.5 | V67: =T67*U67 -> 0 | W67: =IFERROR(VLOOKUP(C67,PIVOT!A:E,5,0),0) -> 0 | X67: =L67/8*1.25*0.1 -> 9.375 | Y67: =X67*W67 -> 0 | Z67: =IFERROR(VLOOKUP(C67,#REF!,6,0),0) -> 0 | AA67: =L67/8*1.3 -> 97.5 | AB67: =Z67*AA67 -> 0 | AD67: =L67/8*1.69 -> 126.75 | AE67: =AD67*AC67 -> 0 | AF67: =IFERROR(VLOOKUP(C67,#REF!,8,0),0) -> 0 | AG67: =L67/8*1.3*0.1 -> 9.75 | AH67: =AF67*AG67 -> 0 | AJ67: =L67/8*1.5 -> 112.5 | AK67: =AI67*AJ67 -> 0 | AM67: =L67/8*1.5*1.3 -> 146.25 | AN67: 0 | AP67: =L67/8*1.5*0.1 -> 11.25 | AQ67: =AO67*AP67 -> 0 | AR67: =IFERROR(VLOOKUP(C67,#REF!,7,0),0) -> 0 | AS67: =L67/8*1.3 -> 97.5 | AT67: =AR67*AS67 -> 0 | AX67: =IFERROR(VLOOKUP(C67,#REF!,8,0),0) -> 0 | AY67: =L67/8*1.3*0.1 -> 9.75 | AZ67: =AX67*AY67 -> 0 | BA67: =IFERROR(VLOOKUP(C67,#REF!,10,0),0) -> 0 | BB67: =600/8*2 -> 150 | BC67: =BA67*BB67 -> 0 | BJ67: =IFERROR(VLOOKUP(C67,#REF!,9,0),0) -> 0 | BK67: =L67/8 -> 75 | BL67: =BJ67*BK67 -> 0 | CG67: =SUM(Y67,V67,S67,P67,M67) -> 6600 | CH67: =VLOOKUP(CX67,SSS_2025!A:N,8) -> 1700 | CI67: =VLOOKUP(CX67,SSS_2025!A:N,13) -> 850 | CJ67: =VLOOKUP(CX67,SSS_2025!A:N,9) -> 30 | CK67: 391.25 | CL67: 391.25 | CM67: 200 | CN67: 200 | CO67: =CG67+CH67+CJ67+CL67+CN67 -> 8921.25 | CP67: =(M67+P67+BN67)*10% -> 660 | CQ67: =CO67+CP67 -> 9581.25 | CS67: =CQ67+CR67 -> 9581.25 | CT67: =SUM(M67+(BC67/2)+BL67+BN67+P67)/12 -> 550 | CV67: =IFERROR(VLOOKUP(C67,'[2]BILLING COMPUTATION'!$C$8:$CI$224,85,0),0) -> 10597.5 | CW67: =CG67 -> 6600 | CX67: =CV67+CW67 -> 17197.5 | CZ67: =IFERROR(VLOOKUP(C67,'[5]BILLING COMPUTATION'!$C$8:$CG$101,83,0),0) -> 8475 | DA67: =CG67 -> 6600 | DB67: =SUM(CZ67:DA67) -> 15075 | DC67: =DB67-CX67 -> -2122.5
A68: 64 | C68: 10424 | D68: =VLOOKUP(E68,'F3 MS (2)'!E:F,2,0) -> GD250117 | E68: Ochea, Adelfa Abrigo | F68: =VLOOKUP(C68,'[1]ACTIVE GH'!$C:$I,7,0) -> METAL STAMPING | G68: =VLOOKUP(C68,'[1]ACTIVE GH'!$C:$J,8,0) -> PRODUCTION | H68: =VLOOKUP(C68,'[1]ACTIVE GH'!$C:$N,12,0) -> Operator 1 | I68: DL | J68: =IFERROR(VLOOKUP(C68,PIVOT!A:B,2,0),0) -> 96 | K68: =J68/8 -> 12 | L68: 600 | M68: =K68*L68 -> 7200 | N68: =IFERROR(VLOOKUP(C68,PIVOT!A:F,6,0),0) -> 0 | O68: =L68/8/60 -> 1.25 | P68: =-N68*O68 -> 0 | Q68: =IFERROR(VLOOKUP(C68,PIVOT!A:C,3,0),0) -> 4 | R68: =L68/8*1.25 -> 93.75 | S68: =Q68*R68 -> 375 | T68: =IFERROR(VLOOKUP(C68,PIVOT!A:D,4,0),0) -> 66 | U68: =L68/8*0.1 -> 7.5 | V68: =T68*U68 -> 495 | W68: =IFERROR(VLOOKUP(C68,PIVOT!A:E,5,0),0) -> 4 | X68: =L68/8*1.25*0.1 -> 9.375 | Y68: =X68*W68 -> 37.5 | Z68: =IFERROR(VLOOKUP(C68,#REF!,6,0),0) -> 0 | AA68: =L68/8*1.3 -> 97.5 | AB68: =Z68*AA68 -> 0 | AD68: =L68/8*1.69 -> 126.75 | AE68: =AD68*AC68 -> 0 | AF68: =IFERROR(VLOOKUP(C68,#REF!,8,0),0) -> 0 | AG68: =L68/8*1.3*0.1 -> 9.75 | AH68: =AF68*AG68 -> 0 | AJ68: =L68/8*1.5 -> 112.5 | AK68: =AI68*AJ68 -> 0 | AM68: =L68/8*1.5*1.3 -> 146.25 | AN68: 0 | AP68: =L68/8*1.5*0.1 -> 11.25 | AQ68: =AO68*AP68 -> 0 | AR68: =IFERROR(VLOOKUP(C68,#REF!,7,0),0) -> 0 | AS68: =L68/8*1.3 -> 97.5 | AT68: =AR68*AS68 -> 0 | AX68: =IFERROR(VLOOKUP(C68,#REF!,8,0),0) -> 0 | AY68: =L68/8*1.3*0.1 -> 9.75 | AZ68: =AX68*AY68 -> 0 | BA68: =IFERROR(VLOOKUP(C68,#REF!,10,0),0) -> 0 | BB68: =600/8*2 -> 150 | BC68: =BA68*BB68 -> 0 | BJ68: =IFERROR(VLOOKUP(C68,#REF!,9,0),0) -> 0 | BK68: =L68/8 -> 75 | BL68: =BJ68*BK68 -> 0 | CG68: =SUM(Y68,V68,S68,P68,M68) -> 8107.5 | CH68: =VLOOKUP(CX68,SSS_2025!A:N,8) -> 1900 | CI68: =VLOOKUP(CX68,SSS_2025!A:N,13) -> 950 | CJ68: =VLOOKUP(CX68,SSS_2025!A:N,9) -> 30 | CK68: 391.25 | CL68: 391.25 | CM68: 200 | CN68: 200 | CO68: =CG68+CH68+CJ68+CL68+CN68 -> 10628.75 | CP68: =(M68+P68+BN68)*10% -> 720 | CQ68: =CO68+CP68 -> 11348.75 | CS68: =CQ68+CR68 -> 11348.75 | CT68: =SUM(M68+(BC68/2)+BL68+BN68+P68)/12 -> 600 | CV68: =IFERROR(VLOOKUP(C68,'[2]BILLING COMPUTATION'!$C$8:$CI$224,85,0),0) -> 10698.75 | CW68: =CG68 -> 8107.5 | CX68: =CV68+CW68 -> 18806.25 | CZ68: =IFERROR(VLOOKUP(C68,'[5]BILLING COMPUTATION'!$C$8:$CG$101,83,0),0) -> 8621.25 | DA68: =CG68 -> 8107.5 | DB68: =SUM(CZ68:DA68) -> 16728.75 | DC68: =DB68-CX68 -> -2077.5
A69: 65 | C69: 8176 | D69: =VLOOKUP(E69,'F3 MS (2)'!E:F,2,0) -> GD250051 | E69: Oclarino, Edena San Buenaventura | F69: =VLOOKUP(C69,'[1]ACTIVE GH'!$C:$I,7,0) -> METAL STAMPING | G69: =VLOOKUP(C69,'[1]ACTIVE GH'!$C:$J,8,0) -> PRODUCTION | H69: =VLOOKUP(C69,'[1]ACTIVE GH'!$C:$N,12,0) -> Operator 1 | I69: DL | J69: =IFERROR(VLOOKUP(C69,PIVOT!A:B,2,0),0) -> 72 | K69: =J69/8 -> 9 | L69: 600 | M69: =K69*L69 -> 5400 | N69: =IFERROR(VLOOKUP(C69,PIVOT!A:F,6,0),0) -> 0 | O69: =L69/8/60 -> 1.25 | P69: =-N69*O69 -> 0 | Q69: =IFERROR(VLOOKUP(C69,PIVOT!A:C,3,0),0) -> 4 | R69: =L69/8*1.25 -> 93.75 | S69: =Q69*R69 -> 375 | T69: =IFERROR(VLOOKUP(C69,PIVOT!A:D,4,0),0) -> 48 | U69: =L69/8*0.1 -> 7.5 | V69: =T69*U69 -> 360 | W69: =IFERROR(VLOOKUP(C69,PIVOT!A:E,5,0),0) -> 4 | X69: =L69/8*1.25*0.1 -> 9.375 | Y69: =X69*W69 -> 37.5 | Z69: =IFERROR(VLOOKUP(C69,#REF!,6,0),0) -> 0 | AA69: =L69/8*1.3 -> 97.5 | AB69: =Z69*AA69 -> 0 | AD69: =L69/8*1.69 -> 126.75 | AE69: =AD69*AC69 -> 0 | AF69: =IFERROR(VLOOKUP(C69,#REF!,8,0),0) -> 0 | AG69: =L69/8*1.3*0.1 -> 9.75 | AH69: =AF69*AG69 -> 0 | AJ69: =L69/8*1.5 -> 112.5 | AK69: =AI69*AJ69 -> 0 | AM69: =L69/8*1.5*1.3 -> 146.25 | AN69: 0 | AP69: =L69/8*1.5*0.1 -> 11.25 | AQ69: =AO69*AP69 -> 0 | AR69: =IFERROR(VLOOKUP(C69,#REF!,7,0),0) -> 0 | AS69: =L69/8*1.3 -> 97.5 | AT69: =AR69*AS69 -> 0 | AX69: =IFERROR(VLOOKUP(C69,#REF!,8,0),0) -> 0 | AY69: =L69/8*1.3*0.1 -> 9.75 | AZ69: =AX69*AY69 -> 0 | BA69: =IFERROR(VLOOKUP(C69,#REF!,10,0),0) -> 0 | BB69: =600/8*2 -> 150 | BC69: =BA69*BB69 -> 0 | BJ69: =IFERROR(VLOOKUP(C69,#REF!,9,0),0) -> 0 | BK69: =L69/8 -> 75 | BL69: =BJ69*BK69 -> 0 | CG69: =SUM(Y69,V69,S69,P69,M69) -> 6172.5 | CH69: =VLOOKUP(CX69,SSS_2025!A:N,8) -> 1150 | CI69: =VLOOKUP(CX69,SSS_2025!A:N,13) -> 575 | CJ69: =VLOOKUP(CX69,SSS_2025!A:N,9) -> 10 | CK69: 391.25 | CL69: 391.25 | CM69: 200 | CN69: 200 | CO69: =CG69+CH69+CJ69+CL69+CN69 -> 7923.75 | CP69: =(M69+P69+BN69)*10% -> 540 | CQ69: =CO69+CP69 -> 8463.75 | CS69: =CQ69+CR69 -> 8463.75 | CT69: =SUM(M69+(BC69/2)+BL69+BN69+P69)/12 -> 450 | CV69: =IFERROR(VLOOKUP(C69,'[2]BILLING COMPUTATION'!$C$8:$CI$224,85,0),0) -> 5325 | CW69: =CG69 -> 6172.5 | CX69: =CV69+CW69 -> 11497.5 | CZ69: =IFERROR(VLOOKUP(C69,'[5]BILLING COMPUTATION'!$C$8:$CG$101,83,0),0) -> 9596.25 | DA69: =CG69 -> 6172.5 | DB69: =SUM(CZ69:DA69) -> 15768.75 | DC69: =DB69-CX69 -> 4271.25
A70: 66 | C70: 11742 | D70: =VLOOKUP(E70,'F3 MS (2)'!E:F,2,0) -> GD250174 | E70: Ordeniza, Lorna Salamangga | F70: =VLOOKUP(C70,'[1]ACTIVE GH'!$C:$I,7,0) -> METAL STAMPING | G70: =VLOOKUP(C70,'[1]ACTIVE GH'!$C:$J,8,0) -> PRODUCTION | H70: =VLOOKUP(C70,'[1]ACTIVE GH'!$C:$N,12,0) -> Operator 1 | I70: DL | J70: =IFERROR(VLOOKUP(C70,PIVOT!A:B,2,0),0) -> 96 | K70: =J70/8 -> 12 | L70: 600 | M70: =K70*L70 -> 7200 | N70: =IFERROR(VLOOKUP(C70,PIVOT!A:F,6,0),0) -> 0 | O70: =L70/8/60 -> 1.25 | P70: =-N70*O70 -> 0 | Q70: =IFERROR(VLOOKUP(C70,PIVOT!A:C,3,0),0) -> 16 | R70: =L70/8*1.25 -> 93.75 | S70: =Q70*R70 -> 1500 | T70: =IFERROR(VLOOKUP(C70,PIVOT!A:D,4,0),0) -> 6 | U70: =L70/8*0.1 -> 7.5 | V70: =T70*U70 -> 45 | W70: =IFERROR(VLOOKUP(C70,PIVOT!A:E,5,0),0) -> 0 | X70: =L70/8*1.25*0.1 -> 9.375 | Y70: =X70*W70 -> 0 | Z70: =IFERROR(VLOOKUP(C70,#REF!,6,0),0) -> 0 | AA70: =L70/8*1.3 -> 97.5 | AB70: =Z70*AA70 -> 0 | AD70: =L70/8*1.69 -> 126.75 | AE70: =AD70*AC70 -> 0 | AF70: =IFERROR(VLOOKUP(C70,#REF!,8,0),0) -> 0 | AG70: =L70/8*1.3*0.1 -> 9.75 | AH70: =AF70*AG70 -> 0 | AJ70: =L70/8*1.5 -> 112.5 | AK70: =AI70*AJ70 -> 0 | AM70: =L70/8*1.5*1.3 -> 146.25 | AN70: 0 | AP70: =L70/8*1.5*0.1 -> 11.25 | AQ70: =AO70*AP70 -> 0 | AR70: =IFERROR(VLOOKUP(C70,#REF!,7,0),0) -> 0 | AS70: =L70/8*1.3 -> 97.5 | AT70: =AR70*AS70 -> 0 | AX70: =IFERROR(VLOOKUP(C70,#REF!,8,0),0) -> 0 | AY70: =L70/8*1.3*0.1 -> 9.75 | AZ70: =AX70*AY70 -> 0 | BA70: =IFERROR(VLOOKUP(C70,#REF!,10,0),0) -> 0 | BB70: =600/8*2 -> 150 | BC70: =BA70*BB70 -> 0 | BJ70: =IFERROR(VLOOKUP(C70,#REF!,9,0),0) -> 0 | BK70: =L70/8 -> 75 | BL70: =BJ70*BK70 -> 0 | CG70: =SUM(Y70,V70,S70,P70,M70) -> 8745 | CH70: =VLOOKUP(CX70,SSS_2025!A:N,8) -> 1900 | CI70: =VLOOKUP(CX70,SSS_2025!A:N,13) -> 950 | CJ70: =VLOOKUP(CX70,SSS_2025!A:N,9) -> 30 | CK70: 391.25 | CL70: 391.25 | CM70: 200 | CN70: 200 | CO70: =CG70+CH70+CJ70+CL70+CN70 -> 11266.25 | CP70: =(M70+P70+BN70)*10% -> 720 | CQ70: =CO70+CP70 -> 11986.25 | CS70: =CQ70+CR70 -> 11986.25 | CT70: =SUM(M70+(BC70/2)+BL70+BN70+P70)/12 -> 600 | CV70: =IFERROR(VLOOKUP(C70,'[2]BILLING COMPUTATION'!$C$8:$CI$224,85,0),0) -> 10492.5 | CW70: =CG70 -> 8745 | CX70: =CV70+CW70 -> 19237.5 | CZ70: =IFERROR(VLOOKUP(C70,'[5]BILLING COMPUTATION'!$C$8:$CG$101,83,0),0) -> 11418.75 | DA70: =CG70 -> 8745 | DB70: =SUM(CZ70:DA70) -> 20163.75 | DC70: =DB70-CX70 -> 926.25
A71: 67 | C71: 32494 | D71: =VLOOKUP(E71,'F3 MS (2)'!E:F,2,0) -> GD260705 | E71: Ortiz, Neomie | F71: =VLOOKUP(C71,'[1]ACTIVE GH'!$C:$I,7,0) -> METAL STAMPING | G71: =VLOOKUP(C71,'[1]ACTIVE GH'!$C:$J,8,0) -> PRODUCTION | H71: =VLOOKUP(C71,'[1]ACTIVE GH'!$C:$N,12,0) -> Operator 1 | I71: DL | J71: =IFERROR(VLOOKUP(C71,PIVOT!A:B,2,0),0) -> 96 | K71: =J71/8 -> 12 | L71: 600 | M71: =K71*L71 -> 7200 | N71: =IFERROR(VLOOKUP(C71,PIVOT!A:F,6,0),0) -> 0 | O71: =L71/8/60 -> 1.25 | P71: =-N71*O71 -> 0 | Q71: =IFERROR(VLOOKUP(C71,PIVOT!A:C,3,0),0) -> 12 | R71: =L71/8*1.25 -> 93.75 | S71: =Q71*R71 -> 1125 | T71: =IFERROR(VLOOKUP(C71,PIVOT!A:D,4,0),0) -> 0 | U71: =L71/8*0.1 -> 7.5 | V71: =T71*U71 -> 0 | W71: =IFERROR(VLOOKUP(C71,PIVOT!A:E,5,0),0) -> 0 | X71: =L71/8*1.25*0.1 -> 9.375 | Y71: =X71*W71 -> 0 | Z71: =IFERROR(VLOOKUP(C71,#REF!,6,0),0) -> 0 | AA71: =L71/8*1.3 -> 97.5 | AB71: =Z71*AA71 -> 0 | AD71: =L71/8*1.69 -> 126.75 | AE71: =AD71*AC71 -> 0 | AF71: =IFERROR(VLOOKUP(C71,#REF!,8,0),0) -> 0 | AG71: =L71/8*1.3*0.1 -> 9.75 | AH71: =AF71*AG71 -> 0 | AJ71: =L71/8*1.5 -> 112.5 | AK71: =AI71*AJ71 -> 0 | AM71: =L71/8*1.5*1.3 -> 146.25 | AN71: 0 | AP71: =L71/8*1.5*0.1 -> 11.25 | AQ71: =AO71*AP71 -> 0 | AR71: =IFERROR(VLOOKUP(C71,#REF!,7,0),0) -> 0 | AS71: =L71/8*1.3 -> 97.5 | AT71: =AR71*AS71 -> 0 | AX71: =IFERROR(VLOOKUP(C71,#REF!,8,0),0) -> 0 | AY71: =L71/8*1.3*0.1 -> 9.75 | AZ71: =AX71*AY71 -> 0 | BA71: =IFERROR(VLOOKUP(C71,#REF!,10,0),0) -> 0 | BB71: =600/8*2 -> 150 | BC71: =BA71*BB71 -> 0 | BJ71: =IFERROR(VLOOKUP(C71,#REF!,9,0),0) -> 0 | BK71: =L71/8 -> 75 | BL71: =BJ71*BK71 -> 0 | CG71: =SUM(Y71,V71,S71,P71,M71) -> 8325 | CH71: =VLOOKUP(CX71,SSS_2025!A:N,8) -> 1850 | CI71: =VLOOKUP(CX71,SSS_2025!A:N,13) -> 925 | CJ71: =VLOOKUP(CX71,SSS_2025!A:N,9) -> 30 | CK71: 391.25 | CL71: 391.25 | CM71: 200 | CN71: 200 | CO71: =CG71+CH71+CJ71+CL71+CN71 -> 10796.25 | CP71: =(M71+P71+BN71)*10% -> 720 | CQ71: =CO71+CP71 -> 11516.25 | CS71: =CQ71+CR71 -> 11516.25 | CT71: =SUM(M71+(BC71/2)+BL71+BN71+P71)/12 -> 600 | CV71: =IFERROR(VLOOKUP(C71,'[2]BILLING COMPUTATION'!$C$8:$CI$224,85,0),0) -> 10305 | CW71: =CG71 -> 8325 | CX71: =CV71+CW71 -> 18630 | CZ71: =IFERROR(VLOOKUP(C71,'[5]BILLING COMPUTATION'!$C$8:$CG$101,83,0),0) -> 7500 | DA71: =CG71 -> 8325 | DB71: =SUM(CZ71:DA71) -> 15825 | DC71: =DB71-CX71 -> -2805
A72: 68 | C72: 6244 | D72: =VLOOKUP(E72,'F3 MS (2)'!E:F,2,0) -> GD250073 | E72: Pagcaliwangan, Jessa Leyesa | F72: =VLOOKUP(C72,'[1]ACTIVE GH'!$C:$I,7,0) -> METAL STAMPING | G72: =VLOOKUP(C72,'[1]ACTIVE GH'!$C:$J,8,0) -> PRODUCTION | H72: =VLOOKUP(C72,'[1]ACTIVE GH'!$C:$N,12,0) -> Operator 1 | I72: DL | J72: =IFERROR(VLOOKUP(C72,PIVOT!A:B,2,0),0) -> 80 | K72: =J72/8 -> 10 | L72: 600 | M72: =K72*L72 -> 6000 | N72: =IFERROR(VLOOKUP(C72,PIVOT!A:F,6,0),0) -> 0 | O72: =L72/8/60 -> 1.25 | P72: =-N72*O72 -> 0 | Q72: =IFERROR(VLOOKUP(C72,PIVOT!A:C,3,0),0) -> 0 | R72: =L72/8*1.25 -> 93.75 | S72: =Q72*R72 -> 0 | T72: =IFERROR(VLOOKUP(C72,PIVOT!A:D,4,0),0) -> 54 | U72: =L72/8*0.1 -> 7.5 | V72: =T72*U72 -> 405 | W72: =IFERROR(VLOOKUP(C72,PIVOT!A:E,5,0),0) -> 0 | X72: =L72/8*1.25*0.1 -> 9.375 | Y72: =X72*W72 -> 0 | Z72: =IFERROR(VLOOKUP(C72,#REF!,6,0),0) -> 0 | AA72: =L72/8*1.3 -> 97.5 | AB72: =Z72*AA72 -> 0 | AD72: =L72/8*1.69 -> 126.75 | AE72: =AD72*AC72 -> 0 | AF72: =IFERROR(VLOOKUP(C72,#REF!,8,0),0) -> 0 | AG72: =L72/8*1.3*0.1 -> 9.75 | AH72: =AF72*AG72 -> 0 | AJ72: =L72/8*1.5 -> 112.5 | AK72: =AI72*AJ72 -> 0 | AM72: =L72/8*1.5*1.3 -> 146.25 | AN72: 0 | AP72: =L72/8*1.5*0.1 -> 11.25 | AQ72: =AO72*AP72 -> 0 | AR72: =IFERROR(VLOOKUP(C72,#REF!,7,0),0) -> 0 | AS72: =L72/8*1.3 -> 97.5 | AT72: =AR72*AS72 -> 0 | AX72: =IFERROR(VLOOKUP(C72,#REF!,8,0),0) -> 0 | AY72: =L72/8*1.3*0.1 -> 9.75 | AZ72: =AX72*AY72 -> 0 | BA72: =IFERROR(VLOOKUP(C72,#REF!,10,0),0) -> 0 | BB72: =600/8*2 -> 150 | BC72: =BA72*BB72 -> 0 | BJ72: =IFERROR(VLOOKUP(C72,#REF!,9,0),0) -> 0 | BK72: =L72/8 -> 75 | BL72: =BJ72*BK72 -> 0 | CG72: =SUM(Y72,V72,S72,P72,M72) -> 6405 | CH72: =VLOOKUP(CX72,SSS_2025!A:N,8) -> 1700 | CI72: =VLOOKUP(CX72,SSS_2025!A:N,13) -> 850 | CJ72: =VLOOKUP(CX72,SSS_2025!A:N,9) -> 30 | CK72: 391.25 | CL72: 391.25 | CM72: 200 | CN72: 200 | CO72: =CG72+CH72+CJ72+CL72+CN72 -> 8726.25 | CP72: =(M72+P72+BN72)*10% -> 600 | CQ72: =CO72+CP72 -> 9326.25 | CS72: =CQ72+CR72 -> 9326.25 | CT72: =SUM(M72+(BC72/2)+BL72+BN72+P72)/12 -> 500 | CV72: =IFERROR(VLOOKUP(C72,'[2]BILLING COMPUTATION'!$C$8:$CI$224,85,0),0) -> 10698.75 | CW72: =CG72 -> 6405 | CX72: =CV72+CW72 -> 17103.75 | CZ72: =IFERROR(VLOOKUP(C72,'[5]BILLING COMPUTATION'!$C$8:$CG$101,83,0),0) -> 9408.75 | DA72: =CG72 -> 6405 | DB72: =SUM(CZ72:DA72) -> 15813.75 | DC72: =DB72-CX72 -> -1290
A73: 69 | C73: 30680 | D73: =VLOOKUP(E73,'F3 MS (2)'!E:F,2,0) -> GD250547 | E73: Pamada, James Benavidez | F73: =VLOOKUP(C73,'[1]ACTIVE GH'!$C:$I,7,0) -> METAL STAMPING | G73: =VLOOKUP(C73,'[1]ACTIVE GH'!$C:$J,8,0) -> PRODUCTION | H73: =VLOOKUP(C73,'[1]ACTIVE GH'!$C:$N,12,0) -> Operator 1 | I73: DL | J73: =IFERROR(VLOOKUP(C73,PIVOT!A:B,2,0),0) -> 88 | K73: =J73/8 -> 11 | L73: 600 | M73: =K73*L73 -> 6600 | N73: =IFERROR(VLOOKUP(C73,PIVOT!A:F,6,0),0) -> 0 | O73: =L73/8/60 -> 1.25 | P73: =-N73*O73 -> 0 | Q73: =IFERROR(VLOOKUP(C73,PIVOT!A:C,3,0),0) -> 4 | R73: =L73/8*1.25 -> 93.75 | S73: =Q73*R73 -> 375 | T73: =IFERROR(VLOOKUP(C73,PIVOT!A:D,4,0),0) -> 66 | U73: =L73/8*0.1 -> 7.5 | V73: =T73*U73 -> 495 | W73: =IFERROR(VLOOKUP(C73,PIVOT!A:E,5,0),0) -> 4 | X73: =L73/8*1.25*0.1 -> 9.375 | Y73: =X73*W73 -> 37.5 | Z73: =IFERROR(VLOOKUP(C73,#REF!,6,0),0) -> 0 | AA73: =L73/8*1.3 -> 97.5 | AB73: =Z73*AA73 -> 0 | AD73: =L73/8*1.69 -> 126.75 | AE73: =AD73*AC73 -> 0 | AF73: =IFERROR(VLOOKUP(C73,#REF!,8,0),0) -> 0 | AG73: =L73/8*1.3*0.1 -> 9.75 | AH73: =AF73*AG73 -> 0 | AJ73: =L73/8*1.5 -> 112.5 | AK73: =AI73*AJ73 -> 0 | AM73: =L73/8*1.5*1.3 -> 146.25 | AN73: 0 | AP73: =L73/8*1.5*0.1 -> 11.25 | AQ73: =AO73*AP73 -> 0 | AR73: =IFERROR(VLOOKUP(C73,#REF!,7,0),0) -> 0 | AS73: =L73/8*1.3 -> 97.5 | AT73: =AR73*AS73 -> 0 | AX73: =IFERROR(VLOOKUP(C73,#REF!,8,0),0) -> 0 | AY73: =L73/8*1.3*0.1 -> 9.75 | AZ73: =AX73*AY73 -> 0 | BA73: =IFERROR(VLOOKUP(C73,#REF!,10,0),0) -> 0 | BB73: =600/8*2 -> 150 | BC73: =BA73*BB73 -> 0 | BJ73: =IFERROR(VLOOKUP(C73,#REF!,9,0),0) -> 0 | BK73: =L73/8 -> 75 | BL73: =BJ73*BK73 -> 0 | CG73: =SUM(Y73,V73,S73,P73,M73) -> 7507.5 | CH73: =VLOOKUP(CX73,SSS_2025!A:N,8) -> 1700 | CI73: =VLOOKUP(CX73,SSS_2025!A:N,13) -> 850 | CJ73: =VLOOKUP(CX73,SSS_2025!A:N,9) -> 30 | CK73: 391.25 | CL73: 391.25 | CM73: 200 | CN73: 200 | CO73: =CG73+CH73+CJ73+CL73+CN73 -> 9828.75 | CP73: =(M73+P73+BN73)*10% -> 660 | CQ73: =CO73+CP73 -> 10488.75 | CS73: =CQ73+CR73 -> 10488.75 | CT73: =SUM(M73+(BC73/2)+BL73+BN73+P73)/12 -> 550 | CV73: =IFERROR(VLOOKUP(C73,'[2]BILLING COMPUTATION'!$C$8:$CI$224,85,0),0) -> 9536.25 | CW73: =CG73 -> 7507.5 | CX73: =CV73+CW73 -> 17043.75 | CZ73: =IFERROR(VLOOKUP(C73,'[5]BILLING COMPUTATION'!$C$8:$CG$101,83,0),0) -> 6352.5 | DA73: =CG73 -> 7507.5 | DB73: =SUM(CZ73:DA73) -> 13860 | DC73: =DB73-CX73 -> -3183.75
A74: 70 | C74: 12460 | D74: =VLOOKUP(E74,'F3 MS (2)'!E:F,2,0) -> GD250123 | E74: Pamplona, Hazel | F74: =VLOOKUP(C74,'[1]ACTIVE GH'!$C:$I,7,0) -> METAL STAMPING | G74: =VLOOKUP(C74,'[1]ACTIVE GH'!$C:$J,8,0) -> PRODUCTION | H74: =VLOOKUP(C74,'[1]ACTIVE GH'!$C:$N,12,0) -> Operator 1 | I74: DL | J74: =IFERROR(VLOOKUP(C74,PIVOT!A:B,2,0),0) -> 96 | K74: =J74/8 -> 12 | L74: 600 | M74: =K74*L74 -> 7200 | N74: =IFERROR(VLOOKUP(C74,PIVOT!A:F,6,0),0) -> 0 | O74: =L74/8/60 -> 1.25 | P74: =-N74*O74 -> 0 | Q74: =IFERROR(VLOOKUP(C74,PIVOT!A:C,3,0),0) -> 10 | R74: =L74/8*1.25 -> 93.75 | S74: =Q74*R74 -> 937.5 | T74: =IFERROR(VLOOKUP(C74,PIVOT!A:D,4,0),0) -> 66 | U74: =L74/8*0.1 -> 7.5 | V74: =T74*U74 -> 495 | W74: =IFERROR(VLOOKUP(C74,PIVOT!A:E,5,0),0) -> 10 | X74: =L74/8*1.25*0.1 -> 9.375 | Y74: =X74*W74 -> 93.75 | Z74: =IFERROR(VLOOKUP(C74,#REF!,6,0),0) -> 0 | AA74: =L74/8*1.3 -> 97.5 | AB74: =Z74*AA74 -> 0 | AD74: =L74/8*1.69 -> 126.75 | AE74: =AD74*AC74 -> 0 | AF74: =IFERROR(VLOOKUP(C74,#REF!,8,0),0) -> 0 | AG74: =L74/8*1.3*0.1 -> 9.75 | AH74: =AF74*AG74 -> 0 | AJ74: =L74/8*1.5 -> 112.5 | AK74: =AI74*AJ74 -> 0 | AM74: =L74/8*1.5*1.3 -> 146.25 | AN74: 0 | AP74: =L74/8*1.5*0.1 -> 11.25 | AQ74: =AO74*AP74 -> 0 | AR74: =IFERROR(VLOOKUP(C74,#REF!,7,0),0) -> 0 | AS74: =L74/8*1.3 -> 97.5 | AT74: =AR74*AS74 -> 0 | AX74: =IFERROR(VLOOKUP(C74,#REF!,8,0),0) -> 0 | AY74: =L74/8*1.3*0.1 -> 9.75 | AZ74: =AX74*AY74 -> 0 | BA74: =IFERROR(VLOOKUP(C74,#REF!,10,0),0) -> 0 | BB74: =600/8*2 -> 150 | BC74: =BA74*BB74 -> 0 | BJ74: =IFERROR(VLOOKUP(C74,#REF!,9,0),0) -> 0 | BK74: =L74/8 -> 75 | BL74: =BJ74*BK74 -> 0 | CG74: =SUM(Y74,V74,S74,P74,M74) -> 8726.25 | CH74: =VLOOKUP(CX74,SSS_2025!A:N,8) -> 1950 | CI74: =VLOOKUP(CX74,SSS_2025!A:N,13) -> 975 | CJ74: =VLOOKUP(CX74,SSS_2025!A:N,9) -> 30 | CK74: 391.25 | CL74: 391.25 | CM74: 200 | CN74: 200 | CO74: =CG74+CH74+CJ74+CL74+CN74 -> 11297.5 | CP74: =(M74+P74+BN74)*10% -> 720 | CQ74: =CO74+CP74 -> 12017.5 | CS74: =CQ74+CR74 -> 12017.5 | CT74: =SUM(M74+(BC74/2)+BL74+BN74+P74)/12 -> 600 | CV74: =IFERROR(VLOOKUP(C74,'[2]BILLING COMPUTATION'!$C$8:$CI$224,85,0),0) -> 10698.75 | CW74: =CG74 -> 8726.25 | CX74: =CV74+CW74 -> 19425 | CZ74: =IFERROR(VLOOKUP(C74,'[5]BILLING COMPUTATION'!$C$8:$CG$101,83,0),0) -> 10562.5 | DA74: =CG74 -> 8726.25 | DB74: =SUM(CZ74:DA74) -> 19288.75 | DC74: =DB74-CX74 -> -136.25
A75: 71 | C75: 30019 | D75: =VLOOKUP(E75,'F3 MS (2)'!E:F,2,0) -> GD250452 | E75: Panta, Jerick | F75: =VLOOKUP(C75,'[1]ACTIVE GH'!$C:$I,7,0) -> METAL STAMPING | G75: =VLOOKUP(C75,'[1]ACTIVE GH'!$C:$J,8,0) -> PRODUCTION | H75: =VLOOKUP(C75,'[1]ACTIVE GH'!$C:$N,12,0) -> Operator 1 | I75: DL | J75: =IFERROR(VLOOKUP(C75,PIVOT!A:B,2,0),0) -> 88 | K75: =J75/8 -> 11 | L75: 600 | M75: =K75*L75 -> 6600 | N75: =IFERROR(VLOOKUP(C75,PIVOT!A:F,6,0),0) -> 0 | O75: =L75/8/60 -> 1.25 | P75: =-N75*O75 -> 0 | Q75: =IFERROR(VLOOKUP(C75,PIVOT!A:C,3,0),0) -> 0 | R75: =L75/8*1.25 -> 93.75 | S75: =Q75*R75 -> 0 | T75: =IFERROR(VLOOKUP(C75,PIVOT!A:D,4,0),0) -> 0 | U75: =L75/8*0.1 -> 7.5 | V75: =T75*U75 -> 0 | W75: =IFERROR(VLOOKUP(C75,PIVOT!A:E,5,0),0) -> 0 | X75: =L75/8*1.25*0.1 -> 9.375 | Y75: =X75*W75 -> 0 | Z75: =IFERROR(VLOOKUP(C75,#REF!,6,0),0) -> 0 | AA75: =L75/8*1.3 -> 97.5 | AB75: =Z75*AA75 -> 0 | AD75: =L75/8*1.69 -> 126.75 | AE75: =AD75*AC75 -> 0 | AF75: =IFERROR(VLOOKUP(C75,#REF!,8,0),0) -> 0 | AG75: =L75/8*1.3*0.1 -> 9.75 | AH75: =AF75*AG75 -> 0 | AJ75: =L75/8*1.5 -> 112.5 | AK75: =AI75*AJ75 -> 0 | AM75: =L75/8*1.5*1.3 -> 146.25 | AN75: 0 | AP75: =L75/8*1.5*0.1 -> 11.25 | AQ75: =AO75*AP75 -> 0 | AR75: =IFERROR(VLOOKUP(C75,#REF!,7,0),0) -> 0 | AS75: =L75/8*1.3 -> 97.5 | AT75: =AR75*AS75 -> 0 | AX75: =IFERROR(VLOOKUP(C75,#REF!,8,0),0) -> 0 | AY75: =L75/8*1.3*0.1 -> 9.75 | AZ75: =AX75*AY75 -> 0 | BA75: =IFERROR(VLOOKUP(C75,#REF!,10,0),0) -> 0 | BB75: =600/8*2 -> 150 | BC75: =BA75*BB75 -> 0 | BJ75: =IFERROR(VLOOKUP(C75,#REF!,9,0),0) -> 0 | BK75: =L75/8 -> 75 | BL75: =BJ75*BK75 -> 0 | CG75: =SUM(Y75,V75,S75,P75,M75) -> 6600 | CH75: =VLOOKUP(CX75,SSS_2025!A:N,8) -> 1000 | CI75: =VLOOKUP(CX75,SSS_2025!A:N,13) -> 500 | CJ75: =VLOOKUP(CX75,SSS_2025!A:N,9) -> 10 | CK75: 391.25 | CL75: 391.25 | CM75: 200 | CN75: 200 | CO75: =CG75+CH75+CJ75+CL75+CN75 -> 8201.25 | CP75: =(M75+P75+BN75)*10% -> 660 | CQ75: =CO75+CP75 -> 8861.25 | CS75: =CQ75+CR75 -> 8861.25 | CT75: =SUM(M75+(BC75/2)+BL75+BN75+P75)/12 -> 550 | CV75: =IFERROR(VLOOKUP(C75,'[2]BILLING COMPUTATION'!$C$8:$CI$224,85,0),0) -> 3375 | CW75: =CG75 -> 6600 | CX75: =CV75+CW75 -> 9975 | CZ75: =IFERROR(VLOOKUP(C75,'[5]BILLING COMPUTATION'!$C$8:$CG$101,83,0),0) -> 9110 | DA75: =CG75 -> 6600 | DB75: =SUM(CZ75:DA75) -> 15710 | DC75: =DB75-CX75 -> 5735
... A79: 75 | C79: 30611 | D79: =VLOOKUP(E79,'F3 MS (2)'!E:F,2,0) -> GD250554 | E79: Pisuena, Jae Ann Espiritu | F79: =VLOOKUP(C79,'[1]ACTIVE GH'!$C:$I,7,0) -> METAL STAMPING | G79: =VLOOKUP(C79,'[1]ACTIVE GH'!$C:$J,8,0) -> PRODUCTION | H79: =VLOOKUP(C79,'[1]ACTIVE GH'!$C:$N,12,0) -> Operator 1 | I79: DL | J79: =IFERROR(VLOOKUP(C79,PIVOT!A:B,2,0),0) -> 96 | K79: =J79/8 -> 12 | L79: 600 | M79: =K79*L79 -> 7200 | N79: =IFERROR(VLOOKUP(C79,PIVOT!A:F,6,0),0) -> 0 | O79: =L79/8/60 -> 1.25 | P79: =-N79*O79 -> 0 | Q79: =IFERROR(VLOOKUP(C79,PIVOT!A:C,3,0),0) -> 6 | R79: =L79/8*1.25 -> 93.75 | S79: =Q79*R79 -> 562.5 | T79: =IFERROR(VLOOKUP(C79,PIVOT!A:D,4,0),0) -> 0 | U79: =L79/8*0.1 -> 7.5 | V79: =T79*U79 -> 0 | W79: =IFERROR(VLOOKUP(C79,PIVOT!A:E,5,0),0) -> 0 | X79: =L79/8*1.25*0.1 -> 9.375 | Y79: =X79*W79 -> 0 | Z79: =IFERROR(VLOOKUP(C79,#REF!,6,0),0) -> 0 | AA79: =L79/8*1.3 -> 97.5 | AB79: =Z79*AA79 -> 0 | AD79: =L79/8*1.69 -> 126.75 | AE79: =AD79*AC79 -> 0 | AF79: =IFERROR(VLOOKUP(C79,#REF!,8,0),0) -> 0 | AG79: =L79/8*1.3*0.1 -> 9.75 | AH79: =AF79*AG79 -> 0 | AJ79: =L79/8*1.5 -> 112.5 | AK79: =AI79*AJ79 -> 0 | AM79: =L79/8*1.5*1.3 -> 146.25 | AN79: 0 | AP79: =L79/8*1.5*0.1 -> 11.25 | AQ79: =AO79*AP79 -> 0 | AR79: =IFERROR(VLOOKUP(C79,#REF!,7,0),0) -> 0 | AS79: =L79/8*1.3 -> 97.5 | AT79: =AR79*AS79 -> 0 | AX79: =IFERROR(VLOOKUP(C79,#REF!,8,0),0) -> 0 | AY79: =L79/8*1.3*0.1 -> 9.75 | AZ79: =AX79*AY79 -> 0 | BA79: =IFERROR(VLOOKUP(C79,#REF!,10,0),0) -> 0 | BB79: =600/8*2 -> 150 | BC79: =BA79*BB79 -> 0 | BJ79: =IFERROR(VLOOKUP(C79,#REF!,9,0),0) -> 0 | BK79: =L79/8 -> 75 | BL79: =BJ79*BK79 -> 0 | CG79: =SUM(Y79,V79,S79,P79,M79) -> 7762.5 | CH79: =VLOOKUP(CX79,SSS_2025!A:N,8) -> 1900 | CI79: =VLOOKUP(CX79,SSS_2025!A:N,13) -> 950 | CJ79: =VLOOKUP(CX79,SSS_2025!A:N,9) -> 30 | CK79: 391.25 | CL79: 391.25 | CM79: 200 | CN79: 200 | CO79: =CG79+CH79+CJ79+CL79+CN79 -> 10283.75 | CP79: =(M79+P79+BN79)*10% -> 720 | CQ79: =CO79+CP79 -> 11003.75 | CS79: =CQ79+CR79 -> 11003.75 | CT79: =SUM(M79+(BC79/2)+BL79+BN79+P79)/12 -> 600 | CV79: =IFERROR(VLOOKUP(C79,'[2]BILLING COMPUTATION'!$C$8:$CI$224,85,0),0) -> 11403.75 | CW79: =CG79 -> 7762.5 | CX79: =CV79+CW79 -> 19166.25 | CZ79: =IFERROR(VLOOKUP(C79,'[5]BILLING COMPUTATION'!$C$8:$CG$101,83,0),0) -> 7912.5 | DA79: =CG79 -> 7762.5 | DB79: =SUM(CZ79:DA79) -> 15675 | DC79: =DB79-CX79 -> -3491.25
A80: 76 | C80: 32460 | D80: GD260702 | E80: Prado, Mary Grace | F80: =VLOOKUP(C80,'[1]ACTIVE GH'!$C:$I,7,0) -> METAL STAMPING | G80: =VLOOKUP(C80,'[1]ACTIVE GH'!$C:$J,8,0) -> PRODUCTION | H80: =VLOOKUP(C80,'[1]ACTIVE GH'!$C:$N,12,0) -> Operator 1 | I80: DL | J80: =IFERROR(VLOOKUP(C80,PIVOT!A:B,2,0),0) -> 96 | K80: =J80/8 -> 12 | L80: 600 | M80: =K80*L80 -> 7200 | N80: =IFERROR(VLOOKUP(C80,PIVOT!A:F,6,0),0) -> 0 | O80: =L80/8/60 -> 1.25 | P80: =-N80*O80 -> 0 | Q80: =IFERROR(VLOOKUP(C80,PIVOT!A:C,3,0),0) -> 12 | R80: =L80/8*1.25 -> 93.75 | S80: =Q80*R80 -> 1125 | T80: =IFERROR(VLOOKUP(C80,PIVOT!A:D,4,0),0) -> 0 | U80: =L80/8*0.1 -> 7.5 | V80: =T80*U80 -> 0 | W80: =IFERROR(VLOOKUP(C80,PIVOT!A:E,5,0),0) -> 0 | X80: =L80/8*1.25*0.1 -> 9.375 | Y80: =X80*W80 -> 0 | Z80: =IFERROR(VLOOKUP(C80,#REF!,6,0),0) -> 0 | AA80: =L80/8*1.3 -> 97.5 | AB80: =Z80*AA80 -> 0 | AD80: =L80/8*1.69 -> 126.75 | AE80: =AD80*AC80 -> 0 | AF80: =IFERROR(VLOOKUP(C80,#REF!,8,0),0) -> 0 | AG80: =L80/8*1.3*0.1 -> 9.75 | AH80: =AF80*AG80 -> 0 | AJ80: =L80/8*1.5 -> 112.5 | AK80: =AI80*AJ80 -> 0 | AM80: =L80/8*1.5*1.3 -> 146.25 | AN80: 0 | AP80: =L80/8*1.5*0.1 -> 11.25 | AQ80: =AO80*AP80 -> 0 | AR80: =IFERROR(VLOOKUP(C80,#REF!,7,0),0) -> 0 | AS80: =L80/8*1.3 -> 97.5 | AT80: =AR80*AS80 -> 0 | AX80: =IFERROR(VLOOKUP(C80,#REF!,8,0),0) -> 0 | AY80: =L80/8*1.3*0.1 -> 9.75 | AZ80: =AX80*AY80 -> 0 | BA80: =IFERROR(VLOOKUP(C80,#REF!,10,0),0) -> 0 | BB80: =600/8*2 -> 150 | BC80: =BA80*BB80 -> 0 | BJ80: =IFERROR(VLOOKUP(C80,#REF!,9,0),0) -> 0 | BK80: =L80/8 -> 75 | BL80: =BJ80*BK80 -> 0 | CG80: =SUM(Y80,V80,S80,P80,M80) -> 8325 | CH80: =VLOOKUP(CX80,SSS_2025!A:N,8) -> 1850 | CI80: =VLOOKUP(CX80,SSS_2025!A:N,13) -> 925 | CJ80: =VLOOKUP(CX80,SSS_2025!A:N,9) -> 30 | CK80: 391.25 | CL80: 391.25 | CM80: 200 | CN80: 200 | CO80: =CG80+CH80+CJ80+CL80+CN80 -> 10796.25 | CP80: =(M80+P80+BN80)*10% -> 720 | CQ80: =CO80+CP80 -> 11516.25 | CS80: =CQ80+CR80 -> 11516.25 | CT80: =SUM(M80+(BC80/2)+BL80+BN80+P80)/12 -> 600 | CV80: =IFERROR(VLOOKUP(C80,'[2]BILLING COMPUTATION'!$C$8:$CI$224,85,0),0) -> 10117.5 | CW80: =CG80 -> 8325 | CX80: =CV80+CW80 -> 18442.5 | CZ80: =IFERROR(VLOOKUP(C80,'[5]BILLING COMPUTATION'!$C$8:$CG$101,83,0),0) -> 8700 | DA80: =CG80 -> 8325 | DB80: =SUM(CZ80:DA80) -> 17025 | DC80: =DB80-CX80 -> -1417.5
A81: 77 | C81: 32458 | D81: =VLOOKUP(E81,'F3 MS (2)'!E:F,2,0) -> GD260704 | E81: Punzalan, Angelica Mae | F81: =VLOOKUP(C81,'[1]ACTIVE GH'!$C:$I,7,0) -> METAL STAMPING | G81: =VLOOKUP(C81,'[1]ACTIVE GH'!$C:$J,8,0) -> PRODUCTION | H81: =VLOOKUP(C81,'[1]ACTIVE GH'!$C:$N,12,0) -> Operator 1 | I81: DL | J81: =IFERROR(VLOOKUP(C81,PIVOT!A:B,2,0),0) -> 96 | K81: =J81/8 -> 12 | L81: 600 | M81: =K81*L81 -> 7200 | N81: =IFERROR(VLOOKUP(C81,PIVOT!A:F,6,0),0) -> 0 | O81: =L81/8/60 -> 1.25 | P81: =-N81*O81 -> 0 | Q81: =IFERROR(VLOOKUP(C81,PIVOT!A:C,3,0),0) -> 16 | R81: =L81/8*1.25 -> 93.75 | S81: =Q81*R81 -> 1500 | T81: =IFERROR(VLOOKUP(C81,PIVOT!A:D,4,0),0) -> 0 | U81: =L81/8*0.1 -> 7.5 | V81: =T81*U81 -> 0 | W81: =IFERROR(VLOOKUP(C81,PIVOT!A:E,5,0),0) -> 0 | X81: =L81/8*1.25*0.1 -> 9.375 | Y81: =X81*W81 -> 0 | Z81: =IFERROR(VLOOKUP(C81,#REF!,6,0),0) -> 0 | AA81: =L81/8*1.3 -> 97.5 | AB81: =Z81*AA81 -> 0 | AD81: =L81/8*1.69 -> 126.75 | AE81: =AD81*AC81 -> 0 | AF81: =IFERROR(VLOOKUP(C81,#REF!,8,0),0) -> 0 | AG81: =L81/8*1.3*0.1 -> 9.75 | AH81: =AF81*AG81 -> 0 | AJ81: =L81/8*1.5 -> 112.5 | AK81: =AI81*AJ81 -> 0 | AM81: =L81/8*1.5*1.3 -> 146.25 | AN81: 0 | AP81: =L81/8*1.5*0.1 -> 11.25 | AQ81: =AO81*AP81 -> 0 | AR81: =IFERROR(VLOOKUP(C81,#REF!,7,0),0) -> 0 | AS81: =L81/8*1.3 -> 97.5 | AT81: =AR81*AS81 -> 0 | AX81: =IFERROR(VLOOKUP(C81,#REF!,8,0),0) -> 0 | AY81: =L81/8*1.3*0.1 -> 9.75 | AZ81: =AX81*AY81 -> 0 | BA81: =IFERROR(VLOOKUP(C81,#REF!,10,0),0) -> 0 | BB81: =600/8*2 -> 150 | BC81: =BA81*BB81 -> 0 | BJ81: =IFERROR(VLOOKUP(C81,#REF!,9,0),0) -> 0 | BK81: =L81/8 -> 75 | BL81: =BJ81*BK81 -> 0 | CG81: =SUM(Y81,V81,S81,P81,M81) -> 8700 | CH81: =VLOOKUP(CX81,SSS_2025!A:N,8) -> 1900 | CI81: =VLOOKUP(CX81,SSS_2025!A:N,13) -> 950 | CJ81: =VLOOKUP(CX81,SSS_2025!A:N,9) -> 30 | CK81: 391.25 | CL81: 391.25 | CM81: 200 | CN81: 200 | CO81: =CG81+CH81+CJ81+CL81+CN81 -> 11221.25 | CP81: =(M81+P81+BN81)*10% -> 720 | CQ81: =CO81+CP81 -> 11941.25 | CS81: =CQ81+CR81 -> 11941.25 | CT81: =SUM(M81+(BC81/2)+BL81+BN81+P81)/12 -> 600 | CV81: =IFERROR(VLOOKUP(C81,'[2]BILLING COMPUTATION'!$C$8:$CI$224,85,0),0) -> 10305 | CW81: =CG81 -> 8700 | CX81: =CV81+CW81 -> 19005 | CZ81: =IFERROR(VLOOKUP(C81,'[5]BILLING COMPUTATION'!$C$8:$CG$101,83,0),0) -> 11235 | DA81: =CG81 -> 8700 | DB81: =SUM(CZ81:DA81) -> 19935 | DC81: =DB81-CX81 -> 930
A82: 78 | C82: 7244 | D82: =VLOOKUP(E82,'F3 MS (2)'!E:F,2,0) -> GD250110 | E82: Raali, Analin Awan | F82: =VLOOKUP(C82,'[1]ACTIVE GH'!$C:$I,7,0) -> METAL STAMPING | G82: =VLOOKUP(C82,'[1]ACTIVE GH'!$C:$J,8,0) -> PRODUCTION | H82: =VLOOKUP(C82,'[1]ACTIVE GH'!$C:$N,12,0) -> Operator 1 | I82: DL | J82: =IFERROR(VLOOKUP(C82,PIVOT!A:B,2,0),0) -> 84 | K82: =J82/8 -> 10.5 | L82: 600 | M82: =K82*L82 -> 6300 | N82: =IFERROR(VLOOKUP(C82,PIVOT!A:F,6,0),0) -> 0 | O82: =L82/8/60 -> 1.25 | P82: =-N82*O82 -> 0 | Q82: =IFERROR(VLOOKUP(C82,PIVOT!A:C,3,0),0) -> 14 | R82: =L82/8*1.25 -> 93.75 | S82: =Q82*R82 -> 1312.5 | T82: =IFERROR(VLOOKUP(C82,PIVOT!A:D,4,0),0) -> 0 | U82: =L82/8*0.1 -> 7.5 | V82: =T82*U82 -> 0 | W82: =IFERROR(VLOOKUP(C82,PIVOT!A:E,5,0),0) -> 0 | X82: =L82/8*1.25*0.1 -> 9.375 | Y82: =X82*W82 -> 0 | Z82: =IFERROR(VLOOKUP(C82,#REF!,6,0),0) -> 0 | AA82: =L82/8*1.3 -> 97.5 | AB82: =Z82*AA82 -> 0 | AD82: =L82/8*1.69 -> 126.75 | AE82: =AD82*AC82 -> 0 | AF82: =IFERROR(VLOOKUP(C82,#REF!,8,0),0) -> 0 | AG82: =L82/8*1.3*0.1 -> 9.75 | AH82: =AF82*AG82 -> 0 | AJ82: =L82/8*1.5 -> 112.5 | AK82: =AI82*AJ82 -> 0 | AM82: =L82/8*1.5*1.3 -> 146.25 | AN82: 0 | AP82: =L82/8*1.5*0.1 -> 11.25 | AQ82: =AO82*AP82 -> 0 | AR82: =IFERROR(VLOOKUP(C82,#REF!,7,0),0) -> 0 | AS82: =L82/8*1.3 -> 97.5 | AT82: =AR82*AS82 -> 0 | AX82: =IFERROR(VLOOKUP(C82,#REF!,8,0),0) -> 0 | AY82: =L82/8*1.3*0.1 -> 9.75 | AZ82: =AX82*AY82 -> 0 | BA82: =IFERROR(VLOOKUP(C82,#REF!,10,0),0) -> 0 | BB82: =600/8*2 -> 150 | BC82: =BA82*BB82 -> 0 | BJ82: =IFERROR(VLOOKUP(C82,#REF!,9,0),0) -> 0 | BK82: =L82/8 -> 75 | BL82: =BJ82*BK82 -> 0 | CG82: =SUM(Y82,V82,S82,P82,M82) -> 7612.5 | CH82: =VLOOKUP(CX82,SSS_2025!A:N,8) -> 1750 | CI82: =VLOOKUP(CX82,SSS_2025!A:N,13) -> 875 | CJ82: =VLOOKUP(CX82,SSS_2025!A:N,9) -> 30 | CK82: 391.25 | CL82: 391.25 | CM82: 200 | CN82: 200 | CO82: =CG82+CH82+CJ82+CL82+CN82 -> 9983.75 | CP82: =(M82+P82+BN82)*10% -> 630 | CQ82: =CO82+CP82 -> 10613.75 | CS82: =CQ82+CR82 -> 10613.75 | CT82: =SUM(M82+(BC82/2)+BL82+BN82+P82)/12 -> 525 | CV82: =IFERROR(VLOOKUP(C82,'[2]BILLING COMPUTATION'!$C$8:$CI$224,85,0),0) -> 9900 | CW82: =CG82 -> 7612.5 | CX82: =CV82+CW82 -> 17512.5 | CZ82: =IFERROR(VLOOKUP(C82,'[5]BILLING COMPUTATION'!$C$8:$CG$101,83,0),0) -> 11047.5 | DA82: =CG82 -> 7612.5 | DB82: =SUM(CZ82:DA82) -> 18660 | DC82: =DB82-CX82 -> 1147.5
A83: 79 | C83: 12110 | D83: =VLOOKUP(E83,'F3 MS (2)'!E:F,2,0) -> GD250143 | E83: Rabaja, Jocelyn Dulay | F83: =VLOOKUP(C83,'[1]ACTIVE GH'!$C:$I,7,0) -> METAL STAMPING | G83: =VLOOKUP(C83,'[1]ACTIVE GH'!$C:$J,8,0) -> PRODUCTION | H83: =VLOOKUP(C83,'[1]ACTIVE GH'!$C:$N,12,0) -> Operator 1 | I83: DL | J83: =IFERROR(VLOOKUP(C83,PIVOT!A:B,2,0),0) -> 88 | K83: =J83/8 -> 11 | L83: 600 | M83: =K83*L83 -> 6600 | N83: =IFERROR(VLOOKUP(C83,PIVOT!A:F,6,0),0) -> 0 | O83: =L83/8/60 -> 1.25 | P83: =-N83*O83 -> 0 | Q83: =IFERROR(VLOOKUP(C83,PIVOT!A:C,3,0),0) -> 18 | R83: =L83/8*1.25 -> 93.75 | S83: =Q83*R83 -> 1687.5 | T83: =IFERROR(VLOOKUP(C83,PIVOT!A:D,4,0),0) -> 0 | U83: =L83/8*0.1 -> 7.5 | V83: =T83*U83 -> 0 | W83: =IFERROR(VLOOKUP(C83,PIVOT!A:E,5,0),0) -> 0 | X83: =L83/8*1.25*0.1 -> 9.375 | Y83: =X83*W83 -> 0 | Z83: =IFERROR(VLOOKUP(C83,#REF!,6,0),0) -> 0 | AA83: =L83/8*1.3 -> 97.5 | AB83: =Z83*AA83 -> 0 | AD83: =L83/8*1.69 -> 126.75 | AE83: =AD83*AC83 -> 0 | AF83: =IFERROR(VLOOKUP(C83,#REF!,8,0),0) -> 0 | AG83: =L83/8*1.3*0.1 -> 9.75 | AH83: =AF83*AG83 -> 0 | AJ83: =L83/8*1.5 -> 112.5 | AK83: =AI83*AJ83 -> 0 | AM83: =L83/8*1.5*1.3 -> 146.25 | AN83: 0 | AP83: =L83/8*1.5*0.1 -> 11.25 | AQ83: =AO83*AP83 -> 0 | AR83: =IFERROR(VLOOKUP(C83,#REF!,7,0),0) -> 0 | AS83: =L83/8*1.3 -> 97.5 | AT83: =AR83*AS83 -> 0 | AX83: =IFERROR(VLOOKUP(C83,#REF!,8,0),0) -> 0 | AY83: =L83/8*1.3*0.1 -> 9.75 | AZ83: =AX83*AY83 -> 0 | BA83: =IFERROR(VLOOKUP(C83,#REF!,10,0),0) -> 0 | BB83: =600/8*2 -> 150 | BC83: =BA83*BB83 -> 0 | BJ83: =IFERROR(VLOOKUP(C83,#REF!,9,0),0) -> 0 | BK83: =L83/8 -> 75 | BL83: =BJ83*BK83 -> 0 | CG83: =SUM(Y83,V83,S83,P83,M83) -> 8287.5 | CH83: =VLOOKUP(CX83,SSS_2025!A:N,8) -> 1800 | CI83: =VLOOKUP(CX83,SSS_2025!A:N,13) -> 900 | CJ83: =VLOOKUP(CX83,SSS_2025!A:N,9) -> 30 | CK83: 391.25 | CL83: 391.25 | CM83: 200 | CN83: 200 | CO83: =CG83+CH83+CJ83+CL83+CN83 -> 10708.75 | CP83: =(M83+P83+BN83)*10% -> 660 | CQ83: =CO83+CP83 -> 11368.75 | CS83: =CQ83+CR83 -> 11368.75 | CT83: =SUM(M83+(BC83/2)+BL83+BN83+P83)/12 -> 550 | CV83: =IFERROR(VLOOKUP(C83,'[2]BILLING COMPUTATION'!$C$8:$CI$224,85,0),0) -> 9892.5 | CW83: =CG83 -> 8287.5 | CX83: =CV83+CW83 -> 18180 | CZ83: =IFERROR(VLOOKUP(C83,'[5]BILLING COMPUTATION'!$C$8:$CG$101,83,0),0) -> 11235 | DA83: =CG83 -> 8287.5 | DB83: =SUM(CZ83:DA83) -> 19522.5 | DC83: =DB83-CX83 -> 1342.5
A84: 80 | C84: 14370 | D84: =VLOOKUP(E84,'F3 MS (2)'!E:F,2,0) -> GD250460 | E84: Ramos, Jairo Fabellar | F84: =VLOOKUP(C84,'[1]ACTIVE GH'!$C:$I,7,0) -> METAL STAMPING | G84: =VLOOKUP(C84,'[1]ACTIVE GH'!$C:$J,8,0) -> PRODUCTION | H84: =VLOOKUP(C84,'[1]ACTIVE GH'!$C:$N,12,0) -> Operator 1 | I84: DL | J84: =IFERROR(VLOOKUP(C84,PIVOT!A:B,2,0),0) -> 88 | K84: =J84/8 -> 11 | L84: 600 | M84: =K84*L84 -> 6600 | N84: =IFERROR(VLOOKUP(C84,PIVOT!A:F,6,0),0) -> 0 | O84: =L84/8/60 -> 1.25 | P84: =-N84*O84 -> 0 | Q84: =IFERROR(VLOOKUP(C84,PIVOT!A:C,3,0),0) -> 18 | R84: =L84/8*1.25 -> 93.75 | S84: =Q84*R84 -> 1687.5 | T84: =IFERROR(VLOOKUP(C84,PIVOT!A:D,4,0),0) -> 0 | U84: =L84/8*0.1 -> 7.5 | V84: =T84*U84 -> 0 | W84: =IFERROR(VLOOKUP(C84,PIVOT!A:E,5,0),0) -> 0 | X84: =L84/8*1.25*0.1 -> 9.375 | Y84: =X84*W84 -> 0 | Z84: =IFERROR(VLOOKUP(C84,#REF!,6,0),0) -> 0 | AA84: =L84/8*1.3 -> 97.5 | AB84: =Z84*AA84 -> 0 | AD84: =L84/8*1.69 -> 126.75 | AE84: =AD84*AC84 -> 0 | AF84: =IFERROR(VLOOKUP(C84,#REF!,8,0),0) -> 0 | AG84: =L84/8*1.3*0.1 -> 9.75 | AH84: =AF84*AG84 -> 0 | AJ84: =L84/8*1.5 -> 112.5 | AK84: =AI84*AJ84 -> 0 | AM84: =L84/8*1.5*1.3 -> 146.25 | AN84: 0 | AP84: =L84/8*1.5*0.1 -> 11.25 | AQ84: =AO84*AP84 -> 0 | AR84: =IFERROR(VLOOKUP(C84,#REF!,7,0),0) -> 0 | AS84: =L84/8*1.3 -> 97.5 | AT84: =AR84*AS84 -> 0 | AX84: =IFERROR(VLOOKUP(C84,#REF!,8,0),0) -> 0 | AY84: =L84/8*1.3*0.1 -> 9.75 | AZ84: =AX84*AY84 -> 0 | BA84: =IFERROR(VLOOKUP(C84,#REF!,10,0),0) -> 0 | BB84: =600/8*2 -> 150 | BC84: =BA84*BB84 -> 0 | BJ84: =IFERROR(VLOOKUP(C84,#REF!,9,0),0) -> 0 | BK84: =L84/8 -> 75 | BL84: =BJ84*BK84 -> 0 | CG84: =SUM(Y84,V84,S84,P84,M84) -> 8287.5 | CH84: =VLOOKUP(CX84,SSS_2025!A:N,8) -> 1900 | CI84: =VLOOKUP(CX84,SSS_2025!A:N,13) -> 950 | CJ84: =VLOOKUP(CX84,SSS_2025!A:N,9) -> 30 | CK84: 391.25 | CL84: 391.25 | CM84: 200 | CN84: 200 | CO84: =CG84+CH84+CJ84+CL84+CN84 -> 10808.75 | CP84: =(M84+P84+BN84)*10% -> 660 | CQ84: =CO84+CP84 -> 11468.75 | CS84: =CQ84+CR84 -> 11468.75 | CT84: =SUM(M84+(BC84/2)+BL84+BN84+P84)/12 -> 550 | CV84: =IFERROR(VLOOKUP(C84,'[2]BILLING COMPUTATION'!$C$8:$CI$224,85,0),0) -> 10820.625 | CW84: =CG84 -> 8287.5 | CX84: =CV84+CW84 -> 19108.125 | CZ84: =IFERROR(VLOOKUP(C84,'[5]BILLING COMPUTATION'!$C$8:$CG$101,83,0),0) -> 11235 | DA84: =CG84 -> 8287.5 | DB84: =SUM(CZ84:DA84) -> 19522.5 | DC84: =DB84-CX84 -> 414.375
A85: 81 | C85: 10876 | D85: =VLOOKUP(E85,'F3 MS (2)'!E:F,2,0) -> GD250691 | E85: Ramos, Marie Rachielle Dumo | F85: =VLOOKUP(C85,'[1]ACTIVE GH'!$C:$I,7,0) -> METAL STAMPING | G85: =VLOOKUP(C85,'[1]ACTIVE GH'!$C:$J,8,0) -> PRODUCTION | H85: =VLOOKUP(C85,'[1]ACTIVE GH'!$C:$N,12,0) -> Operator 1 | I85: DL | J85: =IFERROR(VLOOKUP(C85,PIVOT!A:B,2,0),0) -> 96 | K85: =J85/8 -> 12 | L85: 600 | M85: =K85*L85 -> 7200 | N85: =IFERROR(VLOOKUP(C85,PIVOT!A:F,6,0),0) -> 0 | O85: =L85/8/60 -> 1.25 | P85: =-N85*O85 -> 0 | Q85: =IFERROR(VLOOKUP(C85,PIVOT!A:C,3,0),0) -> 2 | R85: =L85/8*1.25 -> 93.75 | S85: =Q85*R85 -> 187.5 | T85: =IFERROR(VLOOKUP(C85,PIVOT!A:D,4,0),0) -> 6 | U85: =L85/8*0.1 -> 7.5 | V85: =T85*U85 -> 45 | W85: =IFERROR(VLOOKUP(C85,PIVOT!A:E,5,0),0) -> 0 | X85: =L85/8*1.25*0.1 -> 9.375 | Y85: =X85*W85 -> 0 | Z85: =IFERROR(VLOOKUP(C85,#REF!,6,0),0) -> 0 | AA85: =L85/8*1.3 -> 97.5 | AB85: =Z85*AA85 -> 0 | AD85: =L85/8*1.69 -> 126.75 | AE85: =AD85*AC85 -> 0 | AF85: =IFERROR(VLOOKUP(C85,#REF!,8,0),0) -> 0 | AG85: =L85/8*1.3*0.1 -> 9.75 | AH85: =AF85*AG85 -> 0 | AJ85: =L85/8*1.5 -> 112.5 | AK85: =AI85*AJ85 -> 0 | AM85: =L85/8*1.5*1.3 -> 146.25 | AN85: 0 | AP85: =L85/8*1.5*0.1 -> 11.25 | AQ85: =AO85*AP85 -> 0 | AR85: =IFERROR(VLOOKUP(C85,#REF!,7,0),0) -> 0 | AS85: =L85/8*1.3 -> 97.5 | AT85: =AR85*AS85 -> 0 | AX85: =IFERROR(VLOOKUP(C85,#REF!,8,0),0) -> 0 | AY85: =L85/8*1.3*0.1 -> 9.75 | AZ85: =AX85*AY85 -> 0 | BA85: =IFERROR(VLOOKUP(C85,#REF!,10,0),0) -> 0 | BB85: =600/8*2 -> 150 | BC85: =BA85*BB85 -> 0 | BJ85: =IFERROR(VLOOKUP(C85,#REF!,9,0),0) -> 0 | BK85: =L85/8 -> 75 | BL85: =BJ85*BK85 -> 0 | CG85: =SUM(Y85,V85,S85,P85,M85) -> 7432.5 | CH85: =VLOOKUP(CX85,SSS_2025!A:N,8) -> 1750 | CI85: =VLOOKUP(CX85,SSS_2025!A:N,13) -> 875 | CJ85: =VLOOKUP(CX85,SSS_2025!A:N,9) -> 30 | CK85: 391.25 | CL85: 391.25 | CM85: 200 | CN85: 200 | CO85: =CG85+CH85+CJ85+CL85+CN85 -> 9803.75 | CP85: =(M85+P85+BN85)*10% -> 720 | CQ85: =CO85+CP85 -> 10523.75 | CS85: =CQ85+CR85 -> 10523.75 | CT85: =SUM(M85+(BC85/2)+BL85+BN85+P85)/12 -> 600 | CV85: =IFERROR(VLOOKUP(C85,'[2]BILLING COMPUTATION'!$C$8:$CI$224,85,0),0) -> 10230 | CW85: =CG85 -> 7432.5 | CX85: =CV85+CW85 -> 17662.5 | CZ85: =IFERROR(VLOOKUP(C85,'[5]BILLING COMPUTATION'!$C$8:$CG$101,83,0),0) -> 9926.25 | DA85: =CG85 -> 7432.5 | DB85: =SUM(CZ85:DA85) -> 17358.75 | DC85: =DB85-CX85 -> -303.75
A86: 82 | C86: 14372 | D86: =VLOOKUP(E86,'F3 MS (2)'!E:F,2,0) -> GD250462 | E86: Ravadavia, Jonalyn Paloyo | F86: =VLOOKUP(C86,'[1]ACTIVE GH'!$C:$I,7,0) -> METAL STAMPING | G86: =VLOOKUP(C86,'[1]ACTIVE GH'!$C:$J,8,0) -> PRODUCTION | H86: =VLOOKUP(C86,'[1]ACTIVE GH'!$C:$N,12,0) -> Operator 1 | I86: DL | J86: =IFERROR(VLOOKUP(C86,PIVOT!A:B,2,0),0) -> 96 | K86: =J86/8 -> 12 | L86: 600 | M86: =K86*L86 -> 7200 | N86: =IFERROR(VLOOKUP(C86,PIVOT!A:F,6,0),0) -> 0 | O86: =L86/8/60 -> 1.25 | P86: =-N86*O86 -> 0 | Q86: =IFERROR(VLOOKUP(C86,PIVOT!A:C,3,0),0) -> 10 | R86: =L86/8*1.25 -> 93.75 | S86: =Q86*R86 -> 937.5 | T86: =IFERROR(VLOOKUP(C86,PIVOT!A:D,4,0),0) -> 66 | U86: =L86/8*0.1 -> 7.5 | V86: =T86*U86 -> 495 | W86: =IFERROR(VLOOKUP(C86,PIVOT!A:E,5,0),0) -> 10 | X86: =L86/8*1.25*0.1 -> 9.375 | Y86: =X86*W86 -> 93.75 | Z86: =IFERROR(VLOOKUP(C86,#REF!,6,0),0) -> 0 | AA86: =L86/8*1.3 -> 97.5 | AB86: =Z86*AA86 -> 0 | AD86: =L86/8*1.69 -> 126.75 | AE86: =AD86*AC86 -> 0 | AF86: =IFERROR(VLOOKUP(C86,#REF!,8,0),0) -> 0 | AG86: =L86/8*1.3*0.1 -> 9.75 | AH86: =AF86*AG86 -> 0 | AJ86: =L86/8*1.5 -> 112.5 | AK86: =AI86*AJ86 -> 0 | AM86: =L86/8*1.5*1.3 -> 146.25 | AN86: 0 | AP86: =L86/8*1.5*0.1 -> 11.25 | AQ86: =AO86*AP86 -> 0 | AR86: =IFERROR(VLOOKUP(C86,#REF!,7,0),0) -> 0 | AS86: =L86/8*1.3 -> 97.5 | AT86: =AR86*AS86 -> 0 | AX86: =IFERROR(VLOOKUP(C86,#REF!,8,0),0) -> 0 | AY86: =L86/8*1.3*0.1 -> 9.75 | AZ86: =AX86*AY86 -> 0 | BA86: =IFERROR(VLOOKUP(C86,#REF!,10,0),0) -> 0 | BB86: =600/8*2 -> 150 | BC86: =BA86*BB86 -> 0 | BJ86: =IFERROR(VLOOKUP(C86,#REF!,9,0),0) -> 0 | BK86: =L86/8 -> 75 | BL86: =BJ86*BK86 -> 0 | CG86: =SUM(Y86,V86,S86,P86,M86) -> 8726.25 | CH86: =VLOOKUP(CX86,SSS_2025!A:N,8) -> 1900 | CI86: =VLOOKUP(CX86,SSS_2025!A:N,13) -> 950 | CJ86: =VLOOKUP(CX86,SSS_2025!A:N,9) -> 30 | CK86: 391.25 | CL86: 391.25 | CM86: 200 | CN86: 200 | CO86: =CG86+CH86+CJ86+CL86+CN86 -> 11247.5 | CP86: =(M86+P86+BN86)*10% -> 720 | CQ86: =CO86+CP86 -> 11967.5 | CS86: =CQ86+CR86 -> 11967.5 | CT86: =SUM(M86+(BC86/2)+BL86+BN86+P86)/12 -> 600 | CV86: =IFERROR(VLOOKUP(C86,'[2]BILLING COMPUTATION'!$C$8:$CI$224,85,0),0) -> 10305 | CW86: =CG86 -> 8726.25 | CX86: =CV86+CW86 -> 19031.25 | CZ86: =IFERROR(VLOOKUP(C86,'[5]BILLING COMPUTATION'!$C$8:$CG$101,83,0),0) -> 9783.75 | DA86: =CG86 -> 8726.25 | DB86: =SUM(CZ86:DA86) -> 18510 | DC86: =DB86-CX86 -> -521.25
A87: 83 | C87: 3866 | D87: =VLOOKUP(E87,'F3 MS (2)'!E:F,2,0) -> GD250014 | E87: Rementilla, Janice Lunar | F87: =VLOOKUP(C87,'[1]ACTIVE GH'!$C:$I,7,0) -> METAL STAMPING | G87: =VLOOKUP(C87,'[1]ACTIVE GH'!$C:$J,8,0) -> PRODUCTION | H87: =VLOOKUP(C87,'[1]ACTIVE GH'!$C:$N,12,0) -> Operator 1 | I87: DL | J87: =IFERROR(VLOOKUP(C87,PIVOT!A:B,2,0),0) -> 96 | K87: =J87/8 -> 12 | L87: 600 | M87: =K87*L87 -> 7200 | N87: =IFERROR(VLOOKUP(C87,PIVOT!A:F,6,0),0) -> 0 | O87: =L87/8/60 -> 1.25 | P87: =-N87*O87 -> 0 | Q87: =IFERROR(VLOOKUP(C87,PIVOT!A:C,3,0),0) -> 8 | R87: =L87/8*1.25 -> 93.75 | S87: =Q87*R87 -> 750 | T87: =IFERROR(VLOOKUP(C87,PIVOT!A:D,4,0),0) -> 66 | U87: =L87/8*0.1 -> 7.5 | V87: =T87*U87 -> 495 | W87: =IFERROR(VLOOKUP(C87,PIVOT!A:E,5,0),0) -> 8 | X87: =L87/8*1.25*0.1 -> 9.375 | Y87: =X87*W87 -> 75 | Z87: =IFERROR(VLOOKUP(C87,#REF!,6,0),0) -> 0 | AA87: =L87/8*1.3 -> 97.5 | AB87: =Z87*AA87 -> 0 | AD87: =L87/8*1.69 -> 126.75 | AE87: =AD87*AC87 -> 0 | AF87: =IFERROR(VLOOKUP(C87,#REF!,8,0),0) -> 0 | AG87: =L87/8*1.3*0.1 -> 9.75 | AH87: =AF87*AG87 -> 0 | AJ87: =L87/8*1.5 -> 112.5 | AK87: =AI87*AJ87 -> 0 | AM87: =L87/8*1.5*1.3 -> 146.25 | AN87: 0 | AP87: =L87/8*1.5*0.1 -> 11.25 | AQ87: =AO87*AP87 -> 0 | AR87: =IFERROR(VLOOKUP(C87,#REF!,7,0),0) -> 0 | AS87: =L87/8*1.3 -> 97.5 | AT87: =AR87*AS87 -> 0 | AX87: =IFERROR(VLOOKUP(C87,#REF!,8,0),0) -> 0 | AY87: =L87/8*1.3*0.1 -> 9.75 | AZ87: =AX87*AY87 -> 0 | BA87: =IFERROR(VLOOKUP(C87,#REF!,10,0),0) -> 0 | BB87: =600/8*2 -> 150 | BC87: =BA87*BB87 -> 0 | BJ87: =IFERROR(VLOOKUP(C87,#REF!,9,0),0) -> 0 | BK87: =L87/8 -> 75 | BL87: =BJ87*BK87 -> 0 | CG87: =SUM(Y87,V87,S87,P87,M87) -> 8520 | CH87: =VLOOKUP(CX87,SSS_2025!A:N,8) -> 1900 | CI87: =VLOOKUP(CX87,SSS_2025!A:N,13) -> 950 | CJ87: =VLOOKUP(CX87,SSS_2025!A:N,9) -> 30 | CK87: 391.25 | CL87: 391.25 | CM87: 200 | CN87: 200 | CO87: =CG87+CH87+CJ87+CL87+CN87 -> 11041.25 | CP87: =(M87+P87+BN87)*10% -> 720 | CQ87: =CO87+CP87 -> 11761.25 | CS87: =CQ87+CR87 -> 11761.25 | CT87: =SUM(M87+(BC87/2)+BL87+BN87+P87)/12 -> 600 | CV87: =IFERROR(VLOOKUP(C87,'[2]BILLING COMPUTATION'!$C$8:$CI$224,85,0),0) -> 10698.75 | CW87: =CG87 -> 8520 | CX87: =CV87+CW87 -> 19218.75 | CZ87: =IFERROR(VLOOKUP(C87,'[5]BILLING COMPUTATION'!$C$8:$CG$101,83,0),0) -> 8808.75 | DA87: =CG87 -> 8520 | DB87: =SUM(CZ87:DA87) -> 17328.75 | DC87: =DB87-CX87 -> -1890
A88: 84 | C88: 13312 | D88: =VLOOKUP(E88,'F3 MS (2)'!E:F,2,0) -> GD250216 | E88: Rivero, Ronald Sta. Ana | F88: =VLOOKUP(C88,'[1]ACTIVE GH'!$C:$I,7,0) -> METAL STAMPING | G88: =VLOOKUP(C88,'[1]ACTIVE GH'!$C:$J,8,0) -> PRODUCTION | H88: =VLOOKUP(C88,'[1]ACTIVE GH'!$C:$N,12,0) -> Operator 1 | I88: DL | J88: =IFERROR(VLOOKUP(C88,PIVOT!A:B,2,0),0) -> 88 | K88: =J88/8 -> 11 | L88: 600 | M88: =K88*L88 -> 6600 | N88: =IFERROR(VLOOKUP(C88,PIVOT!A:F,6,0),0) -> 0 | O88: =L88/8/60 -> 1.25 | P88: =-N88*O88 -> 0 | Q88: =IFERROR(VLOOKUP(C88,PIVOT!A:C,3,0),0) -> 6 | R88: =L88/8*1.25 -> 93.75 | S88: =Q88*R88 -> 562.5 | T88: =IFERROR(VLOOKUP(C88,PIVOT!A:D,4,0),0) -> 6 | U88: =L88/8*0.1 -> 7.5 | V88: =T88*U88 -> 45 | W88: =IFERROR(VLOOKUP(C88,PIVOT!A:E,5,0),0) -> 0 | X88: =L88/8*1.25*0.1 -> 9.375 | Y88: =X88*W88 -> 0 | Z88: =IFERROR(VLOOKUP(C88,#REF!,6,0),0) -> 0 | AA88: =L88/8*1.3 -> 97.5 | AB88: =Z88*AA88 -> 0 | AD88: =L88/8*1.69 -> 126.75 | AE88: =AD88*AC88 -> 0 | AF88: =IFERROR(VLOOKUP(C88,#REF!,8,0),0) -> 0 | AG88: =L88/8*1.3*0.1 -> 9.75 | AH88: =AF88*AG88 -> 0 | AJ88: =L88/8*1.5 -> 112.5 | AK88: =AI88*AJ88 -> 0 | AM88: =L88/8*1.5*1.3 -> 146.25 | AN88: 0 | AP88: =L88/8*1.5*0.1 -> 11.25 | AQ88: =AO88*AP88 -> 0 | AR88: =IFERROR(VLOOKUP(C88,#REF!,7,0),0) -> 0 | AS88: =L88/8*1.3 -> 97.5 | AT88: =AR88*AS88 -> 0 | AX88: =IFERROR(VLOOKUP(C88,#REF!,8,0),0) -> 0 | AY88: =L88/8*1.3*0.1 -> 9.75 | AZ88: =AX88*AY88 -> 0 | BA88: =IFERROR(VLOOKUP(C88,#REF!,10,0),0) -> 0 | BB88: =600/8*2 -> 150 | BC88: =BA88*BB88 -> 0 | BJ88: =IFERROR(VLOOKUP(C88,#REF!,9,0),0) -> 0 | BK88: =L88/8 -> 75 | BL88: =BJ88*BK88 -> 0 | CG88: =SUM(Y88,V88,S88,P88,M88) -> 7207.5 | CH88: =VLOOKUP(CX88,SSS_2025!A:N,8) -> 1700 | CI88: =VLOOKUP(CX88,SSS_2025!A:N,13) -> 850 | CJ88: =VLOOKUP(CX88,SSS_2025!A:N,9) -> 30 | CK88: 391.25 | CL88: 391.25 | CM88: 200 | CN88: 200 | CO88: =CG88+CH88+CJ88+CL88+CN88 -> 9528.75 | CP88: =(M88+P88+BN88)*10% -> 660 | CQ88: =CO88+CP88 -> 10188.75 | CS88: =CQ88+CR88 -> 10188.75 | CT88: =SUM(M88+(BC88/2)+BL88+BN88+P88)/12 -> 550 | CV88: =IFERROR(VLOOKUP(C88,'[2]BILLING COMPUTATION'!$C$8:$CI$224,85,0),0) -> 9971.25 | CW88: =CG88 -> 7207.5 | CX88: =CV88+CW88 -> 17178.75 | CZ88: =IFERROR(VLOOKUP(C88,'[5]BILLING COMPUTATION'!$C$8:$CG$101,83,0),0) -> 7567.1875 | DA88: =CG88 -> 7207.5 | DB88: =SUM(CZ88:DA88) -> 14774.688 | DC88: =DB88-CX88 -> -2404.0625
A89: 85 | C89: 14555 | D89: =VLOOKUP(E89,'F3 MS (2)'!E:F,2,0) -> GD250270 | E89: Salumbides, Luigi Lazo | F89: =VLOOKUP(C89,'[1]ACTIVE GH'!$C:$I,7,0) -> METAL STAMPING | G89: =VLOOKUP(C89,'[1]ACTIVE GH'!$C:$J,8,0) -> PRODUCTION | H89: =VLOOKUP(C89,'[1]ACTIVE GH'!$C:$N,12,0) -> Operator 1 | I89: DL | J89: =IFERROR(VLOOKUP(C89,PIVOT!A:B,2,0),0) -> 88 | K89: =J89/8 -> 11 | L89: 600 | M89: =K89*L89 -> 6600 | N89: =IFERROR(VLOOKUP(C89,PIVOT!A:F,6,0),0) -> 0 | O89: =L89/8/60 -> 1.25 | P89: =-N89*O89 -> 0 | Q89: =IFERROR(VLOOKUP(C89,PIVOT!A:C,3,0),0) -> 0 | R89: =L89/8*1.25 -> 93.75 | S89: =Q89*R89 -> 0 | T89: =IFERROR(VLOOKUP(C89,PIVOT!A:D,4,0),0) -> 0 | U89: =L89/8*0.1 -> 7.5 | V89: =T89*U89 -> 0 | W89: =IFERROR(VLOOKUP(C89,PIVOT!A:E,5,0),0) -> 0 | X89: =L89/8*1.25*0.1 -> 9.375 | Y89: =X89*W89 -> 0 | Z89: =IFERROR(VLOOKUP(C89,#REF!,6,0),0) -> 0 | AA89: =L89/8*1.3 -> 97.5 | AB89: =Z89*AA89 -> 0 | AD89: =L89/8*1.69 -> 126.75 | AE89: =AD89*AC89 -> 0 | AF89: =IFERROR(VLOOKUP(C89,#REF!,8,0),0) -> 0 | AG89: =L89/8*1.3*0.1 -> 9.75 | AH89: =AF89*AG89 -> 0 | AJ89: =L89/8*1.5 -> 112.5 | AK89: =AI89*AJ89 -> 0 | AM89: =L89/8*1.5*1.3 -> 146.25 | AN89: 0 | AP89: =L89/8*1.5*0.1 -> 11.25 | AQ89: =AO89*AP89 -> 0 | AR89: =IFERROR(VLOOKUP(C89,#REF!,7,0),0) -> 0 | AS89: =L89/8*1.3 -> 97.5 | AT89: =AR89*AS89 -> 0 | AX89: =IFERROR(VLOOKUP(C89,#REF!,8,0),0) -> 0 | AY89: =L89/8*1.3*0.1 -> 9.75 | AZ89: =AX89*AY89 -> 0 | BA89: =IFERROR(VLOOKUP(C89,#REF!,10,0),0) -> 0 | BB89: =600/8*2 -> 150 | BC89: =BA89*BB89 -> 0 | BJ89: =IFERROR(VLOOKUP(C89,#REF!,9,0),0) -> 0 | BK89: =L89/8 -> 75 | BL89: =BJ89*BK89 -> 0 | CG89: =SUM(Y89,V89,S89,P89,M89) -> 6600 | CH89: =VLOOKUP(CX89,SSS_2025!A:N,8) -> 1700 | CI89: =VLOOKUP(CX89,SSS_2025!A:N,13) -> 850 | CJ89: =VLOOKUP(CX89,SSS_2025!A:N,9) -> 30 | CK89: 391.25 | CL89: 391.25 | CM89: 200 | CN89: 200 | CO89: =CG89+CH89+CJ89+CL89+CN89 -> 8921.25 | CP89: =(M89+P89+BN89)*10% -> 660 | CQ89: =CO89+CP89 -> 9581.25 | CS89: =CQ89+CR89 -> 9581.25 | CT89: =SUM(M89+(BC89/2)+BL89+BN89+P89)/12 -> 550 | CV89: =IFERROR(VLOOKUP(C89,'[2]BILLING COMPUTATION'!$C$8:$CI$224,85,0),0) -> 10305 | CW89: =CG89 -> 6600 | CX89: =CV89+CW89 -> 16905 | CZ89: =IFERROR(VLOOKUP(C89,'[5]BILLING COMPUTATION'!$C$8:$CG$101,83,0),0) -> 9596.25 | DA89: =CG89 -> 6600 | DB89: =SUM(CZ89:DA89) -> 16196.25 | DC89: =DB89-CX89 -> -708.75
A90: 86 | C90: 14396 | D90: =VLOOKUP(E90,'F3 MS (2)'!E:F,2,0) -> GD250474 | E90: Sapallo, Marjorie Ramirez | F90: =VLOOKUP(C90,'[1]ACTIVE GH'!$C:$I,7,0) -> METAL STAMPING | G90: =VLOOKUP(C90,'[1]ACTIVE GH'!$C:$J,8,0) -> PRODUCTION | H90: =VLOOKUP(C90,'[1]ACTIVE GH'!$C:$N,12,0) -> Operator 1 | I90: DL | J90: =IFERROR(VLOOKUP(C90,PIVOT!A:B,2,0),0) -> 56 | K90: =J90/8 -> 7 | L90: 600 | M90: =K90*L90 -> 4200 | N90: =IFERROR(VLOOKUP(C90,PIVOT!A:F,6,0),0) -> 0 | O90: =L90/8/60 -> 1.25 | P90: =-N90*O90 -> 0 | Q90: =IFERROR(VLOOKUP(C90,PIVOT!A:C,3,0),0) -> 12 | R90: =L90/8*1.25 -> 93.75 | S90: =Q90*R90 -> 1125 | T90: =IFERROR(VLOOKUP(C90,PIVOT!A:D,4,0),0) -> 0 | U90: =L90/8*0.1 -> 7.5 | V90: =T90*U90 -> 0 | W90: =IFERROR(VLOOKUP(C90,PIVOT!A:E,5,0),0) -> 0 | X90: =L90/8*1.25*0.1 -> 9.375 | Y90: =X90*W90 -> 0 | Z90: =IFERROR(VLOOKUP(C90,#REF!,6,0),0) -> 0 | AA90: =L90/8*1.3 -> 97.5 | AB90: =Z90*AA90 -> 0 | AD90: =L90/8*1.69 -> 126.75 | AE90: =AD90*AC90 -> 0 | AF90: =IFERROR(VLOOKUP(C90,#REF!,8,0),0) -> 0 | AG90: =L90/8*1.3*0.1 -> 9.75 | AH90: =AF90*AG90 -> 0 | AJ90: =L90/8*1.5 -> 112.5 | AK90: =AI90*AJ90 -> 0 | AM90: =L90/8*1.5*1.3 -> 146.25 | AN90: 0 | AP90: =L90/8*1.5*0.1 -> 11.25 | AQ90: =AO90*AP90 -> 0 | AR90: =IFERROR(VLOOKUP(C90,#REF!,7,0),0) -> 0 | AS90: =L90/8*1.3 -> 97.5 | AT90: =AR90*AS90 -> 0 | AX90: =IFERROR(VLOOKUP(C90,#REF!,8,0),0) -> 0 | AY90: =L90/8*1.3*0.1 -> 9.75 | AZ90: =AX90*AY90 -> 0 | BA90: =IFERROR(VLOOKUP(C90,#REF!,10,0),0) -> 0 | BB90: =600/8*2 -> 150 | BC90: =BA90*BB90 -> 0 | BJ90: =IFERROR(VLOOKUP(C90,#REF!,9,0),0) -> 0 | BK90: =L90/8 -> 75 | BL90: =BJ90*BK90 -> 0 | CG90: =SUM(Y90,V90,S90,P90,M90) -> 5325 | CH90: =VLOOKUP(CX90,SSS_2025!A:N,8) -> 1600 | CI90: =VLOOKUP(CX90,SSS_2025!A:N,13) -> 800 | CJ90: =VLOOKUP(CX90,SSS_2025!A:N,9) -> 30 | CK90: 391.25 | CL90: 391.25 | CM90: 200 | CN90: 200 | CO90: =CG90+CH90+CJ90+CL90+CN90 -> 7546.25 | CP90: =(M90+P90+BN90)*10% -> 420 | CQ90: =CO90+CP90 -> 7966.25 | CS90: =CQ90+CR90 -> 7966.25 | CT90: =SUM(M90+(BC90/2)+BL90+BN90+P90)/12 -> 350 | CV90: =IFERROR(VLOOKUP(C90,'[2]BILLING COMPUTATION'!$C$8:$CI$224,85,0),0) -> 10680 | CW90: =CG90 -> 5325 | CX90: =CV90+CW90 -> 16005 | CZ90: =IFERROR(VLOOKUP(C90,'[5]BILLING COMPUTATION'!$C$8:$CG$101,83,0),0) -> 11047.5 | DA90: =CG90 -> 5325 | DB90: =SUM(CZ90:DA90) -> 16372.5 | DC90: =DB90-CX90 -> 367.5
A91: 87 | C91: 8571 | D91: =VLOOKUP(E91,'F3 MS (2)'!E:F,2,0) -> GD250049 | E91: Senosin, Sandylyn Cornelio | F91: =VLOOKUP(C91,'[1]ACTIVE GH'!$C:$I,7,0) -> METAL STAMPING | G91: =VLOOKUP(C91,'[1]ACTIVE GH'!$C:$J,8,0) -> PRODUCTION | H91: =VLOOKUP(C91,'[1]ACTIVE GH'!$C:$N,12,0) -> Operator 1 | I91: DL | J91: =IFERROR(VLOOKUP(C91,PIVOT!A:B,2,0),0) -> 72 | K91: =J91/8 -> 9 | L91: 600 | M91: =K91*L91 -> 5400 | N91: =IFERROR(VLOOKUP(C91,PIVOT!A:F,6,0),0) -> 1 | O91: =L91/8/60 -> 1.25 | P91: =-N91*O91 -> -1.25 | Q91: =IFERROR(VLOOKUP(C91,PIVOT!A:C,3,0),0) -> 4 | R91: =L91/8*1.25 -> 93.75 | S91: =Q91*R91 -> 375 | T91: =IFERROR(VLOOKUP(C91,PIVOT!A:D,4,0),0) -> 47.5 | U91: =L91/8*0.1 -> 7.5 | V91: =T91*U91 -> 356.25 | W91: =IFERROR(VLOOKUP(C91,PIVOT!A:E,5,0),0) -> 4 | X91: =L91/8*1.25*0.1 -> 9.375 | Y91: =X91*W91 -> 37.5 | Z91: =IFERROR(VLOOKUP(C91,#REF!,6,0),0) -> 0 | AA91: =L91/8*1.3 -> 97.5 | AB91: =Z91*AA91 -> 0 | AD91: =L91/8*1.69 -> 126.75 | AE91: =AD91*AC91 -> 0 | AF91: =IFERROR(VLOOKUP(C91,#REF!,8,0),0) -> 0 | AG91: =L91/8*1.3*0.1 -> 9.75 | AH91: =AF91*AG91 -> 0 | AJ91: =L91/8*1.5 -> 112.5 | AK91: =AI91*AJ91 -> 0 | AM91: =L91/8*1.5*1.3 -> 146.25 | AN91: 0 | AP91: =L91/8*1.5*0.1 -> 11.25 | AQ91: =AO91*AP91 -> 0 | AR91: =IFERROR(VLOOKUP(C91,#REF!,7,0),0) -> 0 | AS91: =L91/8*1.3 -> 97.5 | AT91: =AR91*AS91 -> 0 | AX91: =IFERROR(VLOOKUP(C91,#REF!,8,0),0) -> 0 | AY91: =L91/8*1.3*0.1 -> 9.75 | AZ91: =AX91*AY91 -> 0 | BA91: =IFERROR(VLOOKUP(C91,#REF!,10,0),0) -> 0 | BB91: =600/8*2 -> 150 | BC91: =BA91*BB91 -> 0 | BJ91: =IFERROR(VLOOKUP(C91,#REF!,9,0),0) -> 0 | BK91: =L91/8 -> 75 | BL91: =BJ91*BK91 -> 0 | CG91: =SUM(Y91,V91,S91,P91,M91) -> 6167.5 | CH91: =VLOOKUP(CX91,SSS_2025!A:N,8) -> 1550 | CI91: =VLOOKUP(CX91,SSS_2025!A:N,13) -> 775 | CJ91: =VLOOKUP(CX91,SSS_2025!A:N,9) -> 30 | CK91: 391.25 | CL91: 391.25 | CM91: 200 | CN91: 200 | CO91: =CG91+CH91+CJ91+CL91+CN91 -> 8338.75 | CP91: =(M91+P91+BN91)*10% -> 539.875 | CQ91: =CO91+CP91 -> 8878.625 | CS91: =CQ91+CR91 -> 8878.625 | CT91: =SUM(M91+(BC91/2)+BL91+BN91+P91)/12 -> 449.89583 | CV91: =IFERROR(VLOOKUP(C91,'[2]BILLING COMPUTATION'!$C$8:$CI$224,85,0),0) -> 9517.5 | CW91: =CG91 -> 6167.5 | CX91: =CV91+CW91 -> 15685 | CZ91: =IFERROR(VLOOKUP(C91,'[5]BILLING COMPUTATION'!$C$8:$CG$101,83,0),0) -> 9401.25 | DA91: =CG91 -> 6167.5 | DB91: =SUM(CZ91:DA91) -> 15568.75 | DC91: =DB91-CX91 -> -116.25
A92: 88 | C92: 12471 | D92: =VLOOKUP(E92,'F3 MS (2)'!E:F,2,0) -> GD250125 | E92: Somera, Prix Janshien Namuro | F92: =VLOOKUP(C92,'[1]ACTIVE GH'!$C:$I,7,0) -> METAL STAMPING | G92: =VLOOKUP(C92,'[1]ACTIVE GH'!$C:$J,8,0) -> PRODUCTION | H92: =VLOOKUP(C92,'[1]ACTIVE GH'!$C:$N,12,0) -> Operator 1 | I92: DL | J92: =IFERROR(VLOOKUP(C92,PIVOT!A:B,2,0),0) -> 88 | K92: =J92/8 -> 11 | L92: 600 | M92: =K92*L92 -> 6600 | N92: =IFERROR(VLOOKUP(C92,PIVOT!A:F,6,0),0) -> 0 | O92: =L92/8/60 -> 1.25 | P92: =-N92*O92 -> 0 | Q92: =IFERROR(VLOOKUP(C92,PIVOT!A:C,3,0),0) -> 8 | R92: =L92/8*1.25 -> 93.75 | S92: =Q92*R92 -> 750 | T92: =IFERROR(VLOOKUP(C92,PIVOT!A:D,4,0),0) -> 66 | U92: =L92/8*0.1 -> 7.5 | V92: =T92*U92 -> 495 | W92: =IFERROR(VLOOKUP(C92,PIVOT!A:E,5,0),0) -> 8 | X92: =L92/8*1.25*0.1 -> 9.375 | Y92: =X92*W92 -> 75 | Z92: =IFERROR(VLOOKUP(C92,#REF!,6,0),0) -> 0 | AA92: =L92/8*1.3 -> 97.5 | AB92: =Z92*AA92 -> 0 | AD92: =L92/8*1.69 -> 126.75 | AE92: =AD92*AC92 -> 0 | AF92: =IFERROR(VLOOKUP(C92,#REF!,8,0),0) -> 0 | AG92: =L92/8*1.3*0.1 -> 9.75 | AH92: =AF92*AG92 -> 0 | AJ92: =L92/8*1.5 -> 112.5 | AK92: =AI92*AJ92 -> 0 | AM92: =L92/8*1.5*1.3 -> 146.25 | AN92: 0 | AP92: =L92/8*1.5*0.1 -> 11.25 | AQ92: =AO92*AP92 -> 0 | AR92: =IFERROR(VLOOKUP(C92,#REF!,7,0),0) -> 0 | AS92: =L92/8*1.3 -> 97.5 | AT92: =AR92*AS92 -> 0 | AX92: =IFERROR(VLOOKUP(C92,#REF!,8,0),0) -> 0 | AY92: =L92/8*1.3*0.1 -> 9.75 | AZ92: =AX92*AY92 -> 0 | BA92: =IFERROR(VLOOKUP(C92,#REF!,10,0),0) -> 0 | BB92: =600/8*2 -> 150 | BC92: =BA92*BB92 -> 0 | BJ92: =IFERROR(VLOOKUP(C92,#REF!,9,0),0) -> 0 | BK92: =L92/8 -> 75 | BL92: =BJ92*BK92 -> 0 | CG92: =SUM(Y92,V92,S92,P92,M92) -> 7920 | CH92: =VLOOKUP(CX92,SSS_2025!A:N,8) -> 1850 | CI92: =VLOOKUP(CX92,SSS_2025!A:N,13) -> 925 | CJ92: =VLOOKUP(CX92,SSS_2025!A:N,9) -> 30 | CK92: 391.25 | CL92: 391.25 | CM92: 200 | CN92: 200 | CO92: =CG92+CH92+CJ92+CL92+CN92 -> 10391.25 | CP92: =(M92+P92+BN92)*10% -> 660 | CQ92: =CO92+CP92 -> 11051.25 | CS92: =CQ92+CR92 -> 11051.25 | CT92: =SUM(M92+(BC92/2)+BL92+BN92+P92)/12 -> 550 | CV92: =IFERROR(VLOOKUP(C92,'[2]BILLING COMPUTATION'!$C$8:$CI$224,85,0),0) -> 10698.75 | CW92: =CG92 -> 7920 | CX92: =CV92+CW92 -> 18618.75 | CZ92: =IFERROR(VLOOKUP(C92,'[5]BILLING COMPUTATION'!$C$8:$CG$101,83,0),0) -> 7871.25 | DA92: =CG92 -> 7920 | DB92: =SUM(CZ92:DA92) -> 15791.25 | DC92: =DB92-CX92 -> -2827.5
... A96: 92 | C96: 32240 | D96: =VLOOKUP(E96,'F3 MS (2)'!E:F,2,0) -> GD260739 | E96: Untalan,Chris Joshua Semana | F96: =VLOOKUP(C96,'[1]ACTIVE GH'!$C:$I,7,0) -> METAL STAMPING | G96: =VLOOKUP(C96,'[1]ACTIVE GH'!$C:$J,8,0) -> PRODUCTION | H96: =VLOOKUP(C96,'[1]ACTIVE GH'!$C:$N,12,0) -> Operator 1 | I96: DL | J96: =IFERROR(VLOOKUP(C96,PIVOT!A:B,2,0),0) -> 48 | K96: =J96/8 -> 6 | L96: 600 | M96: =K96*L96 -> 3600 | N96: =IFERROR(VLOOKUP(C96,PIVOT!A:F,6,0),0) -> 0 | O96: =L96/8/60 -> 1.25 | P96: =-N96*O96 -> 0 | Q96: =IFERROR(VLOOKUP(C96,PIVOT!A:C,3,0),0) -> 0 | R96: =L96/8*1.25 -> 93.75 | S96: =Q96*R96 -> 0 | T96: =IFERROR(VLOOKUP(C96,PIVOT!A:D,4,0),0) -> 0 | U96: =L96/8*0.1 -> 7.5 | V96: =T96*U96 -> 0 | W96: =IFERROR(VLOOKUP(C96,PIVOT!A:E,5,0),0) -> 0 | X96: =L96/8*1.25*0.1 -> 9.375 | Y96: =X96*W96 -> 0 | Z96: =IFERROR(VLOOKUP(C96,#REF!,6,0),0) -> 0 | AA96: =L96/8*1.3 -> 97.5 | AB96: =Z96*AA96 -> 0 | AD96: =L96/8*1.69 -> 126.75 | AE96: =AD96*AC96 -> 0 | AF96: =IFERROR(VLOOKUP(C96,#REF!,8,0),0) -> 0 | AG96: =L96/8*1.3*0.1 -> 9.75 | AH96: =AF96*AG96 -> 0 | AJ96: =L96/8*1.5 -> 112.5 | AK96: =AI96*AJ96 -> 0 | AM96: =L96/8*1.5*1.3 -> 146.25 | AN96: 0 | AP96: =L96/8*1.5*0.1 -> 11.25 | AQ96: =AO96*AP96 -> 0 | AR96: =IFERROR(VLOOKUP(C96,#REF!,7,0),0) -> 0 | AS96: =L96/8*1.3 -> 97.5 | AT96: =AR96*AS96 -> 0 | AX96: =IFERROR(VLOOKUP(C96,#REF!,8,0),0) -> 0 | AY96: =L96/8*1.3*0.1 -> 9.75 | AZ96: =AX96*AY96 -> 0 | BA96: =IFERROR(VLOOKUP(C96,#REF!,10,0),0) -> 0 | BB96: =600/8*2 -> 150 | BC96: =BA96*BB96 -> 0 | BJ96: =IFERROR(VLOOKUP(C96,#REF!,9,0),0) -> 0 | BK96: =L96/8 -> 75 | BL96: =BJ96*BK96 -> 0 | CG96: =SUM(Y96,V96,S96,P96,M96) -> 3600 | CH96: =VLOOKUP(CX96,SSS_2025!A:N,8) -> 1400 | CI96: =VLOOKUP(CX96,SSS_2025!A:N,13) -> 700 | CJ96: =VLOOKUP(CX96,SSS_2025!A:N,9) -> 10 | CK96: 391.25 | CL96: 391.25 | CM96: 200 | CN96: 200 | CO96: =CG96+CH96+CJ96+CL96+CN96 -> 5601.25 | CP96: =(M96+P96+BN96)*10% -> 360 | CQ96: =CO96+CP96 -> 5961.25 | CS96: =CQ96+CR96 -> 5961.25 | CT96: =SUM(M96+(BC96/2)+BL96+BN96+P96)/12 -> 300 | CV96: =IFERROR(VLOOKUP(C96,'[2]BILLING COMPUTATION'!$C$8:$CI$224,85,0),0) -> 10263.75 | CW96: =CG96 -> 3600 | CX96: =CV96+CW96 -> 13863.75 | CZ96: =IFERROR(VLOOKUP(C96,'[5]BILLING COMPUTATION'!$C$8:$CG$101,83,0),0) -> 7725 | DA96: =CG96 -> 3600 | DB96: =SUM(CZ96:DA96) -> 11325 | DC96: =DB96-CX96 -> -2538.75
A97: 93 | C97: 11741 | D97: GD250175 | E97: Tolentino, Evangeline De Silva | F97: =VLOOKUP(C97,'[1]ACTIVE GH'!$C:$I,7,0) -> METAL STAMPING | G97: =VLOOKUP(C97,'[1]ACTIVE GH'!$C:$J,8,0) -> PRODUCTION | H97: =VLOOKUP(C97,'[1]ACTIVE GH'!$C:$N,12,0) -> Operator 1 | I97: DL | J97: =IFERROR(VLOOKUP(C97,PIVOT!A:B,2,0),0) -> 96 | K97: =J97/8 -> 12 | L97: 600 | M97: =K97*L97 -> 7200 | N97: =IFERROR(VLOOKUP(C97,PIVOT!A:F,6,0),0) -> 0 | O97: =L97/8/60 -> 1.25 | P97: =-N97*O97 -> 0 | Q97: =IFERROR(VLOOKUP(C97,PIVOT!A:C,3,0),0) -> 18 | R97: =L97/8*1.25 -> 93.75 | S97: =Q97*R97 -> 1687.5 | T97: =IFERROR(VLOOKUP(C97,PIVOT!A:D,4,0),0) -> 0 | U97: =L97/8*0.1 -> 7.5 | V97: =T97*U97 -> 0 | W97: =IFERROR(VLOOKUP(C97,PIVOT!A:E,5,0),0) -> 0 | X97: =L97/8*1.25*0.1 -> 9.375 | Y97: =X97*W97 -> 0 | Z97: =IFERROR(VLOOKUP(C97,#REF!,6,0),0) -> 0 | AA97: =L97/8*1.3 -> 97.5 | AB97: =Z97*AA97 -> 0 | AD97: =L97/8*1.69 -> 126.75 | AE97: =AD97*AC97 -> 0 | AF97: =IFERROR(VLOOKUP(C97,#REF!,8,0),0) -> 0 | AG97: =L97/8*1.3*0.1 -> 9.75 | AH97: =AF97*AG97 -> 0 | AJ97: =L97/8*1.5 -> 112.5 | AK97: =AI97*AJ97 -> 0 | AM97: =L97/8*1.5*1.3 -> 146.25 | AN97: 0 | AP97: =L97/8*1.5*0.1 -> 11.25 | AQ97: =AO97*AP97 -> 0 | AR97: =IFERROR(VLOOKUP(C97,#REF!,7,0),0) -> 0 | AS97: =L97/8*1.3 -> 97.5 | AT97: =AR97*AS97 -> 0 | AX97: =IFERROR(VLOOKUP(C97,#REF!,8,0),0) -> 0 | AY97: =L97/8*1.3*0.1 -> 9.75 | AZ97: =AX97*AY97 -> 0 | BA97: =IFERROR(VLOOKUP(C97,#REF!,10,0),0) -> 0 | BB97: =600/8*2 -> 150 | BC97: =BA97*BB97 -> 0 | BJ97: =IFERROR(VLOOKUP(C97,#REF!,9,0),0) -> 0 | BK97: =L97/8 -> 75 | BL97: =BJ97*BK97 -> 0 | CG97: =SUM(Y97,V97,S97,P97,M97) -> 8887.5 | CH97: =VLOOKUP(CX97,SSS_2025!A:N,8) -> 900 | CI97: =VLOOKUP(CX97,SSS_2025!A:N,13) -> 450 | CJ97: =VLOOKUP(CX97,SSS_2025!A:N,9) -> 10 | CK97: 391.25 | CL97: 391.25 | CM97: 200 | CN97: 200 | CO97: =CG97+CH97+CJ97+CL97+CN97 -> 10388.75 | CP97: =(M97+P97+BN97)*10% -> 720 | CQ97: =CO97+CP97 -> 11108.75 | CS97: =CQ97+CR97 -> 11108.75 | CT97: =SUM(M97+(BC97/2)+BL97+BN97+P97)/12 -> 600 | CV97: =IFERROR(VLOOKUP(C97,'[2]BILLING COMPUTATION'!$C$8:$CI$224,85,0),0) -> 0 | CW97: =CG97 -> 8887.5 | CX97: =CV97+CW97 -> 8887.5 | CZ97: =IFERROR(VLOOKUP(C97,'[5]BILLING COMPUTATION'!$C$8:$CG$101,83,0),0) -> 8271.25 | DA97: =CG97 -> 8887.5 | DB97: =SUM(CZ97:DA97) -> 17158.75 | DC97: =DB97-CX97 -> 8271.25
A98: 94 | C98: 7505 | D98: =VLOOKUP(E98,'F3 MS (2)'!E:F,2,0) -> GD250491 | E98: Vale, Christine Ann | F98: =VLOOKUP(C98,'[1]ACTIVE GH'!$C:$I,7,0) -> METAL STAMPING | G98: =VLOOKUP(C98,'[1]ACTIVE GH'!$C:$J,8,0) -> PRODUCTION | H98: =VLOOKUP(C98,'[1]ACTIVE GH'!$C:$N,12,0) -> Operator 1 | I98: DL | J98: =IFERROR(VLOOKUP(C98,PIVOT!A:B,2,0),0) -> 96 | K98: =J98/8 -> 12 | L98: 600 | M98: =K98*L98 -> 7200 | N98: =IFERROR(VLOOKUP(C98,PIVOT!A:F,6,0),0) -> 0 | O98: =L98/8/60 -> 1.25 | P98: =-N98*O98 -> 0 | Q98: =IFERROR(VLOOKUP(C98,PIVOT!A:C,3,0),0) -> 0 | R98: =L98/8*1.25 -> 93.75 | S98: =Q98*R98 -> 0 | T98: =IFERROR(VLOOKUP(C98,PIVOT!A:D,4,0),0) -> 66 | U98: =L98/8*0.1 -> 7.5 | V98: =T98*U98 -> 495 | W98: =IFERROR(VLOOKUP(C98,PIVOT!A:E,5,0),0) -> 0 | X98: =L98/8*1.25*0.1 -> 9.375 | Y98: =X98*W98 -> 0 | Z98: =IFERROR(VLOOKUP(C98,#REF!,6,0),0) -> 0 | AA98: =L98/8*1.3 -> 97.5 | AB98: =Z98*AA98 -> 0 | AD98: =L98/8*1.69 -> 126.75 | AE98: =AD98*AC98 -> 0 | AF98: =IFERROR(VLOOKUP(C98,#REF!,8,0),0) -> 0 | AG98: =L98/8*1.3*0.1 -> 9.75 | AH98: =AF98*AG98 -> 0 | AJ98: =L98/8*1.5 -> 112.5 | AK98: =AI98*AJ98 -> 0 | AM98: =L98/8*1.5*1.3 -> 146.25 | AN98: 0 | AP98: =L98/8*1.5*0.1 -> 11.25 | AQ98: =AO98*AP98 -> 0 | AR98: =IFERROR(VLOOKUP(C98,#REF!,7,0),0) -> 0 | AS98: =L98/8*1.3 -> 97.5 | AT98: =AR98*AS98 -> 0 | AX98: =IFERROR(VLOOKUP(C98,#REF!,8,0),0) -> 0 | AY98: =L98/8*1.3*0.1 -> 9.75 | AZ98: =AX98*AY98 -> 0 | BA98: =IFERROR(VLOOKUP(C98,#REF!,10,0),0) -> 0 | BB98: =600/8*2 -> 150 | BC98: =BA98*BB98 -> 0 | BJ98: =IFERROR(VLOOKUP(C98,#REF!,9,0),0) -> 0 | BK98: =L98/8 -> 75 | BL98: =BJ98*BK98 -> 0 | CG98: =SUM(Y98,V98,S98,P98,M98) -> 7695 | CH98: =VLOOKUP(CX98,SSS_2025!A:N,8) -> 1650 | CI98: =VLOOKUP(CX98,SSS_2025!A:N,13) -> 825 | CJ98: =VLOOKUP(CX98,SSS_2025!A:N,9) -> 30 | CK98: 391.25 | CL98: 391.25 | CM98: 200 | CN98: 200 | CO98: =CG98+CH98+CJ98+CL98+CN98 -> 9966.25 | CP98: =(M98+P98+BN98)*10% -> 720 | CQ98: =CO98+CP98 -> 10686.25 | CS98: =CQ98+CR98 -> 10686.25 | CT98: =SUM(M98+(BC98/2)+BL98+BN98+P98)/12 -> 600 | CV98: =IFERROR(VLOOKUP(C98,'[2]BILLING COMPUTATION'!$C$8:$CI$224,85,0),0) -> 8872.5 | CW98: =CG98 -> 7695 | CX98: =CV98+CW98 -> 16567.5 | CZ98: =IFERROR(VLOOKUP(C98,'[5]BILLING COMPUTATION'!$C$8:$CG$101,83,0),0) -> 8227.5 | DA98: =CG98 -> 7695 | DB98: =SUM(CZ98:DA98) -> 15922.5 | DC98: =DB98-CX98 -> -645
B100: #REF! | J100: 7832 | K100: 979 | L100: 54600 | M100: 587400 | N100: 122 | O100: 113.75 | P100: -152.5 | Q100: 694 | R100: 8531.25 | S100: 65062.5 | T100: 2086.5 | U100: 682.5 | V100: 15648.75 | W100: 211 | X100: 853.125 | Y100: 1978.125 | Z100: 0 | AA100: 8872.5 | AB100: 0 | AC100: 0 | AD100: 11534.25 | AE100: 0 | AF100: 0 | AG100: 887.25 | AH100: 0 | AI100: 0 | AJ100: 10237.5 | AK100: 0 | AL100: 0 | AM100: 13308.75 | AN100: 0 | AO100: 0 | AP100: 1023.75 | AQ100: 0 | AR100: 0 | AS100: 8872.5 | AT100: 0 | AU100: 0 | AV100: 0 | AW100: 0 | AX100: 0 | AY100: 887.25 | AZ100: 0 | BA100: 0 | BB100: 13650 | BC100: 0 | BD100: 0 | BE100: 0 | BF100: 0 | BG100: 0 | BH100: 0 | BI100: 0 | BJ100: 0 | BK100: 6825 | BL100: 0 | BM100: 0 | BN100: 0 | BO100: 0 | BP100: 0 | BQ100: 0 | BR100: 0 | BS100: 0 | BT100: 0 | BU100: 0 | BV100: 0 | BW100: 0 | BX100: 0 | BY100: 0 | BZ100: 0 | CA100: 0 | CB100: 0 | CC100: 0 | CD100: 0 | CE100: 0 | CF100: 0 | CG100: 669936.88 | CH100: 156600 | CI100: 78300 | CJ100: 2510 | CK100: 34821.25 | CL100: 34821.25 | CM100: 17800 | CN100: 17800 | CO100: 881668.12 | CP100: 58724.75 | CQ100: 940392.88 | CR100: 0 | CS100: 940392.88 | CT100: 48937.292 | CU100: 0 | CV100: 916917.38 | CW100: 669936.88 | CX100: 1586854.2
B101: =COUNTIF(E8:E98,"*") -> 91 | J101: =SUM(J8:J98) -> 7832 | K101: =SUM(K8:K98) -> 979 | L101: =SUM(L8:L98) -> 54600 | M101: =SUM(M8:M98) -> 587400 | N101: =SUM(N8:N98) -> 122 | O101: =SUM(O8:O98) -> 113.75 | P101: =SUM(P8:P98) -> -152.5 | Q101: =SUM(Q8:Q98) -> 694 | ... CT101: =SUM(CT8:CT98) -> 48937.292 | CV101: =IFERROR(VLOOKUP(C101,'[4]BILLING COMPUTATION'!$C$8:$BY$685,75,FALSE),0) -> 1825390.4
A102: GRAND TOTAL | J102: =J100 -> 7832 | K102: =K100 -> 979 | L102: =L100 -> 54600 | M102: =M100 -> 587400 | N102: =N100 -> 122 | O102: =O100 -> 113.75 | P102: =P100 -> -152.5 | Q102: =Q100 -> 694 | ... CX102: =CX100 -> 1586854.2
J103: =J102-J101 -> 0 | K103: =K102-K101 -> 0 | L103: =L102-L101 -> 0 | M103: =M102-M101 -> 0 | N103: =N102-N101 -> 0 | O103: =O102-O101 -> 0 | P103: =P102-P101 -> 0 | Q103: =Q102-Q101 -> 0 | ... Y103: =Y102-Y101 -> 0 | CG103: =CG102-CG101 -> 0 | CH103: =CH102-CH101 -> 0 | CI103: =CI102-CI101 -> 0 | CJ103: =CJ102-CJ101 -> 0 | CK103: =CK102-CK101 -> 0 | CL103: =CL102-CL101 -> 0 | CM103: =CM102-CM101 -> 0 | CN103: =CN102-CN101 -> 0 | ... CT103: =CT102-CT101 -> 0
CG105: =CG102-CG103 -> 669936.88 | CR105: TOTAL BILLING BEFORE ADMIN FEE | CT105: =CO102 -> 881668.12
CR106: ADMIN FEE ( 10%) | CT106: =CP102 -> 58724.75
CR107: TOTAL BILLING AFTER ADMIN FEE | CT107: =CQ102 -> 940392.88
E111: Prepared By: | O111: Checked By:
E113: Myrla Bianca Ellaine S. Guinto | CF113: ,
E114: Account Officer I | O114: Payroll & Billing Section

Sheet SSS_2025
A1: Social Security System
A2: Circular No. 2024-006
A3: Schedule of SSS Contributions Effective January 2025
A4: RANGE OF COMPENSATION | C4: MONTHLY SALARY CREDIT | F4: AMOUNT OF CONTRIBUTION
C5: REGULAR SSS | D5: WISP/MPF | E5: TOTAL | F5: EMPLOYER | K5: EMPLOYEE | N5: TOTAL CONTRIBUTION
F6: REGULAR SS | G6: WISP/MPF | H6: TOTAL 1 | I6: EC | J6: TOTAL 2 | K6: REGULAR SS | L6: WISP | M6: TOTAL
A7: 1 | B7: 2 | C7: 3 | D7: 4 | E7: 5 | F7: 6 | G7: 7 | H7: 8 | I7: 9 | J7: 10 | K7: 11 | L7: 12 | M7: 13 | N7: 14
A8: 0 | B8: 0 | C8: 0 | D8: 0 | E8: 0 | F8: 0 | G8: 0 | H8: 0 | I8: 0 | J8: 0 | K8: 0 | L8: 0 | M8: 0 | N8: 0
A9: 1 | B9: 5250 | C9: 5000 | D9: 0 | E9: 5000 | F9: 500 | G9: 0 | H9: =SUM(F9:G9) -> 500 | I9: 10 | J9: =SUM(H9:I9) -> 510 | K9: 250 | L9: 0 | M9: =SUM(K9:L9) -> 250 | N9: =J9+M9 -> 760
A10: 5250 | B10: 5749.99 | C10: 5500 | D10: 0 | E10: 5500 | F10: 550 | G10: 0 | H10: =SUM(F10:G10) -> 550 | I10: 10 | J10: =SUM(H10:I10) -> 560 | K10: 275 | L10: 0 | M10: =SUM(K10:L10) -> 275 | N10: =J10+M10 -> 835
A11: 5750 | B11: 6249.99 | C11: 6000 | D11: 0 | E11: 6000 | F11: 600 | G11: 0 | H11: =SUM(F11:G11) -> 600 | I11: 10 | J11: =SUM(H11:I11) -> 610 | K11: 300 | L11: 0 | M11: =SUM(K11:L11) -> 300 | N11: =J11+M11 -> 910
A12: 6250 | B12: 6749.99 | C12: 6500 | D12: 0 | E12: 6500 | F12: 650 | G12: 0 | H12: =SUM(F12:G12) -> 650 | I12: 10 | J12: =SUM(H12:I12) -> 660 | K12: 325 | L12: 0 | M12: =SUM(K12:L12) -> 325 | N12: =J12+M12 -> 985
A13: 6750 | B13: 7249.99 | C13: 7000 | D13: 0 | E13: 7000 | F13: 700 | G13: 0 | H13: =SUM(F13:G13) -> 700 | I13: 10 | J13: =SUM(H13:I13) -> 710 | K13: 350 | L13: 0 | M13: =SUM(K13:L13) -> 350 | N13: =J13+M13 -> 1060
A14: 7250 | B14: 7749.99 | C14: 7500 | D14: 0 | E14: 7500 | F14: 750 | G14: 0 | H14: =SUM(F14:G14) -> 750 | I14: 10 | J14: =SUM(H14:I14) -> 760 | K14: 375 | L14: 0 | M14: =SUM(K14:L14) -> 375 | N14: =J14+M14 -> 1135
A15: 7750 | B15: 8249.99 | C15: 8000 | D15: 0 | E15: 8000 | F15: 800 | G15: 0 | H15: =SUM(F15:G15) -> 800 | I15: 10 | J15: =SUM(H15:I15) -> 810 | K15: 400 | L15: 0 | M15: =SUM(K15:L15) -> 400 | N15: =J15+M15 -> 1210
A16: 8250 | B16: 8749.99 | C16: 8500 | D16: 0 | E16: 8500 | F16: 850 | G16: 0 | H16: =SUM(F16:G16) -> 850 | I16: 10 | J16: =SUM(H16:I16) -> 860 | K16: 425 | L16: 0 | M16: =SUM(K16:L16) -> 425 | N16: =J16+M16 -> 1285
A17: 8750 | B17: 9249.99 | C17: 9000 | D17: 0 | E17: 9000 | F17: 900 | G17: 0 | H17: =SUM(F17:G17) -> 900 | I17: 10 | J17: =SUM(H17:I17) -> 910 | K17: 450 | L17: 0 | M17: =SUM(K17:L17) -> 450 | N17: =J17+M17 -> 1360
A18: 9250 | B18: 9749.99 | C18: 9500 | D18: 0 | E18: 9500 | F18: 950 | G18: 0 | H18: =SUM(F18:G18) -> 950 | I18: 10 | J18: =SUM(H18:I18) -> 960 | K18: 475 | L18: 0 | M18: =SUM(K18:L18) -> 475 | N18: =J18+M18 -> 1435
A19: 9750 | B19: 10249.99 | C19: 10000 | D19: 0 | E19: 10000 | F19: 1000 | G19: 0 | H19: =SUM(F19:G19) -> 1000 | I19: 10 | J19: =SUM(H19:I19) -> 1010 | K19: 500 | L19: 0 | M19: =SUM(K19:L19) -> 500 | N19: =J19+M19 -> 1510
A20: 10250 | B20: 10749.99 | C20: 10500 | D20: 0 | E20: 10500 | F20: 1050 | G20: 0 | H20: =SUM(F20:G20) -> 1050 | I20: 10 | J20: =SUM(H20:I20) -> 1060 | K20: 525 | L20: 0 | M20: =SUM(K20:L20) -> 525 | N20: =J20+M20 -> 1585
... A68: 34250 | B68: 34749.99 | C68: 20000 | D68: 14500 | E68: 34500 | F68: 2000 | G68: 1450 | H68: =SUM(F68:G68) -> 3450 | I68: 30 | J68: =SUM(H68:I68) -> 3480 | K68: 1000 | L68: 725 | M68: =SUM(K68:L68) -> 1725 | N68: =J68+M68 -> 5205
A69: 34750 | C69: 20000 | D69: 15000 | E69: 35000 | F69: 2000 | G69: 1500 | H69: =SUM(F69:G69) -> 3500 | I69: 30 | J69: =SUM(H69:I69) -> 3530 | K69: 1000 | L69: 750 | M69: =SUM(K69:L69) -> 1750 | N69: =J69+M69 -> 5280

Sheet PIVOT
A3: Row Labels | B3: Sum of REG.HRS. | C3: Sum of REG. OT | D3: Sum of ND | E3: Sum of ND OT | F3: Sum of UT/LATE
A4: 3866 | B4: 96 | C4: 8 | D4: 66 | E4: 8
A5: 4327 | B5: 80 | C5: 2
A6: 5076 | B6: 88
A7: 5585 | B7: 96 | C7: 10 | D7: 66 | E7: 10
A8: 5983 | B8: 80 | C8: 2 | D8: 6
A9: 6244 | B9: 80 | D9: 54
A10: 6317 | B10: 88 | C10: 6 | D10: 66 | E10: 6
A11: 6354 | B11: 96 | D11: 66
A12: 7244 | B12: 84 | C12: 14
A13: 7502 | B13: 96 | C13: 12 | D13: 66 | E13: 12 | F13: 108
A14: 7505 | B14: 96 | D14: 66
A15: 7646 | B15: 64 | C15: 12
A16: 7708 | B16: 96 | D16: 6
A17: 8064 | B17: 96 | D17: 66 | F17: 6
A18: 8176 | B18: 72 | C18: 4 | D18: 48 | E18: 4
A19: 8571 | B19: 72 | C19: 4 | D19: 47.5 | E19: 4 | F19: 1
A20: 10424 | B20: 96 | C20: 4 | D20: 66 | E20: 4
A21: 10876 | B21: 96 | C21: 2 | D21: 6
A22: 10997 | B22: 88
A23: 11741 | B23: 96 | C23: 18
A24: 11742 | B24: 96 | C24: 16 | D24: 6
A25: 11775 | B25: 84 | C25: 12
A26: 11829 | B26: 96 | C26: 20
A27: 11834 | B27: 96 | C27: 16
A28: 11842 | B28: 80 | C28: 14 | D28: 30 | E28: 6
A29: 11863 | B29: 96 | D29: 6
A30: 11872 | B30: 96 | C30: 20
A31: 12110 | B31: 88 | C31: 18
A32: 12164 | B32: 80 | C32: 6
A33: 12397 | B33: 96 | C33: 12
A34: 12460 | B34: 96 | C34: 10 | D34: 66 | E34: 10
A35: 12471 | B35: 88 | C35: 8 | D35: 66 | E35: 8
A36: 12808 | B36: 80 | C36: 6 | D36: 60 | E36: 6
A37: 12810 | B37: 88 | C37: 1 | D37: 6
A38: 12816 | B38: 96 | C38: 20
A39: 12830 | B39: 92 | C39: 16 | D39: 66 | E39: 16
A40: 12870 | B40: 96 | D40: 66
A41: 12909 | B41: 80
A42: 12927 | B42: 88 | D42: 6
A43: 12956 | B43: 80 | C43: 12
A44: 12985 | B44: 96 | D44: 6
A45: 13236 | B45: 96 | C45: 20 | D45: 66 | E45: 20
A46: 13312 | B46: 88 | C46: 6 | D46: 6
A47: 13337 | B47: 96 | C47: 16 | D47: 66 | E47: 16
A48: 13646 | B48: 92 | D48: 6
A49: 13684 | B49: 88 | C49: 4
A50: 14233 | B50: 96 | D50: 6
A51: 14267 | B51: 88 | D51: 66
A52: 14275 | B52: 88 | C52: 8 | D52: 66 | E52: 8
A53: 14285 | B53: 80 | C53: 8 | D53: 60 | E53: 8
A54: 14291 | B54: 96 | C54: 2 | D54: 6
A55: 14326 | B55: 96 | D55: 6
A56: 14328 | B56: 88 | C56: 4 | D56: 66 | E56: 4
A57: 14357 | B57: 92 | C57: 18
A58: 14370 | B58: 88 | C58: 18
A59: 14372 | B59: 96 | C59: 10 | D59: 66 | E59: 10
A60: 14396 | B60: 56 | C60: 12
A61: 14473 | B61: 64 | C61: 6
A62: 14479 | B62: 96 | C62: 10 | D62: 6
A63: 14555 | B63: 88
A64: 14753 | B64: 96 | C64: 2 | D64: 66 | E64: 2
A65: 14760 | B65: 88 | C65: 14 | D65: 66 | E65: 14
A66: 14831 | B66: 88 | C66: 6
A67: 14835 | B67: 96 | C67: 20 | D67: 6
A68: 14915 | B68: 96 | C68: 6 | D68: 6
A69: 30019 | B69: 88
A70: 30246 | B70: 80 | C70: 10
A71: 30254 | B71: 80 | C71: 3 | D71: 59 | E71: 3 | F71: 2
A72: 30261 | B72: 80 | C72: 6
A73: 30292 | B73: 96 | C73: 16
A74: 30293 | B74: 96 | C74: 20
A75: 30296 | B75: 96 | C75: 18
A76: 30332 | B76: 56 | C76: 2
A77: 30356 | B77: 80 | C77: 6
A78: 30611 | B78: 96 | C78: 6
A79: 30612 | B79: 96 | D79: 6 | F79: 5
A80: 30679 | B80: 88 | C80: 6 | D80: 60 | E80: 6
A81: 30680 | B81: 88 | C81: 4 | D81: 66 | E81: 4
A82: 30766 | B82: 76
A83: 32240 | B83: 48
A84: 32242
A85: 32436 | B85: 80 | C85: 8 | D85: 60 | E85: 8
A86: 32457 | B86: 8
A87: 32458 | B87: 96 | C87: 16
A88: 32460 | B88: 96 | C88: 12
A89: 32488 | B89: 96 | C89: 12
A90: 32494 | B90: 96 | C90: 12
A91: 32498 | B91: 96 | C91: 14
A92: 32504 | B92: 88 | C92: 4 | D92: 60 | E92: 4
A93: 32515 | B93: 80 | C93: 10 | D93: 60 | E93: 10
A94: 32518 | B94: 72 | C94: 14
A95: EN | B95: 0 | C95: 0 | D95: 0 | E95: 0 | F95: 0
A96: (blank) | B96: 603064 | C96: 66450.5 | D96: 19821.75 | E96: 2400.125 | F96: 396.5
A97: Grand Total | B97: 610896 | C97: 67144.5 | D97: 21908.25 | E97: 2611.125 | F97: 518.5
B98: =SUM(B4:B94) -> 7832 | C98: =SUM(C4:C94) -> 694 | D98: =SUM(D4:D94) -> 2086.5 | E98: =SUM(E4:E94) -> 211 | F98: =SUM(F4:F94) -> 122

Sheet F3 MS (2)
A1: NO. | B1: FACTORY | C1: EN | D1: HYS ID NUMBER | E1: NAME | F1: HYS ID NUMBER | G1: DATE | I1: REG. TIME | J1: TIME IN | K1: TIME OUT | L1: SHIFT | M1: REG.HRS. | N1: REG. OT | O1: ND | P1: ND OT | Q1: RD | R1: RD OT | S1: RD ND | T1: SH | U1: SH OT | V1: SH ND | W1: ULH | X1: LH | Y1: LH OT | Z1: LH ND | AA1: UT/LATE
B2: F3 | C2: 4327 | D2: GD250042 | E2: Ada, Joemer Vera | F2: GD250042 | G2: 46214
B3: F3 | C3: 4327 | D3: GD250042 | E3: Ada, Joemer Vera | F3: GD250042 | G3: 46215 | J3: SUNDAY
B4: F3 | C4: 4327 | D4: GD250042 | E4: Ada, Joemer Vera | F4: GD250042 | G4: 46216 | I4: 8AM-5PM | J4: 0.32986111 | K4: 0.70902778 | L4: A | M4: 8
B5: F3 | C5: 4327 | D5: GD250042 | E5: Ada, Joemer Vera | F5: GD250042 | G5: 46217 | I5: 8AM-5PM | J5: 0.32986111 | K5: 0.70902778 | L5: A | M5: 8
B6: F3 | C6: 4327 | D6: GD250042 | E6: Ada, Joemer Vera | F6: GD250042 | G6: 46218 | I6: 8AM-5PM | J6: 0.33055556 | K6: 0.70833333 | L6: A | M6: 8
B7: F3 | C7: 4327 | D7: GD250042 | E7: Ada, Joemer Vera | F7: GD250042 | G7: 46219 | I7: 8AM-5PM | J7: 0.32916667 | K7: 0.70833333 | L7: A | M7: 8
B8: F3 | C8: 4327 | D8: GD250042 | E8: Ada, Joemer Vera | F8: GD250042 | G8: 46220 | I8: 8AM-5PM | J8: 0.32916667 | K8: 0.70833333 | L8: A | M8: 8
B9: F3 | C9: 4327 | D9: GD250042 | E9: Ada, Joemer Vera | F9: GD250042 | G9: 46221
B10: F3 | C10: 4327 | D10: GD250042 | E10: Ada, Joemer Vera | F10: GD250042 | G10: 46222 | J10: SUNDAY
B11: F3 | C11: 4327 | D11: GD250042 | E11: Ada, Joemer Vera | F11: GD250042 | G11: 46223 | I11: 8AM-5PM | J11: 0.32847222 | K11: 0.70902778 | L11: A | M11: 8
B12: F3 | C12: 4327 | D12: GD250042 | E12: Ada, Joemer Vera | F12: GD250042 | G12: 46224 | I12: 8AM-5PM | J12: 0.33055556 | K12: 0.70833333 | L12: A | M12: 8
B13: F3 | C13: 4327 | D13: GD250042 | E13: Ada, Joemer Vera | F13: GD250042 | G13: 46225 | I13: 8AM-5PM | J13: 0.32986111 | K13: 0.70833333 | L13: A | M13: 8
B14: F3 | C14: 4327 | D14: GD250042 | E14: Ada, Joemer Vera | F14: GD250042 | G14: 46226 | I14: 8AM-5PM | J14: 0.32916667 | K14: 0.79236111 | L14: A | M14: 8 | N14: 2
B15: F3 | C15: 4327 | D15: GD250042 | E15: Ada, Joemer Vera | F15: GD250042 | G15: 46227 | I15: 8AM-5PM | J15: 0.32916667 | K15: 0.70833333 | L15: A | M15: 8
B16: F3 | C16: 4327 | D16: GD250042 | E16: Ada, Joemer Vera | F16: GD250042 | G16: 46228
M18: =SUM(M2:M16) -> 80 | N18: =SUM(N2:N16) -> 2 | O18: =SUM(O2:O16) -> 0 | P18: =SUM(P2:P16) -> 0 | Q18: =SUM(Q2:Q16) -> 0 | R18: =SUM(R2:R16) -> 0 | S18: =SUM(S2:S16) -> 0 | T18: =SUM(T2:T16) -> 0 | ... AA18: =SUM(AA2:AA16) -> 0
A19: NO. | B19: FACTORY | C19: EN | D19: HYS ID NUMBER | E19: NAME | F19: HYS ID NUMBER | G19: DATE | I19: REG. TIME | J19: TIME IN | K19: TIME OUT | L19: SHIFT | M19: REG.HRS. | N19: REG. OT | O19: ND | P19: ND OT | Q19: RD | R19: RD OT | S19: RD ND | T19: SH | U19: SH OT | V19: SH ND | W19: ULH | X19: LH | Y19: LH OT | Z19: LH ND | AA19: UT/LATE
B20: F3 | C20: 5076 | D20: GD250017 | E20: Aragdon, Edmun Aguilar | F20: GD250017 | G20: 46214
B21: F3 | C21: 5076 | D21: GD250017 | E21: Aragdon, Edmun Aguilar | F21: GD250017 | G21: 46215 | J21: SUNDAY
B22: F3 | C22: 5076 | D22: GD250017 | E22: Aragdon, Edmun Aguilar | F22: GD250017 | G22: 46216 | I22: 8AM-5PM | J22: 0.31944444 | K22: 0.70902778 | L22: A | M22: 8
B23: F3 | C23: 5076 | D23: GD250017 | E23: Aragdon, Edmun Aguilar | F23: GD250017 | G23: 46217 | I23: 8AM-5PM | J23: 0.3125 | K23: 0.70833333 | L23: A | M23: 8
B24: F3 | C24: 5076 | D24: GD250017 | E24: Aragdon, Edmun Aguilar | F24: GD250017 | G24: 46218 | I24: 8AM-5PM | J24: 0.3125 | K24: 0.70902778 | L24: A | M24: 8
B25: F3 | C25: 5076 | D25: GD250017 | E25: Aragdon, Edmun Aguilar | F25: GD250017 | G25: 46219 | I25: 8AM-5PM | J25: 0.31111111 | K25: 0.70833333 | L25: A | M25: 8
B26: F3 | C26: 5076 | D26: GD250017 | E26: Aragdon, Edmun Aguilar | F26: GD250017 | G26: 46220 | I26: 8AM-5PM | J26: 0.31388889 | K26: 0.70902778 | L26: A | M26: 8
B27: F3 | C27: 5076 | D27: GD250017 | E27: Aragdon, Edmun Aguilar | F27: GD250017 | G27: 46221 | I27: 8AM-5PM | J27: 0.31111111 | K27: 0.70902778 | L27: A | M27: 8
B28: F3 | C28: 5076 | D28: GD250017 | E28: Aragdon, Edmun Aguilar | F28: GD250017 | G28: 46222 | J28: SUNDAY
B29: F3 | C29: 5076 | D29: GD250017 | E29: Aragdon, Edmun Aguilar | F29: GD250017 | G29: 46223 | I29: 8AM-5PM | J29: 0.31111111 | K29: 0.70902778 | L29: A | M29: 8
B30: F3 | C30: 5076 | D30: GD250017 | E30: Aragdon, Edmun Aguilar | F30: GD250017 | G30: 46224 | I30: 8AM-5PM | J30: 0.32222222 | K30: 0.70833333 | L30: A | M30: 8
B31: F3 | C31: 5076 | D31: GD250017 | E31: Aragdon, Edmun Aguilar | F31: GD250017 | G31: 46225 | I31: 8AM-5PM | J31: 0.31597222 | K31: 0.70902778 | L31: A | M31: 8
B32: F3 | C32: 5076 | D32: GD250017 | E32: Aragdon, Edmun Aguilar | F32: GD250017 | G32: 46226 | I32: 8AM-5PM | J32: 0.30972222 | K32: 0.70833333 | L32: A | M32: 8
B33: F3 | C33: 5076 | D33: GD250017 | E33: Aragdon, Edmun Aguilar | F33: GD250017 | G33: 46227 | I33: 8AM-5PM | J33: 0.30833333 | K33: 0.70833333 | L33: A | M33: 8
B34: F3 | C34: 5076 | D34: GD250017 | E34: Aragdon, Edmun Aguilar | F34: GD250017 | G34: 46228 | I34: 8AM-5PM
M36: =SUM(M20:M34) -> 88 | N36: =SUM(N20:N34) -> 0 | O36: =SUM(O20:O34) -> 0 | P36: =SUM(P20:P34) -> 0 | Q36: =SUM(Q20:Q34) -> 0 | R36: =SUM(R20:R34) -> 0 | S36: =SUM(S20:S34) -> 0 | T36: =SUM(T20:T34) -> 0 | ... AA36: =SUM(AA20:AA34) -> 0
A37: NO. | B37: FACTORY | C37: EN | D37: HYS ID NUMBER | E37: NAME | F37: HYS ID NUMBER | G37: DATE | I37: REG. TIME | J37: TIME IN | K37: TIME OUT | L37: SHIFT | M37: REG.HRS. | N37: REG. OT | O37: ND | P37: ND OT | Q37: RD | R37: RD OT | S37: RD ND | T37: SH | U37: SH OT | V37: SH ND | W37: ULH | X37: LH | Y37: LH OT | Z37: LH ND | AA37: UT/LATE
B38: F3 | C38: 12927 | D38: GD250343 | E38: Dagli, Renz Jemrick Zara | F38: GD250343 | G38: 46214 | I38: 7PM-4AM | J38: 0.78888889 | K38: 0.16736111 | L38: B | M38: 8 | O38: 6
B39: F3 | C39: 12927 | D39: GD250343 | E39: Dagli, Renz Jemrick Zara | F39: GD250343 | G39: 46215 | J39: SUNDAY
B40: F3 | C40: 12927 | D40: GD250343 | E40: Dagli, Renz Jemrick Zara | F40: GD250343 | G40: 46216 | I40: 8AM-5PM | J40: 0.32777778 | K40: 0.70902778 | L40: A | M40: 8
B41: F3 | C41: 12927 | D41: GD250343 | E41: Dagli, Renz Jemrick Zara | F41: GD250343 | G41: 46217 | I41: 8AM-5PM | J41: 0.325 | K41: 0.70833333 | L41: A | M41: 8
B42: F3 | C42: 12927 | D42: GD250343 | E42: Dagli, Renz Jemrick Zara | F42: GD250343 | G42: 46218 | I42: 8AM-5PM | J42: 0.32638889 | K42: 0.70833333 | L42: A | M42: 8
B43: F3 | C43: 12927 | D43: GD250343 | E43: Dagli, Renz Jemrick Zara | F43: GD250343 | G43: 46219 | I43: 8AM-5PM | J43: 0.325 | K43: 0.70833333 | L43: A | M43: 8
B44: F3 | C44: 12927 | D44: GD250343 | E44: Dagli, Renz Jemrick Zara | F44: GD250343 | G44: 46220 | I44: 8AM-5PM | J44: 0.32430556 | K44: 0.70833333 | L44: A | M44: 8
B45: F3 | C45: 12927 | D45: GD250343 | E45: Dagli, Renz Jemrick Zara | F45: GD250343 | G45: 46221 | I45: 8AM-5PM
B46: F3 | C46: 12927 | D46: GD250343 | E46: Dagli, Renz Jemrick Zara | F46: GD250343 | G46: 46222 | J46: SUNDAY
B47: F3 | C47: 12927 | D47: GD250343 | E47: Dagli, Renz Jemrick Zara | F47: GD250343 | G47: 46223 | I47: 8AM-5PM | J47: 0.325 | K47: 0.70902778 | L47: A | M47: 8
B48: F3 | C48: 12927 | D48: GD250343 | E48: Dagli, Renz Jemrick Zara | F48: GD250343 | G48: 46224 | I48: 8AM-5PM | J48: 0.32569444 | K48: 0.70833333 | L48: A | M48: 8
B49: F3 | C49: 12927 | D49: GD250343 | E49: Dagli, Renz Jemrick Zara | F49: GD250343 | G49: 46225 | I49: 8AM-5PM | J49: 0.32708333 | K49: 0.70833333 | L49: A | M49: 8
B50: F3 | C50: 12927 | D50: GD250343 | E50: Dagli, Renz Jemrick Zara | F50: GD250343 | G50: 46226 | I50: 8AM-5PM | J50: 0.32569444 | K50: 0.70833333 | L50: A | M50: 8
B51: F3 | C51: 12927 | D51: GD250343 | E51: Dagli, Renz Jemrick Zara | F51: GD250343 | G51: 46227 | I51: 8AM-5PM | J51: 0.32916667 | K51: 0.70833333 | L51: A | M51: 8
B52: F3 | C52: 12927 | D52: GD250343 | E52: Dagli, Renz Jemrick Zara | F52: GD250343 | G52: 46228 | I52: 8AM-5PM
M54: =SUM(M38:M52) -> 88 | N54: =SUM(N38:N52) -> 0 | O54: =SUM(O38:O52) -> 6 | P54: =SUM(P38:P52) -> 0 | Q54: =SUM(Q38:Q52) -> 0 | R54: =SUM(R38:R52) -> 0 | S54: =SUM(S38:S52) -> 0 | T54: =SUM(T38:T52) -> 0 | ... AA54: =SUM(AA38:AA52) -> 0
A55: NO. | B55: FACTORY | C55: EN | D55: HYS ID NUMBER | E55: NAME | F55: HYS ID NUMBER | G55: DATE | I55: REG. TIME | J55: TIME IN | K55: TIME OUT | L55: SHIFT | M55: REG.HRS. | N55: REG. OT | O55: ND | P55: ND OT | Q55: RD | R55: RD OT | S55: RD ND | T55: SH | U55: SH OT | V55: SH ND | W55: ULH | X55: LH | Y55: LH OT | Z55: LH ND | AA55: UT/LATE
B56: F3 | C56: 14831 | D56: GD250235 | E56: Gamilla, Karen Niña Lazaro | F56: GD250235 | G56: 46214
B57: F3 | C57: 14831 | D57: GD250235 | E57: Gamilla, Karen Niña Lazaro | F57: GD250235 | G57: 46215 | J57: SUNDAY
B58: F3 | C58: 14831 | D58: GD250235 | E58: Gamilla, Karen Niña Lazaro | F58: GD250235 | G58: 46216 | I58: 8AM-5PM | J58: 0.30416667 | K58: 0.70902778 | L58: A | M58: 8
B59: F3 | C59: 14831 | D59: GD250235 | E59: Gamilla, Karen Niña Lazaro | F59: GD250235 | G59: 46217 | I59: 8AM-5PM | J59: 0.30416667 | K59: 0.70833333 | L59: A | M59: 8
B60: F3 | C60: 14831 | D60: GD250235 | E60: Gamilla, Karen Niña Lazaro | F60: GD250235 | G60: 46218 | I60: 8AM-5PM | J60: 0.3125 | K60: 0.70833333 | L60: A | M60: 8
B61: F3 | C61: 14831 | D61: GD250235 | E61: Gamilla, Karen Niña Lazaro | F61: GD250235 | G61: 46219 | I61: 8AM-5PM | J61: 0.31180556 | K61: 0.79375 | L61: A | M61: 8 | N61: 2
B62: F3 | C62: 14831 | D62: GD250235 | E62: Gamilla, Karen Niña Lazaro | F62: GD250235 | G62: 46220 | I62: 8AM-5PM | J62: 0.31041667 | K62: 0.79305556 | L62: A | M62: 8 | N62: 2
B63: F3 | C63: 14831 | D63: GD250235 | E63: Gamilla, Karen Niña Lazaro | F63: GD250235 | G63: 46221 | I63: 8AM-5PM | J63: 0.31041667 | K63: 0.70972222 | L63: A | M63: 8
B64: F3 | C64: 14831 | D64: GD250235 | E64: Gamilla, Karen Niña Lazaro | F64: GD250235 | G64: 46222 | J64: SUNDAY
B65: F3 | C65: 14831 | D65: GD250235 | E65: Gamilla, Karen Niña Lazaro | F65: GD250235 | G65: 46223 | I65: 8AM-5PM | J65: 0.31041667 | K65: 0.79305556 | L65: A | M65: 8 | N65: 2
B66: F3 | C66: 14831 | D66: GD250235 | E66: Gamilla, Karen Niña Lazaro | F66: GD250235 | G66: 46224 | I66: 8AM-5PM | J66: 0.31041667 | K66: 0.70833333 | L66: A | M66: 8
B67: F3 | C67: 14831 | D67: GD250235 | E67: Gamilla, Karen Niña Lazaro | F67: GD250235 | G67: 46225 | I67: 8AM-5PM | J67: 0.3125 | K67: 0.70902778 | L67: A | M67: 8
B68: F3 | C68: 14831 | D68: GD250235 | E68: Gamilla, Karen Niña Lazaro | F68: GD250235 | G68: 46226 | I68: 8AM-5PM | J68: 0.31458333 | K68: 0.70902778 | L68: A | M68: 8
B69: F3 | C69: 14831 | D69: GD250235 | E69: Gamilla, Karen Niña Lazaro | F69: GD250235 | G69: 46227 | I69: 8AM-5PM | J69: 0.31527778 | K69: 0.70902778 | L69: A | M69: 8
B70: F3 | C70: 14831 | D70: GD250235 | E70: Gamilla, Karen Niña Lazaro | F70: GD250235 | G70: 46228 | I70: 8AM-5PM
M72: =SUM(M56:M70) -> 88 | N72: =SUM(N56:N70) -> 6 | O72: =SUM(O56:O70) -> 0 | P72: =SUM(P56:P70) -> 0 | Q72: =SUM(Q56:Q70) -> 0 | R72: =SUM(R56:R70) -> 0 | S72: =SUM(S56:S70) -> 0 | T72: =SUM(T56:T70) -> 0 | ... AA72: =SUM(AA56:AA70) -> 0
A73: NO. | B73: FACTORY | C73: EN | D73: HYS ID NUMBER | E73: NAME | F73: HYS ID NUMBER | G73: DATE | I73: REG. TIME | J73: TIME IN | K73: TIME OUT | L73: SHIFT | M73: REG.HRS. | N73: REG. OT | O73: ND | P73: ND OT | Q73: RD | R73: RD OT | S73: RD ND | T73: SH | U73: SH OT | V73: SH ND | W73: ULH | X73: LH | Y73: LH OT | Z73: LH ND | AA73: UT/LATE
B74: F3 | C74: 14915 | D74: GD250241 | E74: Natingga, Precious Gotera | F74: GD250241 | G74: 46214 | I74: 7PM-4AM | J74: 0.77361111 | K74: 0.16875 | L74: B | M74: 8 | O74: 6
B75: F3 | C75: 14915 | D75: GD250241 | E75: Natingga, Precious Gotera | F75: GD250241 | G75: 46215 | J75: SUNDAY
B76: F3 | C76: 14915 | D76: GD250241 | E76: Natingga, Precious Gotera | F76: GD250241 | G76: 46216 | I76: 8AM-5PM | J76: 0.31458333 | K76: 0.70902778 | L76: A | M76: 8
B77: F3 | C77: 14915 | D77: GD250241 | E77: Natingga, Precious Gotera | F77: GD250241 | G77: 46217 | I77: 8AM-5PM | J77: 0.31666667 | K77: 0.70902778 | L77: A | M77: 8
B78: F3 | C78: 14915 | D78: GD250241 | E78: Natingga, Precious Gotera | F78: GD250241 | G78: 46218 | I78: 8AM-5PM | J78: 0.31875 | K78: 0.70833333 | L78: A | M78: 8
B79: F3 | C79: 14915 | D79: GD250241 | E79: Natingga, Precious Gotera | F79: GD250241 | G79: 46219 | I79: 8AM-5PM | J79: 0.32916667 | K79: 0.79444444 | L79: A | M79: 8 | N79: 2
B80: F3 | C80: 14915 | D80: GD250241 | E80: Natingga, Precious Gotera | F80: GD250241 | G80: 46220 | I80: 8AM-5PM | J80: 0.32847222 | K80: 0.79375 | L80: A | M80: 8 | N80: 2
B81: F3 | C81: 14915 | D81: GD250241 | E81: Natingga, Precious Gotera | F81: GD250241 | G81: 46221 | I81: 8AM-5PM | J81: 0.32847222 | K81: 0.71041667 | L81: A | M81: 8
B82: F3 | C82: 14915 | D82: GD250241 | E82: Natingga, Precious Gotera | F82: GD250241 | G82: 46222 | J82: SUNDAY
B83: F3 | C83: 14915 | D83: GD250241 | E83: Natingga, Precious Gotera | F83: GD250241 | G83: 46223 | I83: 8AM-5PM | J83: 0.325 | K83: 0.79513889 | L83: A | M83: 8 | N83: 2
B84: F3 | C84: 14915 | D84: GD250241 | E84: Natingga, Precious Gotera | F84: GD250241 | G84: 46224 | I84: 8AM-5PM | J84: 0.32430556 | K84: 0.70833333 | L84: A | M84: 8
B85: F3 | C85: 14915 | D85: GD250241 | E85: Natingga, Precious Gotera | F85: GD250241 | G85: 46225 | I85: 8AM-5PM | J85: 0.32361111 | K85: 0.70833333 | L85: A | M85: 8
B86: F3 | C86: 14915 | D86: GD250241 | E86: Natingga, Precious Gotera | F86: GD250241 | G86: 46226 | I86: 8AM-5PM | J86: 0.32291667 | K86: 0.70833333 | L86: A | M86: 8
B87: F3 | C87: 14915 | D87: GD250241 | E87: Natingga, Precious Gotera | F87: GD250241 | G87: 46227 | I87: 8AM-5PM | J87: 0.32777778 | K87: 0.70833333 | L87: A | M87: 8
B88: F3 | C88: 14915 | D88: GD250241 | E88: Natingga, Precious Gotera | F88: GD250241 | G88: 46228 | I88: 8AM-5PM
M90: =SUM(M74:M88) -> 96 | N90: =SUM(N74:N88) -> 6 | O90: =SUM(O74:O88) -> 6 | P90: =SUM(P74:P88) -> 0 | Q90: =SUM(Q74:Q88) -> 0 | R90: =SUM(R74:R88) -> 0 | S90: =SUM(S74:S88) -> 0 | T90: =SUM(T74:T88) -> 0 | ... AA90: =SUM(AA74:AA88) -> 0
A91: NO. | B91: FACTORY | C91: EN | D91: HYS ID NUMBER | E91: NAME | F91: HYS ID NUMBER | G91: DATE | I91: REG. TIME | J91: TIME IN | K91: TIME OUT | L91: SHIFT | M91: REG.HRS. | N91: REG. OT | O91: ND | P91: ND OT | Q91: RD | R91: RD OT | S91: RD ND | T91: SH | U91: SH OT | V91: SH ND | W91: ULH | X91: LH | Y91: LH OT | Z91: LH ND | AA91: UT/LATE
B92: F3 | C92: 10997 | D92: GD250122 | E92: Nicolas, Joey Camigla | F92: GD250122 | G92: 46214
B93: F3 | C93: 10997 | D93: GD250122 | E93: Nicolas, Joey Camigla | F93: GD250122 | G93: 46215 | J93: SUNDAY
B94: F3 | C94: 10997 | D94: GD250122 | E94: Nicolas, Joey Camigla | F94: GD250122 | G94: 46216 | I94: 8AM-5PM | J94: 0.32013889 | K94: 0.70902778 | L94: A | M94: 8
B95: F3 | C95: 10997 | D95: GD250122 | E95: Nicolas, Joey Camigla | F95: GD250122 | G95: 46217 | I95: 8AM-5PM | J95: 0.325 | K95: 0.70833333 | L95: A | M95: 8
B96: F3 | C96: 10997 | D96: GD250122 | E96: Nicolas, Joey Camigla | F96: GD250122 | G96: 46218 | I96: 8AM-5PM | J96: 0.29513889 | K96: 0.70902778 | L96: A | M96: 8
B97: F3 | C97: 10997 | D97: GD250122 | E97: Nicolas, Joey Camigla | F97: GD250122 | G97: 46219 | I97: 8AM-5PM | J97: 0.32569444 | K97: 0.70902778 | L97: A | M97: 8
B98: F3 | C98: 10997 | D98: GD250122 | E98: Nicolas, Joey Camigla | F98: GD250122 | G98: 46220 | I98: 8AM-5PM | J98: 0.32569444 | K98: 0.70833333 | L98: A | M98: 8
B99: F3 | C99: 10997 | D99: GD250122 | E99: Nicolas, Joey Camigla | F99: GD250122 | G99: 46221 | I99: 8AM-5PM | J99: 0.32847222 | K99: 0.70833333 | L99: A | M99: 8
B100: F3 | C100: 10997 | D100: GD250122 | E100: Nicolas, Joey Camigla | F100: GD250122 | G100: 46222 | J100: SUNDAY
B101: F3 | C101: 10997 | D101: GD250122 | E101: Nicolas, Joey Camigla | F101: GD250122 | G101: 46223 | I101: 8AM-5PM | J101: 0.325 | K101: 0.70902778 | L101: A | M101: 8
B102: F3 | C102: 10997 | D102: GD250122 | E102: Nicolas, Joey Camigla | F102: GD250122 | G102: 46224 | I102: 8AM-5PM | J102: 0.32569444 | K102: 0.70902778 | L102: A | M102: 8
B103: F3 | C103: 10997 | D103: GD250122 | E103: Nicolas, Joey Camigla | F103: GD250122 | G103: 46225 | I103: 8AM-5PM | J103: 0.32361111 | K103: 0.70833333 | L103: A | M103: 8
B104: F3 | C104: 10997 | D104: GD250122 | E104: Nicolas, Joey Camigla | F104: GD250122 | G104: 46226 | I104: 8AM-5PM | J104: 0.32569444 | K104: 0.70833333 | L104: A | M104: 8
B105: F3 | C105: 10997 | D105: GD250122 | E105: Nicolas, Joey Camigla | F105: GD250122 | G105: 46227 | I105: 8AM-5PM | J105: 0.32291667 | K105: 0.70833333 | L105: A | M105: 8
...
