Workbook
Name _____________________AMZ2: [1]LIST!$C$2:$C$112
Name ____________________AMZ2: [2]LIST!$C$2:$C$112
Name ___________________AMZ2: [2]LIST!$C$2:$C$112
Name __________________AMZ2: [2]LIST!$C$2:$C$112
Name _________________AMZ2: [2]LIST!$C$2:$C$112
Name ________________AMZ2: [2]LIST!$C$2:$C$112
Name _______________AMZ2: [3]LIST!$C$2:$C$112
Name ______________AMZ2: [3]LIST!$C$2:$C$112
Name _____________AMZ2: [3]LIST!$C$2:$C$112
Name ____________AMZ2: [3]LIST!$C$2:$C$112
Name ___________AMZ2: [3]LIST!$C$2:$C$112
Name __________AMZ2: [3]LIST!$C$2:$C$112
Name _________AMZ2: [3]LIST!$C$2:$C$112
Name ________AMZ2: [2]LIST!$C$2:$C$112
Name _______AMZ2: [2]LIST!$C$2:$C$112
Name ______AMZ2: [4]LIST!$C$2:$C$112
Name _____AMZ2: [2]LIST!$C$2:$C$112
Name ____AMZ2: [2]LIST!$C$2:$C$112
Name ___AMZ2: [1]LIST!$C$2:$C$112
Name __AMZ2: [4]LIST!$C$2:$C$112
Name _a1: #REF!
Name _a1: #REF!
Name _AMZ2: [5]LIST!$C$2:$C$112
Name _AMZ2: [1]LIST!$C$2:$C$112
Name A: #REF!
Name A: #REF!
Name A: #REF!
Name activity: [6]LIST!$C$2:$C$112
Name activity: [3]LIST!$C$2:$C$112
Name adaskdm: [1]LIST!$C$2:$C$112
Name AJ: #REF!
Name AJ: #REF!
Name AJ: #REF!
Name AM: #REF!
Name AM: #REF!
Name AM: #REF!
Name AMABELLEAUGUSTO: #REF!
Name AMABELLEAUGUSTO: #REF!
Name AMABELLEAUGUSTO: #REF!
Name AMZ: [5]LIST!$C$2:$C$112
Name AMZ: [4]LIST!$C$2:$C$112
Name ANDBOR: '[4]TIMEKEEP DMSF'!#REF!
Name ANDBOR: '[4]TIMEKEEP DMSF'!#REF!
Name ANDBOR: '[4]TIMEKEEP DMSF'!#REF!
Name as: [7]Departments!$A$2:$A$65536
Name asa: [7]Departments!$A$2:$A$65536
Name asd: [7]Departments!$A$2:$A$65536
Name assfdgfgjhgkujhk: #REF!
Name assfdgfgjhgkujhk: #REF!
Name assfdgfgjhgkujhk: #REF!
Name B: #REF!
Name B: #REF!
Name B: #REF!
Name bhgfcjhl: #REF!
Name bhgfcjhl: #REF!
Name bhgfcjhl: #REF!
Name BILL: #REF!
Name BILL: #REF!
Name BILL: #REF!
Name BILLDRAFT: #REF!

Sheet INVOICE
B2: On file | C2: CHIYODA PHILIPPINES MFG. CORP. | H2: =TODAY() -> 46207
C3: B20 L20 LIMA TECH. CENTRAL SPECIAL ECONOMIC , LIPA CITY , BATANGAS
C8: TWO MILLION THREE HUNDRED EIGHTY-THREE THOUSAND TWO HUNDRED FIFTY-THREE PESOS AND 50/100 ONLY
G10: PHP | H10: =H22 -> 2111789.2
B14: Billing for the services rendered by Workers
B15: ='BILLING COMPUTATION '!A2 -> PAYROLL BILLING PERIOD: JUNE 1-15, 2026
C18: TOTAL BILLING BEFORE ADMIN | H18: ='BILLING COMPUTATION '!CQ192 -> 1869643.8 | K18: =H18='[43]BILLING COMPUTATION'!CZ229 -> FALSE
C19: ADMIN FEE (10%) | H19: ='BILLING COMPUTATION '!CR192 -> 186964.38 | K19: =H19='[43]BILLING COMPUTATION'!DA229 -> FALSE
C20: TOTAL BILLING AFTER ADMIN | H20: =SUM(H18:H19) -> 2056608.2 | K20: =H20='[43]BILLING COMPUTATION'!DB229 -> FALSE
C21: MEAL ALLOWANCE | H21: ='BILLING COMPUTATION '!CU192 -> 55180.969 | K21: =H21='[43]BILLING COMPUTATION'!DD229 -> FALSE
C22: Total Amount Billing : | H22: =SUM(H20:H21) -> 2111789.2 | K22: =H22='[43]BILLING COMPUTATION'!DE229 -> FALSE
C23: (See Attachment for Detailed Summary)
B27: =C8 -> TWO MILLION THREE HUNDRED EIGHTY-THREE THOUSAND TWO HUNDRED FIFTY-THREE PESOS AND 50/100 ONLY | G27: PHP | H27: =H22 -> 2111789.2 | K27: =H27='[43]BILLING COMPUTATION'!DE229 -> FALSE
E31: ='BILLING COMPUTATION '!A192 -> 186
A35: HANNAH LEAH Q. REANZARES | E35: REYMARK L. HADIA
A36: BILLING OFFICER | E36: BRANCH HEAD

Sheet SALES INVOICE
C6: CHIYODA PHILIPPINES MANUFACTURING CORPORATION | I6: =TODAY() -> 46207
C8: Lot 2 Block 20 Lima Technology Center SEZ, Lipa City Batangas, 4217, Phils.
I9: 006-361-397-000
C14: Billing for the services rendered by Workers
C15: ='BILLING COMPUTATION '!A2 -> PAYROLL BILLING PERIOD: JUNE 1-15, 2026
C18: Total Billing Operation | I18: ='BILLING COMPUTATION '!CQ192 -> 1869643.8
C19: Admin Fee | I19: ='BILLING COMPUTATION '!CR192 -> 186964.38
C20: TOTAL | I20: =I18+I19 -> 2056608.2
C21: Meal Allowance | I21: ='BILLING COMPUTATION '!CU192 -> 55180.969
C22: GROSS AMOUNT | I22: =SUM(I20:I21) -> 2111789.2
I32: =E40 -> 2111789.2
I33: =E39 -> 0
I34: =E40-I33 -> 2111789.2
I36: =I34-I35 -> 2111789.2
E37: =I22 -> 2111789.2 | I37: =ROUND(I36*0.02,2) -> 42235.78
I38: =I36-I37 -> 2069553.4
E39: =E36*0.12 -> 0 | I39: =E39 -> 0
E40: =SUM(E36:E39) -> 2111789.2 | I40: =SUM(I38:I39) -> 2069553.4

Sheet BILLING COMPUTATION 
A2: PAYROLL BILLING PERIOD: JUNE 1-15, 2026
A3: NO. | B3: ID No. | C3: DATE HIRED | D3: BATCH NO. | E3: NAMES OF EMPLOYEE | G3: LOCATION | H3: DEPARTMENT | I3: BASIC | M3: REGULAR OT | P3: NIGHT DIFF | S3: NIGHT DIFF OT | V3: COMPANY HOLIDAY | Y3: RD REGULAR | AB3: RD OT | AE3: RD ND | AH3: RD OTND | AK3: SPECIAL HOLIDAY HRS | AN3: SPECIAL HOLIDAY OT | AQ3: SPECIAL HOLIDAY ND | AT3: SPECIAL HOLIDAY NDOT | AW3: UNWORKED LEGAL HOLIDAY | AZ3: LEGAL HOLIDAY | BC3: LEGAL HOLIDAY ND | BF3: LATE/ UNDERTIME | BH3: ADJUSTMENT | BZ3: JUNE 6 PAY (SEPARATED EMPLOYEES) | CD3: SAT WORK | CH3: SAT WORK ND | CK3: TOTAL AMOUNT | CM3: MANDATORY CONTIBUTIONS | CP3: 13th MONTH | CQ3: TOTAL BILLING BEFORE ADMIN FEE | CR3: ADMIN FEE 10% | CS3: TOTAL WITH ADMIN FEE | CT3: Deduction to Meal Allowance | CU3: MEAL ALLOWANCE (31 PER DAY) | CV3: TOTAL
I4: HRS | J4: DAYS | K4: RATE | L4: AMOUNT | M4: HRS | N4: RATE | O4: AMOUNT | P4: HRS | Q4: RATE | R4: AMOUNT | S4: HRS | T4: RATE | U4: AMOUNT | V4: HRS | W4: RATE | X4: AMOUNT | Y4: HRS | Z4: RATE | AA4: AMOUNT | AB4: HRS | AC4: RATE | AD4: AMOUNT | AE4: DAYS | AF4: RATE | AG4: AMOUNT | AH4: DAYS | AI4: RATE | AJ4: AMOUNT | AK4: DAYS | AL4: RATE | AM4: AMOUNT | AN4: DAYS | AO4: RATE | AP4: AMOUNT | AQ4: DAYS | AR4: RATE | AS4: AMOUNT | AT4: DAYS | AU4: RATE | AV4: AMOUNT | AW4: HRS | AX4: RATE | AY4: AMOUNT | AZ4: DAYS | BA4: RATE | BB4: AMOUNT | BC4: DAYS | BD4: RATE | BE4: AMOUNT | BF4: MINS | BG4: AMOUNT | BH4: REG HRS | BI4: RATE | BJ4: AMOUNT | BK4: OT | BL4: RATE | BM4: AMOUNT | BN4: ND | BO4: RATE | BP4: AMOUNT | BQ4: NDOT | BR4: RATE | BS4: AMOUNT | BT4: SUN HRS | BU4: RATE | BV4: AMOUNT | BW4: MEAL ALLOWANCE | BX4: RATE | BY4: AMOUNT | BZ4: HRS | CA4: DAYS | CB4: RATE | CC4: AMOUNT | CD4: HRS | CE4: DAYS | CF4: RATE | CG4: AMOUNT | CH4: HRS | CI4: RATE | CJ4: AMOUNT | CL4: HMO | CM4: SSS TOTAL | CN4: Philhealth ER | CO4: Pag-ibig
A5: 1 | B5: 5683 | C5: 45244 | D5: B3 | E5: Abcede, Jomar Pavino | G5: Factory 2 | H5: QC Inspection | I5: 88 | J5: 11 | K5: 600 | L5: 6600 | M5: 27 | N5: 93.75 | O5: 2531.25 | P5: 30 | Q5: 7.5 | R5: 225 | S5: 10 | T5: 9.375 | U5: 93.75 | W5: 93.75 | X5: 0 | Z5: 97.5 | AA5: 0 | AC5: 126.75 | AD5: 0 | AF5: 9.75 | AG5: 0 | AI5: 12.6675 | AJ5: 0 | AL5: 97.5 | AM5: 0 | AO5: 126.75 | AP5: 0 | AR5: 9.75 | AS5: 0 | AU5: 12.675 | AV5: 0 | AW5: 8 | AX5: 600 | AY5: 600 | BA5: 540 | BB5: 0 | BF5: 0 | BG5: 0 | BH5: 0 | BI5: 600 | BJ5: 0 | BL5: 93.75 | BM5: 0 | BO5: 7.5 | BP5: 0 | BR5: 9.375 | BS5: 0 | BU5: 97.5 | BV5: 0 | BW5: 0 | BX5: 31 | BY5: 0 | BZ5: 0 | CA5: 0 | CB5: 67.5 | CC5: 0 | CD5: 0 | CE5: 0 | CF5: 93.75 | CG5: 0 | CI5: 9.375 | CJ5: 0 | CK5: 10050 | CM5: 2130 | CN5: 391.25 | CO5: 200 | CP5: 550 | CQ5: 13321.25 | CR5: 1332.125 | CS5: 14653.375 | CT5: 0 | CU5: 341 | CV5: 14994.375
A6: 2 | B6: 31024 | C6: 45951 | D6: B50 | E6: Abrio, Althea Mae Divila | G6: Factory 1 | H6: Subaru Engine | I6: 80 | J6: 10 | K6: 600 | L6: 6000 | M6: 27 | N6: 93.75 | O6: 2531.25 | P6: 25 | Q6: 7.5 | R6: 187.5 | S6: 10 | T6: 9.375 | U6: 93.75 | W6: 93.75 | X6: 0 | Z6: 97.5 | AA6: 0 | AC6: 126.75 | AD6: 0 | AF6: 9.75 | AG6: 0 | AI6: 12.6675 | AJ6: 0 | AL6: 97.5 | AM6: 0 | AO6: 126.75 | AP6: 0 | AR6: 9.75 | AS6: 0 | AU6: 12.675 | AV6: 0 | AW6: 0 | AX6: 600 | AY6: 0 | BA6: 541 | BB6: 0 | BF6: 0 | BG6: 0 | BH6: 0 | BI6: 600 | BJ6: 0 | BL6: 93.75 | BM6: 0 | BO6: 7.5 | BP6: 0 | BR6: 9.375 | BS6: 0 | BU6: 97.5 | BV6: 0 | BW6: 0 | BX6: 31 | BY6: 0 | BZ6: 0 | CA6: 0 | CB6: 67.5 | CC6: 0 | CD6: 0 | CE6: 0 | CF6: 93.75 | CG6: 0 | CI6: 9.375 | CJ6: 0 | CK6: 8812.5 | CM6: 2030 | CN6: 391.25 | CO6: 200 | CP6: 500 | CQ6: 11933.75 | CR6: 1193.375 | CS6: 13127.125 | CT6: 0 | CU6: 310 | CV6: 13437.125
A7: 3 | B7: 13373 | C7: 45811 | D7: B47 | E7: Acasamoso, Jerico Ladia | G7: Factory 3 | H7: QC Inspection | I7: 80 | J7: 10 | K7: 600 | L7: 6000 | M7: 19.67 | N7: 93.75 | O7: 1844.0625 | P7: 20 | Q7: 7.5 | R7: 150 | S7: 2 | T7: 9.375 | U7: 18.75 | W7: 93.75 | X7: 0 | Z7: 97.5 | AA7: 0 | AC7: 126.75 | AD7: 0 | AF7: 9.75 | AG7: 0 | AI7: 12.6675 | AJ7: 0 | AL7: 97.5 | AM7: 0 | AO7: 126.75 | AP7: 0 | AR7: 9.75 | AS7: 0 | AU7: 12.675 | AV7: 0 | AW7: 8 | AX7: 600 | AY7: 600 | BA7: 542 | BB7: 0 | BF7: 0 | BG7: 0 | BH7: 0 | BI7: 600 | BJ7: 0 | BL7: 93.75 | BM7: 0 | BO7: 7.5 | BP7: 0 | BR7: 9.375 | BS7: 0 | BU7: 97.5 | BV7: 0 | BW7: 0 | BX7: 31 | BY7: 0 | BZ7: 0 | CA7: 0 | CB7: 67.5 | CC7: 0 | CD7: 0 | CE7: 0 | CF7: 93.75 | CG7: 0 | CI7: 9.375 | CJ7: 0 | CK7: 8612.8125 | CM7: 1980 | CN7: 391.25 | CO7: 200 | CP7: 500 | CQ7: 11684.062 | CR7: 1168.4062 | CS7: 12852.469 | CT7: 0 | CU7: 310 | CV7: 13162.469
A8: 4 | B8: 7167 | C8: 45524 | D8: B23 | E8: Aguirre, Christopher Isla | G8: Factory 1 | H8: Subaru Engine | I8: 56 | J8: 7 | K8: 600 | L8: 4200 | M8: 15 | N8: 93.75 | O8: 1406.25 | P8: 20 | Q8: 7.5 | R8: 150 | S8: 6 | T8: 9.375 | U8: 56.25 | W8: 93.75 | X8: 0 | Z8: 97.5 | AA8: 0 | AC8: 126.75 | AD8: 0 | AF8: 9.75 | AG8: 0 | AI8: 12.6675 | AJ8: 0 | AL8: 97.5 | AM8: 0 | AO8: 126.75 | AP8: 0 | AR8: 9.75 | AS8: 0 | AU8: 12.675 | AV8: 0 | AW8: 0 | AX8: 600 | AY8: 0 | BA8: 543 | BB8: 0 | BF8: 0 | BG8: 0 | BH8: 0 | BI8: 600 | BJ8: 0 | BL8: 93.75 | BM8: 0 | BO8: 7.5 | BP8: 0 | BR8: 9.375 | BS8: 0 | BU8: 97.5 | BV8: 0 | BW8: 0 | BX8: 31 | BY8: 0 | BZ8: 0 | CA8: 0 | CB8: 67.5 | CC8: 0 | CD8: 0 | CE8: 0 | CF8: 93.75 | CG8: 0 | CI8: 9.375 | CJ8: 0 | CK8: 5812.5 | CM8: 0 | CN8: 0 | CO8: 0 | CP8: 350 | CQ8: 6162.5 | CR8: 616.25 | CS8: 6778.75 | CT8: 0 | CU8: 217 | CV8: 6995.75
A9: 5 | B9: 32300 | C9: 46175 | D9: B59 | E9: Albello, Joyce Anne Palma | G9: Factory 2 | H9: Trainee | I9: 80 | J9: 10 | K9: 600 | L9: 6000 | M9: 0 | N9: 93.75 | O9: 0 | P9: 0 | Q9: 7.5 | R9: 0 | S9: 0 | T9: 9.375 | U9: 0 | W9: 93.75 | X9: 0 | Z9: 97.5 | AA9: 0 | AC9: 126.75 | AD9: 0 | AF9: 9.75 | AG9: 0 | AI9: 12.6675 | AJ9: 0 | AL9: 97.5 | AM9: 0 | AO9: 126.75 | AP9: 0 | AR9: 9.75 | AS9: 0 | AU9: 12.675 | AV9: 0 | AW9: 8 | AX9: 600 | AY9: 600 | BA9: 544 | BB9: 0 | BF9: 0 | BG9: 0 | BH9: 0 | BI9: 600 | BJ9: 0 | BL9: 93.75 | BM9: 0 | BO9: 7.5 | BP9: 0 | BR9: 9.375 | BS9: 0 | BU9: 97.5 | BV9: 0 | BW9: 0 | BX9: 31 | BY9: 0 | BZ9: 0 | CA9: 0 | CB9: 67.5 | CC9: 0 | CD9: 0 | CE9: 0 | CF9: 93.75 | CG9: 0 | CI9: 9.375 | CJ9: 0 | CK9: 6600 | CM9: 710 | CN9: 391.25 | CO9: 200 | CP9: 500 | CQ9: 8401.25 | CR9: 840.125 | CS9: 9241.375 | CT9: 0 | CU9: 310 | CV9: 9551.375
A10: 6 | B10: 32202 | C10: 46161 | D10: B58 | E10: Alcantara, Felix Salvador Andoque | G10: Factory 2 | H10: Trainee | I10: 80 | J10: 10 | K10: 600 | L10: 6000 | M10: 0 | N10: 93.75 | O10: 0 | P10: 0 | Q10: 7.5 | R10: 0 | S10: 0 | T10: 9.375 | U10: 0 | W10: 93.75 | X10: 0 | Z10: 97.5 | AA10: 0 | AC10: 126.75 | AD10: 0 | AF10: 9.75 | AG10: 0 | AI10: 12.6675 | AJ10: 0 | AL10: 97.5 | AM10: 0 | AO10: 126.75 | AP10: 0 | AR10: 9.75 | AS10: 0 | AU10: 12.675 | AV10: 0 | AW10: 8 | AX10: 600 | AY10: 600 | BA10: 545 | BB10: 0 | BF10: 0 | BG10: 0 | BH10: 0 | BI10: 600 | BJ10: 0 | BL10: 93.75 | BM10: 0 | BO10: 7.5 | BP10: 0 | BR10: 9.375 | BS10: 0 | BU10: 97.5 | BV10: 0 | BW10: 0 | BX10: 31 | BY10: 0 | BZ10: 0 | CA10: 0 | CB10: 67.5 | CC10: 0 | CD10: 0 | CE10: 0 | CF10: 93.75 | CG10: 0 | CI10: 9.375 | CJ10: 0 | CK10: 6600 | CM10: 1310 | CN10: 391.25 | CO10: 200 | CP10: 500 | CQ10: 9001.25 | CR10: 900.125 | CS10: 9901.375 | CT10: 0 | CU10: 310 | CV10: 10211.375
A11: 7 | B11: 32255 | C11: 46175 | D11: B59 | E11: Alikhan, Mohammad King Verona | G11: Factory 2 | H11: Trainee | I11: 80 | J11: 10 | K11: 600 | L11: 6000 | M11: 6 | N11: 93.75 | O11: 562.5 | P11: 30 | Q11: 7.5 | R11: 225 | S11: 4 | T11: 9.375 | U11: 37.5 | W11: 93.75 | X11: 0 | Z11: 97.5 | AA11: 0 | AC11: 126.75 | AD11: 0 | AF11: 9.75 | AG11: 0 | AI11: 12.6675 | AJ11: 0 | AL11: 97.5 | AM11: 0 | AO11: 126.75 | AP11: 0 | AR11: 9.75 | AS11: 0 | AU11: 12.675 | AV11: 0 | AW11: 8 | AX11: 600 | AY11: 600 | BA11: 546 | BB11: 0 | BF11: 0 | BG11: 0 | BH11: 0 | BI11: 600 | BJ11: 0 | BL11: 93.75 | BM11: 0 | BO11: 7.5 | BP11: 0 | BR11: 9.375 | BS11: 0 | BU11: 97.5 | BV11: 0 | BW11: 0 | BX11: 31 | BY11: 0 | BZ11: 0 | CA11: 0 | CB11: 67.5 | CC11: 0 | CD11: 0 | CE11: 0 | CF11: 93.75 | CG11: 0 | CI11: 9.375 | CJ11: 0 | CK11: 7425 | CM11: 760 | CN11: 391.25 | CO11: 200 | CP11: 500 | CQ11: 9276.25 | CR11: 927.625 | CS11: 10203.875 | CT11: 0 | CU11: 310 | CV11: 10513.875
A12: 8 | B12: 11936 | C12: 45734 | D12: B38 | E12: Alongalay, Ruiz Trillanes | G12: Factory 1 | H12: Parts Preparation | I12: 88 | J12: 11 | K12: 600 | L12: 6600 | M12: 13.92 | N12: 93.75 | O12: 1305 | P12: 30 | Q12: 7.5 | R12: 225 | S12: 2 | T12: 9.375 | U12: 18.75 | W12: 93.75 | X12: 0 | Z12: 97.5 | AA12: 0 | AC12: 126.75 | AD12: 0 | AF12: 9.75 | AG12: 0 | AI12: 12.6675 | AJ12: 0 | AL12: 97.5 | AM12: 0 | AO12: 126.75 | AP12: 0 | AR12: 9.75 | AS12: 0 | AU12: 12.675 | AV12: 0 | AW12: 8 | AX12: 600 | AY12: 600 | BA12: 547 | BB12: 0 | BF12: 0 | BG12: 0 | BH12: 0 | BI12: 600 | BJ12: 0 | BL12: 93.75 | BM12: 0 | BO12: 7.5 | BP12: 0 | BR12: 9.375 | BS12: 0 | BU12: 97.5 | BV12: 0 | BW12: 0 | BX12: 31 | BY12: 0 | BZ12: 0 | CA12: 0 | CB12: 67.5 | CC12: 0 | CD12: 0 | CE12: 0 | CF12: 93.75 | CG12: 0 | CI12: 9.375 | CJ12: 0 | CK12: 8748.75 | CM12: 1980 | CN12: 391.25 | CO12: 200 | CP12: 550 | CQ12: 11870 | CR12: 1187 | CS12: 13057 | CT12: 0 | CU12: 341 | CV12: 13398
A13: 9 | B13: 31006 | C13: 45944 | D13: B49 | E13: An, Rey Alcos | G13: Factory 1 | H13: Material Handler | I13: 88 | J13: 11 | K13: 600 | L13: 6600 | M13: 27 | N13: 93.75 | O13: 2531.25 | P13: 25 | Q13: 7.5 | R13: 187.5 | S13: 10 | T13: 9.375 | U13: 93.75 | W13: 93.75 | X13: 0 | Z13: 97.5 | AA13: 0 | AC13: 126.75 | AD13: 0 | AF13: 9.75 | AG13: 0 | AI13: 12.6675 | AJ13: 0 | AL13: 97.5 | AM13: 0 | AO13: 126.75 | AP13: 0 | AR13: 9.75 | AS13: 0 | AU13: 12.675 | AV13: 0 | AW13: 8 | AX13: 600 | AY13: 600 | BA13: 548 | BB13: 0 | BF13: 0 | BG13: 0 | BH13: 0 | BI13: 600 | BJ13: 0 | BL13: 93.75 | BM13: 0 | BO13: 7.5 | BP13: 0 | BR13: 9.375 | BS13: 0 | BU13: 97.5 | BV13: 0 | BW13: 0 | BX13: 31 | BY13: 0 | BZ13: 0 | CA13: 0 | CB13: 67.5 | CC13: 0 | CD13: 0 | CE13: 0 | CF13: 93.75 | CG13: 0 | CI13: 9.375 | CJ13: 0 | CK13: 10012.5 | CM13: 2030 | CN13: 391.25 | CO13: 200 | CP13: 550 | CQ13: 13183.75 | CR13: 1318.375 | CS13: 14502.125 | CT13: 0 | CU13: 341 | CV13: 14843.125
A14: 10 | B14: 32281 | C14: 46175 | D14: B59 | E14: Andal, Ana Mae De Jesus | G14: Factory 2 | H14: Trainee | I14: 80 | J14: 10 | K14: 600 | L14: 6000 | M14: 0 | N14: 93.75 | O14: 0 | P14: 0 | Q14: 7.5 | R14: 0 | S14: 0 | T14: 9.375 | U14: 0 | W14: 93.75 | X14: 0 | Z14: 97.5 | AA14: 0 | AC14: 126.75 | AD14: 0 | AF14: 9.75 | AG14: 0 | AI14: 12.6675 | AJ14: 0 | AL14: 97.5 | AM14: 0 | AO14: 126.75 | AP14: 0 | AR14: 9.75 | AS14: 0 | AU14: 12.675 | AV14: 0 | AW14: 8 | AX14: 600 | AY14: 600 | BA14: 549 | BB14: 0 | BF14: 0 | BG14: 0 | BH14: 0 | BI14: 600 | BJ14: 0 | BL14: 93.75 | BM14: 0 | BO14: 7.5 | BP14: 0 | BR14: 9.375 | BS14: 0 | BU14: 97.5 | BV14: 0 | BW14: 0 | BX14: 31 | BY14: 0 | BZ14: 0 | CA14: 0 | CB14: 67.5 | CC14: 0 | CD14: 0 | CE14: 0 | CF14: 93.75 | CG14: 0 | CI14: 9.375 | CJ14: 0 | CK14: 6600 | CM14: 710 | CN14: 391.25 | CO14: 200 | CP14: 500 | CQ14: 8401.25 | CR14: 840.125 | CS14: 9241.375 | CT14: 0 | CU14: 310 | CV14: 9551.375
A15: 11 | B15: 7080 | C15: 45531 | D15: B24 | E15: Antaran, Alrey jay Barber | G15: Factory 3 | H15: Warehouse | I15: 80 | J15: 10 | K15: 600 | L15: 6000 | M15: 12 | N15: 93.75 | O15: 1125 | P15: 24.96 | Q15: 7.5 | R15: 187.2 | S15: 6 | T15: 9.375 | U15: 56.25 | W15: 93.75 | X15: 0 | Z15: 97.5 | AA15: 0 | AC15: 126.75 | AD15: 0 | AF15: 9.75 | AG15: 0 | AI15: 12.6675 | AJ15: 0 | AL15: 97.5 | AM15: 0 | AO15: 126.75 | AP15: 0 | AR15: 9.75 | AS15: 0 | AU15: 12.675 | AV15: 0 | AW15: 8 | AX15: 600 | AY15: 600 | BA15: 550 | BB15: 0 | BF15: 3 | BG15: -3.75 | BH15: 0 | BI15: 600 | BJ15: 0 | BL15: 93.75 | BM15: 0 | BO15: 7.5 | BP15: 0 | BR15: 9.375 | BS15: 0 | BU15: 97.5 | BV15: 0 | BW15: 0 | BX15: 31 | BY15: 0 | BZ15: 0 | CA15: 0 | CB15: 67.5 | CC15: 0 | CD15: 0 | CE15: 0 | CF15: 93.75 | CG15: 0 | CI15: 9.375 | CJ15: 0 | CK15: 7964.7 | CM15: 1730 | CN15: 391.25 | CO15: 200 | CP15: 499.6875 | CQ15: 10785.638 | CR15: 1078.5638 | CS15: 11864.201 | CT15: 0 | CU15: 310 | CV15: 12174.201
A16: 12 | B16: 31088 | C16: 45993 | D16: B53 | E16: Armada, Simon Estacio | G16: Factory 1 | H16: QC Inspection | I16: 72 | J16: 9 | K16: 600 | L16: 5400 | M16: 18 | N16: 93.75 | O16: 1687.5 | P16: 25 | Q16: 7.5 | R16: 187.5 | S16: 8 | T16: 9.375 | U16: 75 | W16: 93.75 | X16: 0 | Z16: 97.5 | AA16: 0 | AC16: 126.75 | AD16: 0 | AF16: 9.75 | AG16: 0 | AI16: 12.6675 | AJ16: 0 | AL16: 97.5 | AM16: 0 | AO16: 126.75 | AP16: 0 | AR16: 9.75 | AS16: 0 | AU16: 12.675 | AV16: 0 | AW16: 8 | AX16: 600 | AY16: 600 | BA16: 551 | BB16: 0 | BF16: 0 | BG16: 0 | BH16: 0 | BI16: 600 | BJ16: 0 | BL16: 93.75 | BM16: 0 | BO16: 7.5 | BP16: 0 | BR16: 9.375 | BS16: 0 | BU16: 97.5 | BV16: 0 | BW16: 0 | BX16: 31 | BY16: 0 | BZ16: 0 | CA16: 0 | CB16: 67.5 | CC16: 0 | CD16: 0 | CE16: 0 | CF16: 93.75 | CG16: 0 | CI16: 9.375 | CJ16: 0 | CK16: 7950 | CM16: 1830 | CN16: 391.25 | CO16: 200 | CP16: 450 | CQ16: 10821.25 | CR16: 1082.125 | CS16: 11903.375 | CT16: 0 | CU16: 279 | CV16: 12182.375
... A65: 61 | B65: 12450 | C65: 45670 | D65: B30 | E65: Deuna, Rommel Lumpot | G65: Factory 1 | H65: Wire Preparation | I65: 80 | J65: 10 | K65: 600 | L65: 6000 | M65: 15 | N65: 93.75 | O65: 1406.25 | P65: 25 | Q65: 7.5 | R65: 187.5 | S65: 0 | T65: 9.375 | U65: 0 | W65: 93.75 | X65: 0 | Z65: 97.5 | AA65: 0 | AC65: 126.75 | AD65: 0 | AF65: 9.75 | AG65: 0 | AI65: 12.6675 | AJ65: 0 | AL65: 97.5 | AM65: 0 | AO65: 126.75 | AP65: 0 | AR65: 9.75 | AS65: 0 | AU65: 12.675 | AV65: 0 | AW65: 8 | AX65: 600 | AY65: 600 | BA65: 602 | BB65: 0 | BF65: 0 | BG65: 0 | BH65: 0 | BI65: 600 | BJ65: 0 | BL65: 93.75 | BM65: 0 | BO65: 7.5 | BP65: 0 | BR65: 9.375 | BS65: 0 | BU65: 97.5 | BV65: 0 | BW65: 0 | BX65: 31 | BY65: 0 | BZ65: 0 | CA65: 0 | CB65: 67.5 | CC65: 0 | CD65: 0 | CE65: 0 | CF65: 93.75 | CG65: 0 | CI65: 9.375 | CJ65: 0 | CK65: 8193.75 | CM65: 1880 | CN65: 391.25 | CO65: 200 | CP65: 500 | CQ65: 11165 | CR65: 1116.5 | CS65: 12281.5 | CT65: 0 | CU65: 310 | CV65: 12591.5
A66: 62 | B66: 5846 | C66: 45244 | D66: B2 | E66: Diaz, Junel Mago | G66: Factory 1 | H66: Wire Preparation | I66: 80 | J66: 10 | K66: 600 | L66: 6000 | M66: 24 | N66: 93.75 | O66: 2250 | P66: 25 | Q66: 7.5 | R66: 187.5 | S66: 8 | T66: 9.375 | U66: 75 | W66: 93.75 | X66: 0 | Z66: 97.5 | AA66: 0 | AC66: 126.75 | AD66: 0 | AF66: 9.75 | AG66: 0 | AI66: 12.6675 | AJ66: 0 | AL66: 97.5 | AM66: 0 | AO66: 126.75 | AP66: 0 | AR66: 9.75 | AS66: 0 | AU66: 12.675 | AV66: 0 | AW66: 8 | AX66: 600 | AY66: 600 | BA66: 603 | BB66: 0 | BF66: 0 | BG66: 0 | BH66: 0 | BI66: 600 | BJ66: 0 | BK66: 0 | BL66: 93.75 | BM66: 0 | BO66: 7.5 | BP66: 0 | BR66: 9.375 | BS66: 0 | BU66: 97.5 | BV66: 0 | BW66: 0 | BX66: 31 | BY66: 0 | BZ66: 0 | CA66: 0 | CB66: 67.5 | CC66: 0 | CD66: 0 | CE66: 0 | CF66: 93.75 | CG66: 0 | CI66: 9.375 | CJ66: 0 | CK66: 9112.5 | CM66: 1930 | CN66: 391.25 | CO66: 200 | CP66: 500 | CQ66: 12133.75 | CR66: 1213.375 | CS66: 13347.125 | CT66: 0 | CU66: 310 | CV66: 13657.125
A67: 63 | B67: 14872 | C67: 45818 | D67: B48 | E67: Dorado, Merlan Gatdula | G67: Factory 1 | H67: Wire Preparation | I67: 48 | J67: 6 | K67: 600 | L67: 3600 | M67: 0 | N67: 93.75 | O67: 0 | P67: 10 | Q67: 7.5 | R67: 75 | S67: 0 | T67: 9.375 | U67: 0 | W67: 93.75 | X67: 0 | Z67: 97.5 | AA67: 0 | AC67: 126.75 | AD67: 0 | AF67: 9.75 | AG67: 0 | AI67: 12.6675 | AJ67: 0 | AL67: 97.5 | AM67: 0 | AO67: 126.75 | AP67: 0 | AR67: 9.75 | AS67: 0 | AU67: 12.675 | AV67: 0 | AW67: 0 | AX67: 600 | AY67: 0 | BA67: 604 | BB67: 0 | BF67: 0 | BG67: 0 | BH67: 0 | BI67: 600 | BJ67: 0 | BL67: 93.75 | BM67: 0 | BO67: 7.5 | BP67: 0 | BR67: 9.375 | BS67: 0 | BU67: 97.5 | BV67: 0 | BW67: 0 | BX67: 31 | BY67: 0 | BZ67: 0 | CA67: 0 | CB67: 67.5 | CC67: 0 | CD67: 0 | CE67: 0 | CF67: 93.75 | CG67: 0 | CI67: 9.375 | CJ67: 0 | CK67: 3675 | CM67: 1060 | CN67: 391.25 | CO67: 200 | CP67: 300 | CQ67: 5626.25 | CR67: 562.625 | CS67: 6188.875 | CT67: 0 | CU67: 186 | CV67: 6374.875
A68: 64 | B68: 31012 | C68: 45944 | D68: B49 | E68: Encila, Marilyn Lopez | G68: Factory 1 | H68: Wire Preparation | I68: 88 | J68: 11 | K68: 600 | L68: 6600 | M68: 12 | N68: 93.75 | O68: 1125 | P68: 30 | Q68: 7.5 | R68: 225 | S68: 2 | T68: 9.375 | U68: 18.75 | W68: 93.75 | X68: 0 | Z68: 97.5 | AA68: 0 | AC68: 126.75 | AD68: 0 | AF68: 9.75 | AG68: 0 | AI68: 12.6675 | AJ68: 0 | AL68: 97.5 | AM68: 0 | AO68: 126.75 | AP68: 0 | AR68: 9.75 | AS68: 0 | AU68: 12.675 | AV68: 0 | AW68: 8 | AX68: 600 | AY68: 600 | BA68: 605 | BB68: 0 | BF68: 0 | BG68: 0 | BH68: 0 | BI68: 600 | BJ68: 0 | BL68: 93.75 | BM68: 0 | BO68: 7.5 | BP68: 0 | BR68: 9.375 | BS68: 0 | BU68: 97.5 | BV68: 0 | BW68: 0 | BX68: 31 | BY68: 0 | BZ68: 0 | CA68: 0 | CB68: 67.5 | CC68: 0 | CD68: 0 | CE68: 0 | CF68: 93.75 | CG68: 0 | CI68: 9.375 | CJ68: 0 | CK68: 8568.75 | CM68: 1880 | CN68: 391.25 | CO68: 200 | CP68: 550 | CQ68: 11590 | CR68: 1159 | CS68: 12749 | CT68: 0 | CU68: 341 | CV68: 13090
A69: 65 | B69: 32286 | C69: 46175 | D69: B59 | E69: Endozo, Ejay | G69: Factory 2 | H69: Trainee | I69: 80 | J69: 10 | K69: 600 | L69: 6000 | M69: 0 | N69: 93.75 | O69: 0 | P69: 0 | Q69: 7.5 | R69: 0 | S69: 0 | T69: 9.375 | U69: 0 | W69: 93.75 | X69: 0 | Z69: 97.5 | AA69: 0 | AC69: 126.75 | AD69: 0 | AF69: 9.75 | AG69: 0 | AI69: 12.6675 | AJ69: 0 | AL69: 97.5 | AM69: 0 | AO69: 126.75 | AP69: 0 | AR69: 9.75 | AS69: 0 | AU69: 12.675 | AV69: 0 | AW69: 8 | AX69: 600 | AY69: 600 | BA69: 606 | BB69: 0 | BF69: 240 | BG69: -300 | BH69: 0 | BI69: 600 | BJ69: 0 | BL69: 93.75 | BM69: 0 | BO69: 7.5 | BP69: 0 | BR69: 9.375 | BS69: 0 | BU69: 97.5 | BV69: 0 | BW69: 0 | BX69: 31 | BY69: 0 | BZ69: 0 | CA69: 0 | CB69: 67.5 | CC69: 0 | CD69: 0 | CE69: 0 | CF69: 93.75 | CG69: 0 | CI69: 9.375 | CJ69: 0 | CK69: 6300 | CM69: 660 | CN69: 391.25 | CO69: 200 | CP69: 475 | CQ69: 8026.25 | CR69: 802.625 | CS69: 8828.875 | CT69: 15.5 | CU69: 294.5 | CV69: 9123.375
A70: 66 | B70: 32559 | C70: 46154 | D70: B57 | E70: Enecimo, Rodelyn Macahis | G70: Factory 3 | H70: Wire Preparation | I70: 88 | J70: 11 | K70: 600 | L70: 6600 | M70: 0 | N70: 93.75 | O70: 0 | P70: 30 | Q70: 7.5 | R70: 225 | S70: 0 | T70: 9.375 | U70: 0 | W70: 93.75 | X70: 0 | Z70: 97.5 | AA70: 0 | AC70: 126.75 | AD70: 0 | AF70: 9.75 | AG70: 0 | AI70: 12.6675 | AJ70: 0 | AL70: 97.5 | AM70: 0 | AO70: 126.75 | AP70: 0 | AR70: 9.75 | AS70: 0 | AU70: 12.675 | AV70: 0 | AW70: 8 | AX70: 600 | AY70: 600 | BA70: 607 | BB70: 0 | BF70: 0 | BG70: 0 | BH70: 0 | BI70: 600 | BJ70: 0 | BL70: 93.75 | BM70: 0 | BO70: 7.5 | BP70: 0 | BR70: 9.375 | BS70: 0 | BU70: 97.5 | BV70: 0 | BW70: 0 | BX70: 31 | BY70: 0 | BZ70: 0 | CA70: 0 | CB70: 67.5 | CC70: 0 | CD70: 0 | CE70: 0 | CF70: 93.75 | CG70: 0 | CI70: 9.375 | CJ70: 0 | CK70: 7425 | CM70: 1580 | CN70: 391.25 | CO70: 200 | CP70: 550 | CQ70: 10146.25 | CR70: 1014.625 | CS70: 11160.875 | CT70: 0 | CU70: 341 | CV70: 11501.875
A71: 67 | B71: 32537 | C71: 46154 | D71: B57 | E71: Enriquez, Felicidad Dajon | G71: Factory 1 | H71: Wire Preparation | I71: 88 | J71: 11 | K71: 600 | L71: 6600 | M71: 3 | N71: 93.75 | O71: 281.25 | P71: 25 | Q71: 7.5 | R71: 187.5 | S71: 2 | T71: 9.375 | U71: 18.75 | W71: 93.75 | X71: 0 | Z71: 97.5 | AA71: 0 | AC71: 126.75 | AD71: 0 | AF71: 9.75 | AG71: 0 | AI71: 12.6675 | AJ71: 0 | AL71: 97.5 | AM71: 0 | AO71: 126.75 | AP71: 0 | AR71: 9.75 | AS71: 0 | AU71: 12.675 | AV71: 0 | AW71: 8 | AX71: 600 | AY71: 600 | BA71: 608 | BB71: 0 | BF71: 0 | BG71: 0 | BH71: 0 | BI71: 600 | BJ71: 0 | BL71: 93.75 | BM71: 0 | BO71: 7.5 | BP71: 0 | BR71: 9.375 | BS71: 0 | BU71: 97.5 | BV71: 0 | BW71: 0 | BX71: 31 | BY71: 0 | BZ71: 0 | CA71: 0 | CB71: 67.5 | CC71: 0 | CD71: 0 | CE71: 0 | CF71: 93.75 | CG71: 0 | CI71: 9.375 | CJ71: 0 | CK71: 7687.5 | CM71: 1730 | CN71: 391.25 | CO71: 200 | CP71: 550 | CQ71: 10558.75 | CR71: 1055.875 | CS71: 11614.625 | CT71: 0 | CU71: 341 | CV71: 11955.625
A72: 68 | B72: 13357 | C72: 45811 | D72: B47 | E72: Esplana, Ronald N/A | G72: Factory 3 | H72: Wire Preparation | I72: 88 | J72: 11 | K72: 600 | L72: 6600 | M72: 6 | N72: 93.75 | O72: 562.5 | P72: 30 | Q72: 7.5 | R72: 225 | S72: 2 | T72: 9.375 | U72: 18.75 | W72: 93.75 | X72: 0 | Z72: 97.5 | AA72: 0 | AC72: 126.75 | AD72: 0 | AF72: 9.75 | AG72: 0 | AI72: 12.6675 | AJ72: 0 | AL72: 97.5 | AM72: 0 | AO72: 126.75 | AP72: 0 | AR72: 9.75 | AS72: 0 | AU72: 12.675 | AV72: 0 | AW72: 8 | AX72: 600 | AY72: 600 | BA72: 609 | BB72: 0 | BF72: 0 | BG72: 0 | BH72: 0 | BI72: 600 | BJ72: 0 | BL72: 93.75 | BM72: 0 | BO72: 7.5 | BP72: 0 | BR72: 9.375 | BS72: 0 | BU72: 97.5 | BV72: 0 | BW72: 0 | BX72: 31 | BY72: 0 | BZ72: 0 | CA72: 0 | CB72: 67.5 | CC72: 0 | CD72: 0 | CE72: 0 | CF72: 93.75 | CG72: 0 | CI72: 9.375 | CJ72: 0 | CK72: 8006.25 | CM72: 1680 | CN72: 391.25 | CO72: 200 | CP72: 550 | CQ72: 10827.5 | CR72: 1082.75 | CS72: 11910.25 | CT72: 0 | CU72: 341 | CV72: 12251.25
A73: 69 | B73: 12260 | C73: 45768 | D73: B41 | E73: Estipona, Joel De Mesa | G73: Factory 1 | H73: Subaru Engine | I73: 80 | J73: 10 | K73: 600 | L73: 6000 | M73: 9 | N73: 93.75 | O73: 843.75 | P73: 30 | Q73: 7.5 | R73: 225 | S73: 0 | T73: 9.375 | U73: 0 | W73: 93.75 | X73: 0 | Z73: 97.5 | AA73: 0 | AC73: 126.75 | AD73: 0 | AF73: 9.75 | AG73: 0 | AI73: 12.6675 | AJ73: 0 | AL73: 97.5 | AM73: 0 | AO73: 126.75 | AP73: 0 | AR73: 9.75 | AS73: 0 | AU73: 12.675 | AV73: 0 | AW73: 8 | AX73: 600 | AY73: 600 | BA73: 610 | BB73: 0 | BF73: 0 | BG73: 0 | BH73: 0 | BI73: 600 | BJ73: 0 | BL73: 93.75 | BM73: 0 | BO73: 7.5 | BP73: 0 | BR73: 9.375 | BS73: 0 | BU73: 97.5 | BV73: 0 | BW73: 0 | BX73: 31 | BY73: 0 | BZ73: 0 | CA73: 0 | CB73: 67.5 | CC73: 0 | CD73: 0 | CE73: 0 | CF73: 93.75 | CG73: 0 | CI73: 9.375 | CJ73: 0 | CK73: 7668.75 | CM73: 1830 | CN73: 391.25 | CO73: 200 | CP73: 500 | CQ73: 10590 | CR73: 1059 | CS73: 11649 | CT73: 0 | CU73: 310 | CV73: 11959
A74: 70 | B74: 32570 | C74: 46154 | D74: B57 | E74: Estolano, Jade Marie Flores | G74: Factory 1 | H74: Wire Preparation | I74: 88 | J74: 11 | K74: 600 | L74: 6600 | M74: 0 | N74: 93.75 | O74: 0 | P74: 25 | Q74: 7.5 | R74: 187.5 | S74: 0 | T74: 9.375 | U74: 0 | W74: 93.75 | X74: 0 | Z74: 97.5 | AA74: 0 | AC74: 126.75 | AD74: 0 | AF74: 9.75 | AG74: 0 | AI74: 12.6675 | AJ74: 0 | AL74: 97.5 | AM74: 0 | AO74: 126.75 | AP74: 0 | AR74: 9.75 | AS74: 0 | AU74: 12.675 | AV74: 0 | AW74: 8 | AX74: 600 | AY74: 600 | BA74: 611 | BB74: 0 | BF74: 35 | BG74: -43.75 | BH74: 0 | BI74: 600 | BJ74: 0 | BL74: 93.75 | BM74: 0 | BO74: 7.5 | BP74: 0 | BR74: 9.375 | BS74: 0 | BU74: 97.5 | BV74: 0 | BW74: 0 | BX74: 31 | BY74: 0 | BZ74: 0 | CA74: 0 | CB74: 67.5 | CC74: 0 | CD74: 0 | CE74: 0 | CF74: 93.75 | CG74: 0 | CI74: 9.375 | CJ74: 0 | CK74: 7343.75 | CM74: 1310 | CN74: 391.25 | CO74: 200 | CP74: 546.35417 | CQ74: 9791.3542 | CR74: 979.13542 | CS74: 10770.49 | CT74: 0 | CU74: 341 | CV74: 11111.49
A75: 71 | B75: 6905 | C75: 45497 | D75: B19 | E75: Estrada, Kevin James Hernandez | G75: Factory 1 | H75: Subaru Insertion | I75: 88 | J75: 11 | K75: 600 | L75: 6600 | M75: 21 | N75: 93.75 | O75: 1968.75 | P75: 30 | Q75: 7.5 | R75: 225 | S75: 6 | T75: 9.375 | U75: 56.25 | W75: 93.75 | X75: 0 | Z75: 97.5 | AA75: 0 | AC75: 126.75 | AD75: 0 | AF75: 9.75 | AG75: 0 | AI75: 12.6675 | AJ75: 0 | AL75: 97.5 | AM75: 0 | AO75: 126.75 | AP75: 0 | AR75: 9.75 | AS75: 0 | AU75: 12.675 | AV75: 0 | AW75: 8 | AX75: 600 | AY75: 600 | BA75: 612 | BB75: 0 | BF75: 0 | BG75: 0 | BH75: 0 | BI75: 600 | BJ75: 0 | BL75: 93.75 | BM75: 0 | BO75: 7.5 | BP75: 0 | BR75: 9.375 | BS75: 0 | BU75: 97.5 | BV75: 0 | BW75: 0 | BX75: 31 | BY75: 0 | BZ75: 0 | CA75: 0 | CB75: 67.5 | CC75: 0 | CD75: 0 | CE75: 0 | CF75: 93.75 | CG75: 0 | CI75: 9.375 | CJ75: 0 | CK75: 9450 | CM75: 2080 | CN75: 391.25 | CO75: 200 | CP75: 550 | CQ75: 12671.25 | CR75: 1267.125 | CS75: 13938.375 | CT75: 0 | CU75: 341 | CV75: 14279.375
A76: 72 | B76: 13351 | C76: 45811 | D76: B47 | E76: Faderog, Mark Japhet Francisco | G76: Factory 3 | H76: QC Inspection | I76: 88 | J76: 11 | K76: 600 | L76: 6600 | M76: 26.98 | N76: 93.75 | O76: 2529.375 | P76: 30 | Q76: 7.5 | R76: 225 | S76: 10 | T76: 9.375 | U76: 93.75 | W76: 93.75 | X76: 0 | Z76: 97.5 | AA76: 0 | AC76: 126.75 | AD76: 0 | AF76: 9.75 | AG76: 0 | AI76: 12.6675 | AJ76: 0 | AL76: 97.5 | AM76: 0 | AO76: 126.75 | AP76: 0 | AR76: 9.75 | AS76: 0 | AU76: 12.675 | AV76: 0 | AW76: 8 | AX76: 600 | AY76: 600 | BA76: 613 | BB76: 0 | BF76: 0 | BG76: 0 | BH76: 0 | BI76: 600 | BJ76: 0 | BL76: 93.75 | BM76: 0 | BO76: 7.5 | BP76: 0 | BR76: 9.375 | BS76: 0 | BU76: 97.5 | BV76: 0 | BW76: 0 | BX76: 31 | BY76: 0 | BZ76: 0 | CA76: 0 | CB76: 67.5 | CC76: 0 | CD76: 0 | CE76: 0 | CF76: 93.75 | CG76: 0 | CI76: 9.375 | CJ76: 0 | CK76: 10048.125 | CM76: 2130 | CN76: 391.25 | CO76: 200 | CP76: 550 | CQ76: 13319.375 | CR76: 1331.9375 | CS76: 14651.312 | CT76: 0 | CU76: 341 | CV76: 14992.312
A77: 73 | B77: 32292 | C77: 46175 | D77: B59 | E77: Fajardo, Jonaglen Berwega | G77: Factory 2 | H77: Trainee | I77: 80 | J77: 10 | K77: 600 | L77: 6000 | M77: 0 | N77: 99.21875 | O77: 0 | P77: 20 | Q77: 7.5 | R77: 150 | S77: 0 | T77: 9.921875 | U77: 0 | W77: 99.21875 | X77: 0 | Z77: 103.1875 | AA77: 0 | AC77: 134.14375 | AD77: 0 | AF77: 10.31875 | AG77: 0 | AI77: 13.406438 | AJ77: 0 | AL77: 103.1875 | AM77: 0 | AO77: 134.14375 | AP77: 0 | AR77: 10.31875 | AS77: 0 | AU77: 13.414375 | AV77: 0 | AW77: 8 | AX77: 600 | AY77: 600 | BA77: 614 | BB77: 0 | BF77: 0 | BG77: 0 | BH77: 0 | BI77: 600 | BJ77: 0 | BL77: 93.75 | BM77: 0 | BO77: 7.5 | BP77: 0 | BR77: 9.375 | BS77: 0 | BU77: 103.1875 | BV77: 0 | BW77: 0 | BX77: 31 | BY77: 0 | BZ77: 0 | CA77: 0 | CB77: 67.5 | CC77: 0 | CD77: 0 | CE77: 0 | CF77: 99.21875 | CG77: 0 | CI77: 9.921875 | CJ77: 0 | CK77: 7100 | CM77: 710 | CN77: 391.25 | CO77: 200 | CP77: 500 | CQ77: 8551.25 | CR77: 855.125 | CS77: 9406.375 | CT77: 0 | CU77: 310 | CV77: 9716.375
A78: 74 | B78: 31137 | C78: 45951 | D78: B50 | E78: Fidelson, Maria Noralie N/A | G78: Factory 1 | H78: Subaru Engine | I78: 88 | J78: 11 | K78: 600 | L78: 6600 | M78: 21 | N78: 93.75 | O78: 1968.75 | P78: 25 | Q78: 7.5 | R78: 187.5 | S78: 10 | T78: 9.375 | U78: 93.75 | W78: 93.75 | X78: 0 | Z78: 97.5 | AA78: 0 | AC78: 126.75 | AD78: 0 | AF78: 9.75 | AG78: 0 | AI78: 12.6675 | AJ78: 0 | AL78: 97.5 | AM78: 0 | AO78: 126.75 | AP78: 0 | AR78: 9.75 | AS78: 0 | AU78: 12.675 | AV78: 0 | AW78: 8 | AX78: 600 | AY78: 600 | BA78: 615 | BB78: 0 | BF78: 0 | BG78: 0 | BH78: 0 | BI78: 600 | BJ78: 0 | BL78: 93.75 | BM78: 0 | BO78: 7.5 | BP78: 0 | BR78: 9.375 | BS78: 0 | BU78: 97.5 | BV78: 0 | BW78: 0 | BX78: 31 | BY78: 0 | BZ78: 0 | CA78: 0 | CB78: 67.5 | CC78: 0 | CD78: 0 | CE78: 0 | CF78: 93.75 | CG78: 0 | CI78: 9.375 | CJ78: 0 | CK78: 9450 | CM78: 1930 | CN78: 391.25 | CO78: 200 | CP78: 550 | CQ78: 12521.25 | CR78: 1252.125 | CS78: 13773.375 | CT78: 0 | CU78: 341 | CV78: 14114.375
... A123: 119 | B123: 31090 | C123: 45993 | D123: B53 | E123: Mesina, Jhon Patrick Villanueva | G123: Factory 1 | H123: Material Handler | I123: 16 | J123: 2 | K123: 600 | L123: 1200 | M123: 0 | N123: 93.75 | O123: 0 | P123: 10 | Q123: 7.5 | R123: 75 | S123: 0 | T123: 9.375 | U123: 0 | W123: 93.75 | X123: 0 | Z123: 97.5 | AA123: 0 | AC123: 126.75 | AD123: 0 | AF123: 9.75 | AG123: 0 | AI123: 12.6675 | AJ123: 0 | AL123: 97.5 | AM123: 0 | AO123: 126.75 | AP123: 0 | AR123: 9.75 | AS123: 0 | AU123: 12.675 | AV123: 0 | AW123: 0 | AX123: 600 | AY123: 0 | BA123: 660 | BB123: 0 | BF123: 0 | BG123: 0 | BH123: 0 | BI123: 600 | BJ123: 0 | BL123: 93.75 | BM123: 0 | BO123: 7.5 | BP123: 0 | BR123: 9.375 | BS123: 0 | BU123: 97.5 | BV123: 0 | BW123: 0 | BX123: 31 | BY123: 0 | BZ123: 0 | CA123: 0 | CB123: 67.5 | CC123: 0 | CD123: 0 | CE123: 0 | CF123: 93.75 | CG123: 0 | CI123: 9.375 | CJ123: 0 | CK123: 1275 | CM123: 0 | CN123: 0 | CO123: 0 | CP123: 100 | CQ123: 1375 | CR123: 137.5 | CS123: 1512.5 | CT123: 0 | CU123: 62 | CV123: 1574.5
A124: 120 | B124: 32295 | C124: 46175 | D124: B59 | E124: Miranda, Ruben Peregrino De Asis | G124: Factory 2 | H124: Trainee | I124: 80 | J124: 10 | K124: 600 | L124: 6000 | M124: 3 | N124: 93.75 | O124: 281.25 | P124: 20 | Q124: 7.5 | R124: 150 | S124: 2 | T124: 9.375 | U124: 18.75 | W124: 93.75 | X124: 0 | Z124: 97.5 | AA124: 0 | AC124: 126.75 | AD124: 0 | AF124: 9.75 | AG124: 0 | AI124: 12.6675 | AJ124: 0 | AL124: 97.5 | AM124: 0 | AO124: 126.75 | AP124: 0 | AR124: 9.75 | AS124: 0 | AU124: 12.675 | AV124: 0 | AW124: 8 | AX124: 600 | AY124: 600 | BA124: 661 | BB124: 0 | BF124: 0 | BG124: 0 | CK124: 7050 | CM124: 760 | CN124: 391.25 | CO124: 200 | CP124: 500 | CQ124: 8901.25 | CR124: 890.125 | CS124: 9791.375 | CT124: 0 | CU124: 310 | CV124: 10101.375
A125: 121 | B125: 12743 | C125: 45685 | D125: B33 | E125: Misula, Ruden Romualdo | G125: Factory 3 | H125: Transmission | I125: 88 | J125: 11 | K125: 600 | L125: 6600 | M125: 9 | N125: 93.75 | O125: 843.75 | P125: 25 | Q125: 7.5 | R125: 187.5 | S125: 6 | T125: 9.375 | U125: 56.25 | W125: 93.75 | X125: 0 | Z125: 97.5 | AA125: 0 | AC125: 126.75 | AD125: 0 | AF125: 9.75 | AG125: 0 | AI125: 12.6675 | AJ125: 0 | AL125: 97.5 | AM125: 0 | AO125: 126.75 | AP125: 0 | AR125: 9.75 | AS125: 0 | AU125: 12.675 | AV125: 0 | AW125: 8 | AX125: 600 | AY125: 600 | BA125: 662 | BB125: 0 | BF125: 0 | BG125: 0 | CK125: 8287.5 | CM125: 1880 | CN125: 391.25 | CO125: 200 | CP125: 550 | CQ125: 11308.75 | CR125: 1130.875 | CS125: 12439.625 | CT125: 0 | CU125: 341 | CV125: 12780.625
A126: 122 | B126: 32543 | C126: 46154 | D126: B57 | E126: Mojica, Raymart | G126: Factory 2 | H126: Molding | I126: 88 | J126: 11 | K126: 600 | L126: 6600 | M126: 24 | N126: 93.75 | O126: 2250 | P126: 25 | Q126: 7.5 | R126: 187.5 | S126: 10 | T126: 9.375 | U126: 93.75 | W126: 93.75 | X126: 0 | Z126: 97.5 | AA126: 0 | AC126: 126.75 | AD126: 0 | AF126: 9.75 | AG126: 0 | AI126: 12.6675 | AJ126: 0 | AL126: 97.5 | AM126: 0 | AO126: 126.75 | AP126: 0 | AR126: 9.75 | AS126: 0 | AU126: 12.675 | AV126: 0 | AW126: 8 | AX126: 600 | AY126: 600 | BA126: 663 | BB126: 0 | BF126: 0 | BG126: 0 | CK126: 9731.25 | CM126: 1980 | CN126: 391.25 | CO126: 200 | CP126: 550 | CQ126: 12852.5 | CR126: 1285.25 | CS126: 14137.75 | CT126: 0 | CU126: 341 | CV126: 14478.75
A127: 123 | B127: 13893 | C127: 45545 | D127: B26 | E127: Montejo, John Miguel Bitchayda | G127: Factory 1 | H127: Subaru Engine | I127: 88 | J127: 11 | K127: 600 | L127: 6600 | M127: 24 | N127: 93.75 | O127: 2250 | P127: 30 | Q127: 7.5 | R127: 225 | S127: 10 | T127: 9.375 | U127: 93.75 | W127: 93.75 | X127: 0 | Z127: 97.5 | AA127: 0 | AC127: 126.75 | AD127: 0 | AF127: 9.75 | AG127: 0 | AI127: 12.6675 | AJ127: 0 | AL127: 97.5 | AM127: 0 | AO127: 126.75 | AP127: 0 | AR127: 9.75 | AS127: 0 | AU127: 12.675 | AV127: 0 | AW127: 8 | AX127: 600 | AY127: 600 | BA127: 664 | BB127: 0 | BF127: 0 | BG127: 0 | CK127: 9768.75 | CM127: 2030 | CN127: 391.25 | CO127: 200 | CP127: 550 | CQ127: 12940 | CR127: 1294 | CS127: 14234 | CT127: 0 | CU127: 341 | CV127: 14575
A128: 124 | B128: 32819 | C128: 46084 | D128: B56 | E128: Mora, Stephany Jerrylle Robles | G128: Factory 1 | H128: QC Inspection | I128: 88 | J128: 11 | K128: 600 | L128: 6600 | M128: 30 | N128: 93.75 | O128: 2812.5 | P128: 30 | Q128: 7.5 | R128: 225 | S128: 10 | T128: 9.375 | U128: 93.75 | W128: 93.75 | X128: 0 | Z128: 97.5 | AA128: 0 | AC128: 126.75 | AD128: 0 | AF128: 9.75 | AG128: 0 | AI128: 12.6675 | AJ128: 0 | AL128: 97.5 | AM128: 0 | AO128: 126.75 | AP128: 0 | AR128: 9.75 | AS128: 0 | AU128: 12.675 | AV128: 0 | AW128: 8 | AX128: 600 | AY128: 600 | BA128: 665 | BB128: 0 | BF128: 0 | BG128: 0 | CK128: 10331.25 | CM128: 1930 | CN128: 391.25 | CO128: 200 | CP128: 550 | CQ128: 13402.5 | CR128: 1340.25 | CS128: 14742.75 | CT128: 0 | CU128: 341 | CV128: 15083.75
A129: 125 | B129: 32566 | C129: 46154 | D129: B57 | E129: Morales, Eden Motol | G129: Factory 2 | H129: Wire Preparation | I129: 32 | J129: 4 | K129: 600 | L129: 2400 | M129: 0 | N129: 93.75 | O129: 0 | P129: 0 | Q129: 7.5 | R129: 0 | S129: 0 | T129: 9.375 | U129: 0 | W129: 93.75 | X129: 0 | Z129: 97.5 | AA129: 0 | AC129: 126.75 | AD129: 0 | AF129: 9.75 | AG129: 0 | AI129: 12.6675 | AJ129: 0 | AL129: 97.5 | AM129: 0 | AO129: 126.75 | AP129: 0 | AR129: 9.75 | AS129: 0 | AU129: 12.675 | AV129: 0 | AW129: 0 | AX129: 600 | AY129: 0 | BA129: 666 | BB129: 0 | BF129: 0 | BG129: 0 | CK129: 2400 | CM129: 1060 | CN129: 391.25 | CO129: 200 | CP129: 200 | CQ129: 4251.25 | CR129: 425.125 | CS129: 4676.375 | CT129: 0 | CU129: 124 | CV129: 4800.375
A130: 126 | B130: 32282 | C130: 46175 | D130: B59 | E130: Morales, Lira Ann Sabanal | G130: Factory 2 | H130: Trainee | I130: 80 | J130: 10 | K130: 600 | L130: 6000 | M130: 0 | N130: 93.75 | O130: 0 | P130: 0 | Q130: 7.5 | R130: 0 | S130: 0 | T130: 9.375 | U130: 0 | W130: 93.75 | X130: 0 | Z130: 97.5 | AA130: 0 | AC130: 126.75 | AD130: 0 | AF130: 9.75 | AG130: 0 | AI130: 12.6675 | AJ130: 0 | AL130: 97.5 | AM130: 0 | AO130: 126.75 | AP130: 0 | AR130: 9.75 | AS130: 0 | AU130: 12.675 | AV130: 0 | AW130: 8 | AX130: 600 | AY130: 600 | BA130: 667 | BB130: 0 | BF130: 0 | BG130: 0 | CK130: 6600 | CM130: 710 | CN130: 391.25 | CO130: 200 | CP130: 500 | CQ130: 8401.25 | CR130: 840.125 | CS130: 9241.375 | CT130: 0 | CU130: 310 | CV130: 9551.375
A131: 127 | B131: 32562 | C131: 46154 | D131: B57 | E131: Morales, Marwin Rodriguez | G131: Factory 1 | H131: Wire Preparation | I131: 88 | J131: 11 | K131: 600 | L131: 6600 | M131: 21 | N131: 93.75 | O131: 1968.75 | P131: 25 | Q131: 7.5 | R131: 187.5 | S131: 6 | T131: 9.375 | U131: 56.25 | W131: 93.75 | X131: 0 | Z131: 97.5 | AA131: 0 | AC131: 126.75 | AD131: 0 | AF131: 9.75 | AG131: 0 | AI131: 12.6675 | AJ131: 0 | AL131: 97.5 | AM131: 0 | AO131: 126.75 | AP131: 0 | AR131: 9.75 | AS131: 0 | AU131: 12.675 | AV131: 0 | AW131: 8 | AX131: 600 | AY131: 600 | BA131: 668 | BB131: 0 | BF131: 0 | BG131: 0 | CK131: 9412.5 | CM131: 1880 | CN131: 391.25 | CO131: 200 | CP131: 550 | CQ131: 12433.75 | CR131: 1243.375 | CS131: 13677.125 | CT131: 0 | CU131: 341 | CV131: 14018.125
A132: 128 | B132: 13360 | C132: 45811 | D132: B47 | E132: Moratin, Ian Vincent Libet | G132: Factory 1 | H132: Wire Preparation | I132: 80 | J132: 10 | K132: 600 | L132: 6000 | M132: 21 | N132: 93.75 | O132: 1968.75 | P132: 30 | Q132: 7.5 | R132: 225 | S132: 8 | T132: 9.375 | U132: 75 | W132: 93.75 | X132: 0 | Z132: 97.5 | AA132: 0 | AC132: 126.75 | AD132: 0 | AF132: 9.75 | AG132: 0 | AI132: 12.6675 | AJ132: 0 | AL132: 97.5 | AM132: 0 | AO132: 126.75 | AP132: 0 | AR132: 9.75 | AS132: 0 | AU132: 12.675 | AV132: 0 | AW132: 8 | AX132: 600 | AY132: 600 | BA132: 669 | BB132: 0 | BF132: 0 | BG132: 0 | CK132: 8868.75 | CM132: 1880 | CN132: 391.25 | CO132: 200 | CP132: 500 | CQ132: 11840 | CR132: 1184 | CS132: 13024 | CT132: 0 | CU132: 310 | CV132: 13334
A133: 129 | B133: 13358 | C133: 45811 | D133: B47 | E133: Moster, Danilyn Padrique | G133: Factory 1 | H133: Transmission | I133: 16 | J133: 2 | K133: 600 | L133: 1200 | M133: 0 | N133: 93.75 | O133: 0 | P133: 10 | Q133: 7.5 | R133: 75 | S133: 0 | T133: 9.375 | U133: 0 | W133: 93.75 | X133: 0 | Z133: 97.5 | AA133: 0 | AC133: 126.75 | AD133: 0 | AF133: 9.75 | AG133: 0 | AI133: 12.6675 | AJ133: 0 | AL133: 97.5 | AM133: 0 | AO133: 126.75 | AP133: 0 | AR133: 9.75 | AS133: 0 | AU133: 12.675 | AV133: 0 | AW133: 0 | AX133: 600 | AY133: 0 | BA133: 670 | BB133: 0 | BF133: 0 | BG133: 0 | CK133: 1275 | CM133: 0 | CN133: 0 | CO133: 0 | CP133: 100 | CQ133: 1375 | CR133: 137.5 | CS133: 1512.5 | CT133: 0 | CU133: 62 | CV133: 1574.5
A134: 130 | B134: 32219 | C134: 46161 | D134: B58 | E134: Naling, Ryan Mel Marasigan | G134: Factory 2 | H134: Subaru Engine/TM | I134: 88 | J134: 11 | K134: 600 | L134: 6600 | M134: 0 | N134: 93.75 | O134: 0 | P134: 25 | Q134: 7.5 | R134: 187.5 | S134: 0 | T134: 9.375 | U134: 0 | W134: 93.75 | X134: 0 | Z134: 97.5 | AA134: 0 | AC134: 126.75 | AD134: 0 | AF134: 9.75 | AG134: 0 | AI134: 12.6675 | AJ134: 0 | AL134: 97.5 | AM134: 0 | AO134: 126.75 | AP134: 0 | AR134: 9.75 | AS134: 0 | AU134: 12.675 | AV134: 0 | AW134: 8 | AX134: 600 | AY134: 600 | BA134: 671 | BB134: 0 | BF134: 1 | BG134: -1.25 | CK134: 7386.25 | CM134: 1460 | CN134: 391.25 | CO134: 200 | CP134: 549.89583 | CQ134: 9987.3958 | CR134: 998.73958 | CS134: 10986.135 | CT134: 0 | CU134: 341 | CV134: 11327.135
A135: 131 | B135: 32275 | C135: 46175 | D135: B59 | E135: Nascional, Joycelyn Medrano | G135: Factory 2 | H135: Trainee | I135: 80 | J135: 10 | K135: 600 | L135: 6000 | M135: 0 | N135: 93.75 | O135: 0 | P135: 0 | Q135: 7.5 | R135: 0 | S135: 0 | T135: 9.375 | U135: 0 | W135: 93.75 | X135: 0 | Z135: 97.5 | AA135: 0 | AC135: 126.75 | AD135: 0 | AF135: 9.75 | AG135: 0 | AI135: 12.6675 | AJ135: 0 | AL135: 97.5 | AM135: 0 | AO135: 126.75 | AP135: 0 | AR135: 9.75 | AS135: 0 | AU135: 12.675 | AV135: 0 | AW135: 8 | AX135: 600 | AY135: 600 | BA135: 672 | BB135: 0 | BF135: 0 | BG135: 0 | CK135: 6600 | CM135: 710 | CN135: 391.25 | CO135: 200 | CP135: 500 | CQ135: 8401.25 | CR135: 840.125 | CS135: 9241.375 | CT135: 0 | CU135: 310 | CV135: 9551.375
... A166: 162 | B166: 32290 | C166: 46175 | D166: B59 | E166: Romero, Eduardo Jr Chavez | G166: Factory 2 | H166: Trainee | I166: 80 | J166: 10 | K166: 600 | L166: 6000 | M166: 0 | N166: 93.75 | O166: 0 | P166: 0 | Q166: 7.5 | R166: 0 | S166: 0 | T166: 9.375 | U166: 0 | W166: 93.75 | X166: 0 | Z166: 97.5 | AA166: 0 | AC166: 126.75 | AD166: 0 | AF166: 9.75 | AG166: 0 | AI166: 12.6675 | AJ166: 0 | AL166: 97.5 | AM166: 0 | AO166: 126.75 | AP166: 0 | AR166: 9.75 | AS166: 0 | AU166: 12.675 | AV166: 0 | AW166: 8 | AX166: 600 | AY166: 600 | BA166: 703 | BB166: 0 | BF166: 0 | BG166: 0 | CK166: 6600 | CM166: 710 | CN166: 391.25 | CO166: 200 | CP166: 500 | CQ166: 8401.25 | CR166: 840.125 | CS166: 9241.375 | CT166: 0 | CU166: 310 | CV166: 9551.375
A167: 163 | B167: 7113 | C167: 45531 | D167: B24 | E167: Saldo, Jymuell Maxuell Chavez | G167: Factory 1 | H167: QA Packing | I167: 88 | J167: 11 | K167: 600 | L167: 6600 | M167: 30 | N167: 93.75 | O167: 2812.5 | P167: 30 | Q167: 7.5 | R167: 225 | S167: 10 | T167: 9.375 | U167: 93.75 | W167: 93.75 | X167: 0 | Z167: 97.5 | AA167: 0 | AC167: 126.75 | AD167: 0 | AF167: 9.75 | AG167: 0 | AI167: 12.6675 | AJ167: 0 | AL167: 97.5 | AM167: 0 | AO167: 126.75 | AP167: 0 | AR167: 9.75 | AS167: 0 | AU167: 12.675 | AV167: 0 | AW167: 8 | AX167: 600 | AY167: 600 | BA167: 704 | BB167: 0 | BF167: 0 | BG167: 0 | BH167: 0 | BI167: 600 | BJ167: 0 | BL167: 93.75 | BM167: 0 | BO167: 7.5 | BP167: 0 | BR167: 9.375 | BS167: 0 | BU167: 97.5 | BV167: 0 | BW167: 0 | BX167: 31 | BY167: 0 | BZ167: 0 | CA167: 0 | CB167: 67.5 | CC167: 0 | CD167: 0 | CE167: 0 | CF167: 93.75 | CG167: 0 | CI167: 9.375 | CJ167: 0 | CK167: 10331.25 | CM167: 2130 | CN167: 391.25 | CO167: 200 | CP167: 550 | CQ167: 13602.5 | CR167: 1360.25 | CS167: 14962.75 | CT167: 0 | CU167: 341 | CV167: 15303.75
A168: 164 | B168: 32815 | C168: 46084 | D168: B56 | E168: Sancho, Herman Olmedo | G168: Factory 1 | H168: Subaru Engine | I168: 88 | J168: 11 | K168: 600 | L168: 6600 | M168: 21 | N168: 93.75 | O168: 1968.75 | P168: 30 | Q168: 7.5 | R168: 225 | S168: 6 | T168: 9.375 | U168: 56.25 | W168: 93.75 | X168: 0 | Z168: 97.5 | AA168: 0 | AC168: 126.75 | AD168: 0 | AF168: 9.75 | AG168: 0 | AI168: 12.6675 | AJ168: 0 | AL168: 97.5 | AM168: 0 | AO168: 126.75 | AP168: 0 | AR168: 9.75 | AS168: 0 | AU168: 12.675 | AV168: 0 | AW168: 8 | AX168: 600 | AY168: 600 | BA168: 705 | BB168: 0 | BF168: 0 | BG168: 0 | BH168: 0 | BI168: 600 | BJ168: 0 | BL168: 93.75 | BM168: 0 | BO168: 7.5 | BP168: 0 | BR168: 9.375 | BS168: 0 | BU168: 97.5 | BV168: 0 | BW168: 0 | BX168: 31 | BY168: 0 | BZ168: 0 | CA168: 0 | CB168: 67.5 | CC168: 0 | CD168: 0 | CE168: 0 | CF168: 93.75 | CG168: 0 | CI168: 9.375 | CJ168: 0 | CK168: 9450 | CM168: 1880 | CN168: 391.25 | CO168: 200 | CP168: 550 | CQ168: 12471.25 | CR168: 1247.125 | CS168: 13718.375 | CT168: 0 | CU168: 341 | CV168: 14059.375
A169: 165 | B169: 32302 | C169: 46175 | D169: B59 | E169: Santiago, Cheska Topia | G169: Factory 2 | H169: Trainee | I169: 80 | J169: 10 | K169: 600 | L169: 6000 | M169: 3 | N169: 93.75 | O169: 281.25 | P169: 30 | Q169: 7.5 | R169: 225 | S169: 2 | T169: 9.375 | U169: 18.75 | W169: 93.75 | X169: 0 | Z169: 97.5 | AA169: 0 | AC169: 126.75 | AD169: 0 | AF169: 9.75 | AG169: 0 | AI169: 12.6675 | AJ169: 0 | AL169: 97.5 | AM169: 0 | AO169: 126.75 | AP169: 0 | AR169: 9.75 | AS169: 0 | AU169: 12.675 | AV169: 0 | AW169: 8 | AX169: 600 | AY169: 600 | BA169: 706 | BB169: 0 | BF169: 0 | BG169: 0 | BH169: 0 | BI169: 600 | BJ169: 0 | BL169: 93.75 | BM169: 0 | BO169: 7.5 | BP169: 0 | BR169: 9.375 | BS169: 0 | BU169: 97.5 | BV169: 0 | BW169: 0 | BX169: 31 | BY169: 0 | BZ169: 0 | CA169: 0 | CB169: 67.5 | CC169: 0 | CD169: 0 | CE169: 0 | CF169: 93.75 | CG169: 0 | CI169: 9.375 | CJ169: 0 | CK169: 7125 | CM169: 760 | CN169: 391.25 | CO169: 200 | CP169: 500 | CQ169: 8976.25 | CR169: 897.625 | CS169: 9873.875 | CT169: 0 | CU169: 310 | CV169: 10183.875
A170: 166 | B170: 13340 | C170: 45811 | D170: B47 | E170: Sobito, Jaymar Balagosa | G170: Factory 1 | H170: Wire Preparation | I170: 80 | J170: 10 | K170: 600 | L170: 6000 | M170: 21 | N170: 93.75 | O170: 1968.75 | P170: 25 | Q170: 7.5 | R170: 187.5 | S170: 10 | T170: 9.375 | U170: 93.75 | W170: 93.75 | X170: 0 | Z170: 97.5 | AA170: 0 | AC170: 126.75 | AD170: 0 | AF170: 9.75 | AG170: 0 | AI170: 12.6675 | AJ170: 0 | AL170: 97.5 | AM170: 0 | AO170: 126.75 | AP170: 0 | AR170: 9.75 | AS170: 0 | AU170: 12.675 | AV170: 0 | AW170: 8 | AX170: 600 | AY170: 600 | BA170: 707 | BB170: 0 | BF170: 35 | BG170: -43.75 | BH170: 0 | BI170: 600 | BJ170: 0 | BL170: 93.75 | BM170: 0 | BO170: 7.5 | BP170: 0 | BR170: 9.375 | BS170: 0 | BU170: 97.5 | BV170: 0 | BW170: 0 | BX170: 31 | BY170: 0 | BZ170: 0 | CA170: 0 | CB170: 67.5 | CC170: 0 | CD170: 0 | CE170: 0 | CF170: 93.75 | CG170: 0 | CI170: 9.375 | CJ170: 0 | CK170: 8806.25 | CM170: 1780 | CN170: 391.25 | CO170: 200 | CP170: 496.35417 | CQ170: 11673.854 | CR170: 1167.3854 | CS170: 12841.24 | CT170: 0 | CU170: 310 | CV170: 13151.24
A171: 167 | B171: 32305 | C171: 46175 | D171: B59 | E171: Soriano, Jonalyn Magmanlac | G171: Factory 2 | H171: Trainee | I171: 80 | J171: 10 | K171: 600 | L171: 6000 | M171: 0 | N171: 93.75 | O171: 0 | P171: 0 | Q171: 7.5 | R171: 0 | S171: 0 | T171: 9.375 | U171: 0 | W171: 93.75 | X171: 0 | Z171: 97.5 | AA171: 0 | AC171: 126.75 | AD171: 0 | AF171: 9.75 | AG171: 0 | AI171: 12.6675 | AJ171: 0 | AL171: 97.5 | AM171: 0 | AO171: 126.75 | AP171: 0 | AR171: 9.75 | AS171: 0 | AU171: 12.675 | AV171: 0 | AW171: 8 | AX171: 600 | AY171: 600 | BA171: 708 | BB171: 0 | BF171: 0 | BG171: 0 | BH171: 0 | BI171: 600 | BJ171: 0 | BL171: 93.75 | BM171: 0 | BO171: 7.5 | BP171: 0 | BR171: 9.375 | BS171: 0 | BU171: 97.5 | BV171: 0 | BW171: 0 | BX171: 31 | BY171: 0 | BZ171: 0 | CA171: 0 | CB171: 67.5 | CC171: 0 | CD171: 0 | CE171: 0 | CF171: 93.75 | CG171: 0 | CI171: 9.375 | CJ171: 0 | CK171: 6600 | CM171: 710 | CN171: 391.25 | CO171: 200 | CP171: 500 | CQ171: 8401.25 | CR171: 840.125 | CS171: 9241.375 | CT171: 0 | CU171: 310 | CV171: 9551.375
A172: 168 | B172: 12258 | C172: 45768 | D172: B41 | E172: Soriano, Laurence Carl Bicada | G172: Factory 1 | H172: Subaru Engine | I172: 88 | J172: 11 | K172: 600 | L172: 6600 | M172: 24 | N172: 93.75 | O172: 2250 | P172: 25 | Q172: 7.5 | R172: 187.5 | S172: 8 | T172: 9.375 | U172: 75 | W172: 93.75 | X172: 0 | Z172: 97.5 | AA172: 0 | AC172: 126.75 | AD172: 0 | AF172: 9.75 | AG172: 0 | AI172: 12.6675 | AJ172: 0 | AL172: 97.5 | AM172: 0 | AO172: 126.75 | AP172: 0 | AR172: 9.75 | AS172: 0 | AU172: 12.675 | AV172: 0 | AW172: 8 | AX172: 600 | AY172: 600 | BA172: 709 | BB172: 0 | BF172: 0 | BG172: 0 | BH172: 0 | BI172: 600 | BJ172: 0 | BL172: 93.75 | BM172: 0 | BO172: 7.5 | BP172: 0 | BR172: 9.375 | BS172: 0 | BU172: 97.5 | BV172: 0 | BW172: 0 | BX172: 31 | BY172: 0 | BZ172: 0 | CA172: 0 | CB172: 67.5 | CC172: 0 | CD172: 0 | CE172: 0 | CF172: 93.75 | CG172: 0 | CI172: 9.375 | CJ172: 0 | CK172: 9712.5 | CM172: 2030 | CN172: 391.25 | CO172: 200 | CP172: 550 | CQ172: 12883.75 | CR172: 1288.375 | CS172: 14172.125 | CT172: 0 | CU172: 341 | CV172: 14513.125
A173: 169 | B173: 32299 | C173: 46175 | D173: B59 | E173: Sotomango, Michael Nogales | G173: Factory 2 | H173: Trainee | I173: 80 | J173: 10 | K173: 600 | L173: 6000 | M173: 0 | N173: 93.75 | O173: 0 | P173: 0 | Q173: 7.5 | R173: 0 | S173: 0 | T173: 9.375 | U173: 0 | W173: 93.75 | X173: 0 | Z173: 97.5 | AA173: 0 | AC173: 126.75 | AD173: 0 | AF173: 9.75 | AG173: 0 | AI173: 12.6675 | AJ173: 0 | AL173: 97.5 | AM173: 0 | AO173: 126.75 | AP173: 0 | AR173: 9.75 | AS173: 0 | AU173: 12.675 | AV173: 0 | AW173: 8 | AX173: 600 | AY173: 600 | BA173: 710 | BB173: 0 | BF173: 0 | BG173: 0 | BH173: 0 | BI173: 600 | BJ173: 0 | BL173: 93.75 | BM173: 0 | BO173: 7.5 | BP173: 0 | BR173: 9.375 | BS173: 0 | BU173: 97.5 | BV173: 0 | BW173: 0 | BX173: 31 | BY173: 0 | BZ173: 0 | CA173: 0 | CB173: 67.5 | CC173: 0 | CD173: 0 | CE173: 0 | CF173: 93.75 | CG173: 0 | CI173: 9.375 | CJ173: 0 | CK173: 6600 | CM173: 710 | CN173: 391.25 | CO173: 200 | CP173: 500 | CQ173: 8401.25 | CR173: 840.125 | CS173: 9241.375 | CT173: 0 | CU173: 310 | CV173: 9551.375
A174: 170 | B174: 13697 | C174: 45670 | D174: B31 | E174: Targa, JohnCel Malaguit | G174: Factory 1 | H174: Material Handler | I174: 24 | J174: 3 | K174: 600 | L174: 1800 | M174: 0 | N174: 93.75 | O174: 0 | P174: 15 | Q174: 7.5 | R174: 112.5 | S174: 0 | T174: 9.375 | U174: 0 | W174: 93.75 | X174: 0 | Z174: 97.5 | AA174: 0 | AC174: 126.75 | AD174: 0 | AF174: 9.75 | AG174: 0 | AI174: 12.6675 | AJ174: 0 | AL174: 97.5 | AM174: 0 | AO174: 126.75 | AP174: 0 | AR174: 9.75 | AS174: 0 | AU174: 12.675 | AV174: 0 | AW174: 0 | AX174: 600 | AY174: 0 | BA174: 711 | BB174: 0 | BF174: 0 | BG174: 0 | BH174: 0 | BI174: 600 | BJ174: 0 | BL174: 93.75 | BM174: 0 | BO174: 7.5 | BP174: 0 | BR174: 9.375 | BS174: 0 | BU174: 97.5 | BV174: 0 | BW174: 0 | BX174: 31 | BY174: 0 | BZ174: 0 | CA174: 0 | CB174: 67.5 | CC174: 0 | CD174: 0 | CE174: 0 | CF174: 93.75 | CG174: 0 | CI174: 9.375 | CJ174: 0 | CK174: 1912.5 | CM174: 1010 | CN174: 391.25 | CO174: 200 | CP174: 150 | CQ174: 3663.75 | CR174: 366.375 | CS174: 4030.125 | CT174: 0 | CU174: 93 | CV174: 4123.125
A175: 171 | B175: 12734 | C175: 45734 | D175: B38 | E175: Targa, Samantha Louise Geaga | G175: Factory 3 | H175: Yamaha | I175: 64 | J175: 8 | K175: 600 | L175: 4800 | M175: 15 | N175: 93.75 | O175: 1406.25 | P175: 25 | Q175: 7.5 | R175: 187.5 | S175: 8 | T175: 9.375 | U175: 75 | W175: 93.75 | X175: 0 | Z175: 97.5 | AA175: 0 | AC175: 126.75 | AD175: 0 | AF175: 9.75 | AG175: 0 | AI175: 12.6675 | AJ175: 0 | AL175: 97.5 | AM175: 0 | AO175: 126.75 | AP175: 0 | AR175: 9.75 | AS175: 0 | AU175: 12.675 | AV175: 0 | AW175: 8 | AX175: 600 | AY175: 600 | BA175: 712 | BB175: 0 | BF175: 0 | BG175: 0 | BH175: 0 | BI175: 600 | BJ175: 0 | BL175: 93.75 | BM175: 0 | BO175: 7.5 | BP175: 0 | BR175: 9.375 | BS175: 0 | BU175: 97.5 | BV175: 0 | BW175: 0 | BX175: 31 | BY175: 0 | BZ175: 0 | CA175: 0 | CB175: 67.5 | CC175: 0 | CD175: 0 | CE175: 0 | CF175: 93.75 | CG175: 0 | CI175: 9.375 | CJ175: 0 | CK175: 7068.75 | CM175: 1730 | CN175: 391.25 | CO175: 200 | CP175: 400 | CQ175: 9790 | CR175: 979 | CS175: 10769 | CT175: 0 | CU175: 248 | CV175: 11017
A176: 172 | B176: 13345 | C176: 45811 | D176: B47 | E176: Tortosa, Jonathan Macalalad | G176: Factory 3 | H176: Wire Preparation - Yamaha | I176: 88 | J176: 11 | K176: 600 | L176: 6600 | M176: 21 | N176: 93.75 | O176: 1968.75 | P176: 25 | Q176: 7.5 | R176: 187.5 | S176: 8 | T176: 9.375 | U176: 75 | W176: 93.75 | X176: 0 | Z176: 97.5 | AA176: 0 | AC176: 126.75 | AD176: 0 | AF176: 9.75 | AG176: 0 | AI176: 12.6675 | AJ176: 0 | AL176: 97.5 | AM176: 0 | AO176: 126.75 | AP176: 0 | AR176: 9.75 | AS176: 0 | AU176: 12.675 | AV176: 0 | AW176: 8 | AX176: 600 | AY176: 600 | BA176: 713 | BB176: 0 | BF176: 5 | BG176: -6.25 | BH176: 0 | BI176: 600 | BJ176: 0 | BL176: 93.75 | BM176: 0 | BO176: 7.5 | BP176: 0 | BR176: 9.375 | BS176: 0 | BU176: 97.5 | BV176: 0 | BW176: 0 | BX176: 31 | BY176: 0 | BZ176: 0 | CA176: 0 | CB176: 67.5 | CC176: 0 | CD176: 0 | CE176: 0 | CF176: 93.75 | CG176: 0 | CI176: 9.375 | CJ176: 0 | CK176: 9425 | CM176: 2030 | CN176: 391.25 | CO176: 200 | CP176: 549.47917 | CQ176: 12595.729 | CR176: 1259.5729 | CS176: 13855.302 | CT176: 0 | CU176: 341 | CV176: 14196.302
A177: 173 | B177: 32546 | C177: 46154 | D177: B57 | E177: Torzar, John Paul Bayal | G177: Factory 1 | H177: Material Handler | I177: 88 | J177: 11 | K177: 600 | L177: 6600 | M177: 27 | N177: 93.75 | O177: 2531.25 | P177: 30 | Q177: 7.5 | R177: 225 | S177: 8 | T177: 9.375 | U177: 75 | W177: 93.75 | X177: 0 | Z177: 97.5 | AA177: 0 | AC177: 126.75 | AD177: 0 | AF177: 9.75 | AG177: 0 | AI177: 12.6675 | AJ177: 0 | AL177: 97.5 | AM177: 0 | AO177: 126.75 | AP177: 0 | AR177: 9.75 | AS177: 0 | AU177: 12.675 | AV177: 0 | AW177: 8 | AX177: 600 | AY177: 600 | BA177: 714 | BB177: 0 | BF177: 0 | BG177: 0 | BH177: 0 | BI177: 600 | BJ177: 0 | BL177: 93.75 | BM177: 0 | BO177: 7.5 | BP177: 0 | BR177: 9.375 | BS177: 0 | BU177: 97.5 | BV177: 0 | BW177: 0 | BX177: 31 | BY177: 0 | BZ177: 0 | CA177: 0 | CB177: 67.5 | CC177: 0 | CD177: 0 | CE177: 0 | CF177: 93.75 | CG177: 0 | CI177: 9.375 | CJ177: 0 | CK177: 10031.25 | CM177: 2080 | CN177: 391.25 | CO177: 200 | CP177: 550 | CQ177: 13252.5 | CR177: 1325.25 | CS177: 14577.75 | CT177: 0 | CU177: 341 | CV177: 14918.75
A178: 174 | B178: 32222 | C178: 46161 | D178: B58 | E178: Trinidad, Ethelbert Calabio | G178: Factory 2 | H178: Subaru Engine/TM | I178: 80 | J178: 10 | K178: 600 | L178: 6000 | M178: 0 | N178: 93.75 | O178: 0 | P178: 50 | Q178: 7.5 | R178: 375 | S178: 0 | T178: 9.375 | U178: 0 | W178: 93.75 | X178: 0 | Z178: 97.5 | AA178: 0 | AC178: 126.75 | AD178: 0 | AF178: 9.75 | AG178: 0 | AI178: 12.6675 | AJ178: 0 | AL178: 97.5 | AM178: 0 | AO178: 126.75 | AP178: 0 | AR178: 9.75 | AS178: 0 | AU178: 12.675 | AV178: 0 | AW178: 0 | AX178: 600 | AY178: 0 | BA178: 715 | BB178: 0 | BF178: 0 | BG178: 0 | BH178: 0 | BI178: 600 | BJ178: 0 | BL178: 93.75 | BM178: 0 | BO178: 7.5 | BP178: 0 | BR178: 9.375 | BS178: 0 | BU178: 97.5 | BV178: 0 | BW178: 0 | BX178: 31 | BY178: 0 | BZ178: 0 | CA178: 0 | CB178: 67.5 | CC178: 0 | CD178: 0 | CE178: 0 | CF178: 93.75 | CG178: 0 | CI178: 9.375 | CJ178: 0 | CK178: 6375 | CM178: 1260 | CN178: 391.25 | CO178: 200 | CP178: 500 | CQ178: 8726.25 | CR178: 872.625 | CS178: 9598.875 | CT178: 0 | CU178: 310 | CV178: 9908.875
... A190: 186 | B190: 31089 | C190: 45993 | D190: B53 | E190: Zepeda, Mairose Cardaño | G190: Factory 1 | H190: Wire Preparation | I190: 88 | J190: 11 | K190: 600 | L190: 6600 | M190: 12 | N190: 93.75 | O190: 1125 | P190: 25 | Q190: 7.5 | R190: 187.5 | S190: 6 | T190: 9.375 | U190: 56.25 | W190: 93.75 | X190: 0 | Z190: 97.5 | AA190: 0 | AC190: 126.75 | AD190: 0 | AF190: 9.75 | AG190: 0 | AI190: 12.6675 | AJ190: 0 | AL190: 97.5 | AM190: 0 | AO190: 126.75 | AP190: 0 | AR190: 9.75 | AS190: 0 | AU190: 12.675 | AV190: 0 | AW190: 8 | AX190: 600 | AY190: 600 | BA190: 727 | BB190: 0 | BF190: 0 | BG190: 0 | BH190: 0 | BI190: 600 | BJ190: 0 | BL190: 93.75 | BM190: 0 | BO190: 7.5 | BP190: 0 | BR190: 9.375 | BS190: 0 | BU190: 97.5 | BV190: 0 | BW190: 0 | BX190: 31 | BY190: 0 | BZ190: 0 | CA190: 0 | CB190: 67.5 | CC190: 0 | CD190: 0 | CE190: 0 | CF190: 93.75 | CG190: 0 | CI190: 9.375 | CJ190: 0 | CK190: 8568.75 | CM190: 2030 | CN190: 391.25 | CO190: 200 | CP190: 550 | CQ190: 11740 | CR190: 1174 | CS190: 12914 | CT190: 0 | CU190: 341 | CV190: 13255
A192: 186 | B192: GRAND TOTAL | I192: 14256 | J192: 1782 | K192: 111635 | L192: 1069480 | M192: 2142.53 | N192: 17448.438 | O192: 200878.59 | P192: 3696.78 | Q192: 1395.4375 | R192: 27725.85 | S192: 704 | T192: 1744.8438 | U192: 6600 | V192: 0 | W192: 17448.438 | X192: 0 | Y192: 0 | Z192: 18146.375 | AA192: 0 | AB192: 0 | AC192: 23590.287 | AD192: 0 | AE192: 0 | AF192: 1814.6375 | AG192: 0 | AH192: 0 | AI192: 2357.6329 | AJ192: 0 | AK192: 0 | AL192: 18146.375 | AM192: 0 | AN192: 0 | AO192: 23590.287 | AP192: 0 | AQ192: 0 | AR192: 1814.6375 | AS192: 0 | AT192: 0 | AU192: 2359.0287 | AV192: 0 | AW192: 1280 | AX192: 111635 | AY192: 96035 | AZ192: 0 | BA192: 117924 | BB192: 0 | BC192: 0 | BD192: 0 | BE192: 0 | BF192: 1169 | BG192: -1461.25 | BH192: 0 | BI192: 85800 | BJ192: 0 | BK192: 0 | BL192: 13406.25 | BM192: 0 | BN192: 0 | BO192: 1072.5 | BP192: 0 | BQ192: 0 | BR192: 1340.625 | BS192: 0 | BT192: 0 | BU192: 13953.875 | BV192: 0 | BW192: 0 | BX192: 4433 | BY192: 0 | BZ192: 0 | CA192: 0 | CB192: 9652.5 | CC192: 0 | CD192: 0 | CE192: 0 | CF192: 13417.188 | CG192: 0 | CH192: 0 | CI192: 1341.7188 | CJ192: 0 | CK192: 1399608.2 | CL192: 0 | CM192: 276710 | CN192: 69274.07 | CO192: 35400 | CP192: 89001.563 | CQ192: 1869643.8 | CR192: 186964.38 | CS192: 2056608.2 | CT192: 61.03125 | CU192: 55180.969 | CV192: 2111789.2

Sheet SSS_2025
A1: RANGE OF COMPENSATION | C1: MONTHLY SALARY CREDIT | F1: AMOUNT OF CONTRIBUTION
C2: REGULAR SSS | D2: WISP/MPF | E2: TOTAL | F2: EMPLOYER | K2: EMPLOYEE | N2: TOTAL CONTRIBUTION
F3: REGULAR SS | G3: WISP/MPF | H3: TOTAL 1 | I3: EC | J3: TOTAL 2 | K3: REGULAR SS | L3: WISP | M3: TOTAL
A4: 1 | B4: 2 | C4: 3 | D4: 4 | E4: 5 | F4: 6 | G4: 7 | H4: 8 | I4: 9 | J4: 10 | K4: 11 | L4: 12 | M4: 13 | N4: 14
A5: 0 | B5: 0 | C5: 0 | D5: 0 | E5: 0 | F5: 0 | G5: 0 | H5: 0 | I5: 0 | J5: 0 | K5: 0 | L5: 0 | M5: 0 | N5: 0
A6: 1 | B6: 5250 | C6: 5000 | D6: 0 | E6: 5000 | F6: 500 | G6: 0 | H6: =SUM(F6:G6) -> 500 | I6: 10 | J6: =SUM(H6:I6) -> 510 | K6: 250 | L6: 0 | M6: =SUM(K6:L6) -> 250 | N6: =J6+M6 -> 760
A7: 5250 | B7: 5749.99 | C7: 5500 | D7: 0 | E7: 5500 | F7: 550 | G7: 0 | H7: =SUM(F7:G7) -> 550 | I7: 10 | J7: =SUM(H7:I7) -> 560 | K7: 275 | L7: 0 | M7: =SUM(K7:L7) -> 275 | N7: =J7+M7 -> 835
A8: 5750 | B8: 6249.99 | C8: 6000 | D8: 0 | E8: 6000 | F8: 600 | G8: 0 | H8: =SUM(F8:G8) -> 600 | I8: 10 | J8: =SUM(H8:I8) -> 610 | K8: 300 | L8: 0 | M8: =SUM(K8:L8) -> 300 | N8: =J8+M8 -> 910
A9: 6250 | B9: 6749.99 | C9: 6500 | D9: 0 | E9: 6500 | F9: 650 | G9: 0 | H9: =SUM(F9:G9) -> 650 | I9: 10 | J9: =SUM(H9:I9) -> 660 | K9: 325 | L9: 0 | M9: =SUM(K9:L9) -> 325 | N9: =J9+M9 -> 985
A10: 6750 | B10: 7249.99 | C10: 7000 | D10: 0 | E10: 7000 | F10: 700 | G10: 0 | H10: =SUM(F10:G10) -> 700 | I10: 10 | J10: =SUM(H10:I10) -> 710 | K10: 350 | L10: 0 | M10: =SUM(K10:L10) -> 350 | N10: =J10+M10 -> 1060
A11: 7250 | B11: 7749.99 | C11: 7500 | D11: 0 | E11: 7500 | F11: 750 | G11: 0 | H11: =SUM(F11:G11) -> 750 | I11: 10 | J11: =SUM(H11:I11) -> 760 | K11: 375 | L11: 0 | M11: =SUM(K11:L11) -> 375 | N11: =J11+M11 -> 1135
A12: 7750 | B12: 8249.99 | C12: 8000 | D12: 0 | E12: 8000 | F12: 800 | G12: 0 | H12: =SUM(F12:G12) -> 800 | I12: 10 | J12: =SUM(H12:I12) -> 810 | K12: 400 | L12: 0 | M12: =SUM(K12:L12) -> 400 | N12: =J12+M12 -> 1210
A13: 8250 | B13: 8749.99 | C13: 8500 | D13: 0 | E13: 8500 | F13: 850 | G13: 0 | H13: =SUM(F13:G13) -> 850 | I13: 10 | J13: =SUM(H13:I13) -> 860 | K13: 425 | L13: 0 | M13: =SUM(K13:L13) -> 425 | N13: =J13+M13 -> 1285
A14: 8750 | B14: 9249.99 | C14: 9000 | D14: 0 | E14: 9000 | F14: 900 | G14: 0 | H14: =SUM(F14:G14) -> 900 | I14: 10 | J14: =SUM(H14:I14) -> 910 | K14: 450 | L14: 0 | M14: =SUM(K14:L14) -> 450 | N14: =J14+M14 -> 1360
A15: 9250 | B15: 9749.99 | C15: 9500 | D15: 0 | E15: 9500 | F15: 950 | G15: 0 | H15: =SUM(F15:G15) -> 950 | I15: 10 | J15: =SUM(H15:I15) -> 960 | K15: 475 | L15: 0 | M15: =SUM(K15:L15) -> 475 | N15: =J15+M15 -> 1435
A16: 9750 | B16: 10249.99 | C16: 10000 | D16: 0 | E16: 10000 | F16: 1000 | G16: 0 | H16: =SUM(F16:G16) -> 1000 | I16: 10 | J16: =SUM(H16:I16) -> 1010 | K16: 500 | L16: 0 | M16: =SUM(K16:L16) -> 500 | N16: =J16+M16 -> 1510
A17: 10250 | B17: 10749.99 | C17: 10500 | D17: 0 | E17: 10500 | F17: 1050 | G17: 0 | H17: =SUM(F17:G17) -> 1050 | I17: 10 | J17: =SUM(H17:I17) -> 1060 | K17: 525 | L17: 0 | M17: =SUM(K17:L17) -> 525 | N17: =J17+M17 -> 1585
... A65: 34250 | B65: 34749.99 | C65: 20000 | D65: 14500 | E65: 34500 | F65: 2000 | G65: 1450 | H65: =SUM(F65:G65) -> 3450 | I65: 30 | J65: =SUM(H65:I65) -> 3480 | K65: 1000 | L65: 725 | M65: =SUM(K65:L65) -> 1725 | N65: =J65+M65 -> 5205
A66: 34750 | C66: 20000 | D66: 15000 | E66: 35000 | F66: 2000 | G66: 1500 | H66: =SUM(F66:G66) -> 3500 | I66: 30 | J66: =SUM(H66:I66) -> 3530 | K66: 1000 | L66: 750 | M66: =SUM(K66:L66) -> 1750 | N66: =J66+M66 -> 5280

Sheet SUMMARY
A1: NO. | B1: DATE HIRED | C1: BATCH | D1: EMPLOYEE ID | E1: NAME | F1: LOCATION | G1: SCHEDULE | H1: SECTION | I1: DATE | J1: IN | K1: OUT | L1: REMARKS | M1: SHIFT | N1: REGULAR HOURS | O1: OT | P1: OTND | Q1: ND | R1: LATE | S1: UNDERTIME | T1: LATE/UT | U1: SAT WORK | V1: SAT WORK ND | W1: RD REG | X1: RD OT | Y1: RD NDOT | Z1: RD ND | AA1: UNWORKED LH | AB1: SH REG | AC1: SH OT | AD1: SH NDOT | AE1: SH ND
A2: 1 | B2: 45244 | C2: B3 | D2: 5683 | E2: Abcede, Jomar Pavino | F2: Factory 2 | G2: Shift 1 | H2: QC Inspection | I2: 46174 | J2: 0.25313657 | K2: 0.79354167 | M2: DS | N2: 8 | O2: 3 | T2: =SUM(R2:S2) -> 0
A3: 2 | B3: 45951 | C3: B50 | D3: 31024 | E3: Abrio, Althea Mae Divila | F3: Factory 1 | G3: Shift 2 | H3: Subaru Engine | I3: 46174 | J3: 0.75875 | K3: 0.29373843 | M3: NS | N3: 8 | O3: 3 | P3: 2 | Q3: 5 | T3: =SUM(R3:S3) -> 0
A4: 3 | B4: 45811 | C4: B47 | D4: 13373 | E4: Acasamoso, Jerico Ladia | F4: Factory 3 | G4: Shift 2 | H4: QC Inspection | I4: 46174 | J4: 0.7643287 | K4: 0.29236111 | L4: NO TIME OUT | M4: NS | N4: 8 | O4: 3 | P4: 2 | Q4: 5 | T4: =SUM(R4:S4) -> 0
A5: 4 | B5: 45524 | C5: B23 | D5: 7167 | E5: Aguirre, Christopher Isla | F5: Factory 1 | G5: Shift 2 | H5: Subaru Engine | I5: 46174 | J5: 0.7694213 | K5: 0.29445602 | M5: NS | N5: 8 | O5: 3 | P5: 2 | Q5: 5 | T5: =SUM(R5:S5) -> 0
A6: 5 | B6: 46161 | C6: B58 | D6: 32202 | E6: Alcantara, Felix Salvador Andoque | F6: Factory 2 | G6: ADS | H6: Trainee | I6: 46174 | J6: 0.26751157 | K6: 0.66711806 | M6: ADS | N6: 8 | T6: =SUM(R6:S6) -> 0
A7: 6 | B7: 45734 | C7: B38 | D7: 11936 | E7: Alongalay, Ruiz Trillanes | F7: Factory 1 | G7: Shift 1 | H7: Parts Preparation | I7: 46174 | J7: 0.24447917 | K7: 0.66824074 | M7: DS | N7: 8 | T7: =SUM(R7:S7) -> 0
A8: 7 | B8: 45944 | C8: B49 | D8: 31006 | E8: An, Rey Alcos | F8: Factory 1 | G8: Shift 2 | H8: Material Handler | I8: 46174 | J8: 0.77131944 | K8: 0.29315972 | M8: NS | N8: 8 | O8: 3 | P8: 2 | Q8: 5 | T8: =SUM(R8:S8) -> 0
A9: 8 | B9: 45531 | C9: B24 | D9: 7080 | E9: Antaran, Alrey jay Barber | F9: Factory 3 | G9: Shift 2 | H9: Warehouse | I9: 46174 | J9: 0.7690625 | K9: 0.29287037 | M9: NS | N9: 8 | O9: 3 | P9: 2 | Q9: 5 | T9: =SUM(R9:S9) -> 0
A10: 9 | B10: 45993 | C10: B53 | D10: 31088 | E10: Armada, Simon Estacio | F10: Factory 1 | G10: Shift 2 | H10: QC Inspection | I10: 46174 | J10: 0.75329861 | K10: 0.2987963 | M10: NS | N10: 8 | O10: 3 | P10: 2 | Q10: 5 | T10: =SUM(R10:S10) -> 0
A11: 10 | B11: 45755 | C11: B40 | D11: 11601 | E11: Asuncion, Rhenzo N/A | F11: Factory 2 | G11: ADS | H11: Warehouse | I11: 46174 | J11: 0.26724537 | K11: 0.66912037 | M11: ADS | N11: 8 | T11: =SUM(R11:S11) -> 0
A12: 11 | B12: 45531 | C12: B24 | D12: 7115 | E12: Aveñon, Reymart Magnaye | F12: Factory 1 | G12: Shift 2 | H12: Transmission | I12: 46174 | J12: 0.77155093 | K12: 0.96527778 | L12: UNDERTIME | M12: NS | N12: 8 | Q12: 0.42 | S12: 275 | T12: =SUM(R12:S12) -> 275
A13: 12 | B13: 46084 | C13: B56 | D13: 32818 | E13: Azarga, Glebel Nañola | F13: Factory 1 | G13: Shift 2 | H13: Wire Preparation | I13: 46174 | L13: ABSENT | M13: NS | T13: 0
A14: 13 | B14: 45734 | C14: B38 | D14: 11939 | E14: Baay, Edrian Samar | F14: Factory 1 | G14: Shift 1 | H14: QC Inspection | I14: 46174 | L14: ABSENT | M14: DS | T14: =SUM(R14:S14) -> 0
A15: 14 | B15: 45951 | C15: B50 | D15: 31047 | E15: Bacay, Princess Jane Garcia | F15: Factory 1 | G15: Shift 1 | H15: Subaru Insertion | I15: 46174 | J15: 0.26722222 | K15: 0.79333333 | M15: DS | N15: 8 | O15: 3 | T15: =SUM(R15:S15) -> 0
A16: 15 | B16: 46161 | C16: B58 | D16: 32205 | E16: Bada, Genm Bryant Carino | F16: Factory 2 | G16: Shift 2 | H16: Subaru Engine/TM | I16: 46174 | J16: 0.75599537 | K16: 0.17145833 | M16: NS | N16: 8 | Q16: 5 | T16: =SUM(R16:S16) -> 0
A17: 16 | B17: 46161 | C17: B58 | D17: 32203 | E17: Bagsic, Protacio Jr. Conception | F17: Factory 2 | G17: Shift 2 | H17: Trainee | I17: 46174 | J17: 0.75010417 | K17: 0.29375 | M17: NS | N17: 8 | O17: 3 | P17: 2 | Q17: 5 | T17: =SUM(R17:S17) -> 0
A18: 17 | B18: 45468 | C18: B15 | D18: 7738 | E18: Balmes, Sheila May Godoy | F18: Factory 1 | G18: Shift 2 | H18: Wire Preparation | I18: 46174 | J18: 0.76915509 | K18: 0.16975694 | M18: NS | N18: 8 | Q18: 5 | T18: =SUM(R18:S18) -> 0
A19: 18 | B19: 45629 | C19: B28 | D19: 10894 | E19: Balobaldo, Jhon Lister Ponpon | F19: Factory 1 | G19: Shift 1 | H19: Wire Preparation | I19: 46174 | J19: 0.2869213 | K19: 0.79435185 | M19: DS | N19: 8 | O19: 3 | T19: =SUM(R19:S19) -> 0
A20: 19 | B20: 45719 | C20: B36 | D20: 12092 | E20: Banaira, Jason Aldovino | F20: Factory 3 | G20: Shift 2 | H20: QA | I20: 46174 | J20: 0.76107639 | K20: 0.29248843 | M20: NS | N20: 8 | O20: 3 | P20: 2 | Q20: 5 | T20: =SUM(R20:S20) -> 0
A21: 20 | B21: 45468 | C21: B15 | D21: 7731 | E21: Baril, Edelyn Digo | F21: Factory 1 | G21: Shift 2 | H21: Wire Preparation | I21: 46174 | J21: 0.76605324 | K21: 0.29438657 | M21: NS | N21: 8 | O21: 3 | P21: 2 | Q21: 5 | T21: =SUM(R21:S21) -> 0
A22: 21 | B22: 45719 | C22: B36 | D22: 12019 | E22: Basila, Mayrelyn Flores | F22: Factory 3 | G22: ADS | H22: Yamaha | I22: 46174 | J22: 0.2624537 | K22: 0.79184028 | M22: ADS | N22: 8 | O22: 3 | T22: =SUM(R22:S22) -> 0
A23: 22 | B23: 46161 | C23: B58 | D23: 32223 | E23: Bathan, Gellie Biscocho | F23: Factory 2 | G23: ADS | H23: Trainee | I23: 46174 | J23: 0.25902778 | K23: 0.67127315 | M23: ADS | N23: 8 | T23: =SUM(R23:S23) -> 0
A24: 23 | B24: 45797 | C24: B45 | D24: 14750 | E24: Bea, Dominic Penano | F24: Factory 3 | G24: Shift 1 | H24: Wire Preparation - Yamaha | I24: 46174 | J24: 0.26570602 | K24: 0.79361111 | M24: DS | N24: 8 | O24: 3 | T24: =SUM(R24:S24) -> 0
A25: 24 | B25: 45622 | C25: B27 | D25: 10941 | E25: Begonia, Christopher Bolo | F25: Factory 3 | G25: Shift 2 | H25: Yamaha | I25: 46174 | J25: 0.7608912 | K25: 0.29315972 | M25: NS | N25: 8 | O25: 3 | P25: 2 | Q25: 5 | T25: =SUM(R25:S25) -> 0
A26: 25 | B26: 45993 | C26: B53 | D26: 31086 | E26: Belardo, Mariel Volante | F26: Factory 1 | G26: Shift 2 | H26: Wire Preparation | I26: 46174 | J26: 0.77030093 | K26: 0.16899306 | M26: NS | N26: 8 | Q26: 5 | T26: =SUM(R26:S26) -> 0
A27: 26 | B27: 46084 | C27: B56 | D27: 32817 | E27: Belir, Mark Shane N/A | F27: Factory 1 | G27: Shift 1 | H27: Subaru Engine | I27: 46174 | J27: 0.27199074 | K27: 0.67074074 | M27: DS | N27: 8 | T27: 0
A28: 27 | B28: 45818 | C28: B48 | D28: 14851 | E28: Beltrano, Celjay N/A | F28: Factory 3 | G28: Shift 2 | H28: Wire Preparation | I28: 46174 | L28: ABSENT | M28: NS | T28: =SUM(R28:S28) -> 0
A29: 28 | B29: 45670 | C29: B30 | D29: 12577 | E29: Bocado, Richard Cocayco | F29: Factory 2 | G29: Shift 1 | H29: Warehouse | I29: 46174 | J29: 0.25935185 | K29: 0.6684838 | M29: DS | N29: 8 | T29: =SUM(R29:S29) -> 0
A30: 29 | B30: 45811 | C30: B47 | D30: 13366 | E30: Bonaobra, Andro Pineda | F30: Factory 1 | G30: Shift 2 | H30: QA Packing | I30: 46174 | J30: 0.7722338 | K30: 0.29549769 | M30: NS | N30: 8 | O30: 3 | P30: 2 | Q30: 5 | T30: =SUM(R30:S30) -> 0
A31: 30 | B31: 45670 | C31: B31 | D31: 13678 | E31: Botin, Jhon Carlo Medallion | F31: Factory 1 | G31: Shift 1 | H31: Wire Preparation | I31: 46174 | J31: 0.26771991 | K31: 0.79451389 | M31: DS | N31: 8 | O31: 3 | T31: =SUM(R31:S31) -> 0
A32: 31 | B32: 45719 | C32: B36 | D32: 12083 | E32: Brozo, Jonel Bautista | F32: Factory 3 | G32: Shift 1 | H32: QA | I32: 46174 | L32: ABSENT | M32: DS | T32: =SUM(R32:S32) -> 0
A33: 32 | B33: 46154 | C33: B57 | D33: 32571 | E33: Brucelo Joshua Alano | F33: Factory 1 | G33: Shift 1 | H33: Material Handler | I33: 46174 | L33: ABSENT | M33: DS | T33: =SUM(R33:S33) -> 0
A34: 33 | B34: 45944 | C34: B49 | D34: 31010 | E34: Burac, Ma. Kaycha Antonio | F34: Factory 1 | G34: Shift 1 | H34: Transmission | I34: 46174 | J34: 0.25394676 | K34: 0.79690972 | M34: DS | N34: 8 | O34: 3 | T34: =SUM(R34:S34) -> 0
A35: 34 | B35: 45685 | C35: B33 | D35: 12634 | E35: Burgos, Yonathan Robles | F35: Factory 1 | G35: Shift 1 | H35: Wire Preparation-Yamaha | I35: 46174 | J35: 0.26125 | K35: 0.79619213 | M35: DS | N35: 8 | O35: 3 | T35: =SUM(R35:S35) -> 0
A36: 35 | B36: 45818 | C36: B48 | D36: 14841 | E36: Caburobias, Aerole John Asparin | F36: Factory 3 | G36: ADS | H36: Warehouse | I36: 46174 | J36: 0.25869213 | K36: 0.79269676 | M36: ADS | N36: 8 | O36: 3 | T36: =SUM(R36:S36) -> 0
A37: 36 | B37: 46084 | C37: B56 | D37: 32803 | E37: Calalo, Hyacinth Ruba | F37: Factory 1 | G37: Shift 1 | H37: QC Inspection | I37: 46174 | J37: 0.26111111 | K37: 0.79778935 | M37: DS | N37: 8 | O37: 3 | T37: 0
A38: 37 | B38: 46084 | C38: B56 | D38: 32822 | E38: Cañelas, Michelle Ann Ramos | F38: Factory 3 | G38: Shift 2 | H38: Wire Preparation - Yamaha | I38: 46174 | J38: 0.7581713 | K38: 0.29282407 | M38: NS | N38: 8 | O38: 3 | P38: 2 | Q38: 5 | T38: 0
A39: 38 | B39: 46084 | C39: B56 | D39: 32814 | E39: Canson, Gerald Corral | F39: Factory 1 | G39: Shift 1 | H39: Subaru Engine | I39: 46174 | J39: 0.26716435 | K39: 0.67048611 | M39: DS | N39: 8 | T39: 0
A40: 39 | B40: 45440 | C40: B11 | D40: 6362 | E40: Clores, Lea Amaro | F40: Factory 1 | G40: Shift 1 | H40: QA Inspection | I40: 46174 | L40: ABSENT | M40: DS | T40: =SUM(R40:S40) -> 0
A41: 40 | B41: 46154 | C41: B57 | D41: 32561 | E41: Codilla, Edrick Vonn Medina | F41: Factory 1 | G41: Shift 2 | H41: Wire Preparation | I41: 46174 | L41: ABSENT | M41: NS | T41: =SUM(R41:S41) -> 0
A42: 41 | B42: 46084 | C42: B56 | D42: 32824 | E42: Coquiat, Samuel Jhames Brigondo | F42: Factory 1 | G42: Shift 1 | H42: Wire Preparation | I42: 46174 | L42: ABSENT | M42: DS | T42: 0
A43: 42 | B43: 46161 | C43: B58 | D43: 32221 | E43: Corong, Edwardo | F43: Factory 2 | G43: Shift 2 | H43: Trainee | I43: 46174 | J43: 0.76699074 | K43: 0.16835648 | M43: NS | N43: 8 | Q43: 5 | T43: =SUM(R43:S43) -> 0
A44: 43 | B44: 46161 | C44: B58 | D44: 32212 | E44: Correa, Ervin Ramos | F44: Factory 2 | G44: Shift 2 | H44: Subaru Engine/TM | I44: 46174 | J44: 0.75949074 | K44: 0.17100694 | M44: NS | N44: 8 | Q44: 5 | T44: =SUM(R44:S44) -> 0
A45: 44 | B45: 45818 | C45: B48 | D45: 14874 | E45: Cupo, Adrian Dela Masa | F45: Factory 2 | G45: Shift 2 | H45: Wire Preparation | I45: 46174 | L45: ABSENT | M45: NS | T45: =SUM(R45:S45) -> 0
A46: 45 | B46: 45462 | C46: B14 | D46: 7697 | E46: Custodio, Jessa May Rubia | F46: Factory 2 | G46: ADS | H46: Planning | I46: 46174 | L46: ABSENT | M46: ADS | T46: =SUM(R46:S46) -> 0
A47: 46 | B47: 45734 | C47: B38 | D47: 11938 | E47: Dadap, Kim cedrick Piol | F47: Factory 1 | G47: Shift 1 | H47: QA | I47: 46174 | J47: 0.26135417 | K47: 0.79309028 | M47: DS | N47: 8 | O47: 3 | T47: =SUM(R47:S47) -> 0
A48: 47 | B48: 45804 | C48: B46 | D48: 14606 | E48: Dan-Uya, Jayson Malijan | F48: Factory 1 | G48: Shift 2 | H48: Wire Preparation | I48: 46174 | J48: 0.75538194 | K48: 0.29385417 | M48: NS | N48: 8 | O48: 3 | P48: 2 | Q48: 5 | T48: =SUM(R48:S48) -> 0
A49: 48 | B49: 45818 | C49: B48 | D49: 14865 | E49: De Castro, Ma. Judith Depalco | F49: Factory 3 | G49: Shift 2 | H49: Wire Preparation | I49: 46174 | L49: ABSENT | M49: NS | T49: =SUM(R49:S49) -> 0
A50: 49 | B50: 45692 | C50: B34 | D50: 11160 | E50: De Los Reyes, John Robert Creus | F50: Factory 1 | G50: Shift 2 | H50: QC Inspection | I50: 46174 | J50: 0.74652778 | K50: 0.29395833 | M50: NS | N50: 8 | O50: 3 | P50: 2 | Q50: 5 | T50: =SUM(R50:S50) -> 0
A51: 50 | B51: 45768 | C51: B41 | D51: 12262 | E51: De Mesa, Patrick Estipona | F51: Factory 3 | G51: Shift 2 | H51: Yamaha | I51: 46174 | J51: 0.76042824 | K51: 0.29270833 | M51: NS | N51: 8 | O51: 3 | P51: 2 | Q51: 5 | T51: =SUM(R51:S51) -> 0
A52: 51 | B52: 46161 | C52: B58 | D52: 32220 | E52: Dedase, Mark Dosujan | F52: Factory 2 | G52: ADS | H52: Trainee | I52: 46174 | L52: ABSENT | M52: ADS | T52: =SUM(R52:S52) -> 0
A53: 52 | B53: 45783 | C53: B43 | D53: 14105 | E53: Del Rosario, John Robert Punzalan | F53: Factory 3 | G53: Shift 2 | H53: Wire Preparation-Yamaha | I53: 46174 | J53: 0.76828704 | K53: 0.2927662 | M53: NS | N53: 8 | O53: 3 | P53: 2 | Q53: 5 | T53: =SUM(R53:S53) -> 0
A54: 53 | B54: 45972 | C54: B52 | D54: 31406 | E54: Dela Rosa, Edmun Mosca | F54: Factory 1 | G54: Shift 2 | H54: Subaru Engine | I54: 46174 | J54: 0.75961806 | K54: 0.29365741 | M54: NS | N54: 8 | O54: 3 | P54: 2 | Q54: 5 | T54: =SUM(R54:S54) -> 0
A55: 54 | B55: 45670 | C55: B30 | D55: 12450 | E55: Deuna, Rommel Lumpot | F55: Factory 1 | G55: Shift 2 | H55: Wire Preparation | I55: 46174 | J55: 0.77832176 | K55: 0.17127315 | M55: NS | N55: 8 | Q55: 5 | T55: =SUM(R55:S55) -> 0
A56: 55 | B56: 45244 | C56: B2 | D56: 5846 | E56: Diaz, Junel Mago | F56: Factory 1 | G56: Shift 1 | H56: Wire Preparation | I56: 46174 | J56: 0.2737037 | K56: 0.79394676 | M56: DS | N56: 8 | O56: 3 | T56: =SUM(R56:S56) -> 0
A57: 56 | B57: 45818 | C57: B48 | D57: 14872 | E57: Dorado, Merlan Gatdula | F57: Factory 1 | G57: Shift 1 | H57: Wire Preparation | I57: 46174 | J57: 0.26947917 | K57: 0.66835648 | M57: DS | N57: 8 | T57: =SUM(R57:S57) -> 0
A58: 57 | B58: 45944 | C58: B49 | D58: 31012 | E58: Encila, Marilyn Lopez | F58: Factory 1 | G58: Shift 1 | H58: Wire Preparation | I58: 46174 | J58: 0.27078704 | K58: 0.66886574 | M58: DS | N58: 8 | T58: =SUM(R58:S58) -> 0
A59: 58 | B59: 46154 | C59: B57 | D59: 32559 | E59: Enecimo, Rodelyn Macahis | F59: Factory 3 | G59: Shift 1 | H59: Wire Preparation | I59: 46174 | J59: 0.26274306 | K59: 0.66829861 | M59: DS | N59: 8 | T59: =SUM(R59:S59) -> 0
A60: 59 | B60: 46154 | C60: B57 | D60: 32537 | E60: Enriquez, Felicidad Dajon | F60: Factory 1 | G60: Shift 2 | H60: Wire Preparation | I60: 46174 | J60: 0.77077546 | K60: 0.16989583 | M60: NS | N60: 8 | Q60: 5 | T60: =SUM(R60:S60) -> 0
A61: 60 | B61: 45811 | C61: B47 | D61: 13357 | E61: Esplana, Ronald N/A | F61: Factory 3 | G61: Shift 1 | H61: Wire Preparation | I61: 46174 | J61: 0.26638889 | K61: 0.66725694 | M61: DS | N61: 8 | T61: =SUM(R61:S61) -> 0
A62: 61 | B62: 45768 | C62: B41 | D62: 12260 | E62: Estipona, Joel De Mesa | F62: Factory 1 | G62: Shift 1 | H62: Subaru Engine | I62: 46174 | L62: ABSENT | M62: DS | T62: =SUM(R62:S62) -> 0
A63: 62 | B63: 46154 | C63: B57 | D63: 32570 | E63: Estolano, Jade Marie Flores | F63: Factory 1 | G63: Shift 2 | H63: Wire Preparation | I63: 46174 | J63: 0.76591435 | K63: 0.16996528 | M63: NS | N63: 8 | Q63: 5 | T63: =SUM(R63:S63) -> 0
A64: 63 | B64: 45497 | C64: B19 | D64: 6905 | E64: Estrada, Kevin James Hernandez | F64: Factory 1 | G64: Shift 1 | H64: Subaru Insertion | I64: 46174 | J64: 0.26128472 | K64: 0.79347222 | M64: DS | N64: 8 | O64: 3 | T64: =SUM(R64:S64) -> 0
A65: 64 | B65: 45811 | C65: B47 | D65: 13351 | E65: Faderog, Mark Japhet Francisco | F65: Factory 3 | G65: Shift 1 | H65: QC Inspection | I65: 46174 | J65: 0.28055556 | K65: 0.79628472 | M65: DS | N65: 8 | O65: 3 | T65: =SUM(R65:S65) -> 0
A66: 65 | B66: 45951 | C66: B50 | D66: 31137 | E66: Fidelson, Maria Noralie N/A | F66: Factory 1 | G66: Shift 2 | H66: Subaru Engine | I66: 46174 | J66: 0.7741088 | K66: 0.29844907 | M66: NS | N66: 8 | O66: 3 | P66: 2 | Q66: 5 | T66: =SUM(R66:S66) -> 0
A67: 66 | B67: 45482 | C67: B17 | D67: 6703 | E67: Fornasa, Marlon Fernandez | F67: Factory 1 | G67: Shift 2 | H67: Transmission | I67: 46174 | J67: 0.77243056 | K67: 0.29431713 | M67: NS | N67: 8 | O67: 3 | P67: 2 | Q67: 5 | T67: =SUM(R67:S67) -> 0
A68: 67 | B68: 46161 | C68: B58 | D68: 32217 | E68: Gado, Jordan Sualog | F68: Factory 2 | G68: Shift 2 | H68: Subaru Engine/TM | I68: 46174 | J68: 0.76599537 | K68: 0.17103009 | M68: NS | N68: 8 | Q68: 5 | T68: =SUM(R68:S68) -> 0
A69: 68 | B69: 45818 | C69: B48 | D69: 14855 | E69: Gargar, Ronel Calumpang | F69: Factory 1 | G69: Shift 2 | H69: Material Handler | I69: 46174 | L69: ABSENT | M69: NS | T69: =SUM(R69:S69) -> 0
A70: 69 | B70: 46161 | C70: B58 | D70: 32216 | E70: Gob, Maribel Navarro | F70: Factory 2 | G70: ADS | H70: Trainee | I70: 46174 | J70: 0.25898148 | K70: 0.67131944 | M70: ADS | N70: 8 | T70: =SUM(R70:S70) -> 0
A71: 70 | B71: 45993 | C71: B53 | D71: 31084 | E71: Guab, Rhae Mae Naguimbing | F71: Factory 1 | G71: Shift 2 | H71: Wire Preparation | I71: 46174 | J71: 0.75938657 | K71: 0.29638889 | M71: NS | N71: 8 | O71: 3 | P71: 2 | Q71: 5 | T71: =SUM(R71:S71) -> 0
A72: 71 | B72: 46154 | C72: B57 | D72: 32569 | E72: Gunay, James Ryan Castillo | F72: Factory 1 | G72: Shift 2 | H72: Wire Preparation | I72: 46174 | L72: ABSENT | M72: NS | T72: =SUM(R72:S72) -> 0
A73: 72 | B73: 46161 | C73: B58 | D73: 32204 | E73: Gunay, Jade Kenneth Castillo | F73: Factory 2 | G73: Shift 2 | H73: Subaru Engine/TM | I73: 46174 | J73: 0.76513889 | K73: 0.17166667 | M73: NS | N73: 8 | Q73: 5 | T73: =SUM(R73:S73) -> 0
A74: 73 | B74: 46161 | C74: B58 | D74: 32209 | E74: Gutierrez, Alexander Espinocilla | F74: Factory 2 | G74: Shift 2 | H74: Subaru Engine/TM | I74: 46174 | J74: 0.76596065 | K74: 0.17105324 | M74: NS | N74: 8 | Q74: 5 | T74: =SUM(R74:S74) -> 0
A75: 74 | B75: 46154 | C75: B57 | D75: 32557 | E75: Hermoso, Kristine Manaog | F75: Factory 3 | G75: Shift 2 | H75: Wire Preparation | I75: 46174 | L75: ABSENT | M75: NS | T75: =SUM(R75:S75) -> 0
A76: 75 | B76: 45944 | C76: B49 | D76: 31013 | E76: Hernandez, Christine Sosa | F76: Factory 1 | G76: Shift 2 | H76: Material Handler | I76: 46174 | J76: 0.75799769 | K76: 0.1703588 | M76: NS | N76: 8 | Q76: 5 | T76: =SUM(R76:S76) -> 0
A77: 76 | B77: 45818 | C77: B48 | D77: 14866 | E77: Holgado, Kayshia Marie Lantin | F77: Factory 1 | G77: Shift 2 | H77: QC Inspection | I77: 46174 | J77: 0.73625 | K77: 0.29424769 | M77: NS | N77: 8 | O77: 3 | P77: 2 | Q77: 5 | T77: =SUM(R77:S77) -> 0
A78: 77 | B78: 45636 | C78: B29 | D78: 10338 | E78: Humiwat Jr., Abelardo Bugtong | F78: Factory 1 | G78: Shift 2 | H78: Material Handler | I78: 46174 | J78: 0.77398148 | K78: 0.29642361 | M78: NS | N78: 8 | O78: 3 | P78: 2 | Q78: 5 | T78: =SUM(R78:S78) -> 0
A79: 78 | B79: 45719 | C79: B36 | D79: 12081 | E79: Ilagan, Zyra Barcelona | F79: Factory 3 | G79: Shift 2 | H79: Subaru Insertion | I79: 46174 | J79: 0.75929398 | K79: 0.29290509 | M79: NS | N79: 8 | O79: 3 | P79: 2 | Q79: 5 | T79: =SUM(R79:S79) -> 0
A80: 79 | B80: 46154 | C80: B57 | D80: 32547 | E80: Inocencio, Adrian Rebancos | F80: Factory 1 | G80: Shift 2 | H80: Wire Preparation | I80: 46174 | J80: 0.75840278 | K80: 0.16957176 | M80: NS | N80: 8 | Q80: 5 | T80: =SUM(R80:S80) -> 0
A81: 80 | B81: 45993 | C81: B53 | D81: 31092 | E81: Isabedra, Jhozua Abanador | F81: Factory 1 | G81: Shift 1 | H81: QC Inspection | I81: 46174 | J81: 0.25568287 | K81: 0.6678125 | M81: DS | N81: 8 | T81: =SUM(R81:S81) -> 0
A82: 81 | B82: 46084 | C82: B56 | D82: 32820 | E82: Jabagat, Anna Grace Manit | F82: Factory 1 | G82: Shift 2 | H82: Wire Preparation | I82: 46174 | J82: 0.76616898 | K82: 0.29767361 | M82: NS | N82: 8 | O82: 3 | P82: 2 | Q82: 5 | T82: 0
A83: 82 | B83: 45670 | C83: B30 | D83: 12457 | E83: Jorvina, Schemark Mandreza | F83: Factory 1 | G83: Shift 2 | H83: Subaru Engine | I83: 46174 | J83: 0.77018519 | K83: 0.16741898 | M83: NS | N83: 8 | Q83: 5 | T83: =SUM(R83:S83) -> 0
A84: 83 | B84: 46154 | C84: B57 | D84: 32558 | E84: Jumawan, Lj Chiong | F84: Factory 3 | G84: Shift 2 | H84: Wire Preparation | I84: 46174 | J84: 0.75827546 | K84: 0.16836806 | M84: NS | N84: 8 | Q84: 5 | T84: =SUM(R84:S84) -> 0
A85: 84 | B85: 46154 | C85: B57 | D85: 32548 | E85: Lanic, Mark Andrie | F85: Factory 1 | G85: Shift 2 | H85: Wire Preparation | I85: 46174 | J85: 0.75835648 | K85: 0.29774306 | M85: NS | N85: 8 | O85: 3 | P85: 2 | Q85: 5 | T85: =SUM(R85:S85) -> 0
A86: 85 | B86: 45951 | C86: B50 | D86: 31022 | E86: Lanuza, Karen Llantino | F86: Factory 1 | G86: Shift 1 | H86: Subaru Engine | I86: 46174 | J86: 0.26305556 | K86: 0.79458333 | M86: DS | N86: 8 | O86: 3 | T86: =SUM(R86:S86) -> 0
A87: 86 | B87: 45440 | C87: B11 | D87: 6456 | E87: Latorre, Rolly Rigos | F87: Factory 1 | G87: Shift 2 | H87: Warehouse | I87: 46174 | J87: 0.76099537 | K87: 0.29646991 | M87: NS | N87: 8 | O87: 3 | P87: 2 | Q87: 5 | T87: =SUM(R87:S87) -> 0
A88: 87 | B88: 45811 | C88: B47 | D88: 13362 | E88: Leswe, Leonalyn Asaytuno | F88: Factory 1 | G88: Shift 1 | H88: Wire Preparation | I88: 46174 | J88: 0.27865741 | K88: 0.67241898 | M88: DS | N88: 8 | T88: =SUM(R88:S88) -> 0
A89: 88 | B89: 45685 | C89: B33 | D89: 12783 | E89: Limbo, Alexander Andrew De Silva | F89: Factory 1 | G89: Shift 2 | H89: Shipment | I89: 46174 | J89: 0.74640046 | K89: 0.29225694 | M89: NS | N89: 8 | O89: 3 | P89: 2 | Q89: 5 | T89: =SUM(R89:S89) -> 0
A90: 89 | B90: 46084 | C90: B56 | D90: 31638 | E90: Llamas, Shullan Sisno | F90: Factory 1 | G90: Shift 1 | H90: Subaru Engine | I90: 46174 | J90: 0.25402778 | K90: 0.79599537 | M90: DS | N90: 8 | O90: 3 | T90: 0
A91: 90 | B91: 46161 | C91: B58 | D91: 32213 | E91: Lombo, Joanne Sayago | F91: Factory 2 | G91: ADS | H91: Trainee | I91: 46174 | J91: 0.26582176 | K91: 0.67155093 | M91: ADS | N91: 8 | T91: =SUM(R91:S91) -> 0
A92: 91 | B92: 46154 | C92: B57 | D92: 32554 | E92: Macalintal, Albert Maligsi | F92: Factory 3 | G92: Shift 1 | H92: Wire Preparation | I92: 46174 | J92: 0.25331019 | K92: 0.79260417 | M92: DS | N92: 8 | O92: 3 | T92: =SUM(R92:S92) -> 0
A93: 92 | B93: 45456 | C93: B13 | D93: 6555 | E93: Magsino, Jaymark Aclan | F93: Factory 1 | G93: Shift 1 | H93: QA | I93: 46174 | J93: 0.27353009 | K93: 0.79328704 | M93: DS | N93: 8 | O93: 3 | T93: =SUM(R93:S93) -> 0
A94: 93 | B94: 46161 | C94: B58 | D94: 32218 | E94: Malaluan, Joshua Mungcal | F94: Factory 2 | G94: ADS | H94: Trainee | I94: 46174 | J94: 0.25859954 | K94: 0.67121528 | M94: ADS | N94: 8 | T94: =SUM(R94:S94) -> 0
A95: 94 | B95: 45531 | C95: B24 | D95: 7091 | E95: Malaza, Ruthann Cuenca | F95: Factory 1 | G95: Shift 2 | H95: Material Handler | I95: 46174 | J95: 0.76236111 | K95: 0.29857639 | M95: NS | N95: 8 | O95: 3 | P95: 2 | Q95: 5 | T95: =SUM(R95:S95) -> 0
A96: 95 | B96: 45818 | C96: B48 | D96: 14873 | E96: Manalo, Alfred Sacupon | F96: Factory 1 | G96: Shift 2 | H96: Material Handler | I96: 46174 | J96: 0.75969907 | K96: 0.16868056 | M96: NS | N96: 8 | Q96: 5 | T96: =SUM(R96:S96) -> 0
A97: 96 | B97: 45755 | C97: B40 | D97: 11675 | E97: Manalo, Donabel Rivera | F97: Factory 1 | G97: Shift 2 | H97: Transmission | I97: 46174 | J97: 0.76571759 | K97: 0.29717593 | M97: NS | N97: 8 | O97: 3 | P97: 2 | Q97: 5 | T97: =SUM(R97:S97) -> 0
A98: 97 | B98: 45755 | C98: B40 | D98: 11728 | E98: Manito, Jumenic Gabatan | F98: Factory 3 | G98: Shift 2 | H98: QC Inspection | I98: 46174 | J98: 0.75305556 | K98: 0.29194444 | M98: NS | N98: 8 | O98: 3 | P98: 2 | Q98: 5 | T98: =SUM(R98:S98) -> 0
A99: 98 | B99: 46084 | C99: B56 | D99: 32825 | E99: Marquez, Vincent Panganiban | F99: Factory 1 | G99: Shift 2 | H99: Subaru Engine | I99: 46174 | L99: ABSENT | M99: NS | T99: 0
A100: 99 | B100: 46161 | C100: B58 | D100: 32215 | E100: Medrano, Cris Panganiban | F100: Factory 2 | G100: ADS | H100: Trainee | I100: 46174 | L100: ABSENT | M100: ADS | T100: =SUM(R100:S100) -> 0
...

Sheet PVT
B3: Row Labels | C3: Sum of REGULAR HOURS | D3: Sum of UNWORKED LH | E3: Sum of LATE/UT | F3: Sum of ND | G3: Sum of OTND | H3: Sum of OT | J3: REG HRS | K3: ULH | L3: UT/LATE | M3: ND | N3: OTND | O3: OT
A4: 5683 | B4: Abcede, Jomar Pavino | C4: 88 | D4: 8 | E4: 0 | F4: 30 | G4: 10 | H4: 27 | J4: =600/8*C:C -> 6600 | K4: =600/8*D:D -> 600 | L4: =600/8/60*E:E -> 0 | M4: =600/8*0.1*F:F -> 225 | N4: =600/8*0.1*1.25*G:G -> 93.75 | O4: =600/8*1.25*H:H -> 2531.25
A5: 31024 | B5: Abrio, Althea Mae Divila | C5: 80 | E5: 0 | F5: 25 | G5: 10 | H5: 27 | J5: =600/8*C:C -> 6000 | K5: =600/8*D:D -> 0 | L5: =600/8/60*E:E -> 0 | M5: =600/8*0.1*F:F -> 187.5 | N5: =600/8*0.1*1.25*G:G -> 93.75 | O5: =600/8*1.25*H:H -> 2531.25
A6: 13373 | B6: Acasamoso, Jerico Ladia | C6: 80 | D6: 8 | E6: 0 | F6: 20 | G6: 2 | H6: 19.67 | J6: =600/8*C:C -> 6000 | K6: =600/8*D:D -> 600 | L6: =600/8/60*E:E -> 0 | M6: =600/8*0.1*F:F -> 150 | N6: =600/8*0.1*1.25*G:G -> 18.75 | O6: =600/8*1.25*H:H -> 1844.0625
A7: 7167 | B7: Aguirre, Christopher Isla | C7: 56 | E7: 0 | F7: 20 | G7: 6 | H7: 15 | J7: =600/8*C:C -> 4200 | K7: =600/8*D:D -> 0 | L7: =600/8/60*E:E -> 0 | M7: =600/8*0.1*F:F -> 150 | N7: =600/8*0.1*1.25*G:G -> 56.25 | O7: =600/8*1.25*H:H -> 1406.25
A8: 32300 | B8: Albello, Joyce Anne Palma | C8: 80 | D8: 8 | E8: 0 | J8: =600/8*C:C -> 6000 | K8: =600/8*D:D -> 600 | L8: =600/8/60*E:E -> 0 | M8: =600/8*0.1*F:F -> 0 | N8: =600/8*0.1*1.25*G:G -> 0 | O8: =600/8*1.25*H:H -> 0
A9: 32202 | B9: Alcantara, Felix Salvador Andoque | C9: 80 | D9: 8 | E9: 0 | J9: =600/8*C:C -> 6000 | K9: =600/8*D:D -> 600 | L9: =600/8/60*E:E -> 0 | M9: =600/8*0.1*F:F -> 0 | N9: =600/8*0.1*1.25*G:G -> 0 | O9: =600/8*1.25*H:H -> 0
A10: 32255 | B10: Alikhan, Mohammad King Verona | C10: 80 | D10: 8 | E10: 0 | F10: 30 | G10: 4 | H10: 6 | J10: =600/8*C:C -> 6000 | K10: =600/8*D:D -> 600 | L10: =600/8/60*E:E -> 0 | M10: =600/8*0.1*F:F -> 225 | N10: =600/8*0.1*1.25*G:G -> 37.5 | O10: =600/8*1.25*H:H -> 562.5
A11: 11936 | B11: Alongalay, Ruiz Trillanes | C11: 88 | D11: 8 | E11: 0 | F11: 30 | G11: 2 | H11: 13.92 | J11: =600/8*C:C -> 6600 | K11: =600/8*D:D -> 600 | L11: =600/8/60*E:E -> 0 | M11: =600/8*0.1*F:F -> 225 | N11: =600/8*0.1*1.25*G:G -> 18.75 | O11: =600/8*1.25*H:H -> 1305
A12: 31006 | B12: An, Rey Alcos | C12: 88 | D12: 8 | E12: 0 | F12: 25 | G12: 10 | H12: 27 | J12: =600/8*C:C -> 6600 | K12: =600/8*D:D -> 600 | L12: =600/8/60*E:E -> 0 | M12: =600/8*0.1*F:F -> 187.5 | N12: =600/8*0.1*1.25*G:G -> 93.75 | O12: =600/8*1.25*H:H -> 2531.25
A13: 32281 | B13: Andal, Ana Mae De Jesus | C13: 80 | D13: 8 | E13: 0 | J13: =600/8*C:C -> 6000 | K13: =600/8*D:D -> 600 | L13: =600/8/60*E:E -> 0 | M13: =600/8*0.1*F:F -> 0 | N13: =600/8*0.1*1.25*G:G -> 0 | O13: =600/8*1.25*H:H -> 0
A14: 7080 | B14: Antaran, Alrey jay Barber | C14: 80 | D14: 8 | E14: 3 | F14: 24.96 | G14: 6 | H14: 12 | J14: =600/8*C:C -> 6000 | K14: =600/8*D:D -> 600 | L14: =600/8/60*E:E -> 3.75 | M14: =600/8*0.1*F:F -> 187.2 | N14: =600/8*0.1*1.25*G:G -> 56.25 | O14: =600/8*1.25*H:H -> 1125
A15: 31088 | B15: Armada, Simon Estacio | C15: 72 | D15: 8 | E15: 0 | F15: 25 | G15: 8 | H15: 18 | J15: =600/8*C:C -> 5400 | K15: =600/8*D:D -> 600 | L15: =600/8/60*E:E -> 0 | M15: =600/8*0.1*F:F -> 187.5 | N15: =600/8*0.1*1.25*G:G -> 75 | O15: =600/8*1.25*H:H -> 1687.5
A16: 11601 | B16: Asuncion, Rhenzo N/A | C16: 88 | D16: 8 | E16: 0 | H16: 18 | J16: =600/8*C:C -> 6600 | K16: =600/8*D:D -> 600 | L16: =600/8/60*E:E -> 0 | M16: =600/8*0.1*F:F -> 0 | N16: =600/8*0.1*1.25*G:G -> 0 | O16: =600/8*1.25*H:H -> 1687.5
A17: 7115 | B17: Aveñon, Reymart Magnaye | C17: 88 | D17: 8 | E17: 275 | F17: 20.42 | G17: 8 | H17: 30 | J17: =600/8*C:C -> 6600 | K17: =600/8*D:D -> 600 | L17: =600/8/60*E:E -> 343.75 | M17: =600/8*0.1*F:F -> 153.15 | N17: =600/8*0.1*1.25*G:G -> 75 | O17: =600/8*1.25*H:H -> 2812.5
A18: 32818 | B18: Azarga, Glebel Nañola | C18: 48 | D18: 8 | E18: 0 | H18: 6 | J18: =600/8*C:C -> 3600 | K18: =600/8*D:D -> 600 | L18: =600/8/60*E:E -> 0 | M18: =600/8*0.1*F:F -> 0 | N18: =600/8*0.1*1.25*G:G -> 0 | O18: =600/8*1.25*H:H -> 562.5
A19: 11939 | B19: Baay, Edrian Samar | C19: 56 | D19: 8 | E19: 0 | F19: 15 | G19: 2 | H19: 15 | J19: =600/8*C:C -> 4200 | K19: =600/8*D:D -> 600 | L19: =600/8/60*E:E -> 0 | M19: =600/8*0.1*F:F -> 112.5 | N19: =600/8*0.1*1.25*G:G -> 18.75 | O19: =600/8*1.25*H:H -> 1406.25
A20: 31047 | B20: Bacay, Princess Jane Garcia | C20: 88 | D20: 8 | E20: 0 | F20: 30 | G20: 8 | H20: 24 | J20: =600/8*C:C -> 6600 | K20: =600/8*D:D -> 600 | L20: =600/8/60*E:E -> 0 | M20: =600/8*0.1*F:F -> 225 | N20: =600/8*0.1*1.25*G:G -> 75 | O20: =600/8*1.25*H:H -> 2250
A21: 32205 | B21: Bada, Genm Bryant Carino | C21: 80 | D21: 8 | E21: 0 | F21: 25 | J21: =600/8*C:C -> 6000 | K21: =600/8*D:D -> 600 | L21: =600/8/60*E:E -> 0 | M21: =600/8*0.1*F:F -> 187.5 | N21: =600/8*0.1*1.25*G:G -> 0 | O21: =600/8*1.25*H:H -> 0
A22: 32203 | B22: Bagsic, Protacio Jr. Conception | C22: 88 | D22: 8 | E22: 0 | F22: 25 | G22: 6 | H22: 12 | J22: =600/8*C:C -> 6600 | K22: =600/8*D:D -> 600 | L22: =600/8/60*E:E -> 0 | M22: =600/8*0.1*F:F -> 187.5 | N22: =600/8*0.1*1.25*G:G -> 56.25 | O22: =600/8*1.25*H:H -> 1125
A23: 7738 | B23: Balmes, Sheila May Godoy | C23: 88 | D23: 8 | E23: 0 | F23: 25 | H23: 3 | J23: =600/8*C:C -> 6600 | K23: =600/8*D:D -> 600 | L23: =600/8/60*E:E -> 0 | M23: =600/8*0.1*F:F -> 187.5 | N23: =600/8*0.1*1.25*G:G -> 0 | O23: =600/8*1.25*H:H -> 281.25
A24: 10894 | B24: Balobaldo, Jhon Lister Ponpon | C24: 88 | D24: 8 | E24: 0 | F24: 30 | G24: 2 | H24: 18 | J24: =600/8*C:C -> 6600 | K24: =600/8*D:D -> 600 | L24: =600/8/60*E:E -> 0 | M24: =600/8*0.1*F:F -> 225 | N24: =600/8*0.1*1.25*G:G -> 18.75 | O24: =600/8*1.25*H:H -> 1687.5
A25: 12092 | B25: Banaira, Jason Aldovino | C25: 80 | D25: 8 | E25: 0 | F25: 25 | G25: 8 | H25: 24 | J25: =600/8*C:C -> 6000 | K25: =600/8*D:D -> 600 | L25: =600/8/60*E:E -> 0 | M25: =600/8*0.1*F:F -> 187.5 | N25: =600/8*0.1*1.25*G:G -> 75 | O25: =600/8*1.25*H:H -> 2250
A26: 7731 | B26: Baril, Edelyn Digo | C26: 88 | D26: 8 | E26: 7 | F26: 25 | G26: 6 | H26: 9 | J26: =600/8*C:C -> 6600 | K26: =600/8*D:D -> 600 | L26: =600/8/60*E:E -> 8.75 | M26: =600/8*0.1*F:F -> 187.5 | N26: =600/8*0.1*1.25*G:G -> 56.25 | O26: =600/8*1.25*H:H -> 843.75
A27: 12019 | B27: Basila, Mayrelyn Flores | C27: 88 | D27: 8 | E27: 0 | F27: 5 | G27: 2 | H27: 24 | J27: =600/8*C:C -> 6600 | K27: =600/8*D:D -> 600 | L27: =600/8/60*E:E -> 0 | M27: =600/8*0.1*F:F -> 37.5 | N27: =600/8*0.1*1.25*G:G -> 18.75 | O27: =600/8*1.25*H:H -> 2250
A28: 32223 | B28: Bathan, Gellie Biscocho | C28: 88 | D28: 8 | E28: 0 | F28: 5 | G28: 2 | H28: 3 | J28: =600/8*C:C -> 6600 | K28: =600/8*D:D -> 600 | L28: =600/8/60*E:E -> 0 | M28: =600/8*0.1*F:F -> 37.5 | N28: =600/8*0.1*1.25*G:G -> 18.75 | O28: =600/8*1.25*H:H -> 281.25
A29: 14750 | B29: Bea, Dominic Penano | C29: 80 | D29: 8 | E29: 0 | F29: 25 | H29: 9 | J29: =600/8*C:C -> 6000 | K29: =600/8*D:D -> 600 | L29: =600/8/60*E:E -> 0 | M29: =600/8*0.1*F:F -> 187.5 | N29: =600/8*0.1*1.25*G:G -> 0 | O29: =600/8*1.25*H:H -> 843.75
A30: 10941 | B30: Begonia, Christopher Bolo | C30: 88 | D30: 8 | E30: 0 | F30: 25 | G30: 8 | H30: 24 | J30: =600/8*C:C -> 6600 | K30: =600/8*D:D -> 600 | L30: =600/8/60*E:E -> 0 | M30: =600/8*0.1*F:F -> 187.5 | N30: =600/8*0.1*1.25*G:G -> 75 | O30: =600/8*1.25*H:H -> 2250
A31: 32279 | B31: Bejasa, Marielle Balasa | C31: 80 | D31: 8 | E31: 0 | J31: =600/8*C:C -> 6000 | K31: =600/8*D:D -> 600 | L31: =600/8/60*E:E -> 0 | M31: =600/8*0.1*F:F -> 0 | N31: =600/8*0.1*1.25*G:G -> 0 | O31: =600/8*1.25*H:H -> 0
A32: 31086 | B32: Belardo, Mariel Volante | C32: 80 | E32: 0 | F32: 25 | J32: =600/8*C:C -> 6000 | K32: =600/8*D:D -> 0 | L32: =600/8/60*E:E -> 0 | M32: =600/8*0.1*F:F -> 187.5 | N32: =600/8*0.1*1.25*G:G -> 0 | O32: =600/8*1.25*H:H -> 0
A33: 32817 | B33: Belir, Mark Shane N/A | C33: 48 | E33: 0 | F33: 10 | H33: 3 | J33: =600/8*C:C -> 3600 | K33: =600/8*D:D -> 0 | L33: =600/8/60*E:E -> 0 | M33: =600/8*0.1*F:F -> 75 | N33: =600/8*0.1*1.25*G:G -> 0 | O33: =600/8*1.25*H:H -> 281.25
A34: 14851 | B34: Beltrano, Celjay N/A | C34: 32 | E34: 0 | F34: 15 | J34: =600/8*C:C -> 2400 | K34: =600/8*D:D -> 0 | L34: =600/8/60*E:E -> 0 | M34: =600/8*0.1*F:F -> 112.5 | N34: =600/8*0.1*1.25*G:G -> 0 | O34: =600/8*1.25*H:H -> 0
A35: 12577 | B35: Bocado, Richard Cocayco | C35: 88 | D35: 8 | E35: 0 | F35: 30 | G35: 4 | H35: 15 | J35: =600/8*C:C -> 6600 | K35: =600/8*D:D -> 600 | L35: =600/8/60*E:E -> 0 | M35: =600/8*0.1*F:F -> 225 | N35: =600/8*0.1*1.25*G:G -> 37.5 | O35: =600/8*1.25*H:H -> 1406.25
A36: 13366 | B36: Bonaobra, Andro Pineda | C36: 88 | D36: 8 | E36: 0 | F36: 25 | G36: 8 | H36: 29.98 | J36: =600/8*C:C -> 6600 | K36: =600/8*D:D -> 600 | L36: =600/8/60*E:E -> 0 | M36: =600/8*0.1*F:F -> 187.5 | N36: =600/8*0.1*1.25*G:G -> 75 | O36: =600/8*1.25*H:H -> 2810.625
A37: 32294 | B37: Bontigao, Donelyn Fortes | C37: 80 | D37: 8 | E37: 0 | J37: =600/8*C:C -> 6000 | K37: =600/8*D:D -> 600 | L37: =600/8/60*E:E -> 0 | M37: =600/8*0.1*F:F -> 0 | N37: =600/8*0.1*1.25*G:G -> 0 | O37: =600/8*1.25*H:H -> 0
A38: 13678 | B38: Botin, Jhon Carlo Medallion | C38: 80 | D38: 8 | E38: 0 | F38: 25 | G38: 4 | H38: 18 | J38: =600/8*C:C -> 6000 | K38: =600/8*D:D -> 600 | L38: =600/8/60*E:E -> 0 | M38: =600/8*0.1*F:F -> 187.5 | N38: =600/8*0.1*1.25*G:G -> 37.5 | O38: =600/8*1.25*H:H -> 1687.5
A39: 12083 | B39: Brozo, Jonel Bautista | C39: 32 | E39: 0 | H39: 9 | J39: =600/8*C:C -> 2400 | K39: =600/8*D:D -> 0 | L39: =600/8/60*E:E -> 0 | M39: =600/8*0.1*F:F -> 0 | N39: =600/8*0.1*1.25*G:G -> 0 | O39: =600/8*1.25*H:H -> 843.75
A40: 32571 | B40: Brucelo Joshua Alano | E40: 0 | J40: =600/8*C:C -> 0 | K40: =600/8*D:D -> 0 | L40: =600/8/60*E:E -> 0 | M40: =600/8*0.1*F:F -> 0 | N40: =600/8*0.1*1.25*G:G -> 0 | O40: =600/8*1.25*H:H -> 0
A41: 31010 | B41: Burac, Ma. Kaycha Antonio | C41: 88 | D41: 8 | E41: 0 | F41: 30 | G41: 12 | H41: 30 | J41: =600/8*C:C -> 6600 | K41: =600/8*D:D -> 600 | L41: =600/8/60*E:E -> 0 | M41: =600/8*0.1*F:F -> 225 | N41: =600/8*0.1*1.25*G:G -> 112.5 | O41: =600/8*1.25*H:H -> 2812.5
A42: 12634 | B42: Burgos, Yonathan Robles | C42: 88 | D42: 8 | E42: 0 | F42: 30 | G42: 8 | H42: 18 | J42: =600/8*C:C -> 6600 | K42: =600/8*D:D -> 600 | L42: =600/8/60*E:E -> 0 | M42: =600/8*0.1*F:F -> 225 | N42: =600/8*0.1*1.25*G:G -> 75 | O42: =600/8*1.25*H:H -> 1687.5
A43: 32277 | B43: Buriel, Jade Agaloos | C43: 80 | D43: 8 | E43: 0 | J43: =600/8*C:C -> 6000 | K43: =600/8*D:D -> 600 | L43: =600/8/60*E:E -> 0 | M43: =600/8*0.1*F:F -> 0 | N43: =600/8*0.1*1.25*G:G -> 0 | O43: =600/8*1.25*H:H -> 0
A44: 14841 | B44: Caburobias, Aerole John Asparin | C44: 88 | D44: 8 | E44: 0 | H44: 15 | J44: =600/8*C:C -> 6600 | K44: =600/8*D:D -> 600 | L44: =600/8/60*E:E -> 0 | M44: =600/8*0.1*F:F -> 0 | N44: =600/8*0.1*1.25*G:G -> 0 | O44: =600/8*1.25*H:H -> 1406.25
A45: 32803 | B45: Calalo, Hyacinth Ruba | C45: 80 | D45: 8 | E45: 0 | F45: 30 | G45: 8 | H45: 21 | J45: =600/8*C:C -> 6000 | K45: =600/8*D:D -> 600 | L45: =600/8/60*E:E -> 0 | M45: =600/8*0.1*F:F -> 225 | N45: =600/8*0.1*1.25*G:G -> 75 | O45: =600/8*1.25*H:H -> 1968.75
A46: 32822 | B46: Cañelas, Michelle Ann Ramos | C46: 88 | D46: 8 | E46: 0 | F46: 25 | G46: 4 | H46: 6 | J46: =600/8*C:C -> 6600 | K46: =600/8*D:D -> 600 | L46: =600/8/60*E:E -> 0 | M46: =600/8*0.1*F:F -> 187.5 | N46: =600/8*0.1*1.25*G:G -> 37.5 | O46: =600/8*1.25*H:H -> 562.5
A47: 32814 | B47: Canson, Gerald Corral | C47: 88 | D47: 8 | E47: 0 | F47: 30 | G47: 4 | H47: 6 | J47: =600/8*C:C -> 6600 | K47: =600/8*D:D -> 600 | L47: =600/8/60*E:E -> 0 | M47: =600/8*0.1*F:F -> 225 | N47: =600/8*0.1*1.25*G:G -> 37.5 | O47: =600/8*1.25*H:H -> 562.5
A48: 32307 | B48: Castañeda, John Paul Plado | C48: 80 | D48: 8 | E48: 0 | F48: 30 | J48: =600/8*C:C -> 6000 | K48: =600/8*D:D -> 600 | L48: =600/8/60*E:E -> 0 | M48: =600/8*0.1*F:F -> 225 | N48: =600/8*0.1*1.25*G:G -> 0 | O48: =600/8*1.25*H:H -> 0
A49: 6362 | B49: Clores, Lea Amaro | C49: 72 | D49: 8 | E49: 0 | F49: 30 | G49: 10 | H49: 24 | J49: =600/8*C:C -> 5400 | K49: =600/8*D:D -> 600 | L49: =600/8/60*E:E -> 0 | M49: =600/8*0.1*F:F -> 225 | N49: =600/8*0.1*1.25*G:G -> 93.75 | O49: =600/8*1.25*H:H -> 2250
A50: 32561 | B50: Codilla, Edrick Vonn Medina | C50: 80 | D50: 8 | E50: 0 | F50: 20 | G50: 6 | H50: 18 | J50: =600/8*C:C -> 6000 | K50: =600/8*D:D -> 600 | L50: =600/8/60*E:E -> 0 | M50: =600/8*0.1*F:F -> 150 | N50: =600/8*0.1*1.25*G:G -> 56.25 | O50: =600/8*1.25*H:H -> 1687.5
A51: 32824 | B51: Coquiat, Samuel Jhames Brigondo | C51: 72 | D51: 8 | E51: 0 | F51: 30 | G51: 8 | H51: 12 | J51: =600/8*C:C -> 5400 | K51: =600/8*D:D -> 600 | L51: =600/8/60*E:E -> 0 | M51: =600/8*0.1*F:F -> 225 | N51: =600/8*0.1*1.25*G:G -> 75 | O51: =600/8*1.25*H:H -> 1125
A52: 32221 | B52: Corong, Edwardo | C52: 80 | D52: 8 | E52: 0 | F52: 20 | J52: =600/8*C:C -> 6000 | K52: =600/8*D:D -> 600 | L52: =600/8/60*E:E -> 0 | M52: =600/8*0.1*F:F -> 150 | N52: =600/8*0.1*1.25*G:G -> 0 | O52: =600/8*1.25*H:H -> 0
A53: 32212 | B53: Correa, Ervin Ramos | C53: 88 | D53: 8 | E53: 0 | F53: 25 | J53: =600/8*C:C -> 6600 | K53: =600/8*D:D -> 600 | L53: =600/8/60*E:E -> 0 | M53: =600/8*0.1*F:F -> 187.5 | N53: =600/8*0.1*1.25*G:G -> 0 | O53: =600/8*1.25*H:H -> 0
A54: 14874 | B54: Cupo, Adrian Dela Masa | C54: 32 | E54: 0 | F54: 20 | J54: =600/8*C:C -> 2400 | K54: =600/8*D:D -> 0 | L54: =600/8/60*E:E -> 0 | M54: =600/8*0.1*F:F -> 150 | N54: =600/8*0.1*1.25*G:G -> 0 | O54: =600/8*1.25*H:H -> 0
A55: 7697 | B55: Custodio, Jessa May Rubia | C55: 64 | D55: 8 | E55: 37 | H55: 3 | J55: =600/8*C:C -> 4800 | K55: =600/8*D:D -> 600 | L55: =600/8/60*E:E -> 46.25 | M55: =600/8*0.1*F:F -> 0 | N55: =600/8*0.1*1.25*G:G -> 0 | O55: =600/8*1.25*H:H -> 281.25
A56: 11938 | B56: Dadap, Kim cedrick Piol | C56: 80 | D56: 8 | E56: 0 | F56: 25 | G56: 8 | H56: 27 | J56: =600/8*C:C -> 6000 | K56: =600/8*D:D -> 600 | L56: =600/8/60*E:E -> 0 | M56: =600/8*0.1*F:F -> 187.5 | N56: =600/8*0.1*1.25*G:G -> 75 | O56: =600/8*1.25*H:H -> 2531.25
A57: 14606 | B57: Dan-Uya, Jayson Malijan | C57: 80 | D57: 8 | E57: 0 | F57: 25 | G57: 6 | H57: 21 | J57: =600/8*C:C -> 6000 | K57: =600/8*D:D -> 600 | L57: =600/8/60*E:E -> 0 | M57: =600/8*0.1*F:F -> 187.5 | N57: =600/8*0.1*1.25*G:G -> 56.25 | O57: =600/8*1.25*H:H -> 1968.75
A58: 14865 | B58: De Castro, Ma. Judith Depalco | C58: 40 | E58: 0 | F58: 15 | J58: =600/8*C:C -> 3000 | K58: =600/8*D:D -> 0 | L58: =600/8/60*E:E -> 0 | M58: =600/8*0.1*F:F -> 112.5 | N58: =600/8*0.1*1.25*G:G -> 0 | O58: =600/8*1.25*H:H -> 0
A59: 32283 | B59: De Leon, Jessa Labrador | C59: 72 | D59: 8 | E59: 0 | F59: 5 | J59: =600/8*C:C -> 5400 | K59: =600/8*D:D -> 600 | L59: =600/8/60*E:E -> 0 | M59: =600/8*0.1*F:F -> 37.5 | N59: =600/8*0.1*1.25*G:G -> 0 | O59: =600/8*1.25*H:H -> 0
A60: 11160 | B60: De Los Reyes, John Robert Creus | C60: 88 | D60: 8 | E60: 0 | F60: 25 | G60: 10 | H60: 27 | J60: =600/8*C:C -> 6600 | K60: =600/8*D:D -> 600 | L60: =600/8/60*E:E -> 0 | M60: =600/8*0.1*F:F -> 187.5 | N60: =600/8*0.1*1.25*G:G -> 93.75 | O60: =600/8*1.25*H:H -> 2531.25
A61: 12262 | B61: De Mesa, Patrick Estipona | C61: 80 | D61: 8 | E61: 0 | F61: 25 | G61: 6 | H61: 12 | J61: =600/8*C:C -> 6000 | K61: =600/8*D:D -> 600 | L61: =600/8/60*E:E -> 0 | M61: =600/8*0.1*F:F -> 187.5 | N61: =600/8*0.1*1.25*G:G -> 56.25 | O61: =600/8*1.25*H:H -> 1125
A62: 32220 | B62: Dedase, Mark Dosujan | E62: 0 | J62: =600/8*C:C -> 0 | K62: =600/8*D:D -> 0 | L62: =600/8/60*E:E -> 0 | M62: =600/8*0.1*F:F -> 0 | N62: =600/8*0.1*1.25*G:G -> 0 | O62: =600/8*1.25*H:H -> 0
A63: 32293 | B63: Del Mundo, Alvin John Cabagua | C63: 80 | D63: 8 | E63: 0 | F63: 30 | J63: =600/8*C:C -> 6000 | K63: =600/8*D:D -> 600 | L63: =600/8/60*E:E -> 0 | M63: =600/8*0.1*F:F -> 225 | N63: =600/8*0.1*1.25*G:G -> 0 | O63: =600/8*1.25*H:H -> 0
A64: 14105 | B64: Del Rosario, John Robert Punzalan | C64: 80 | D64: 8 | E64: 0 | F64: 25 | G64: 2 | H64: 3 | J64: =600/8*C:C -> 6000 | K64: =600/8*D:D -> 600 | L64: =600/8/60*E:E -> 0 | M64: =600/8*0.1*F:F -> 187.5 | N64: =600/8*0.1*1.25*G:G -> 18.75 | O64: =600/8*1.25*H:H -> 281.25
A65: 31406 | B65: Dela Rosa, Edmun Mosca | C65: 88 | D65: 8 | E65: 0 | F65: 25 | G65: 4 | H65: 15 | J65: =600/8*C:C -> 6600 | K65: =600/8*D:D -> 600 | L65: =600/8/60*E:E -> 0 | M65: =600/8*0.1*F:F -> 187.5 | N65: =600/8*0.1*1.25*G:G -> 37.5 | O65: =600/8*1.25*H:H -> 1406.25
A66: 12450 | B66: Deuna, Rommel Lumpot | C66: 80 | D66: 8 | E66: 0 | F66: 25 | H66: 15 | J66: =600/8*C:C -> 6000 | K66: =600/8*D:D -> 600 | L66: =600/8/60*E:E -> 0 | M66: =600/8*0.1*F:F -> 187.5 | N66: =600/8*0.1*1.25*G:G -> 0 | O66: =600/8*1.25*H:H -> 1406.25
A67: 5846 | B67: Diaz, Junel Mago | C67: 80 | D67: 8 | E67: 0 | F67: 25 | G67: 8 | H67: 24 | J67: =600/8*C:C -> 6000 | K67: =600/8*D:D -> 600 | L67: =600/8/60*E:E -> 0 | M67: =600/8*0.1*F:F -> 187.5 | N67: =600/8*0.1*1.25*G:G -> 75 | O67: =600/8*1.25*H:H -> 2250
A68: 14872 | B68: Dorado, Merlan Gatdula | C68: 48 | E68: 0 | F68: 10 | J68: =600/8*C:C -> 3600 | K68: =600/8*D:D -> 0 | L68: =600/8/60*E:E -> 0 | M68: =600/8*0.1*F:F -> 75 | N68: =600/8*0.1*1.25*G:G -> 0 | O68: =600/8*1.25*H:H -> 0
A69: 31012 | B69: Encila, Marilyn Lopez | C69: 88 | D69: 8 | E69: 0 | F69: 30 | G69: 2 | H69: 12 | J69: =600/8*C:C -> 6600 | K69: =600/8*D:D -> 600 | L69: =600/8/60*E:E -> 0 | M69: =600/8*0.1*F:F -> 225 | N69: =600/8*0.1*1.25*G:G -> 18.75 | O69: =600/8*1.25*H:H -> 1125
A70: 32286 | B70: Endozo, Ejay | C70: 80 | D70: 8 | E70: 240 | J70: =600/8*C:C -> 6000 | K70: =600/8*D:D -> 600 | L70: =600/8/60*E:E -> 300 | M70: =600/8*0.1*F:F -> 0 | N70: =600/8*0.1*1.25*G:G -> 0 | O70: =600/8*1.25*H:H -> 0
A71: 32559 | B71: Enecimo, Rodelyn Macahis | C71: 88 | D71: 8 | E71: 0 | F71: 30 | J71: =600/8*C:C -> 6600 | K71: =600/8*D:D -> 600 | L71: =600/8/60*E:E -> 0 | M71: =600/8*0.1*F:F -> 225 | N71: =600/8*0.1*1.25*G:G -> 0 | O71: =600/8*1.25*H:H -> 0
A72: 32537 | B72: Enriquez, Felicidad Dajon | C72: 88 | D72: 8 | E72: 0 | F72: 25 | G72: 2 | H72: 3 | J72: =600/8*C:C -> 6600 | K72: =600/8*D:D -> 600 | L72: =600/8/60*E:E -> 0 | M72: =600/8*0.1*F:F -> 187.5 | N72: =600/8*0.1*1.25*G:G -> 18.75 | O72: =600/8*1.25*H:H -> 281.25
A73: 13357 | B73: Esplana, Ronald N/A | C73: 88 | D73: 8 | E73: 0 | F73: 30 | G73: 2 | H73: 6 | J73: =600/8*C:C -> 6600 | K73: =600/8*D:D -> 600 | L73: =600/8/60*E:E -> 0 | M73: =600/8*0.1*F:F -> 225 | N73: =600/8*0.1*1.25*G:G -> 18.75 | O73: =600/8*1.25*H:H -> 562.5
A74: 12260 | B74: Estipona, Joel De Mesa | C74: 80 | D74: 8 | E74: 0 | F74: 30 | H74: 9 | J74: =600/8*C:C -> 6000 | K74: =600/8*D:D -> 600 | L74: =600/8/60*E:E -> 0 | M74: =600/8*0.1*F:F -> 225 | N74: =600/8*0.1*1.25*G:G -> 0 | O74: =600/8*1.25*H:H -> 843.75
A75: 32570 | B75: Estolano, Jade Marie Flores | C75: 88 | D75: 8 | E75: 35 | F75: 25 | J75: =600/8*C:C -> 6600 | K75: =600/8*D:D -> 600 | L75: =600/8/60*E:E -> 43.75 | M75: =600/8*0.1*F:F -> 187.5 | N75: =600/8*0.1*1.25*G:G -> 0 | O75: =600/8*1.25*H:H -> 0
A76: 6905 | B76: Estrada, Kevin James Hernandez | C76: 88 | D76: 8 | E76: 0 | F76: 30 | G76: 6 | H76: 21 | J76: =600/8*C:C -> 6600 | K76: =600/8*D:D -> 600 | L76: =600/8/60*E:E -> 0 | M76: =600/8*0.1*F:F -> 225 | N76: =600/8*0.1*1.25*G:G -> 56.25 | O76: =600/8*1.25*H:H -> 1968.75
A77: 13351 | B77: Faderog, Mark Japhet Francisco | C77: 88 | D77: 8 | E77: 0 | F77: 30 | G77: 10 | H77: 26.98 | J77: =600/8*C:C -> 6600 | K77: =600/8*D:D -> 600 | L77: =600/8/60*E:E -> 0 | M77: =600/8*0.1*F:F -> 225 | N77: =600/8*0.1*1.25*G:G -> 93.75 | O77: =600/8*1.25*H:H -> 2529.375
A78: 32292 | B78: Fajardo, Jonaglen Berwega | C78: 80 | D78: 8 | E78: 0 | F78: 20 | J78: =600/8*C:C -> 6000 | K78: =600/8*D:D -> 600 | L78: =600/8/60*E:E -> 0 | M78: =600/8*0.1*F:F -> 150 | N78: =600/8*0.1*1.25*G:G -> 0 | O78: =600/8*1.25*H:H -> 0
A79: 31137 | B79: Fidelson, Maria Noralie N/A | C79: 88 | D79: 8 | E79: 0 | F79: 25 | G79: 10 | H79: 21 | J79: =600/8*C:C -> 6600 | K79: =600/8*D:D -> 600 | L79: =600/8/60*E:E -> 0 | M79: =600/8*0.1*F:F -> 187.5 | N79: =600/8*0.1*1.25*G:G -> 93.75 | O79: =600/8*1.25*H:H -> 1968.75
A80: 6703 | B80: Fornasa, Marlon Fernandez | C80: 56 | D80: 8 | E80: 0 | F80: 20 | G80: 8 | H80: 15 | J80: =600/8*C:C -> 4200 | K80: =600/8*D:D -> 600 | L80: =600/8/60*E:E -> 0 | M80: =600/8*0.1*F:F -> 150 | N80: =600/8*0.1*1.25*G:G -> 75 | O80: =600/8*1.25*H:H -> 1406.25
A81: 32217 | B81: Gado, Jordan Sualog | C81: 80 | D81: 8 | E81: 0 | F81: 25 | J81: =600/8*C:C -> 6000 | K81: =600/8*D:D -> 600 | L81: =600/8/60*E:E -> 0 | M81: =600/8*0.1*F:F -> 187.5 | N81: =600/8*0.1*1.25*G:G -> 0 | O81: =600/8*1.25*H:H -> 0
A82: 14855 | B82: Gargar, Ronel Calumpang | C82: 16 | E82: 0 | F82: 10 | J82: =600/8*C:C -> 1200 | K82: =600/8*D:D -> 0 | L82: =600/8/60*E:E -> 0 | M82: =600/8*0.1*F:F -> 75 | N82: =600/8*0.1*1.25*G:G -> 0 | O82: =600/8*1.25*H:H -> 0
A83: 32278 | B83: Gerela, Edward Belen | C83: 72 | D83: 8 | E83: 0 | F83: 25 | J83: =600/8*C:C -> 5400 | K83: =600/8*D:D -> 600 | L83: =600/8/60*E:E -> 0 | M83: =600/8*0.1*F:F -> 187.5 | N83: =600/8*0.1*1.25*G:G -> 0 | O83: =600/8*1.25*H:H -> 0
A84: 32216 | B84: Gob, Maribel Navarro | C84: 88 | D84: 8 | E84: 0 | J84: =600/8*C:C -> 6600 | K84: =600/8*D:D -> 600 | L84: =600/8/60*E:E -> 0 | M84: =600/8*0.1*F:F -> 0 | N84: =600/8*0.1*1.25*G:G -> 0 | O84: =600/8*1.25*H:H -> 0
A85: 31084 | B85: Guab, Rhae Mae Naguimbing | C85: 88 | D85: 8 | E85: 0 | F85: 25 | G85: 6 | H85: 12 | J85: =600/8*C:C -> 6600 | K85: =600/8*D:D -> 600 | L85: =600/8/60*E:E -> 0 | M85: =600/8*0.1*F:F -> 187.5 | N85: =600/8*0.1*1.25*G:G -> 56.25 | O85: =600/8*1.25*H:H -> 1125
A86: 32204 | B86: Gunay, Jade Kenneth Castillo | C86: 80 | D86: 8 | E86: 18 | F86: 25 | J86: =600/8*C:C -> 6000 | K86: =600/8*D:D -> 600 | L86: =600/8/60*E:E -> 22.5 | M86: =600/8*0.1*F:F -> 187.5 | N86: =600/8*0.1*1.25*G:G -> 0 | O86: =600/8*1.25*H:H -> 0
A87: 32569 | B87: Gunay, James Ryan Castillo | C87: 40 | D87: 8 | E87: 0 | J87: =600/8*C:C -> 3000 | K87: =600/8*D:D -> 600 | L87: =600/8/60*E:E -> 0 | M87: =600/8*0.1*F:F -> 0 | N87: =600/8*0.1*1.25*G:G -> 0 | O87: =600/8*1.25*H:H -> 0
A88: 32209 | B88: Gutierrez, Alexander Espinocilla | C88: 88 | D88: 8 | E88: 0 | F88: 25 | J88: =600/8*C:C -> 6600 | K88: =600/8*D:D -> 600 | L88: =600/8/60*E:E -> 0 | M88: =600/8*0.1*F:F -> 187.5 | N88: =600/8*0.1*1.25*G:G -> 0 | O88: =600/8*1.25*H:H -> 0
A89: 32557 | B89: Hermoso, Kristine Manaog | C89: 72 | D89: 8 | E89: 0 | F89: 20 | J89: =600/8*C:C -> 5400 | K89: =600/8*D:D -> 600 | L89: =600/8/60*E:E -> 0 | M89: =600/8*0.1*F:F -> 150 | N89: =600/8*0.1*1.25*G:G -> 0 | O89: =600/8*1.25*H:H -> 0
A90: 31013 | B90: Hernandez, Christine Sosa | C90: 88 | D90: 8 | E90: 0 | F90: 25 | G90: 4 | H90: 18 | J90: =600/8*C:C -> 6600 | K90: =600/8*D:D -> 600 | L90: =600/8/60*E:E -> 0 | M90: =600/8*0.1*F:F -> 187.5 | N90: =600/8*0.1*1.25*G:G -> 37.5 | O90: =600/8*1.25*H:H -> 1687.5
A91: 32287 | B91: Hernandez, Jerald Garan | C91: 80 | D91: 8 | E91: 0 | J91: =600/8*C:C -> 6000 | K91: =600/8*D:D -> 600 | L91: =600/8/60*E:E -> 0 | M91: =600/8*0.1*F:F -> 0 | N91: =600/8*0.1*1.25*G:G -> 0 | O91: =600/8*1.25*H:H -> 0
A92: 14866 | B92: Holgado, Kayshia Marie Lantin | C92: 72 | D92: 8 | E92: 0 | F92: 20 | G92: 6 | H92: 18 | J92: =600/8*C:C -> 5400 | K92: =600/8*D:D -> 600 | L92: =600/8/60*E:E -> 0 | M92: =600/8*0.1*F:F -> 150 | N92: =600/8*0.1*1.25*G:G -> 56.25 | O92: =600/8*1.25*H:H -> 1687.5
A93: 10338 | B93: Humiwat Jr., Abelardo Bugtong | C93: 88 | D93: 8 | E93: 0 | F93: 25 | G93: 8 | H93: 24 | J93: =600/8*C:C -> 6600 | K93: =600/8*D:D -> 600 | L93: =600/8/60*E:E -> 0 | M93: =600/8*0.1*F:F -> 187.5 | N93: =600/8*0.1*1.25*G:G -> 75 | O93: =600/8*1.25*H:H -> 2250
A94: 12081 | B94: Ilagan, Zyra Barcelona | C94: 64 | D94: 8 | E94: 0 | F94: 20 | G94: 8 | H94: 21 | J94: =600/8*C:C -> 4800 | K94: =600/8*D:D -> 600 | L94: =600/8/60*E:E -> 0 | M94: =600/8*0.1*F:F -> 150 | N94: =600/8*0.1*1.25*G:G -> 75 | O94: =600/8*1.25*H:H -> 1968.75
A95: 32298 | B95: Imperial, John Rey Oreste | C95: 80 | D95: 8 | E95: 5 | J95: =600/8*C:C -> 6000 | K95: =600/8*D:D -> 600 | L95: =600/8/60*E:E -> 6.25 | M95: =600/8*0.1*F:F -> 0 | N95: =600/8*0.1*1.25*G:G -> 0 | O95: =600/8*1.25*H:H -> 0
A96: 32547 | B96: Inocencio, Adrian Rebancos | C96: 80 | E96: 0 | F96: 25 | G96: 6 | H96: 21 | J96: =600/8*C:C -> 6000 | K96: =600/8*D:D -> 0 | L96: =600/8/60*E:E -> 0 | M96: =600/8*0.1*F:F -> 187.5 | N96: =600/8*0.1*1.25*G:G -> 56.25 | O96: =600/8*1.25*H:H -> 1968.75
A97: 31092 | B97: Isabedra, Jhozua Abanador | C97: 16 | E97: 0 | J97: =600/8*C:C -> 1200 | K97: =600/8*D:D -> 0 | L97: =600/8/60*E:E -> 0 | M97: =600/8*0.1*F:F -> 0 | N97: =600/8*0.1*1.25*G:G -> 0 | O97: =600/8*1.25*H:H -> 0
A98: 32820 | B98: Jabagat, Anna Grace Manit | C98: 88 | D98: 8 | E98: 0 | F98: 25 | G98: 8 | H98: 18 | J98: =600/8*C:C -> 6600 | K98: =600/8*D:D -> 600 | L98: =600/8/60*E:E -> 0 | M98: =600/8*0.1*F:F -> 187.5 | N98: =600/8*0.1*1.25*G:G -> 75 | O98: =600/8*1.25*H:H -> 1687.5
A99: 32285 | B99: Jarito, Marlon Morales | C99: 80 | D99: 8 | E99: 0 | J99: =600/8*C:C -> 6000 | K99: =600/8*D:D -> 600 | L99: =600/8/60*E:E -> 0 | M99: =600/8*0.1*F:F -> 0 | N99: =600/8*0.1*1.25*G:G -> 0 | O99: =600/8*1.25*H:H -> 0
A100: 12457 | B100: Jorvina, Schemark Mandreza | C100: 88 | D100: 8 | E100: 0 | F100: 25 | G100: 2 | H100: 12 | J100: =600/8*C:C -> 6600 | K100: =600/8*D:D -> 600 | L100: =600/8/60*E:E -> 0 | M100: =600/8*0.1*F:F -> 187.5 | N100: =600/8*0.1*1.25*G:G -> 18.75 | O100: =600/8*1.25*H:H -> 1125
A101: 32558 | B101: Jumawan, Lj Chiong | C101: 88 | D101: 8 | E101: 0 | F101: 25 | J101: =600/8*C:C -> 6600 | K101: =600/8*D:D -> 600 | L101: =600/8/60*E:E -> 0 | M101: =600/8*0.1*F:F -> 187.5 | N101: =600/8*0.1*1.25*G:G -> 0 | O101: =600/8*1.25*H:H -> 0
A102: 32548 | B102: Lanic, Mark Andrie | C102: 88 | D102: 8 | E102: 0 | F102: 25 | G102: 8 | H102: 21 | J102: =600/8*C:C -> 6600 | K102: =600/8*D:D -> 600 | L102: =600/8/60*E:E -> 0 | M102: =600/8*0.1*F:F -> 187.5 | N102: =600/8*0.1*1.25*G:G -> 75 | O102: =600/8*1.25*H:H -> 1968.75
...
